Workbook

Sheet 说明
B2: 中国国家气候目标数据库 (v1.0.0) | S2: CC BY 4.0
B3: 本数据集汇编了中国中央政府自2004年至2026年年中制定的量化气候相关目标，这些目标源自官方政策文件和政府网站条目，并按不同主题领域进行整理。 | R3: 作者 | S3: Florian Wengel
B4: 在中国，目标在实践中具有指令性质，是政府机构的重要工作指引。 | S4: 伦敦大学亚非学院
B5: 最后更新 | C5: 46272 | Q5: 免责声明：所有错误均由作者承担。 | S5: 705404@soas.ac.uk
B6: 2026-09-07：根据《促进数字化绿色化协同转型发展实施方案（2026-2030年）》（IP2604）新增1条目标：算力设施等重点领域可再生能源电力消费水平达到所在省份可再生能源电力消纳责任权重水平（2030）。
B7: 2026-09-07：简化目标类别名称，删除“目标”后缀（如“可再生能源目标”→“可再生能源”），中英文同步。
B8: 2026-09-04：按收录口径（直接减排/间接促进减排/显著影响排放路径）筛查，删除62条与气候无直接关联的指标（出行便利、安检流程、车辆技术参数、就业营收、生物多样性等）。 2026-09-04：新增17份2026年政策文件的169条目标（新目标98条、重申目标63条、强化或放宽目标8条），并在「来源」表新增26份政策文件。
B9: 数据来源说明
B10: 目标摘录自中国中央政府各部门发布的中国气候相关文件。这些文本文件来源于政府机构网站、在线百科全书百度百科、中国官方媒体或其他网站。
B12: 气候目标定义
B13: 为编制本数据集之目的，我们将气候目标广义地定义为旨在直接减少温室气体排放、间接促进减排、或对温室气体排放路径产生重大影响的量化承诺。
B14: 本数据集既包括硬性目标，也包括较为软性的指导性目标。
B16: 范围与覆盖
B17: 本数据集仅涵盖国家级气候目标，不提供次国家级目标的信息。目标摘录自2004年以来发布的政策文件。
B18: 本数据集力求尽可能全面，但仍可能有部分目标未能收录。
B20: 数据集结构
B21: 工作表 | C21: 说明
B22: 概览 | C22: 汇总统计
B23: 温室气体排放 | C23: 所有涉及温室气体排放的目标，涵盖全社会经济或特定行业、系统或过程
B24: 能源|电力 | C24: 所有与能源供应（包括煤电相关目标）和消费相关的目标
B25: 工业 | C25: 所有与工业部门相关的目标，特别是高碳工业过程
B26: 建筑 | C26: 所有与建筑和基础设施相关的目标
B27: 交通 | C27: 所有与交通运输和物流相关的目标
B28: 土地利用、土地利用变化和林业 | C28: 所有与土地利用、农业和林业相关的目标
B29: 循环经济 | C29: 所有与废弃物和水资源管理及循环利用相关的目标
B30: 污染 | C30: 所有涉及空气或水污染物排放的目标，涵盖全社会经济或特定行业、系统或过程
B31: 金融 | C31: 所有与实现脱碳目标融资相关的目标
B32: 来源 | C32: 用于标识目标数据来源的政策文件代码。代码及其对应的政策文件完整标题可在「来源」工作表中找到。
B34: 列说明
B35: 发布年份 | C35: 目标所在源文件正式发布或出版的年份。
B36: 指标 | C36: 目标所涉及的核心指标（衡量的内容）。
B37: 方向 | C37: 目标所表达的预期变化方向或类型
B38: 目标值 | C38: 目标水平或变化幅度（数值及其单位）
B39: 基线 | C39: 衡量目标进展的基准水平或年份（如源文件中有说明）。这是变化幅度的起始参考年份。
C40: 目标预定实现的年份或时期。
C41: 表示目标是新增、重复、强化或放宽的代码：
C42: n = 新目标（首次出现）
C43: r = 重复目标（同一目标水平和目标年份在多个政策文件中出现）
C44: s/l = 强化或放宽目标（相同目标年份或时期，但目标水平有所提高或降低）
D45: s/l-UNC | E45: 气候影响不明确的强化或放宽目标
D46: s/l-POS | E46: 具有积极气候影响的强化或放宽目标
D47: s/l-NEG | E47: 具有消极气候影响的强化或放宽目标
C48: 根据目标旨在促进气候减缓或环境成效的底层机制对目标进行分类的属性：
C49: 碳减排 | E49: 排放量的绝对减少
C50: 碳强度 | E50: 单位产出排放量的相对减少
C51: 碳汇 | E51: 森林覆盖率或碳汇能力的提高
C52: 节能 | E52: 能源消耗的减少
C53: 能源效率 | E53: 提高能源利用效率
C54: 资源效率 | E54: 提高资源利用效率
C55: 可再生能源 | E55: 扩大可再生能源
C56: 电气化 | E56: 提高电气化水平
C57: 过渡能源 | E57: 从煤炭向其他化石燃料和核能转变
C58: 涉煤 | E58: 煤电的转型与淘汰
C59: 生产导向 | E59: 绿色产业生产的扩大或高碳生产的限制
C60: 工业转型 | E60: 高碳行业的脱碳
... C66: 气候金融 | E66: 动员资金以减缓和适应气候变化
C67: 表示目标所适用的责任实施单位的属性：
C68: 企事业单位 | E68: 适用于特定企业/工厂/机构
C69: 城市与地区 | E69: 适用于特定城市/地区/区域
C70: 行业 | E70: 适用于特定行业或经济活动（如钢铁）
C71: 全社会经济 | E71: 全国范围内适用于所有经济活动
C72: 不明确 | E72: 范围/责任单位未明确说明
B73: 原文句子 | C73: 源文件中包含量化目标的句子，部分经小幅编辑以提高清晰度或完整性但不改变原意。
B74: 文件 | C74: 目标所摘录的源文件的文件名。前缀通常表示政策类型（如「AP」= 行动方案，「FYP」= 五年规划），后接发布年份（21 = 2021年）和内部编号。
B75: 主题标签 | C75: 目标所属的主题类别。
B76: 子主题标签（仅在「能源|电力」工作表中） | C76: 主题标签内更细粒度的分类，用于精细化主题归类。

Sheet 概览
B2: 描述性统计
B4: 按行业/主题分列的目标数量 | E4: 按子主题分列的"能源|电力"目标数量 | H4: 按目标类型分列的目标数量 | K4: 按公布年份分列的目标数量 | N4: 按目标年份分列的目标数量 | Q4: 按类别分列的目标数量 | T4: 按责任主体分列的目标
B6: 温室气体排放 | C6: =COUNTIFS(温室气体排放!G:G, "新目标") + COUNTIFS(温室气体排放!G:G, "强化或放宽目标（气候影响不明确）") + COUNTIFS(温室气体排放!G:G, "强化或放宽目标（积极气候影响）") + COUNTIFS(温室气体排放!G:G, "强化或放宽目标（消极气候影响）") | E6: 能源消费 | F6: =COUNTIFS('能源|电力'!M:M, "能源消费") | H6: 新目标 | I6: =COUNTIF(温室气体排放!G:G,"新目标") +COUNTIF(污染!G:G,"新目标") +COUNTIF('能源|电力'!G:G,"新目标") +COUNTIF(工业!G:G,"新目标") +COUNTIF(建筑!G:G,"新目标") +COUNTIF(交通!G:G,"新目标") +COUNTIF('土地利用、土地利用变化和林业'!G:G,"新目标") +COUNTIF(循环经济!G:G,"新目标") +COUNTIF(金融!G:G,"新目标") | K6: 2004 | L6: =COUNTIFS(温室气体排放!A:A, 2004, 温室气体排放!G:G, "新目标") + COUNTIFS(温室气体排放!A:A, 2004, 温室气体排放!G:G, "强化或放宽目标（气候影响不明确）") + COUNTIFS(温室气体排放!A:A, 2004, 温室气体排放!G:G, "强化或放宽目标（积极气候影响）") + COUNTIFS(温室气体排放!A:A, 2004, 温室气体排放!G:G, "强化或放宽目标（消极气候影响）") + COUNTIFS(污染!A:A, 2004, 污染!G:G, "新目标") + COUNTIFS(污染!A:A, 2004, 污染!G:G, "强化或放宽目标（气候影响不明确）") + COUNTIFS(污染!A:A, 2004, 污染!G:G, "强化或放宽目标（积极气候影响）") + COUNTIFS(污染!A:A, 2004, 污染!G:G, "强化或放宽目标（消极气候影响）") + COUNTIFS('能源|电力'!A:A, 2004, '能源|电力'!G:G, "新目标") + COUNTIFS('能源|电力'!A:A, 2004, '能源|电力'!G:G, "强化或放宽目标（气候影响不明确）") + COUNTIFS('能源|电力'!A:A, 2004, '能源|电力'!G:G, "强化或放宽目标（积极气候影响）") + COUNTIFS('能源|电力'!A:A, 2004, '能源|电力'!G:G, "强化或放宽目标（消极气候影响）") + COUNTIFS(工业!A:A, 2004, 工业!G:G, "新目标") + COUNTIFS(工业!A:A, 2004, 工业!G:G, "强化或放宽目标（气候影响不明确）") + COUNTIFS(工业!A:A, 2004, 工业!G:G, "强化或放宽目标（积极气候影响）") + COUNTIFS(工业!A:A, 2004, 工业!G:G, "强化或放宽目标（消极气候影响）") + COUNTIFS(建筑!A:A, 2004, 建筑!G:G, "新目标") + COUNTIFS(建筑!A:A, 2004, 建筑!G:G, "强化或放宽目标（气候影响不明确）") + COUNTIFS(建筑!A:A, 2004, 建筑!G:G, "强化或放宽目标（积极气候影响）") + COUNTIFS(建筑!A:A, 2004, 建筑!G:G, "强化或放宽目标（消极气候影响）") + COUNTIFS(交通!A:A, 2004, 交通!G:G, "新目标") + COUNTIFS(交通!A:A, 2004, 交通!G:G, "强化或放宽目标（气候影响不明确）") + COUNTIFS(交通!A:A, 2004, 交通!G:G, "强化或放宽目标（积极气候影响）") + COUNTIFS(交通!A:A, 2004, 交通!G:G, "强化或放宽目标（消极气候影响）") + COUNTIFS('土地利用、土地利用变化和林业'!A:A, 2004, '土地利用、土地利用变化和林业'!G:G, "新目标") + COUNTIFS('土地利用、土地利用变化和林业'!A:A, 2004, '土地利用、土地利用变化和林业'!G:G, "强化或放宽目标（气候影响不明确）") + COUNTIFS('土地利用、土地利用变化和林业'!A:A, 2004, '土地利用、土地利用变化和林业'!G:G, "强化或放宽目标（积极气候影响）") + COUNTIFS('土地利用、土地利用变化和林业'!A:A, 2004, '土地利用、土地利用变化和林业'!G:G, "强化或放宽目标（消极气候影响）") + COUNTIFS(循环经济!A:A, 2004, 循环经济!G:G, "新目标") + COUNTIFS(循环经济!A:A, 2004, 循环经济!G:G, "强化或放宽目标（气候影响不明确）") + COUNTIFS(循环经济!A:A, 2004, 循环经济!G:G, "强化或放宽目标（积极气候影响）") + COUNTIFS(循环经济!A:A, 2004, 循环经济!G:G, "强化或放宽目标（消极气候影响）") + COUNTIFS(金融!A:A, 2004, 金融!G:G, "新目标") + COUNTIFS(金融!A:A, 2004, 金融!G:G, "强化或放宽目标（气候影响不明确）") + COUNTIFS(金融!A:A, 2004, 金融!G:G, "强化或放宽目标（积极气候影响）") + COUNTIFS(金融!A:A, 2004, 金融!G:G, "强化或放宽目标（消极气候影响）") | N6: 2007 | O6: =COUNTIFS(温室气体排放!F:F, 2007, 温室气体排放!G:G, "新目标") + COUNTIFS(温室气体排放!F:F, 2007, 温室气体排放!G:G, "强化或放宽目标（气候影响不明确）") + COUNTIFS(温室气体排放!F:F, 2007, 温室气体排放!G:G, "强化或放宽目标（积极气候影响）") + COUNTIFS(温室气体排放!F:F, 2007, 温室气体排放!G:G, "强化或放宽目标（消极气候影响）") + COUNTIFS(污染!F:F, 2007, 污染!G:G, "新目标") + COUNTIFS(污染!F:F, 2007, 污染!G:G, "强化或放宽目标（气候影响不明确）") + COUNTIFS(污染!F:F, 2007, 污染!G:G, "强化或放宽目标（积极气候影响）") + COUNTIFS(污染!F:F, 2007, 污染!G:G, "强化或放宽目标（消极气候影响）") + COUNTIFS('能源|电力'!F:F, 2007, '能源|电力'!G:G, "新目标") + COUNTIFS('能源|电力'!F:F, 2007, '能源|电力'!G:G, "强化或放宽目标（气候影响不明确）") + COUNTIFS('能源|电力'!F:F, 2007, '能源|电力'!G:G, "强化或放宽目标（积极气候影响）") + COUNTIFS('能源|电力'!F:F, 2007, '能源|电力'!G:G, "强化或放宽目标（消极气候影响）") + COUNTIFS(工业!F:F, 2007, 工业!G:G, "新目标") + COUNTIFS(工业!F:F, 2007, 工业!G:G, "强化或放宽目标（气候影响不明确）") + COUNTIFS(工业!F:F, 2007, 工业!G:G, "强化或放宽目标（积极气候影响）") + COUNTIFS(工业!F:F, 2007, 工业!G:G, "强化或放宽目标（消极气候影响）") + COUNTIFS(建筑!F:F, 2007, 建筑!G:G, "新目标") + COUNTIFS(建筑!F:F, 2007, 建筑!G:G, "强化或放宽目标（气候影响不明确）") + COUNTIFS(建筑!F:F, 2007, 建筑!G:G, "强化或放宽目标（积极气候影响）") + COUNTIFS(建筑!F:F, 2007, 建筑!G:G, "强化或放宽目标（消极气候影响）") + COUNTIFS(交通!F:F, 2007, 交通!G:G, "新目标") + COUNTIFS(交通!F:F, 2007, 交通!G:G, "强化或放宽目标（气候影响不明确）") + COUNTIFS(交通!F:F, 2007, 交通!G:G, "强化或放宽目标（积极气候影响）") + COUNTIFS(交通!F:F, 2007, 交通!G:G, "强化或放宽目标（消极气候影响）") + COUNTIFS('土地利用、土地利用变化和林业'!F:F, 2007, '土地利用、土地利用变化和林业'!G:G, "新目标") + COUNTIFS('土地利用、土地利用变化和林业'!F:F, 2007, '土地利用、土地利用变化和林业'!G:G, "强化或放宽目标（气候影响不明确）") + COUNTIFS('土地利用、土地利用变化和林业'!F:F, 2007, '土地利用、土地利用变化和林业'!G:G, "强化或放宽目标（积极气候影响）") + COUNTIFS('土地利用、土地利用变化和林业'!F:F, 2007, '土地利用、土地利用变化和林业'!G:G, "强化或放宽目标（消极气候影响）") + COUNTIFS(循环经济!F:F, 2007, 循环经济!G:G, "新目标") + COUNTIFS(循环经济!F:F, 2007, 循环经济!G:G, "强化或放宽目标（气候影响不明确）") + COUNTIFS(循环经济!F:F, 2007, 循环经济!G:G, "强化或放宽目标（积极气候影响）") + COUNTIFS(循环经济!F:F, 2007, 循环经济!G:G, "强化或放宽目标（消极气候影响）") + COUNTIFS(金融!F:F, 2007, 金融!G:G, "新目标") + COUNTIFS(金融!F:F, 2007, 金融!G:G, "强化或放宽目标（气候影响不明确）") + COUNTIFS(金融!F:F, 2007, 金融!G:G, "强化或放宽目标（积极气候影响）") + COUNTIFS(金融!F:F, 2007, 金融!G:G, "强化或放宽目标（消极气候影响）") | Q6: 碳减排 | R6: =COUNTIFS(温室气体排放!H:H, "碳减排", 温室气体排放!G:G, "新目标") + COUNTIFS(温室气体排放!H:H, "碳减排", 温室气体排放!G:G, "强化或放宽目标（气候影响不明确）") + COUNTIFS(温室气体排放!H:H, "碳减排", 温室气体排放!G:G, "强化或放宽目标（积极气候影响）") + COUNTIFS(温室气体排放!H:H, "碳减排", 温室气体排放!G:G, "强化或放宽目标（消极气候影响）") + COUNTIFS(污染!H:H, "碳减排", 污染!G:G, "新目标") + COUNTIFS(污染!H:H, "碳减排", 污染!G:G, "强化或放宽目标（气候影响不明确）") + COUNTIFS(污染!H:H, "碳减排", 污染!G:G, "强化或放宽目标（积极气候影响）") + COUNTIFS(污染!H:H, "碳减排", 污染!G:G, "强化或放宽目标（消极气候影响）") + COUNTIFS('能源|电力'!H:H, "碳减排", '能源|电力'!G:G, "新目标") + COUNTIFS('能源|电力'!H:H, "碳减排", '能源|电力'!G:G, "强化或放宽目标（气候影响不明确）") + COUNTIFS('能源|电力'!H:H, "碳减排", '能源|电力'!G:G, "强化或放宽目标（积极气候影响）") + COUNTIFS('能源|电力'!H:H, "碳减排", '能源|电力'!G:G, "强化或放宽目标（消极气候影响）") + COUNTIFS(工业!H:H, "碳减排", 工业!G:G, "新目标") + COUNTIFS(工业!H:H, "碳减排", 工业!G:G, "强化或放宽目标（气候影响不明确）") + COUNTIFS(工业!H:H, "碳减排", 工业!G:G, "强化或放宽目标（积极气候影响）") + COUNTIFS(工业!H:H, "碳减排", 工业!G:G, "强化或放宽目标（消极气候影响）") + COUNTIFS(建筑!H:H, "碳减排", 建筑!G:G, "新目标") + COUNTIFS(建筑!H:H, "碳减排", 建筑!G:G, "强化或放宽目标（气候影响不明确）") + COUNTIFS(建筑!H:H, "碳减排", 建筑!G:G, "强化或放宽目标（积极气候影响）") + COUNTIFS(建筑!H:H, "碳减排", 建筑!G:G, "强化或放宽目标（消极气候影响）") + COUNTIFS(交通!H:H, "碳减排", 交通!G:G, "新目标") + COUNTIFS(交通!H:H, "碳减排", 交通!G:G, "强化或放宽目标（气候影响不明确）") + COUNTIFS(交通!H:H, "碳减排", 交通!G:G, "强化或放宽目标（积极气候影响）") + COUNTIFS(交通!H:H, "碳减排", 交通!G:G, "强化或放宽目标（消极气候影响）") + COUNTIFS('土地利用、土地利用变化和林业'!H:H, "碳减排", '土地利用、土地利用变化和林业'!G:G, "新目标") + COUNTIFS('土地利用、土地利用变化和林业'!H:H, "碳减排", '土地利用、土地利用变化和林业'!G:G, "强化或放宽目标（气候影响不明确）") + COUNTIFS('土地利用、土地利用变化和林业'!H:H, "碳减排", '土地利用、土地利用变化和林业'!G:G, "强化或放宽目标（积极气候影响）") + COUNTIFS('土地利用、土地利用变化和林业'!H:H, "碳减排", '土地利用、土地利用变化和林业'!G:G, "强化或放宽目标（消极气候影响）") + COUNTIFS(循环经济!H:H, "碳减排", 循环经济!G:G, "新目标") + COUNTIFS(循环经济!H:H, "碳减排", 循环经济!G:G, "强化或放宽目标（气候影响不明确）") + COUNTIFS(循环经济!H:H, "碳减排", 循环经济!G:G, "强化或放宽目标（积极气候影响）") + COUNTIFS(循环经济!H:H, "碳减排", 循环经济!G:G, "强化或放宽目标（消极气候影响）") + COUNTIFS(金融!H:H, "碳减排", 金融!G:G, "新目标") + COUNTIFS(金融!H:H, "碳减排", 金融!G:G, "强化或放宽目标（气候影响不明确）") + COUNTIFS(金融!H:H, "碳减排", 金融!G:G, "强化或放宽目标（积极气候影响）") + COUNTIFS(金融!H:H, "碳减排", 金融!G:G, "强化或放宽目标（消极气候影响）") | T6: 企事业单位 | U6: =COUNTIFS(温室气体排放!I:I,"企业",温室气体排放!G:G,"新目标") +COUNTIFS(温室气体排放!I:I,"企业",温室气体排放!G:G,"强化或放宽目标（气候影响不明确）") +COUNTIFS(温室气体排放!I:I,"企业",温室气体排放!G:G,"强化或放宽目标（积极气候影响）") +COUNTIFS(温室气体排放!I:I,"企业",温室气体排放!G:G,"强化或放宽目标（消极气候影响）") +COUNTIFS(污染!I:I,"企业",污染!G:G,"新目标") +COUNTIFS(污染!I:I,"企业",污染!G:G,"强化或放宽目标（气候影响不明确）") +COUNTIFS(污染!I:I,"企业",污染!G:G,"强化或放宽目标（积极气候影响）") +COUNTIFS(污染!I:I,"企业",污染!G:G,"强化或放宽目标（消极气候影响）") +COUNTIFS('能源|电力'!I:I,"企业",'能源|电力'!G:G,"新目标") +COUNTIFS('能源|电力'!I:I,"企业",'能源|电力'!G:G,"强化或放宽目标（气候影响不明确）") +COUNTIFS('能源|电力'!I:I,"企业",'能源|电力'!G:G,"强化或放宽目标（积极气候影响）") +COUNTIFS('能源|电力'!I:I,"企业",'能源|电力'!G:G,"强化或放宽目标（消极气候影响）") +COUNTIFS(工业!I:I,"企业",工业!G:G,"新目标") +COUNTIFS(工业!I:I,"企业",工业!G:G,"强化或放宽目标（气候影响不明确）") +COUNTIFS(工业!I:I,"企业",工业!G:G,"强化或放宽目标（积极气候影响）") +COUNTIFS(工业!I:I,"企业",工业!G:G,"强化或放宽目标（消极气候影响）") +COUNTIFS(建筑!I:I,"企业",建筑!G:G,"新目标") +COUNTIFS(建筑!I:I,"企业",建筑!G:G,"强化或放宽目标（气候影响不明确）") +COUNTIFS(建筑!I:I,"企业",建筑!G:G,"强化或放宽目标（积极气候影响）") +COUNTIFS(建筑!I:I,"企业",建筑!G:G,"强化或放宽目标（消极气候影响）") +COUNTIFS(交通!I:I,"企业",交通!G:G,"新目标") +COUNTIFS(交通!I:I,"企业",交通!G:G,"强化或放宽目标（气候影响不明确）") +COUNTIFS(交通!I:I,"企业",交通!G:G,"强化或放宽目标（积极气候影响）") +COUNTIFS(交通!I:I,"企业",交通!G:G,"强化或放宽目标（消极气候影响）") +COUNTIFS('土地利用、土地利用变化和林业'!I:I,"企业",'土地利用、土地利用变化和林业'!G:G,"新目标") +COUNTIFS('土地利用、土地利用变化和林业'!I:I,"企业",'土地利用、土地利用变化和林业'!G:G,"强化或放宽目标（气候影响不明确）") +COUNTIFS('土地利用、土地利用变化和林业'!I:I,"企业",'土地利用、土地利用变化和林业'!G:G,"强化或放宽目标（积极气候影响）") +COUNTIFS('土地利用、土地利用变化和林业'!I:I,"企业",'土地利用、土地利用变化和林业'!G:G,"强化或放宽目标（消极气候影响）") +COUNTIFS(循环经济!I:I,"企业",循环经济!G:G,"新目标") +COUNTIFS(循环经济!I:I,"企业",循环经济!G:G,"强化或放宽目标（气候影响不明确）") +COUNTIFS(循环经济!I:I,"企业",循环经济!G:G,"强化或放宽目标（积极气候影响）") +COUNTIFS(循环经济!I:I,"企业",循环经济!G:G,"强化或放宽目标（消极气候影响）") +COUNTIFS(金融!I:I,"企业",金融!G:G,"新目标") +COUNTIFS(金融!I:I,"企业",金融!G:G,"强化或放宽目标（气候影响不明确）") +COUNTIFS(金融!I:I,"企业",金融!G:G,"强化或放宽目标（积极气候影响）") +COUNTIFS(金融!I:I,"企业",金融!G:G,"强化或放宽目标（消极气候影响）")
B7: 污染 | C7: =COUNTIFS(污染!G:G, "新目标") + COUNTIFS(污染!G:G, "强化或放宽目标（气候影响不明确）") + COUNTIFS(污染!G:G, "强化或放宽目标（积极气候影响）") + COUNTIFS(污染!G:G, "强化或放宽目标（消极气候影响）") | E7: 电力供应 | F7: =COUNTIFS('能源|电力'!M:M, "电力供应") | H7: 气候影响不明确的强化或放宽目标 | I7: =COUNTIF(温室气体排放!G:G,"强化或放宽目标（气候影响不明确）") +COUNTIF(污染!G:G,"强化或放宽目标（气候影响不明确）") +COUNTIF('能源|电力'!G:G,"强化或放宽目标（气候影响不明确）") +COUNTIF(工业!G:G,"强化或放宽目标（气候影响不明确）") +COUNTIF(建筑!G:G,"强化或放宽目标（气候影响不明确）") +COUNTIF(交通!G:G,"强化或放宽目标（气候影响不明确）") +COUNTIF('土地利用、土地利用变化和林业'!G:G,"强化或放宽目标（气候影响不明确）") +COUNTIF(循环经济!G:G,"强化或放宽目标（气候影响不明确）") +COUNTIF(金融!G:G,"强化或放宽目标（气候影响不明确）") | K7: 2005 | L7: =COUNTIFS(温室气体排放!A:A, 2005, 温室气体排放!G:G, "新目标") + COUNTIFS(温室气体排放!A:A, 2005, 温室气体排放!G:G, "强化或放宽目标（气候影响不明确）") + COUNTIFS(温室气体排放!A:A, 2005, 温室气体排放!G:G, "强化或放宽目标（积极气候影响）") + COUNTIFS(温室气体排放!A:A, 2005, 温室气体排放!G:G, "强化或放宽目标（消极气候影响）") + COUNTIFS(污染!A:A, 2005, 污染!G:G, "新目标") + COUNTIFS(污染!A:A, 2005, 污染!G:G, "强化或放宽目标（气候影响不明确）") + COUNTIFS(污染!A:A, 2005, 污染!G:G, "强化或放宽目标（积极气候影响）") + COUNTIFS(污染!A:A, 2005, 污染!G:G, "强化或放宽目标（消极气候影响）") + COUNTIFS('能源|电力'!A:A, 2005, '能源|电力'!G:G, "新目标") + COUNTIFS('能源|电力'!A:A, 2005, '能源|电力'!G:G, "强化或放宽目标（气候影响不明确）") + COUNTIFS('能源|电力'!A:A, 2005, '能源|电力'!G:G, "强化或放宽目标（积极气候影响）") + COUNTIFS('能源|电力'!A:A, 2005, '能源|电力'!G:G, "强化或放宽目标（消极气候影响）") + COUNTIFS(工业!A:A, 2005, 工业!G:G, "新目标") + COUNTIFS(工业!A:A, 2005, 工业!G:G, "强化或放宽目标（气候影响不明确）") + COUNTIFS(工业!A:A, 2005, 工业!G:G, "强化或放宽目标（积极气候影响）") + COUNTIFS(工业!A:A, 2005, 工业!G:G, "强化或放宽目标（消极气候影响）") + COUNTIFS(建筑!A:A, 2005, 建筑!G:G, "新目标") + COUNTIFS(建筑!A:A, 2005, 建筑!G:G, "强化或放宽目标（气候影响不明确）") + COUNTIFS(建筑!A:A, 2005, 建筑!G:G, "强化或放宽目标（积极气候影响）") + COUNTIFS(建筑!A:A, 2005, 建筑!G:G, "强化或放宽目标（消极气候影响）") + COUNTIFS(交通!A:A, 2005, 交通!G:G, "新目标") + COUNTIFS(交通!A:A, 2005, 交通!G:G, "强化或放宽目标（气候影响不明确）") + COUNTIFS(交通!A:A, 2005, 交通!G:G, "强化或放宽目标（积极气候影响）") + COUNTIFS(交通!A:A, 2005, 交通!G:G, "强化或放宽目标（消极气候影响）") + COUNTIFS('土地利用、土地利用变化和林业'!A:A, 2005, '土地利用、土地利用变化和林业'!G:G, "新目标") + COUNTIFS('土地利用、土地利用变化和林业'!A:A, 2005, '土地利用、土地利用变化和林业'!G:G, "强化或放宽目标（气候影响不明确）") + COUNTIFS('土地利用、土地利用变化和林业'!A:A, 2005, '土地利用、土地利用变化和林业'!G:G, "强化或放宽目标（积极气候影响）") + COUNTIFS('土地利用、土地利用变化和林业'!A:A, 2005, '土地利用、土地利用变化和林业'!G:G, "强化或放宽目标（消极气候影响）") + COUNTIFS(循环经济!A:A, 2005, 循环经济!G:G, "新目标") + COUNTIFS(循环经济!A:A, 2005, 循环经济!G:G, "强化或放宽目标（气候影响不明确）") + COUNTIFS(循环经济!A:A, 2005, 循环经济!G:G, "强化或放宽目标（积极气候影响）") + COUNTIFS(循环经济!A:A, 2005, 循环经济!G:G, "强化或放宽目标（消极气候影响）") + COUNTIFS(金融!A:A, 2005, 金融!G:G, "新目标") + COUNTIFS(金融!A:A, 2005, 金融!G:G, "强化或放宽目标（气候影响不明确）") + COUNTIFS(金融!A:A, 2005, 金融!G:G, "强化或放宽目标（积极气候影响）") + COUNTIFS(金融!A:A, 2005, 金融!G:G, "强化或放宽目标（消极气候影响）") | N7: 2008 | O7: =COUNTIFS(温室气体排放!F:F, 2008, 温室气体排放!G:G, "新目标") + COUNTIFS(温室气体排放!F:F, 2008, 温室气体排放!G:G, "强化或放宽目标（气候影响不明确）") + COUNTIFS(温室气体排放!F:F, 2008, 温室气体排放!G:G, "强化或放宽目标（积极气候影响）") + COUNTIFS(温室气体排放!F:F, 2008, 温室气体排放!G:G, "强化或放宽目标（消极气候影响）") + COUNTIFS(污染!F:F, 2008, 污染!G:G, "新目标") + COUNTIFS(污染!F:F, 2008, 污染!G:G, "强化或放宽目标（气候影响不明确）") + COUNTIFS(污染!F:F, 2008, 污染!G:G, "强化或放宽目标（积极气候影响）") + COUNTIFS(污染!F:F, 2008, 污染!G:G, "强化或放宽目标（消极气候影响）") + COUNTIFS('能源|电力'!F:F, 2008, '能源|电力'!G:G, "新目标") + COUNTIFS('能源|电力'!F:F, 2008, '能源|电力'!G:G, "强化或放宽目标（气候影响不明确）") + COUNTIFS('能源|电力'!F:F, 2008, '能源|电力'!G:G, "强化或放宽目标（积极气候影响）") + COUNTIFS('能源|电力'!F:F, 2008, '能源|电力'!G:G, "强化或放宽目标（消极气候影响）") + COUNTIFS(工业!F:F, 2008, 工业!G:G, "新目标") + COUNTIFS(工业!F:F, 2008, 工业!G:G, "强化或放宽目标（气候影响不明确）") + COUNTIFS(工业!F:F, 2008, 工业!G:G, "强化或放宽目标（积极气候影响）") + COUNTIFS(工业!F:F, 2008, 工业!G:G, "强化或放宽目标（消极气候影响）") + COUNTIFS(建筑!F:F, 2008, 建筑!G:G, "新目标") + COUNTIFS(建筑!F:F, 2008, 建筑!G:G, "强化或放宽目标（气候影响不明确）") + COUNTIFS(建筑!F:F, 2008, 建筑!G:G, "强化或放宽目标（积极气候影响）") + COUNTIFS(建筑!F:F, 2008, 建筑!G:G, "强化或放宽目标（消极气候影响）") + COUNTIFS(交通!F:F, 2008, 交通!G:G, "新目标") + COUNTIFS(交通!F:F, 2008, 交通!G:G, "强化或放宽目标（气候影响不明确）") + COUNTIFS(交通!F:F, 2008, 交通!G:G, "强化或放宽目标（积极气候影响）") + COUNTIFS(交通!F:F, 2008, 交通!G:G, "强化或放宽目标（消极气候影响）") + COUNTIFS('土地利用、土地利用变化和林业'!F:F, 2008, '土地利用、土地利用变化和林业'!G:G, "新目标") + COUNTIFS('土地利用、土地利用变化和林业'!F:F, 2008, '土地利用、土地利用变化和林业'!G:G, "强化或放宽目标（气候影响不明确）") + COUNTIFS('土地利用、土地利用变化和林业'!F:F, 2008, '土地利用、土地利用变化和林业'!G:G, "强化或放宽目标（积极气候影响）") + COUNTIFS('土地利用、土地利用变化和林业'!F:F, 2008, '土地利用、土地利用变化和林业'!G:G, "强化或放宽目标（消极气候影响）") + COUNTIFS(循环经济!F:F, 2008, 循环经济!G:G, "新目标") + COUNTIFS(循环经济!F:F, 2008, 循环经济!G:G, "强化或放宽目标（气候影响不明确）") + COUNTIFS(循环经济!F:F, 2008, 循环经济!G:G, "强化或放宽目标（积极气候影响）") + COUNTIFS(循环经济!F:F, 2008, 循环经济!G:G, "强化或放宽目标（消极气候影响）") + COUNTIFS(金融!F:F, 2008, 金融!G:G, "新目标") + COUNTIFS(金融!F:F, 2008, 金融!G:G, "强化或放宽目标（气候影响不明确）") + COUNTIFS(金融!F:F, 2008, 金融!G:G, "强化或放宽目标（积极气候影响）") + COUNTIFS(金融!F:F, 2008, 金融!G:G, "强化或放宽目标（消极气候影响）") | Q7: 碳强度 | R7: =COUNTIFS(温室气体排放!H:H, "碳强度", 温室气体排放!G:G, "新目标") + COUNTIFS(温室气体排放!H:H, "碳强度", 温室气体排放!G:G, "强化或放宽目标（气候影响不明确）") + COUNTIFS(温室气体排放!H:H, "碳强度", 温室气体排放!G:G, "强化或放宽目标（积极气候影响）") + COUNTIFS(温室气体排放!H:H, "碳强度", 温室气体排放!G:G, "强化或放宽目标（消极气候影响）") + COUNTIFS(污染!H:H, "碳强度", 污染!G:G, "新目标") + COUNTIFS(污染!H:H, "碳强度", 污染!G:G, "强化或放宽目标（气候影响不明确）") + COUNTIFS(污染!H:H, "碳强度", 污染!G:G, "强化或放宽目标（积极气候影响）") + COUNTIFS(污染!H:H, "碳强度", 污染!G:G, "强化或放宽目标（消极气候影响）") + COUNTIFS('能源|电力'!H:H, "碳强度", '能源|电力'!G:G, "新目标") + COUNTIFS('能源|电力'!H:H, "碳强度", '能源|电力'!G:G, "强化或放宽目标（气候影响不明确）") + COUNTIFS('能源|电力'!H:H, "碳强度", '能源|电力'!G:G, "强化或放宽目标（积极气候影响）") + COUNTIFS('能源|电力'!H:H, "碳强度", '能源|电力'!G:G, "强化或放宽目标（消极气候影响）") + COUNTIFS(工业!H:H, "碳强度", 工业!G:G, "新目标") + COUNTIFS(工业!H:H, "碳强度", 工业!G:G, "强化或放宽目标（气候影响不明确）") + COUNTIFS(工业!H:H, "碳强度", 工业!G:G, "强化或放宽目标（积极气候影响）") + COUNTIFS(工业!H:H, "碳强度", 工业!G:G, "强化或放宽目标（消极气候影响）") + COUNTIFS(建筑!H:H, "碳强度", 建筑!G:G, "新目标") + COUNTIFS(建筑!H:H, "碳强度", 建筑!G:G, "强化或放宽目标（气候影响不明确）") + COUNTIFS(建筑!H:H, "碳强度", 建筑!G:G, "强化或放宽目标（积极气候影响）") + COUNTIFS(建筑!H:H, "碳强度", 建筑!G:G, "强化或放宽目标（消极气候影响）") + COUNTIFS(交通!H:H, "碳强度", 交通!G:G, "新目标") + COUNTIFS(交通!H:H, "碳强度", 交通!G:G, "强化或放宽目标（气候影响不明确）") + COUNTIFS(交通!H:H, "碳强度", 交通!G:G, "强化或放宽目标（积极气候影响）") + COUNTIFS(交通!H:H, "碳强度", 交通!G:G, "强化或放宽目标（消极气候影响）") + COUNTIFS('土地利用、土地利用变化和林业'!H:H, "碳强度", '土地利用、土地利用变化和林业'!G:G, "新目标") + COUNTIFS('土地利用、土地利用变化和林业'!H:H, "碳强度", '土地利用、土地利用变化和林业'!G:G, "强化或放宽目标（气候影响不明确）") + COUNTIFS('土地利用、土地利用变化和林业'!H:H, "碳强度", '土地利用、土地利用变化和林业'!G:G, "强化或放宽目标（积极气候影响）") + COUNTIFS('土地利用、土地利用变化和林业'!H:H, "碳强度", '土地利用、土地利用变化和林业'!G:G, "强化或放宽目标（消极气候影响）") + COUNTIFS(循环经济!H:H, "碳强度", 循环经济!G:G, "新目标") + COUNTIFS(循环经济!H:H, "碳强度", 循环经济!G:G, "强化或放宽目标（气候影响不明确）") + COUNTIFS(循环经济!H:H, "碳强度", 循环经济!G:G, "强化或放宽目标（积极气候影响）") + COUNTIFS(循环经济!H:H, "碳强度", 循环经济!G:G, "强化或放宽目标（消极气候影响）") + COUNTIFS(金融!H:H, "碳强度", 金融!G:G, "新目标") + COUNTIFS(金融!H:H, "碳强度", 金融!G:G, "强化或放宽目标（气候影响不明确）") + COUNTIFS(金融!H:H, "碳强度", 金融!G:G, "强化或放宽目标（积极气候影响）") + COUNTIFS(金融!H:H, "碳强度", 金融!G:G, "强化或放宽目标（消极气候影响）") | T7: 城市与地区 | U7: =COUNTIFS(温室气体排放!I:I,"地区",温室气体排放!G:G,"新目标") +COUNTIFS(温室气体排放!I:I,"地区",温室气体排放!G:G,"强化或放宽目标（气候影响不明确）") +COUNTIFS(温室气体排放!I:I,"地区",温室气体排放!G:G,"强化或放宽目标（积极气候影响）") +COUNTIFS(温室气体排放!I:I,"地区",温室气体排放!G:G,"强化或放宽目标（消极气候影响）") +COUNTIFS(污染!I:I,"地区",污染!G:G,"新目标") +COUNTIFS(污染!I:I,"地区",污染!G:G,"强化或放宽目标（气候影响不明确）") +COUNTIFS(污染!I:I,"地区",污染!G:G,"强化或放宽目标（积极气候影响）") +COUNTIFS(污染!I:I,"地区",污染!G:G,"强化或放宽目标（消极气候影响）") +COUNTIFS('能源|电力'!I:I,"地区",'能源|电力'!G:G,"新目标") +COUNTIFS('能源|电力'!I:I,"地区",'能源|电力'!G:G,"强化或放宽目标（气候影响不明确）") +COUNTIFS('能源|电力'!I:I,"地区",'能源|电力'!G:G,"强化或放宽目标（积极气候影响）") +COUNTIFS('能源|电力'!I:I,"地区",'能源|电力'!G:G,"强化或放宽目标（消极气候影响）") +COUNTIFS(工业!I:I,"地区",工业!G:G,"新目标") +COUNTIFS(工业!I:I,"地区",工业!G:G,"强化或放宽目标（气候影响不明确）") +COUNTIFS(工业!I:I,"地区",工业!G:G,"强化或放宽目标（积极气候影响）") +COUNTIFS(工业!I:I,"地区",工业!G:G,"强化或放宽目标（消极气候影响）") +COUNTIFS(建筑!I:I,"地区",建筑!G:G,"新目标") +COUNTIFS(建筑!I:I,"地区",建筑!G:G,"强化或放宽目标（气候影响不明确）") +COUNTIFS(建筑!I:I,"地区",建筑!G:G,"强化或放宽目标（积极气候影响）") +COUNTIFS(建筑!I:I,"地区",建筑!G:G,"强化或放宽目标（消极气候影响）") +COUNTIFS(交通!I:I,"地区",交通!G:G,"新目标") +COUNTIFS(交通!I:I,"地区",交通!G:G,"强化或放宽目标（气候影响不明确）") +COUNTIFS(交通!I:I,"地区",交通!G:G,"强化或放宽目标（积极气候影响）") +COUNTIFS(交通!I:I,"地区",交通!G:G,"强化或放宽目标（消极气候影响）") +COUNTIFS('土地利用、土地利用变化和林业'!I:I,"地区",'土地利用、土地利用变化和林业'!G:G,"新目标") +COUNTIFS('土地利用、土地利用变化和林业'!I:I,"地区",'土地利用、土地利用变化和林业'!G:G,"强化或放宽目标（气候影响不明确）") +COUNTIFS('土地利用、土地利用变化和林业'!I:I,"地区",'土地利用、土地利用变化和林业'!G:G,"强化或放宽目标（积极气候影响）") +COUNTIFS('土地利用、土地利用变化和林业'!I:I,"地区",'土地利用、土地利用变化和林业'!G:G,"强化或放宽目标（消极气候影响）") +COUNTIFS(循环经济!I:I,"地区",循环经济!G:G,"新目标") +COUNTIFS(循环经济!I:I,"地区",循环经济!G:G,"强化或放宽目标（气候影响不明确）") +COUNTIFS(循环经济!I:I,"地区",循环经济!G:G,"强化或放宽目标（积极气候影响）") +COUNTIFS(循环经济!I:I,"地区",循环经济!G:G,"强化或放宽目标（消极气候影响）") +COUNTIFS(金融!I:I,"地区",金融!G:G,"新目标") +COUNTIFS(金融!I:I,"地区",金融!G:G,"强化或放宽目标（气候影响不明确）") +COUNTIFS(金融!I:I,"地区",金融!G:G,"强化或放宽目标（积极气候影响）") +COUNTIFS(金融!I:I,"地区",金融!G:G,"强化或放宽目标（消极气候影响）")
B8: 能源|电力 | C8: =COUNTIFS('能源|电力'!G:G, "新目标") + COUNTIFS('能源|电力'!G:G, "强化或放宽目标（气候影响不明确）") + COUNTIFS('能源|电力'!G:G, "强化或放宽目标（积极气候影响）") + COUNTIFS('能源|电力'!G:G, "强化或放宽目标（消极气候影响）") | E8: 电力传输/能源运输 | F8: =COUNTIFS('能源|电力'!M:M, "电力传输/能源运输") | H8: 具有积极气候影响的强化或放宽目标 | I8: =COUNTIF(温室气体排放!G:G,"强化或放宽目标（积极气候影响）") +COUNTIF(污染!G:G,"强化或放宽目标（积极气候影响）") +COUNTIF('能源|电力'!G:G,"强化或放宽目标（积极气候影响）") +COUNTIF(工业!G:G,"强化或放宽目标（积极气候影响）") +COUNTIF(建筑!G:G,"强化或放宽目标（积极气候影响）") +COUNTIF(交通!G:G,"强化或放宽目标（积极气候影响）") +COUNTIF('土地利用、土地利用变化和林业'!G:G,"强化或放宽目标（积极气候影响）") +COUNTIF(循环经济!G:G,"强化或放宽目标（积极气候影响）") +COUNTIF(金融!G:G,"强化或放宽目标（积极气候影响）") | K8: 2006 | L8: =COUNTIFS(温室气体排放!A:A, 2006, 温室气体排放!G:G, "新目标") + COUNTIFS(温室气体排放!A:A, 2006, 温室气体排放!G:G, "强化或放宽目标（气候影响不明确）") + COUNTIFS(温室气体排放!A:A, 2006, 温室气体排放!G:G, "强化或放宽目标（积极气候影响）") + COUNTIFS(温室气体排放!A:A, 2006, 温室气体排放!G:G, "强化或放宽目标（消极气候影响）") + COUNTIFS(污染!A:A, 2006, 污染!G:G, "新目标") + COUNTIFS(污染!A:A, 2006, 污染!G:G, "强化或放宽目标（气候影响不明确）") + COUNTIFS(污染!A:A, 2006, 污染!G:G, "强化或放宽目标（积极气候影响）") + COUNTIFS(污染!A:A, 2006, 污染!G:G, "强化或放宽目标（消极气候影响）") + COUNTIFS('能源|电力'!A:A, 2006, '能源|电力'!G:G, "新目标") + COUNTIFS('能源|电力'!A:A, 2006, '能源|电力'!G:G, "强化或放宽目标（气候影响不明确）") + COUNTIFS('能源|电力'!A:A, 2006, '能源|电力'!G:G, "强化或放宽目标（积极气候影响）") + COUNTIFS('能源|电力'!A:A, 2006, '能源|电力'!G:G, "强化或放宽目标（消极气候影响）") + COUNTIFS(工业!A:A, 2006, 工业!G:G, "新目标") + COUNTIFS(工业!A:A, 2006, 工业!G:G, "强化或放宽目标（气候影响不明确）") + COUNTIFS(工业!A:A, 2006, 工业!G:G, "强化或放宽目标（积极气候影响）") + COUNTIFS(工业!A:A, 2006, 工业!G:G, "强化或放宽目标（消极气候影响）") + COUNTIFS(建筑!A:A, 2006, 建筑!G:G, "新目标") + COUNTIFS(建筑!A:A, 2006, 建筑!G:G, "强化或放宽目标（气候影响不明确）") + COUNTIFS(建筑!A:A, 2006, 建筑!G:G, "强化或放宽目标（积极气候影响）") + COUNTIFS(建筑!A:A, 2006, 建筑!G:G, "强化或放宽目标（消极气候影响）") + COUNTIFS(交通!A:A, 2006, 交通!G:G, "新目标") + COUNTIFS(交通!A:A, 2006, 交通!G:G, "强化或放宽目标（气候影响不明确）") + COUNTIFS(交通!A:A, 2006, 交通!G:G, "强化或放宽目标（积极气候影响）") + COUNTIFS(交通!A:A, 2006, 交通!G:G, "强化或放宽目标（消极气候影响）") + COUNTIFS('土地利用、土地利用变化和林业'!A:A, 2006, '土地利用、土地利用变化和林业'!G:G, "新目标") + COUNTIFS('土地利用、土地利用变化和林业'!A:A, 2006, '土地利用、土地利用变化和林业'!G:G, "强化或放宽目标（气候影响不明确）") + COUNTIFS('土地利用、土地利用变化和林业'!A:A, 2006, '土地利用、土地利用变化和林业'!G:G, "强化或放宽目标（积极气候影响）") + COUNTIFS('土地利用、土地利用变化和林业'!A:A, 2006, '土地利用、土地利用变化和林业'!G:G, "强化或放宽目标（消极气候影响）") + COUNTIFS(循环经济!A:A, 2006, 循环经济!G:G, "新目标") + COUNTIFS(循环经济!A:A, 2006, 循环经济!G:G, "强化或放宽目标（气候影响不明确）") + COUNTIFS(循环经济!A:A, 2006, 循环经济!G:G, "强化或放宽目标（积极气候影响）") + COUNTIFS(循环经济!A:A, 2006, 循环经济!G:G, "强化或放宽目标（消极气候影响）") + COUNTIFS(金融!A:A, 2006, 金融!G:G, "新目标") + COUNTIFS(金融!A:A, 2006, 金融!G:G, "强化或放宽目标（气候影响不明确）") + COUNTIFS(金融!A:A, 2006, 金融!G:G, "强化或放宽目标（积极气候影响）") + COUNTIFS(金融!A:A, 2006, 金融!G:G, "强化或放宽目标（消极气候影响）") | N8: 2010 | O8: =COUNTIFS(温室气体排放!F:F, 2010, 温室气体排放!G:G, "新目标") + COUNTIFS(温室气体排放!F:F, 2010, 温室气体排放!G:G, "强化或放宽目标（气候影响不明确）") + COUNTIFS(温室气体排放!F:F, 2010, 温室气体排放!G:G, "强化或放宽目标（积极气候影响）") + COUNTIFS(温室气体排放!F:F, 2010, 温室气体排放!G:G, "强化或放宽目标（消极气候影响）") + COUNTIFS(污染!F:F, 2010, 污染!G:G, "新目标") + COUNTIFS(污染!F:F, 2010, 污染!G:G, "强化或放宽目标（气候影响不明确）") + COUNTIFS(污染!F:F, 2010, 污染!G:G, "强化或放宽目标（积极气候影响）") + COUNTIFS(污染!F:F, 2010, 污染!G:G, "强化或放宽目标（消极气候影响）") + COUNTIFS('能源|电力'!F:F, 2010, '能源|电力'!G:G, "新目标") + COUNTIFS('能源|电力'!F:F, 2010, '能源|电力'!G:G, "强化或放宽目标（气候影响不明确）") + COUNTIFS('能源|电力'!F:F, 2010, '能源|电力'!G:G, "强化或放宽目标（积极气候影响）") + COUNTIFS('能源|电力'!F:F, 2010, '能源|电力'!G:G, "强化或放宽目标（消极气候影响）") + COUNTIFS(工业!F:F, 2010, 工业!G:G, "新目标") + COUNTIFS(工业!F:F, 2010, 工业!G:G, "强化或放宽目标（气候影响不明确）") + COUNTIFS(工业!F:F, 2010, 工业!G:G, "强化或放宽目标（积极气候影响）") + COUNTIFS(工业!F:F, 2010, 工业!G:G, "强化或放宽目标（消极气候影响）") + COUNTIFS(建筑!F:F, 2010, 建筑!G:G, "新目标") + COUNTIFS(建筑!F:F, 2010, 建筑!G:G, "强化或放宽目标（气候影响不明确）") + COUNTIFS(建筑!F:F, 2010, 建筑!G:G, "强化或放宽目标（积极气候影响）") + COUNTIFS(建筑!F:F, 2010, 建筑!G:G, "强化或放宽目标（消极气候影响）") + COUNTIFS(交通!F:F, 2010, 交通!G:G, "新目标") + COUNTIFS(交通!F:F, 2010, 交通!G:G, "强化或放宽目标（气候影响不明确）") + COUNTIFS(交通!F:F, 2010, 交通!G:G, "强化或放宽目标（积极气候影响）") + COUNTIFS(交通!F:F, 2010, 交通!G:G, "强化或放宽目标（消极气候影响）") + COUNTIFS('土地利用、土地利用变化和林业'!F:F, 2010, '土地利用、土地利用变化和林业'!G:G, "新目标") + COUNTIFS('土地利用、土地利用变化和林业'!F:F, 2010, '土地利用、土地利用变化和林业'!G:G, "强化或放宽目标（气候影响不明确）") + COUNTIFS('土地利用、土地利用变化和林业'!F:F, 2010, '土地利用、土地利用变化和林业'!G:G, "强化或放宽目标（积极气候影响）") + COUNTIFS('土地利用、土地利用变化和林业'!F:F, 2010, '土地利用、土地利用变化和林业'!G:G, "强化或放宽目标（消极气候影响）") + COUNTIFS(循环经济!F:F, 2010, 循环经济!G:G, "新目标") + COUNTIFS(循环经济!F:F, 2010, 循环经济!G:G, "强化或放宽目标（气候影响不明确）") + COUNTIFS(循环经济!F:F, 2010, 循环经济!G:G, "强化或放宽目标（积极气候影响）") + COUNTIFS(循环经济!F:F, 2010, 循环经济!G:G, "强化或放宽目标（消极气候影响）") + COUNTIFS(金融!F:F, 2010, 金融!G:G, "新目标") + COUNTIFS(金融!F:F, 2010, 金融!G:G, "强化或放宽目标（气候影响不明确）") + COUNTIFS(金融!F:F, 2010, 金融!G:G, "强化或放宽目标（积极气候影响）") + COUNTIFS(金融!F:F, 2010, 金融!G:G, "强化或放宽目标（消极气候影响）") | Q8: 碳汇 | R8: =COUNTIFS(温室气体排放!H:H, "碳汇", 温室气体排放!G:G, "新目标") + COUNTIFS(温室气体排放!H:H, "碳汇", 温室气体排放!G:G, "强化或放宽目标（气候影响不明确）") + COUNTIFS(温室气体排放!H:H, "碳汇", 温室气体排放!G:G, "强化或放宽目标（积极气候影响）") + COUNTIFS(温室气体排放!H:H, "碳汇", 温室气体排放!G:G, "强化或放宽目标（消极气候影响）") + COUNTIFS(污染!H:H, "碳汇", 污染!G:G, "新目标") + COUNTIFS(污染!H:H, "碳汇", 污染!G:G, "强化或放宽目标（气候影响不明确）") + COUNTIFS(污染!H:H, "碳汇", 污染!G:G, "强化或放宽目标（积极气候影响）") + COUNTIFS(污染!H:H, "碳汇", 污染!G:G, "强化或放宽目标（消极气候影响）") + COUNTIFS('能源|电力'!H:H, "碳汇", '能源|电力'!G:G, "新目标") + COUNTIFS('能源|电力'!H:H, "碳汇", '能源|电力'!G:G, "强化或放宽目标（气候影响不明确）") + COUNTIFS('能源|电力'!H:H, "碳汇", '能源|电力'!G:G, "强化或放宽目标（积极气候影响）") + COUNTIFS('能源|电力'!H:H, "碳汇", '能源|电力'!G:G, "强化或放宽目标（消极气候影响）") + COUNTIFS(工业!H:H, "碳汇", 工业!G:G, "新目标") + COUNTIFS(工业!H:H, "碳汇", 工业!G:G, "强化或放宽目标（气候影响不明确）") + COUNTIFS(工业!H:H, "碳汇", 工业!G:G, "强化或放宽目标（积极气候影响）") + COUNTIFS(工业!H:H, "碳汇", 工业!G:G, "强化或放宽目标（消极气候影响）") + COUNTIFS(建筑!H:H, "碳汇", 建筑!G:G, "新目标") + COUNTIFS(建筑!H:H, "碳汇", 建筑!G:G, "强化或放宽目标（气候影响不明确）") + COUNTIFS(建筑!H:H, "碳汇", 建筑!G:G, "强化或放宽目标（积极气候影响）") + COUNTIFS(建筑!H:H, "碳汇", 建筑!G:G, "强化或放宽目标（消极气候影响）") + COUNTIFS(交通!H:H, "碳汇", 交通!G:G, "新目标") + COUNTIFS(交通!H:H, "碳汇", 交通!G:G, "强化或放宽目标（气候影响不明确）") + COUNTIFS(交通!H:H, "碳汇", 交通!G:G, "强化或放宽目标（积极气候影响）") + COUNTIFS(交通!H:H, "碳汇", 交通!G:G, "强化或放宽目标（消极气候影响）") + COUNTIFS('土地利用、土地利用变化和林业'!H:H, "碳汇", '土地利用、土地利用变化和林业'!G:G, "新目标") + COUNTIFS('土地利用、土地利用变化和林业'!H:H, "碳汇", '土地利用、土地利用变化和林业'!G:G, "强化或放宽目标（气候影响不明确）") + COUNTIFS('土地利用、土地利用变化和林业'!H:H, "碳汇", '土地利用、土地利用变化和林业'!G:G, "强化或放宽目标（积极气候影响）") + COUNTIFS('土地利用、土地利用变化和林业'!H:H, "碳汇", '土地利用、土地利用变化和林业'!G:G, "强化或放宽目标（消极气候影响）") + COUNTIFS(循环经济!H:H, "碳汇", 循环经济!G:G, "新目标") + COUNTIFS(循环经济!H:H, "碳汇", 循环经济!G:G, "强化或放宽目标（气候影响不明确）") + COUNTIFS(循环经济!H:H, "碳汇", 循环经济!G:G, "强化或放宽目标（积极气候影响）") + COUNTIFS(循环经济!H:H, "碳汇", 循环经济!G:G, "强化或放宽目标（消极气候影响）") + COUNTIFS(金融!H:H, "碳汇", 金融!G:G, "新目标") + COUNTIFS(金融!H:H, "碳汇", 金融!G:G, "强化或放宽目标（气候影响不明确）") + COUNTIFS(金融!H:H, "碳汇", 金融!G:G, "强化或放宽目标（积极气候影响）") + COUNTIFS(金融!H:H, "碳汇", 金融!G:G, "强化或放宽目标（消极气候影响）") | T8: 行业 | U8: =COUNTIFS(温室气体排放!I:I,"行业",温室气体排放!G:G,"新目标") +COUNTIFS(温室气体排放!I:I,"行业",温室气体排放!G:G,"强化或放宽目标（气候影响不明确）") +COUNTIFS(温室气体排放!I:I,"行业",温室气体排放!G:G,"强化或放宽目标（积极气候影响）") +COUNTIFS(温室气体排放!I:I,"行业",温室气体排放!G:G,"强化或放宽目标（消极气候影响）") +COUNTIFS(污染!I:I,"行业",污染!G:G,"新目标") +COUNTIFS(污染!I:I,"行业",污染!G:G,"强化或放宽目标（气候影响不明确）") +COUNTIFS(污染!I:I,"行业",污染!G:G,"强化或放宽目标（积极气候影响）") +COUNTIFS(污染!I:I,"行业",污染!G:G,"强化或放宽目标（消极气候影响）") +COUNTIFS('能源|电力'!I:I,"行业",'能源|电力'!G:G,"新目标") +COUNTIFS('能源|电力'!I:I,"行业",'能源|电力'!G:G,"强化或放宽目标（气候影响不明确）") +COUNTIFS('能源|电力'!I:I,"行业",'能源|电力'!G:G,"强化或放宽目标（积极气候影响）") +COUNTIFS('能源|电力'!I:I,"行业",'能源|电力'!G:G,"强化或放宽目标（消极气候影响）") +COUNTIFS(工业!I:I,"行业",工业!G:G,"新目标") +COUNTIFS(工业!I:I,"行业",工业!G:G,"强化或放宽目标（气候影响不明确）") +COUNTIFS(工业!I:I,"行业",工业!G:G,"强化或放宽目标（积极气候影响）") +COUNTIFS(工业!I:I,"行业",工业!G:G,"强化或放宽目标（消极气候影响）") +COUNTIFS(建筑!I:I,"行业",建筑!G:G,"新目标") +COUNTIFS(建筑!I:I,"行业",建筑!G:G,"强化或放宽目标（气候影响不明确）") +COUNTIFS(建筑!I:I,"行业",建筑!G:G,"强化或放宽目标（积极气候影响）") +COUNTIFS(建筑!I:I,"行业",建筑!G:G,"强化或放宽目标（消极气候影响）") +COUNTIFS(交通!I:I,"行业",交通!G:G,"新目标") +COUNTIFS(交通!I:I,"行业",交通!G:G,"强化或放宽目标（气候影响不明确）") +COUNTIFS(交通!I:I,"行业",交通!G:G,"强化或放宽目标（积极气候影响）") +COUNTIFS(交通!I:I,"行业",交通!G:G,"强化或放宽目标（消极气候影响）") +COUNTIFS('土地利用、土地利用变化和林业'!I:I,"行业",'土地利用、土地利用变化和林业'!G:G,"新目标") +COUNTIFS('土地利用、土地利用变化和林业'!I:I,"行业",'土地利用、土地利用变化和林业'!G:G,"强化或放宽目标（气候影响不明确）") +COUNTIFS('土地利用、土地利用变化和林业'!I:I,"行业",'土地利用、土地利用变化和林业'!G:G,"强化或放宽目标（积极气候影响）") +COUNTIFS('土地利用、土地利用变化和林业'!I:I,"行业",'土地利用、土地利用变化和林业'!G:G,"强化或放宽目标（消极气候影响）") +COUNTIFS(循环经济!I:I,"行业",循环经济!G:G,"新目标") +COUNTIFS(循环经济!I:I,"行业",循环经济!G:G,"强化或放宽目标（气候影响不明确）") +COUNTIFS(循环经济!I:I,"行业",循环经济!G:G,"强化或放宽目标（积极气候影响）") +COUNTIFS(循环经济!I:I,"行业",循环经济!G:G,"强化或放宽目标（消极气候影响）") +COUNTIFS(金融!I:I,"行业",金融!G:G,"新目标") +COUNTIFS(金融!I:I,"行业",金融!G:G,"强化或放宽目标（气候影响不明确）") +COUNTIFS(金融!I:I,"行业",金融!G:G,"强化或放宽目标（积极气候影响）") +COUNTIFS(金融!I:I,"行业",金融!G:G,"强化或放宽目标（消极气候影响）")
B9: 工业 | C9: =COUNTIFS(工业!G:G, "新目标") + COUNTIFS(工业!G:G, "强化或放宽目标（气候影响不明确）") + COUNTIFS(工业!G:G, "强化或放宽目标（积极气候影响）") + COUNTIFS(工业!G:G, "强化或放宽目标（消极气候影响）") | E9: 煤电 | F9: =COUNTIFS('能源|电力'!M:M, "煤电") | H9: 具有消极气候影响的强化或放宽目标 | I9: =COUNTIF(温室气体排放!G:G,"强化或放宽目标（消极气候影响）") +COUNTIF(污染!G:G,"强化或放宽目标（消极气候影响）") +COUNTIF('能源|电力'!G:G,"强化或放宽目标（消极气候影响）") +COUNTIF(工业!G:G,"强化或放宽目标（消极气候影响）") +COUNTIF(建筑!G:G,"强化或放宽目标（消极气候影响）") +COUNTIF(交通!G:G,"强化或放宽目标（消极气候影响）") +COUNTIF('土地利用、土地利用变化和林业'!G:G,"强化或放宽目标（消极气候影响）") +COUNTIF(循环经济!G:G,"强化或放宽目标（消极气候影响）") +COUNTIF(金融!G:G,"强化或放宽目标（消极气候影响）") | K9: 2007 | L9: =COUNTIFS(温室气体排放!A:A, 2007, 温室气体排放!G:G, "新目标") + COUNTIFS(温室气体排放!A:A, 2007, 温室气体排放!G:G, "强化或放宽目标（气候影响不明确）") + COUNTIFS(温室气体排放!A:A, 2007, 温室气体排放!G:G, "强化或放宽目标（积极气候影响）") + COUNTIFS(温室气体排放!A:A, 2007, 温室气体排放!G:G, "强化或放宽目标（消极气候影响）") + COUNTIFS(污染!A:A, 2007, 污染!G:G, "新目标") + COUNTIFS(污染!A:A, 2007, 污染!G:G, "强化或放宽目标（气候影响不明确）") + COUNTIFS(污染!A:A, 2007, 污染!G:G, "强化或放宽目标（积极气候影响）") + COUNTIFS(污染!A:A, 2007, 污染!G:G, "强化或放宽目标（消极气候影响）") + COUNTIFS('能源|电力'!A:A, 2007, '能源|电力'!G:G, "新目标") + COUNTIFS('能源|电力'!A:A, 2007, '能源|电力'!G:G, "强化或放宽目标（气候影响不明确）") + COUNTIFS('能源|电力'!A:A, 2007, '能源|电力'!G:G, "强化或放宽目标（积极气候影响）") + COUNTIFS('能源|电力'!A:A, 2007, '能源|电力'!G:G, "强化或放宽目标（消极气候影响）") + COUNTIFS(工业!A:A, 2007, 工业!G:G, "新目标") + COUNTIFS(工业!A:A, 2007, 工业!G:G, "强化或放宽目标（气候影响不明确）") + COUNTIFS(工业!A:A, 2007, 工业!G:G, "强化或放宽目标（积极气候影响）") + COUNTIFS(工业!A:A, 2007, 工业!G:G, "强化或放宽目标（消极气候影响）") + COUNTIFS(建筑!A:A, 2007, 建筑!G:G, "新目标") + COUNTIFS(建筑!A:A, 2007, 建筑!G:G, "强化或放宽目标（气候影响不明确）") + COUNTIFS(建筑!A:A, 2007, 建筑!G:G, "强化或放宽目标（积极气候影响）") + COUNTIFS(建筑!A:A, 2007, 建筑!G:G, "强化或放宽目标（消极气候影响）") + COUNTIFS(交通!A:A, 2007, 交通!G:G, "新目标") + COUNTIFS(交通!A:A, 2007, 交通!G:G, "强化或放宽目标（气候影响不明确）") + COUNTIFS(交通!A:A, 2007, 交通!G:G, "强化或放宽目标（积极气候影响）") + COUNTIFS(交通!A:A, 2007, 交通!G:G, "强化或放宽目标（消极气候影响）") + COUNTIFS('土地利用、土地利用变化和林业'!A:A, 2007, '土地利用、土地利用变化和林业'!G:G, "新目标") + COUNTIFS('土地利用、土地利用变化和林业'!A:A, 2007, '土地利用、土地利用变化和林业'!G:G, "强化或放宽目标（气候影响不明确）") + COUNTIFS('土地利用、土地利用变化和林业'!A:A, 2007, '土地利用、土地利用变化和林业'!G:G, "强化或放宽目标（积极气候影响）") + COUNTIFS('土地利用、土地利用变化和林业'!A:A, 2007, '土地利用、土地利用变化和林业'!G:G, "强化或放宽目标（消极气候影响）") + COUNTIFS(循环经济!A:A, 2007, 循环经济!G:G, "新目标") + COUNTIFS(循环经济!A:A, 2007, 循环经济!G:G, "强化或放宽目标（气候影响不明确）") + COUNTIFS(循环经济!A:A, 2007, 循环经济!G:G, "强化或放宽目标（积极气候影响）") + COUNTIFS(循环经济!A:A, 2007, 循环经济!G:G, "强化或放宽目标（消极气候影响）") + COUNTIFS(金融!A:A, 2007, 金融!G:G, "新目标") + COUNTIFS(金融!A:A, 2007, 金融!G:G, "强化或放宽目标（气候影响不明确）") + COUNTIFS(金融!A:A, 2007, 金融!G:G, "强化或放宽目标（积极气候影响）") + COUNTIFS(金融!A:A, 2007, 金融!G:G, "强化或放宽目标（消极气候影响）") | N9: 十一五 | O9: =COUNTIFS(温室气体排放!F:F, "十一五", 温室气体排放!G:G, "新目标") + COUNTIFS(温室气体排放!F:F, "十一五", 温室气体排放!G:G, "强化或放宽目标（气候影响不明确）") + COUNTIFS(温室气体排放!F:F, "十一五", 温室气体排放!G:G, "强化或放宽目标（积极气候影响）") + COUNTIFS(温室气体排放!F:F, "十一五", 温室气体排放!G:G, "强化或放宽目标（消极气候影响）") + COUNTIFS(污染!F:F, "十一五", 污染!G:G, "新目标") + COUNTIFS(污染!F:F, "十一五", 污染!G:G, "强化或放宽目标（气候影响不明确）") + COUNTIFS(污染!F:F, "十一五", 污染!G:G, "强化或放宽目标（积极气候影响）") + COUNTIFS(污染!F:F, "十一五", 污染!G:G, "强化或放宽目标（消极气候影响）") + COUNTIFS('能源|电力'!F:F, "十一五", '能源|电力'!G:G, "新目标") + COUNTIFS('能源|电力'!F:F, "十一五", '能源|电力'!G:G, "强化或放宽目标（气候影响不明确）") + COUNTIFS('能源|电力'!F:F, "十一五", '能源|电力'!G:G, "强化或放宽目标（积极气候影响）") + COUNTIFS('能源|电力'!F:F, "十一五", '能源|电力'!G:G, "强化或放宽目标（消极气候影响）") + COUNTIFS(工业!F:F, "十一五", 工业!G:G, "新目标") + COUNTIFS(工业!F:F, "十一五", 工业!G:G, "强化或放宽目标（气候影响不明确）") + COUNTIFS(工业!F:F, "十一五", 工业!G:G, "强化或放宽目标（积极气候影响）") + COUNTIFS(工业!F:F, "十一五", 工业!G:G, "强化或放宽目标（消极气候影响）") + COUNTIFS(建筑!F:F, "十一五", 建筑!G:G, "新目标") + COUNTIFS(建筑!F:F, "十一五", 建筑!G:G, "强化或放宽目标（气候影响不明确）") + COUNTIFS(建筑!F:F, "十一五", 建筑!G:G, "强化或放宽目标（积极气候影响）") + COUNTIFS(建筑!F:F, "十一五", 建筑!G:G, "强化或放宽目标（消极气候影响）") + COUNTIFS(交通!F:F, "十一五", 交通!G:G, "新目标") + COUNTIFS(交通!F:F, "十一五", 交通!G:G, "强化或放宽目标（气候影响不明确）") + COUNTIFS(交通!F:F, "十一五", 交通!G:G, "强化或放宽目标（积极气候影响）") + COUNTIFS(交通!F:F, "十一五", 交通!G:G, "强化或放宽目标（消极气候影响）") + COUNTIFS('土地利用、土地利用变化和林业'!F:F, "十一五", '土地利用、土地利用变化和林业'!G:G, "新目标") + COUNTIFS('土地利用、土地利用变化和林业'!F:F, "十一五", '土地利用、土地利用变化和林业'!G:G, "强化或放宽目标（气候影响不明确）") + COUNTIFS('土地利用、土地利用变化和林业'!F:F, "十一五", '土地利用、土地利用变化和林业'!G:G, "强化或放宽目标（积极气候影响）") + COUNTIFS('土地利用、土地利用变化和林业'!F:F, "十一五", '土地利用、土地利用变化和林业'!G:G, "强化或放宽目标（消极气候影响）") + COUNTIFS(循环经济!F:F, "十一五", 循环经济!G:G, "新目标") + COUNTIFS(循环经济!F:F, "十一五", 循环经济!G:G, "强化或放宽目标（气候影响不明确）") + COUNTIFS(循环经济!F:F, "十一五", 循环经济!G:G, "强化或放宽目标（积极气候影响）") + COUNTIFS(循环经济!F:F, "十一五", 循环经济!G:G, "强化或放宽目标（消极气候影响）") + COUNTIFS(金融!F:F, "十一五", 金融!G:G, "新目标") + COUNTIFS(金融!F:F, "十一五", 金融!G:G, "强化或放宽目标（气候影响不明确）") + COUNTIFS(金融!F:F, "十一五", 金融!G:G, "强化或放宽目标（积极气候影响）") + COUNTIFS(金融!F:F, "十一五", 金融!G:G, "强化或放宽目标（消极气候影响）") | Q9: 污染控制 | R9: =COUNTIFS(温室气体排放!H:H, "污染控制", 温室气体排放!G:G, "新目标") + COUNTIFS(温室气体排放!H:H, "污染控制", 温室气体排放!G:G, "强化或放宽目标（气候影响不明确）") + COUNTIFS(温室气体排放!H:H, "污染控制", 温室气体排放!G:G, "强化或放宽目标（积极气候影响）") + COUNTIFS(温室气体排放!H:H, "污染控制", 温室气体排放!G:G, "强化或放宽目标（消极气候影响）") + COUNTIFS(污染!H:H, "污染控制", 污染!G:G, "新目标") + COUNTIFS(污染!H:H, "污染控制", 污染!G:G, "强化或放宽目标（气候影响不明确）") + COUNTIFS(污染!H:H, "污染控制", 污染!G:G, "强化或放宽目标（积极气候影响）") + COUNTIFS(污染!H:H, "污染控制", 污染!G:G, "强化或放宽目标（消极气候影响）") + COUNTIFS('能源|电力'!H:H, "污染控制", '能源|电力'!G:G, "新目标") + COUNTIFS('能源|电力'!H:H, "污染控制", '能源|电力'!G:G, "强化或放宽目标（气候影响不明确）") + COUNTIFS('能源|电力'!H:H, "污染控制", '能源|电力'!G:G, "强化或放宽目标（积极气候影响）") + COUNTIFS('能源|电力'!H:H, "污染控制", '能源|电力'!G:G, "强化或放宽目标（消极气候影响）") + COUNTIFS(工业!H:H, "污染控制", 工业!G:G, "新目标") + COUNTIFS(工业!H:H, "污染控制", 工业!G:G, "强化或放宽目标（气候影响不明确）") + COUNTIFS(工业!H:H, "污染控制", 工业!G:G, "强化或放宽目标（积极气候影响）") + COUNTIFS(工业!H:H, "污染控制", 工业!G:G, "强化或放宽目标（消极气候影响）") + COUNTIFS(建筑!H:H, "污染控制", 建筑!G:G, "新目标") + COUNTIFS(建筑!H:H, "污染控制", 建筑!G:G, "强化或放宽目标（气候影响不明确）") + COUNTIFS(建筑!H:H, "污染控制", 建筑!G:G, "强化或放宽目标（积极气候影响）") + COUNTIFS(建筑!H:H, "污染控制", 建筑!G:G, "强化或放宽目标（消极气候影响）") + COUNTIFS(交通!H:H, "污染控制", 交通!G:G, "新目标") + COUNTIFS(交通!H:H, "污染控制", 交通!G:G, "强化或放宽目标（气候影响不明确）") + COUNTIFS(交通!H:H, "污染控制", 交通!G:G, "强化或放宽目标（积极气候影响）") + COUNTIFS(交通!H:H, "污染控制", 交通!G:G, "强化或放宽目标（消极气候影响）") + COUNTIFS('土地利用、土地利用变化和林业'!H:H, "污染控制", '土地利用、土地利用变化和林业'!G:G, "新目标") + COUNTIFS('土地利用、土地利用变化和林业'!H:H, "污染控制", '土地利用、土地利用变化和林业'!G:G, "强化或放宽目标（气候影响不明确）") + COUNTIFS('土地利用、土地利用变化和林业'!H:H, "污染控制", '土地利用、土地利用变化和林业'!G:G, "强化或放宽目标（积极气候影响）") + COUNTIFS('土地利用、土地利用变化和林业'!H:H, "污染控制", '土地利用、土地利用变化和林业'!G:G, "强化或放宽目标（消极气候影响）") + COUNTIFS(循环经济!H:H, "污染控制", 循环经济!G:G, "新目标") + COUNTIFS(循环经济!H:H, "污染控制", 循环经济!G:G, "强化或放宽目标（气候影响不明确）") + COUNTIFS(循环经济!H:H, "污染控制", 循环经济!G:G, "强化或放宽目标（积极气候影响）") + COUNTIFS(循环经济!H:H, "污染控制", 循环经济!G:G, "强化或放宽目标（消极气候影响）") + COUNTIFS(金融!H:H, "污染控制", 金融!G:G, "新目标") + COUNTIFS(金融!H:H, "污染控制", 金融!G:G, "强化或放宽目标（气候影响不明确）") + COUNTIFS(金融!H:H, "污染控制", 金融!G:G, "强化或放宽目标（积极气候影响）") + COUNTIFS(金融!H:H, "污染控制", 金融!G:G, "强化或放宽目标（消极气候影响）") | T9: 全社会经济 | U9: =COUNTIFS(温室气体排放!I:I,"全社会经济",温室气体排放!G:G,"新目标") +COUNTIFS(温室气体排放!I:I,"全社会经济",温室气体排放!G:G,"强化或放宽目标（气候影响不明确）") +COUNTIFS(温室气体排放!I:I,"全社会经济",温室气体排放!G:G,"强化或放宽目标（积极气候影响）") +COUNTIFS(温室气体排放!I:I,"全社会经济",温室气体排放!G:G,"强化或放宽目标（消极气候影响）") +COUNTIFS(污染!I:I,"全社会经济",污染!G:G,"新目标") +COUNTIFS(污染!I:I,"全社会经济",污染!G:G,"强化或放宽目标（气候影响不明确）") +COUNTIFS(污染!I:I,"全社会经济",污染!G:G,"强化或放宽目标（积极气候影响）") +COUNTIFS(污染!I:I,"全社会经济",污染!G:G,"强化或放宽目标（消极气候影响）") +COUNTIFS('能源|电力'!I:I,"全社会经济",'能源|电力'!G:G,"新目标") +COUNTIFS('能源|电力'!I:I,"全社会经济",'能源|电力'!G:G,"强化或放宽目标（气候影响不明确）") +COUNTIFS('能源|电力'!I:I,"全社会经济",'能源|电力'!G:G,"强化或放宽目标（积极气候影响）") +COUNTIFS('能源|电力'!I:I,"全社会经济",'能源|电力'!G:G,"强化或放宽目标（消极气候影响）") +COUNTIFS(工业!I:I,"全社会经济",工业!G:G,"新目标") +COUNTIFS(工业!I:I,"全社会经济",工业!G:G,"强化或放宽目标（气候影响不明确）") +COUNTIFS(工业!I:I,"全社会经济",工业!G:G,"强化或放宽目标（积极气候影响）") +COUNTIFS(工业!I:I,"全社会经济",工业!G:G,"强化或放宽目标（消极气候影响）") +COUNTIFS(建筑!I:I,"全社会经济",建筑!G:G,"新目标") +COUNTIFS(建筑!I:I,"全社会经济",建筑!G:G,"强化或放宽目标（气候影响不明确）") +COUNTIFS(建筑!I:I,"全社会经济",建筑!G:G,"强化或放宽目标（积极气候影响）") +COUNTIFS(建筑!I:I,"全社会经济",建筑!G:G,"强化或放宽目标（消极气候影响）") +COUNTIFS(交通!I:I,"全社会经济",交通!G:G,"新目标") +COUNTIFS(交通!I:I,"全社会经济",交通!G:G,"强化或放宽目标（气候影响不明确）") +COUNTIFS(交通!I:I,"全社会经济",交通!G:G,"强化或放宽目标（积极气候影响）") +COUNTIFS(交通!I:I,"全社会经济",交通!G:G,"强化或放宽目标（消极气候影响）") +COUNTIFS('土地利用、土地利用变化和林业'!I:I,"全社会经济",'土地利用、土地利用变化和林业'!G:G,"新目标") +COUNTIFS('土地利用、土地利用变化和林业'!I:I,"全社会经济",'土地利用、土地利用变化和林业'!G:G,"强化或放宽目标（气候影响不明确）") +COUNTIFS('土地利用、土地利用变化和林业'!I:I,"全社会经济",'土地利用、土地利用变化和林业'!G:G,"强化或放宽目标（积极气候影响）") +COUNTIFS('土地利用、土地利用变化和林业'!I:I,"全社会经济",'土地利用、土地利用变化和林业'!G:G,"强化或放宽目标（消极气候影响）") +COUNTIFS(循环经济!I:I,"全社会经济",循环经济!G:G,"新目标") +COUNTIFS(循环经济!I:I,"全社会经济",循环经济!G:G,"强化或放宽目标（气候影响不明确）") +COUNTIFS(循环经济!I:I,"全社会经济",循环经济!G:G,"强化或放宽目标（积极气候影响）") +COUNTIFS(循环经济!I:I,"全社会经济",循环经济!G:G,"强化或放宽目标（消极气候影响）") +COUNTIFS(金融!I:I,"全社会经济",金融!G:G,"新目标") +COUNTIFS(金融!I:I,"全社会经济",金融!G:G,"强化或放宽目标（气候影响不明确）") +COUNTIFS(金融!I:I,"全社会经济",金融!G:G,"强化或放宽目标（积极气候影响）") +COUNTIFS(金融!I:I,"全社会经济",金融!G:G,"强化或放宽目标（消极气候影响）")
B10: 建筑 | C10: =COUNTIFS(建筑!G:G, "新目标") + COUNTIFS(建筑!G:G, "强化或放宽目标（气候影响不明确）") + COUNTIFS(建筑!G:G, "强化或放宽目标（积极气候影响）") + COUNTIFS(建筑!G:G, "强化或放宽目标（消极气候影响）") | E10: 化石燃料储量 | F10: =COUNTIFS('能源|电力'!M:M, "化石燃料储量") | K10: 2008 | L10: =COUNTIFS(温室气体排放!A:A, 2008, 温室气体排放!G:G, "新目标") + COUNTIFS(温室气体排放!A:A, 2008, 温室气体排放!G:G, "强化或放宽目标（气候影响不明确）") + COUNTIFS(温室气体排放!A:A, 2008, 温室气体排放!G:G, "强化或放宽目标（积极气候影响）") + COUNTIFS(温室气体排放!A:A, 2008, 温室气体排放!G:G, "强化或放宽目标（消极气候影响）") + COUNTIFS(污染!A:A, 2008, 污染!G:G, "新目标") + COUNTIFS(污染!A:A, 2008, 污染!G:G, "强化或放宽目标（气候影响不明确）") + COUNTIFS(污染!A:A, 2008, 污染!G:G, "强化或放宽目标（积极气候影响）") + COUNTIFS(污染!A:A, 2008, 污染!G:G, "强化或放宽目标（消极气候影响）") + COUNTIFS('能源|电力'!A:A, 2008, '能源|电力'!G:G, "新目标") + COUNTIFS('能源|电力'!A:A, 2008, '能源|电力'!G:G, "强化或放宽目标（气候影响不明确）") + COUNTIFS('能源|电力'!A:A, 2008, '能源|电力'!G:G, "强化或放宽目标（积极气候影响）") + COUNTIFS('能源|电力'!A:A, 2008, '能源|电力'!G:G, "强化或放宽目标（消极气候影响）") + COUNTIFS(工业!A:A, 2008, 工业!G:G, "新目标") + COUNTIFS(工业!A:A, 2008, 工业!G:G, "强化或放宽目标（气候影响不明确）") + COUNTIFS(工业!A:A, 2008, 工业!G:G, "强化或放宽目标（积极气候影响）") + COUNTIFS(工业!A:A, 2008, 工业!G:G, "强化或放宽目标（消极气候影响）") + COUNTIFS(建筑!A:A, 2008, 建筑!G:G, "新目标") + COUNTIFS(建筑!A:A, 2008, 建筑!G:G, "强化或放宽目标（气候影响不明确）") + COUNTIFS(建筑!A:A, 2008, 建筑!G:G, "强化或放宽目标（积极气候影响）") + COUNTIFS(建筑!A:A, 2008, 建筑!G:G, "强化或放宽目标（消极气候影响）") + COUNTIFS(交通!A:A, 2008, 交通!G:G, "新目标") + COUNTIFS(交通!A:A, 2008, 交通!G:G, "强化或放宽目标（气候影响不明确）") + COUNTIFS(交通!A:A, 2008, 交通!G:G, "强化或放宽目标（积极气候影响）") + COUNTIFS(交通!A:A, 2008, 交通!G:G, "强化或放宽目标（消极气候影响）") + COUNTIFS('土地利用、土地利用变化和林业'!A:A, 2008, '土地利用、土地利用变化和林业'!G:G, "新目标") + COUNTIFS('土地利用、土地利用变化和林业'!A:A, 2008, '土地利用、土地利用变化和林业'!G:G, "强化或放宽目标（气候影响不明确）") + COUNTIFS('土地利用、土地利用变化和林业'!A:A, 2008, '土地利用、土地利用变化和林业'!G:G, "强化或放宽目标（积极气候影响）") + COUNTIFS('土地利用、土地利用变化和林业'!A:A, 2008, '土地利用、土地利用变化和林业'!G:G, "强化或放宽目标（消极气候影响）") + COUNTIFS(循环经济!A:A, 2008, 循环经济!G:G, "新目标") + COUNTIFS(循环经济!A:A, 2008, 循环经济!G:G, "强化或放宽目标（气候影响不明确）") + COUNTIFS(循环经济!A:A, 2008, 循环经济!G:G, "强化或放宽目标（积极气候影响）") + COUNTIFS(循环经济!A:A, 2008, 循环经济!G:G, "强化或放宽目标（消极气候影响）") + COUNTIFS(金融!A:A, 2008, 金融!G:G, "新目标") + COUNTIFS(金融!A:A, 2008, 金融!G:G, "强化或放宽目标（气候影响不明确）") + COUNTIFS(金融!A:A, 2008, 金融!G:G, "强化或放宽目标（积极气候影响）") + COUNTIFS(金融!A:A, 2008, 金融!G:G, "强化或放宽目标（消极气候影响）") | N10: 2011 | O10: =COUNTIFS(温室气体排放!F:F, 2011, 温室气体排放!G:G, "新目标") + COUNTIFS(温室气体排放!F:F, 2011, 温室气体排放!G:G, "强化或放宽目标（气候影响不明确）") + COUNTIFS(温室气体排放!F:F, 2011, 温室气体排放!G:G, "强化或放宽目标（积极气候影响）") + COUNTIFS(温室气体排放!F:F, 2011, 温室气体排放!G:G, "强化或放宽目标（消极气候影响）") + COUNTIFS(污染!F:F, 2011, 污染!G:G, "新目标") + COUNTIFS(污染!F:F, 2011, 污染!G:G, "强化或放宽目标（气候影响不明确）") + COUNTIFS(污染!F:F, 2011, 污染!G:G, "强化或放宽目标（积极气候影响）") + COUNTIFS(污染!F:F, 2011, 污染!G:G, "强化或放宽目标（消极气候影响）") + COUNTIFS('能源|电力'!F:F, 2011, '能源|电力'!G:G, "新目标") + COUNTIFS('能源|电力'!F:F, 2011, '能源|电力'!G:G, "强化或放宽目标（气候影响不明确）") + COUNTIFS('能源|电力'!F:F, 2011, '能源|电力'!G:G, "强化或放宽目标（积极气候影响）") + COUNTIFS('能源|电力'!F:F, 2011, '能源|电力'!G:G, "强化或放宽目标（消极气候影响）") + COUNTIFS(工业!F:F, 2011, 工业!G:G, "新目标") + COUNTIFS(工业!F:F, 2011, 工业!G:G, "强化或放宽目标（气候影响不明确）") + COUNTIFS(工业!F:F, 2011, 工业!G:G, "强化或放宽目标（积极气候影响）") + COUNTIFS(工业!F:F, 2011, 工业!G:G, "强化或放宽目标（消极气候影响）") + COUNTIFS(建筑!F:F, 2011, 建筑!G:G, "新目标") + COUNTIFS(建筑!F:F, 2011, 建筑!G:G, "强化或放宽目标（气候影响不明确）") + COUNTIFS(建筑!F:F, 2011, 建筑!G:G, "强化或放宽目标（积极气候影响）") + COUNTIFS(建筑!F:F, 2011, 建筑!G:G, "强化或放宽目标（消极气候影响）") + COUNTIFS(交通!F:F, 2011, 交通!G:G, "新目标") + COUNTIFS(交通!F:F, 2011, 交通!G:G, "强化或放宽目标（气候影响不明确）") + COUNTIFS(交通!F:F, 2011, 交通!G:G, "强化或放宽目标（积极气候影响）") + COUNTIFS(交通!F:F, 2011, 交通!G:G, "强化或放宽目标（消极气候影响）") + COUNTIFS('土地利用、土地利用变化和林业'!F:F, 2011, '土地利用、土地利用变化和林业'!G:G, "新目标") + COUNTIFS('土地利用、土地利用变化和林业'!F:F, 2011, '土地利用、土地利用变化和林业'!G:G, "强化或放宽目标（气候影响不明确）") + COUNTIFS('土地利用、土地利用变化和林业'!F:F, 2011, '土地利用、土地利用变化和林业'!G:G, "强化或放宽目标（积极气候影响）") + COUNTIFS('土地利用、土地利用变化和林业'!F:F, 2011, '土地利用、土地利用变化和林业'!G:G, "强化或放宽目标（消极气候影响）") + COUNTIFS(循环经济!F:F, 2011, 循环经济!G:G, "新目标") + COUNTIFS(循环经济!F:F, 2011, 循环经济!G:G, "强化或放宽目标（气候影响不明确）") + COUNTIFS(循环经济!F:F, 2011, 循环经济!G:G, "强化或放宽目标（积极气候影响）") + COUNTIFS(循环经济!F:F, 2011, 循环经济!G:G, "强化或放宽目标（消极气候影响）") + COUNTIFS(金融!F:F, 2011, 金融!G:G, "新目标") + COUNTIFS(金融!F:F, 2011, 金融!G:G, "强化或放宽目标（气候影响不明确）") + COUNTIFS(金融!F:F, 2011, 金融!G:G, "强化或放宽目标（积极气候影响）") + COUNTIFS(金融!F:F, 2011, 金融!G:G, "强化或放宽目标（消极气候影响）") | Q10: 节能 | R10: =COUNTIFS(温室气体排放!H:H, "节能", 温室气体排放!G:G, "新目标") + COUNTIFS(温室气体排放!H:H, "节能", 温室气体排放!G:G, "强化或放宽目标（气候影响不明确）") + COUNTIFS(温室气体排放!H:H, "节能", 温室气体排放!G:G, "强化或放宽目标（积极气候影响）") + COUNTIFS(温室气体排放!H:H, "节能", 温室气体排放!G:G, "强化或放宽目标（消极气候影响）") + COUNTIFS(污染!H:H, "节能", 污染!G:G, "新目标") + COUNTIFS(污染!H:H, "节能", 污染!G:G, "强化或放宽目标（气候影响不明确）") + COUNTIFS(污染!H:H, "节能", 污染!G:G, "强化或放宽目标（积极气候影响）") + COUNTIFS(污染!H:H, "节能", 污染!G:G, "强化或放宽目标（消极气候影响）") + COUNTIFS('能源|电力'!H:H, "节能", '能源|电力'!G:G, "新目标") + COUNTIFS('能源|电力'!H:H, "节能", '能源|电力'!G:G, "强化或放宽目标（气候影响不明确）") + COUNTIFS('能源|电力'!H:H, "节能", '能源|电力'!G:G, "强化或放宽目标（积极气候影响）") + COUNTIFS('能源|电力'!H:H, "节能", '能源|电力'!G:G, "强化或放宽目标（消极气候影响）") + COUNTIFS(工业!H:H, "节能", 工业!G:G, "新目标") + COUNTIFS(工业!H:H, "节能", 工业!G:G, "强化或放宽目标（气候影响不明确）") + COUNTIFS(工业!H:H, "节能", 工业!G:G, "强化或放宽目标（积极气候影响）") + COUNTIFS(工业!H:H, "节能", 工业!G:G, "强化或放宽目标（消极气候影响）") + COUNTIFS(建筑!H:H, "节能", 建筑!G:G, "新目标") + COUNTIFS(建筑!H:H, "节能", 建筑!G:G, "强化或放宽目标（气候影响不明确）") + COUNTIFS(建筑!H:H, "节能", 建筑!G:G, "强化或放宽目标（积极气候影响）") + COUNTIFS(建筑!H:H, "节能", 建筑!G:G, "强化或放宽目标（消极气候影响）") + COUNTIFS(交通!H:H, "节能", 交通!G:G, "新目标") + COUNTIFS(交通!H:H, "节能", 交通!G:G, "强化或放宽目标（气候影响不明确）") + COUNTIFS(交通!H:H, "节能", 交通!G:G, "强化或放宽目标（积极气候影响）") + COUNTIFS(交通!H:H, "节能", 交通!G:G, "强化或放宽目标（消极气候影响）") + COUNTIFS('土地利用、土地利用变化和林业'!H:H, "节能", '土地利用、土地利用变化和林业'!G:G, "新目标") + COUNTIFS('土地利用、土地利用变化和林业'!H:H, "节能", '土地利用、土地利用变化和林业'!G:G, "强化或放宽目标（气候影响不明确）") + COUNTIFS('土地利用、土地利用变化和林业'!H:H, "节能", '土地利用、土地利用变化和林业'!G:G, "强化或放宽目标（积极气候影响）") + COUNTIFS('土地利用、土地利用变化和林业'!H:H, "节能", '土地利用、土地利用变化和林业'!G:G, "强化或放宽目标（消极气候影响）") + COUNTIFS(循环经济!H:H, "节能", 循环经济!G:G, "新目标") + COUNTIFS(循环经济!H:H, "节能", 循环经济!G:G, "强化或放宽目标（气候影响不明确）") + COUNTIFS(循环经济!H:H, "节能", 循环经济!G:G, "强化或放宽目标（积极气候影响）") + COUNTIFS(循环经济!H:H, "节能", 循环经济!G:G, "强化或放宽目标（消极气候影响）") + COUNTIFS(金融!H:H, "节能", 金融!G:G, "新目标") + COUNTIFS(金融!H:H, "节能", 金融!G:G, "强化或放宽目标（气候影响不明确）") + COUNTIFS(金融!H:H, "节能", 金融!G:G, "强化或放宽目标（积极气候影响）") + COUNTIFS(金融!H:H, "节能", 金融!G:G, "强化或放宽目标（消极气候影响）") | T10: 不明确 | U10: =COUNTIFS(温室气体排放!I:I,"不明确",温室气体排放!G:G,"新目标") +COUNTIFS(温室气体排放!I:I,"不明确",温室气体排放!G:G,"强化或放宽目标（气候影响不明确）") +COUNTIFS(温室气体排放!I:I,"不明确",温室气体排放!G:G,"强化或放宽目标（积极气候影响）") +COUNTIFS(温室气体排放!I:I,"不明确",温室气体排放!G:G,"强化或放宽目标（消极气候影响）") +COUNTIFS(污染!I:I,"不明确",污染!G:G,"新目标") +COUNTIFS(污染!I:I,"不明确",污染!G:G,"强化或放宽目标（气候影响不明确）") +COUNTIFS(污染!I:I,"不明确",污染!G:G,"强化或放宽目标（积极气候影响）") +COUNTIFS(污染!I:I,"不明确",污染!G:G,"强化或放宽目标（消极气候影响）") +COUNTIFS('能源|电力'!I:I,"不明确",'能源|电力'!G:G,"新目标") +COUNTIFS('能源|电力'!I:I,"不明确",'能源|电力'!G:G,"强化或放宽目标（气候影响不明确）") +COUNTIFS('能源|电力'!I:I,"不明确",'能源|电力'!G:G,"强化或放宽目标（积极气候影响）") +COUNTIFS('能源|电力'!I:I,"不明确",'能源|电力'!G:G,"强化或放宽目标（消极气候影响）") +COUNTIFS(工业!I:I,"不明确",工业!G:G,"新目标") +COUNTIFS(工业!I:I,"不明确",工业!G:G,"强化或放宽目标（气候影响不明确）") +COUNTIFS(工业!I:I,"不明确",工业!G:G,"强化或放宽目标（积极气候影响）") +COUNTIFS(工业!I:I,"不明确",工业!G:G,"强化或放宽目标（消极气候影响）") +COUNTIFS(建筑!I:I,"不明确",建筑!G:G,"新目标") +COUNTIFS(建筑!I:I,"不明确",建筑!G:G,"强化或放宽目标（气候影响不明确）") +COUNTIFS(建筑!I:I,"不明确",建筑!G:G,"强化或放宽目标（积极气候影响）") +COUNTIFS(建筑!I:I,"不明确",建筑!G:G,"强化或放宽目标（消极气候影响）") +COUNTIFS(交通!I:I,"不明确",交通!G:G,"新目标") +COUNTIFS(交通!I:I,"不明确",交通!G:G,"强化或放宽目标（气候影响不明确）") +COUNTIFS(交通!I:I,"不明确",交通!G:G,"强化或放宽目标（积极气候影响）") +COUNTIFS(交通!I:I,"不明确",交通!G:G,"强化或放宽目标（消极气候影响）") +COUNTIFS('土地利用、土地利用变化和林业'!I:I,"不明确",'土地利用、土地利用变化和林业'!G:G,"新目标") +COUNTIFS('土地利用、土地利用变化和林业'!I:I,"不明确",'土地利用、土地利用变化和林业'!G:G,"强化或放宽目标（气候影响不明确）") +COUNTIFS('土地利用、土地利用变化和林业'!I:I,"不明确",'土地利用、土地利用变化和林业'!G:G,"强化或放宽目标（积极气候影响）") +COUNTIFS('土地利用、土地利用变化和林业'!I:I,"不明确",'土地利用、土地利用变化和林业'!G:G,"强化或放宽目标（消极气候影响）") +COUNTIFS(循环经济!I:I,"不明确",循环经济!G:G,"新目标") +COUNTIFS(循环经济!I:I,"不明确",循环经济!G:G,"强化或放宽目标（气候影响不明确）") +COUNTIFS(循环经济!I:I,"不明确",循环经济!G:G,"强化或放宽目标（积极气候影响）") +COUNTIFS(循环经济!I:I,"不明确",循环经济!G:G,"强化或放宽目标（消极气候影响）") +COUNTIFS(金融!I:I,"不明确",金融!G:G,"新目标") +COUNTIFS(金融!I:I,"不明确",金融!G:G,"强化或放宽目标（气候影响不明确）") +COUNTIFS(金融!I:I,"不明确",金融!G:G,"强化或放宽目标（积极气候影响）") +COUNTIFS(金融!I:I,"不明确",金融!G:G,"强化或放宽目标（消极气候影响）")
B11: 交通 | C11: =COUNTIFS(交通!G:G, "新目标") + COUNTIFS(交通!G:G, "强化或放宽目标（气候影响不明确）") + COUNTIFS(交通!G:G, "强化或放宽目标（积极气候影响）") + COUNTIFS(交通!G:G, "强化或放宽目标（消极气候影响）") | E11: 其他 | F11: =COUNTIFS('能源|电力'!M:M, "其他") | K11: 2009 | L11: =COUNTIFS(温室气体排放!A:A, 2009, 温室气体排放!G:G, "新目标") + COUNTIFS(温室气体排放!A:A, 2009, 温室气体排放!G:G, "强化或放宽目标（气候影响不明确）") + COUNTIFS(温室气体排放!A:A, 2009, 温室气体排放!G:G, "强化或放宽目标（积极气候影响）") + COUNTIFS(温室气体排放!A:A, 2009, 温室气体排放!G:G, "强化或放宽目标（消极气候影响）") + COUNTIFS(污染!A:A, 2009, 污染!G:G, "新目标") + COUNTIFS(污染!A:A, 2009, 污染!G:G, "强化或放宽目标（气候影响不明确）") + COUNTIFS(污染!A:A, 2009, 污染!G:G, "强化或放宽目标（积极气候影响）") + COUNTIFS(污染!A:A, 2009, 污染!G:G, "强化或放宽目标（消极气候影响）") + COUNTIFS('能源|电力'!A:A, 2009, '能源|电力'!G:G, "新目标") + COUNTIFS('能源|电力'!A:A, 2009, '能源|电力'!G:G, "强化或放宽目标（气候影响不明确）") + COUNTIFS('能源|电力'!A:A, 2009, '能源|电力'!G:G, "强化或放宽目标（积极气候影响）") + COUNTIFS('能源|电力'!A:A, 2009, '能源|电力'!G:G, "强化或放宽目标（消极气候影响）") + COUNTIFS(工业!A:A, 2009, 工业!G:G, "新目标") + COUNTIFS(工业!A:A, 2009, 工业!G:G, "强化或放宽目标（气候影响不明确）") + COUNTIFS(工业!A:A, 2009, 工业!G:G, "强化或放宽目标（积极气候影响）") + COUNTIFS(工业!A:A, 2009, 工业!G:G, "强化或放宽目标（消极气候影响）") + COUNTIFS(建筑!A:A, 2009, 建筑!G:G, "新目标") + COUNTIFS(建筑!A:A, 2009, 建筑!G:G, "强化或放宽目标（气候影响不明确）") + COUNTIFS(建筑!A:A, 2009, 建筑!G:G, "强化或放宽目标（积极气候影响）") + COUNTIFS(建筑!A:A, 2009, 建筑!G:G, "强化或放宽目标（消极气候影响）") + COUNTIFS(交通!A:A, 2009, 交通!G:G, "新目标") + COUNTIFS(交通!A:A, 2009, 交通!G:G, "强化或放宽目标（气候影响不明确）") + COUNTIFS(交通!A:A, 2009, 交通!G:G, "强化或放宽目标（积极气候影响）") + COUNTIFS(交通!A:A, 2009, 交通!G:G, "强化或放宽目标（消极气候影响）") + COUNTIFS('土地利用、土地利用变化和林业'!A:A, 2009, '土地利用、土地利用变化和林业'!G:G, "新目标") + COUNTIFS('土地利用、土地利用变化和林业'!A:A, 2009, '土地利用、土地利用变化和林业'!G:G, "强化或放宽目标（气候影响不明确）") + COUNTIFS('土地利用、土地利用变化和林业'!A:A, 2009, '土地利用、土地利用变化和林业'!G:G, "强化或放宽目标（积极气候影响）") + COUNTIFS('土地利用、土地利用变化和林业'!A:A, 2009, '土地利用、土地利用变化和林业'!G:G, "强化或放宽目标（消极气候影响）") + COUNTIFS(循环经济!A:A, 2009, 循环经济!G:G, "新目标") + COUNTIFS(循环经济!A:A, 2009, 循环经济!G:G, "强化或放宽目标（气候影响不明确）") + COUNTIFS(循环经济!A:A, 2009, 循环经济!G:G, "强化或放宽目标（积极气候影响）") + COUNTIFS(循环经济!A:A, 2009, 循环经济!G:G, "强化或放宽目标（消极气候影响）") + COUNTIFS(金融!A:A, 2009, 金融!G:G, "新目标") + COUNTIFS(金融!A:A, 2009, 金融!G:G, "强化或放宽目标（气候影响不明确）") + COUNTIFS(金融!A:A, 2009, 金融!G:G, "强化或放宽目标（积极气候影响）") + COUNTIFS(金融!A:A, 2009, 金融!G:G, "强化或放宽目标（消极气候影响）") | N11: 2014 | O11: =COUNTIFS(温室气体排放!F:F, 2014, 温室气体排放!G:G, "新目标") + COUNTIFS(温室气体排放!F:F, 2014, 温室气体排放!G:G, "强化或放宽目标（气候影响不明确）") + COUNTIFS(温室气体排放!F:F, 2014, 温室气体排放!G:G, "强化或放宽目标（积极气候影响）") + COUNTIFS(温室气体排放!F:F, 2014, 温室气体排放!G:G, "强化或放宽目标（消极气候影响）") + COUNTIFS(污染!F:F, 2014, 污染!G:G, "新目标") + COUNTIFS(污染!F:F, 2014, 污染!G:G, "强化或放宽目标（气候影响不明确）") + COUNTIFS(污染!F:F, 2014, 污染!G:G, "强化或放宽目标（积极气候影响）") + COUNTIFS(污染!F:F, 2014, 污染!G:G, "强化或放宽目标（消极气候影响）") + COUNTIFS('能源|电力'!F:F, 2014, '能源|电力'!G:G, "新目标") + COUNTIFS('能源|电力'!F:F, 2014, '能源|电力'!G:G, "强化或放宽目标（气候影响不明确）") + COUNTIFS('能源|电力'!F:F, 2014, '能源|电力'!G:G, "强化或放宽目标（积极气候影响）") + COUNTIFS('能源|电力'!F:F, 2014, '能源|电力'!G:G, "强化或放宽目标（消极气候影响）") + COUNTIFS(工业!F:F, 2014, 工业!G:G, "新目标") + COUNTIFS(工业!F:F, 2014, 工业!G:G, "强化或放宽目标（气候影响不明确）") + COUNTIFS(工业!F:F, 2014, 工业!G:G, "强化或放宽目标（积极气候影响）") + COUNTIFS(工业!F:F, 2014, 工业!G:G, "强化或放宽目标（消极气候影响）") + COUNTIFS(建筑!F:F, 2014, 建筑!G:G, "新目标") + COUNTIFS(建筑!F:F, 2014, 建筑!G:G, "强化或放宽目标（气候影响不明确）") + COUNTIFS(建筑!F:F, 2014, 建筑!G:G, "强化或放宽目标（积极气候影响）") + COUNTIFS(建筑!F:F, 2014, 建筑!G:G, "强化或放宽目标（消极气候影响）") + COUNTIFS(交通!F:F, 2014, 交通!G:G, "新目标") + COUNTIFS(交通!F:F, 2014, 交通!G:G, "强化或放宽目标（气候影响不明确）") + COUNTIFS(交通!F:F, 2014, 交通!G:G, "强化或放宽目标（积极气候影响）") + COUNTIFS(交通!F:F, 2014, 交通!G:G, "强化或放宽目标（消极气候影响）") + COUNTIFS('土地利用、土地利用变化和林业'!F:F, 2014, '土地利用、土地利用变化和林业'!G:G, "新目标") + COUNTIFS('土地利用、土地利用变化和林业'!F:F, 2014, '土地利用、土地利用变化和林业'!G:G, "强化或放宽目标（气候影响不明确）") + COUNTIFS('土地利用、土地利用变化和林业'!F:F, 2014, '土地利用、土地利用变化和林业'!G:G, "强化或放宽目标（积极气候影响）") + COUNTIFS('土地利用、土地利用变化和林业'!F:F, 2014, '土地利用、土地利用变化和林业'!G:G, "强化或放宽目标（消极气候影响）") + COUNTIFS(循环经济!F:F, 2014, 循环经济!G:G, "新目标") + COUNTIFS(循环经济!F:F, 2014, 循环经济!G:G, "强化或放宽目标（气候影响不明确）") + COUNTIFS(循环经济!F:F, 2014, 循环经济!G:G, "强化或放宽目标（积极气候影响）") + COUNTIFS(循环经济!F:F, 2014, 循环经济!G:G, "强化或放宽目标（消极气候影响）") + COUNTIFS(金融!F:F, 2014, 金融!G:G, "新目标") + COUNTIFS(金融!F:F, 2014, 金融!G:G, "强化或放宽目标（气候影响不明确）") + COUNTIFS(金融!F:F, 2014, 金融!G:G, "强化或放宽目标（积极气候影响）") + COUNTIFS(金融!F:F, 2014, 金融!G:G, "强化或放宽目标（消极气候影响）") | Q11: 能源效率 | R11: =COUNTIFS(温室气体排放!H:H, "能源效率", 温室气体排放!G:G, "新目标") + COUNTIFS(温室气体排放!H:H, "能源效率", 温室气体排放!G:G, "强化或放宽目标（气候影响不明确）") + COUNTIFS(温室气体排放!H:H, "能源效率", 温室气体排放!G:G, "强化或放宽目标（积极气候影响）") + COUNTIFS(温室气体排放!H:H, "能源效率", 温室气体排放!G:G, "强化或放宽目标（消极气候影响）") + COUNTIFS(污染!H:H, "能源效率", 污染!G:G, "新目标") + COUNTIFS(污染!H:H, "能源效率", 污染!G:G, "强化或放宽目标（气候影响不明确）") + COUNTIFS(污染!H:H, "能源效率", 污染!G:G, "强化或放宽目标（积极气候影响）") + COUNTIFS(污染!H:H, "能源效率", 污染!G:G, "强化或放宽目标（消极气候影响）") + COUNTIFS('能源|电力'!H:H, "能源效率", '能源|电力'!G:G, "新目标") + COUNTIFS('能源|电力'!H:H, "能源效率", '能源|电力'!G:G, "强化或放宽目标（气候影响不明确）") + COUNTIFS('能源|电力'!H:H, "能源效率", '能源|电力'!G:G, "强化或放宽目标（积极气候影响）") + COUNTIFS('能源|电力'!H:H, "能源效率", '能源|电力'!G:G, "强化或放宽目标（消极气候影响）") + COUNTIFS(工业!H:H, "能源效率", 工业!G:G, "新目标") + COUNTIFS(工业!H:H, "能源效率", 工业!G:G, "强化或放宽目标（气候影响不明确）") + COUNTIFS(工业!H:H, "能源效率", 工业!G:G, "强化或放宽目标（积极气候影响）") + COUNTIFS(工业!H:H, "能源效率", 工业!G:G, "强化或放宽目标（消极气候影响）") + COUNTIFS(建筑!H:H, "能源效率", 建筑!G:G, "新目标") + COUNTIFS(建筑!H:H, "能源效率", 建筑!G:G, "强化或放宽目标（气候影响不明确）") + COUNTIFS(建筑!H:H, "能源效率", 建筑!G:G, "强化或放宽目标（积极气候影响）") + COUNTIFS(建筑!H:H, "能源效率", 建筑!G:G, "强化或放宽目标（消极气候影响）") + COUNTIFS(交通!H:H, "能源效率", 交通!G:G, "新目标") + COUNTIFS(交通!H:H, "能源效率", 交通!G:G, "强化或放宽目标（气候影响不明确）") + COUNTIFS(交通!H:H, "能源效率", 交通!G:G, "强化或放宽目标（积极气候影响）") + COUNTIFS(交通!H:H, "能源效率", 交通!G:G, "强化或放宽目标（消极气候影响）") + COUNTIFS('土地利用、土地利用变化和林业'!H:H, "能源效率", '土地利用、土地利用变化和林业'!G:G, "新目标") + COUNTIFS('土地利用、土地利用变化和林业'!H:H, "能源效率", '土地利用、土地利用变化和林业'!G:G, "强化或放宽目标（气候影响不明确）") + COUNTIFS('土地利用、土地利用变化和林业'!H:H, "能源效率", '土地利用、土地利用变化和林业'!G:G, "强化或放宽目标（积极气候影响）") + COUNTIFS('土地利用、土地利用变化和林业'!H:H, "能源效率", '土地利用、土地利用变化和林业'!G:G, "强化或放宽目标（消极气候影响）") + COUNTIFS(循环经济!H:H, "能源效率", 循环经济!G:G, "新目标") + COUNTIFS(循环经济!H:H, "能源效率", 循环经济!G:G, "强化或放宽目标（气候影响不明确）") + COUNTIFS(循环经济!H:H, "能源效率", 循环经济!G:G, "强化或放宽目标（积极气候影响）") + COUNTIFS(循环经济!H:H, "能源效率", 循环经济!G:G, "强化或放宽目标（消极气候影响）") + COUNTIFS(金融!H:H, "能源效率", 金融!G:G, "新目标") + COUNTIFS(金融!H:H, "能源效率", 金融!G:G, "强化或放宽目标（气候影响不明确）") + COUNTIFS(金融!H:H, "能源效率", 金融!G:G, "强化或放宽目标（积极气候影响）") + COUNTIFS(金融!H:H, "能源效率", 金融!G:G, "强化或放宽目标（消极气候影响）")
B12: 土地利用、土地利用变化和林业 | C12: =COUNTIFS('土地利用、土地利用变化和林业'!G:G, "新目标") + COUNTIFS('土地利用、土地利用变化和林业'!G:G, "强化或放宽目标（气候影响不明确）") + COUNTIFS('土地利用、土地利用变化和林业'!G:G, "强化或放宽目标（积极气候影响）") + COUNTIFS('土地利用、土地利用变化和林业'!G:G, "强化或放宽目标（消极气候影响）") | K12: 2010 | L12: =COUNTIFS(温室气体排放!A:A, 2010, 温室气体排放!G:G, "新目标") + COUNTIFS(温室气体排放!A:A, 2010, 温室气体排放!G:G, "强化或放宽目标（气候影响不明确）") + COUNTIFS(温室气体排放!A:A, 2010, 温室气体排放!G:G, "强化或放宽目标（积极气候影响）") + COUNTIFS(温室气体排放!A:A, 2010, 温室气体排放!G:G, "强化或放宽目标（消极气候影响）") + COUNTIFS(污染!A:A, 2010, 污染!G:G, "新目标") + COUNTIFS(污染!A:A, 2010, 污染!G:G, "强化或放宽目标（气候影响不明确）") + COUNTIFS(污染!A:A, 2010, 污染!G:G, "强化或放宽目标（积极气候影响）") + COUNTIFS(污染!A:A, 2010, 污染!G:G, "强化或放宽目标（消极气候影响）") + COUNTIFS('能源|电力'!A:A, 2010, '能源|电力'!G:G, "新目标") + COUNTIFS('能源|电力'!A:A, 2010, '能源|电力'!G:G, "强化或放宽目标（气候影响不明确）") + COUNTIFS('能源|电力'!A:A, 2010, '能源|电力'!G:G, "强化或放宽目标（积极气候影响）") + COUNTIFS('能源|电力'!A:A, 2010, '能源|电力'!G:G, "强化或放宽目标（消极气候影响）") + COUNTIFS(工业!A:A, 2010, 工业!G:G, "新目标") + COUNTIFS(工业!A:A, 2010, 工业!G:G, "强化或放宽目标（气候影响不明确）") + COUNTIFS(工业!A:A, 2010, 工业!G:G, "强化或放宽目标（积极气候影响）") + COUNTIFS(工业!A:A, 2010, 工业!G:G, "强化或放宽目标（消极气候影响）") + COUNTIFS(建筑!A:A, 2010, 建筑!G:G, "新目标") + COUNTIFS(建筑!A:A, 2010, 建筑!G:G, "强化或放宽目标（气候影响不明确）") + COUNTIFS(建筑!A:A, 2010, 建筑!G:G, "强化或放宽目标（积极气候影响）") + COUNTIFS(建筑!A:A, 2010, 建筑!G:G, "强化或放宽目标（消极气候影响）") + COUNTIFS(交通!A:A, 2010, 交通!G:G, "新目标") + COUNTIFS(交通!A:A, 2010, 交通!G:G, "强化或放宽目标（气候影响不明确）") + COUNTIFS(交通!A:A, 2010, 交通!G:G, "强化或放宽目标（积极气候影响）") + COUNTIFS(交通!A:A, 2010, 交通!G:G, "强化或放宽目标（消极气候影响）") + COUNTIFS('土地利用、土地利用变化和林业'!A:A, 2010, '土地利用、土地利用变化和林业'!G:G, "新目标") + COUNTIFS('土地利用、土地利用变化和林业'!A:A, 2010, '土地利用、土地利用变化和林业'!G:G, "强化或放宽目标（气候影响不明确）") + COUNTIFS('土地利用、土地利用变化和林业'!A:A, 2010, '土地利用、土地利用变化和林业'!G:G, "强化或放宽目标（积极气候影响）") + COUNTIFS('土地利用、土地利用变化和林业'!A:A, 2010, '土地利用、土地利用变化和林业'!G:G, "强化或放宽目标（消极气候影响）") + COUNTIFS(循环经济!A:A, 2010, 循环经济!G:G, "新目标") + COUNTIFS(循环经济!A:A, 2010, 循环经济!G:G, "强化或放宽目标（气候影响不明确）") + COUNTIFS(循环经济!A:A, 2010, 循环经济!G:G, "强化或放宽目标（积极气候影响）") + COUNTIFS(循环经济!A:A, 2010, 循环经济!G:G, "强化或放宽目标（消极气候影响）") + COUNTIFS(金融!A:A, 2010, 金融!G:G, "新目标") + COUNTIFS(金融!A:A, 2010, 金融!G:G, "强化或放宽目标（气候影响不明确）") + COUNTIFS(金融!A:A, 2010, 金融!G:G, "强化或放宽目标（积极气候影响）") + COUNTIFS(金融!A:A, 2010, 金融!G:G, "强化或放宽目标（消极气候影响）") | N12: 2015 | O12: =COUNTIFS(温室气体排放!F:F, 2015, 温室气体排放!G:G, "新目标") + COUNTIFS(温室气体排放!F:F, 2015, 温室气体排放!G:G, "强化或放宽目标（气候影响不明确）") + COUNTIFS(温室气体排放!F:F, 2015, 温室气体排放!G:G, "强化或放宽目标（积极气候影响）") + COUNTIFS(温室气体排放!F:F, 2015, 温室气体排放!G:G, "强化或放宽目标（消极气候影响）") + COUNTIFS(污染!F:F, 2015, 污染!G:G, "新目标") + COUNTIFS(污染!F:F, 2015, 污染!G:G, "强化或放宽目标（气候影响不明确）") + COUNTIFS(污染!F:F, 2015, 污染!G:G, "强化或放宽目标（积极气候影响）") + COUNTIFS(污染!F:F, 2015, 污染!G:G, "强化或放宽目标（消极气候影响）") + COUNTIFS('能源|电力'!F:F, 2015, '能源|电力'!G:G, "新目标") + COUNTIFS('能源|电力'!F:F, 2015, '能源|电力'!G:G, "强化或放宽目标（气候影响不明确）") + COUNTIFS('能源|电力'!F:F, 2015, '能源|电力'!G:G, "强化或放宽目标（积极气候影响）") + COUNTIFS('能源|电力'!F:F, 2015, '能源|电力'!G:G, "强化或放宽目标（消极气候影响）") + COUNTIFS(工业!F:F, 2015, 工业!G:G, "新目标") + COUNTIFS(工业!F:F, 2015, 工业!G:G, "强化或放宽目标（气候影响不明确）") + COUNTIFS(工业!F:F, 2015, 工业!G:G, "强化或放宽目标（积极气候影响）") + COUNTIFS(工业!F:F, 2015, 工业!G:G, "强化或放宽目标（消极气候影响）") + COUNTIFS(建筑!F:F, 2015, 建筑!G:G, "新目标") + COUNTIFS(建筑!F:F, 2015, 建筑!G:G, "强化或放宽目标（气候影响不明确）") + COUNTIFS(建筑!F:F, 2015, 建筑!G:G, "强化或放宽目标（积极气候影响）") + COUNTIFS(建筑!F:F, 2015, 建筑!G:G, "强化或放宽目标（消极气候影响）") + COUNTIFS(交通!F:F, 2015, 交通!G:G, "新目标") + COUNTIFS(交通!F:F, 2015, 交通!G:G, "强化或放宽目标（气候影响不明确）") + COUNTIFS(交通!F:F, 2015, 交通!G:G, "强化或放宽目标（积极气候影响）") + COUNTIFS(交通!F:F, 2015, 交通!G:G, "强化或放宽目标（消极气候影响）") + COUNTIFS('土地利用、土地利用变化和林业'!F:F, 2015, '土地利用、土地利用变化和林业'!G:G, "新目标") + COUNTIFS('土地利用、土地利用变化和林业'!F:F, 2015, '土地利用、土地利用变化和林业'!G:G, "强化或放宽目标（气候影响不明确）") + COUNTIFS('土地利用、土地利用变化和林业'!F:F, 2015, '土地利用、土地利用变化和林业'!G:G, "强化或放宽目标（积极气候影响）") + COUNTIFS('土地利用、土地利用变化和林业'!F:F, 2015, '土地利用、土地利用变化和林业'!G:G, "强化或放宽目标（消极气候影响）") + COUNTIFS(循环经济!F:F, 2015, 循环经济!G:G, "新目标") + COUNTIFS(循环经济!F:F, 2015, 循环经济!G:G, "强化或放宽目标（气候影响不明确）") + COUNTIFS(循环经济!F:F, 2015, 循环经济!G:G, "强化或放宽目标（积极气候影响）") + COUNTIFS(循环经济!F:F, 2015, 循环经济!G:G, "强化或放宽目标（消极气候影响）") + COUNTIFS(金融!F:F, 2015, 金融!G:G, "新目标") + COUNTIFS(金融!F:F, 2015, 金融!G:G, "强化或放宽目标（气候影响不明确）") + COUNTIFS(金融!F:F, 2015, 金融!G:G, "强化或放宽目标（积极气候影响）") + COUNTIFS(金融!F:F, 2015, 金融!G:G, "强化或放宽目标（消极气候影响）") | Q12: 资源效率 | R12: =COUNTIFS(温室气体排放!H:H, "资源效率", 温室气体排放!G:G, "新目标") + COUNTIFS(温室气体排放!H:H, "资源效率", 温室气体排放!G:G, "强化或放宽目标（气候影响不明确）") + COUNTIFS(温室气体排放!H:H, "资源效率", 温室气体排放!G:G, "强化或放宽目标（积极气候影响）") + COUNTIFS(温室气体排放!H:H, "资源效率", 温室气体排放!G:G, "强化或放宽目标（消极气候影响）") + COUNTIFS(污染!H:H, "资源效率", 污染!G:G, "新目标") + COUNTIFS(污染!H:H, "资源效率", 污染!G:G, "强化或放宽目标（气候影响不明确）") + COUNTIFS(污染!H:H, "资源效率", 污染!G:G, "强化或放宽目标（积极气候影响）") + COUNTIFS(污染!H:H, "资源效率", 污染!G:G, "强化或放宽目标（消极气候影响）") + COUNTIFS('能源|电力'!H:H, "资源效率", '能源|电力'!G:G, "新目标") + COUNTIFS('能源|电力'!H:H, "资源效率", '能源|电力'!G:G, "强化或放宽目标（气候影响不明确）") + COUNTIFS('能源|电力'!H:H, "资源效率", '能源|电力'!G:G, "强化或放宽目标（积极气候影响）") + COUNTIFS('能源|电力'!H:H, "资源效率", '能源|电力'!G:G, "强化或放宽目标（消极气候影响）") + COUNTIFS(工业!H:H, "资源效率", 工业!G:G, "新目标") + COUNTIFS(工业!H:H, "资源效率", 工业!G:G, "强化或放宽目标（气候影响不明确）") + COUNTIFS(工业!H:H, "资源效率", 工业!G:G, "强化或放宽目标（积极气候影响）") + COUNTIFS(工业!H:H, "资源效率", 工业!G:G, "强化或放宽目标（消极气候影响）") + COUNTIFS(建筑!H:H, "资源效率", 建筑!G:G, "新目标") + COUNTIFS(建筑!H:H, "资源效率", 建筑!G:G, "强化或放宽目标（气候影响不明确）") + COUNTIFS(建筑!H:H, "资源效率", 建筑!G:G, "强化或放宽目标（积极气候影响）") + COUNTIFS(建筑!H:H, "资源效率", 建筑!G:G, "强化或放宽目标（消极气候影响）") + COUNTIFS(交通!H:H, "资源效率", 交通!G:G, "新目标") + COUNTIFS(交通!H:H, "资源效率", 交通!G:G, "强化或放宽目标（气候影响不明确）") + COUNTIFS(交通!H:H, "资源效率", 交通!G:G, "强化或放宽目标（积极气候影响）") + COUNTIFS(交通!H:H, "资源效率", 交通!G:G, "强化或放宽目标（消极气候影响）") + COUNTIFS('土地利用、土地利用变化和林业'!H:H, "资源效率", '土地利用、土地利用变化和林业'!G:G, "新目标") + COUNTIFS('土地利用、土地利用变化和林业'!H:H, "资源效率", '土地利用、土地利用变化和林业'!G:G, "强化或放宽目标（气候影响不明确）") + COUNTIFS('土地利用、土地利用变化和林业'!H:H, "资源效率", '土地利用、土地利用变化和林业'!G:G, "强化或放宽目标（积极气候影响）") + COUNTIFS('土地利用、土地利用变化和林业'!H:H, "资源效率", '土地利用、土地利用变化和林业'!G:G, "强化或放宽目标（消极气候影响）") + COUNTIFS(循环经济!H:H, "资源效率", 循环经济!G:G, "新目标") + COUNTIFS(循环经济!H:H, "资源效率", 循环经济!G:G, "强化或放宽目标（气候影响不明确）") + COUNTIFS(循环经济!H:H, "资源效率", 循环经济!G:G, "强化或放宽目标（积极气候影响）") + COUNTIFS(循环经济!H:H, "资源效率", 循环经济!G:G, "强化或放宽目标（消极气候影响）") + COUNTIFS(金融!H:H, "资源效率", 金融!G:G, "新目标") + COUNTIFS(金融!H:H, "资源效率", 金融!G:G, "强化或放宽目标（气候影响不明确）") + COUNTIFS(金融!H:H, "资源效率", 金融!G:G, "强化或放宽目标（积极气候影响）") + COUNTIFS(金融!H:H, "资源效率", 金融!G:G, "强化或放宽目标（消极气候影响）")
B13: 循环经济 | C13: =COUNTIFS(循环经济!G:G, "新目标") + COUNTIFS(循环经济!G:G, "强化或放宽目标（气候影响不明确）") + COUNTIFS(循环经济!G:G, "强化或放宽目标（积极气候影响）") + COUNTIFS(循环经济!G:G, "强化或放宽目标（消极气候影响）") | K13: 2011 | L13: =COUNTIFS(温室气体排放!A:A, 2011, 温室气体排放!G:G, "新目标") + COUNTIFS(温室气体排放!A:A, 2011, 温室气体排放!G:G, "强化或放宽目标（气候影响不明确）") + COUNTIFS(温室气体排放!A:A, 2011, 温室气体排放!G:G, "强化或放宽目标（积极气候影响）") + COUNTIFS(温室气体排放!A:A, 2011, 温室气体排放!G:G, "强化或放宽目标（消极气候影响）") + COUNTIFS(污染!A:A, 2011, 污染!G:G, "新目标") + COUNTIFS(污染!A:A, 2011, 污染!G:G, "强化或放宽目标（气候影响不明确）") + COUNTIFS(污染!A:A, 2011, 污染!G:G, "强化或放宽目标（积极气候影响）") + COUNTIFS(污染!A:A, 2011, 污染!G:G, "强化或放宽目标（消极气候影响）") + COUNTIFS('能源|电力'!A:A, 2011, '能源|电力'!G:G, "新目标") + COUNTIFS('能源|电力'!A:A, 2011, '能源|电力'!G:G, "强化或放宽目标（气候影响不明确）") + COUNTIFS('能源|电力'!A:A, 2011, '能源|电力'!G:G, "强化或放宽目标（积极气候影响）") + COUNTIFS('能源|电力'!A:A, 2011, '能源|电力'!G:G, "强化或放宽目标（消极气候影响）") + COUNTIFS(工业!A:A, 2011, 工业!G:G, "新目标") + COUNTIFS(工业!A:A, 2011, 工业!G:G, "强化或放宽目标（气候影响不明确）") + COUNTIFS(工业!A:A, 2011, 工业!G:G, "强化或放宽目标（积极气候影响）") + COUNTIFS(工业!A:A, 2011, 工业!G:G, "强化或放宽目标（消极气候影响）") + COUNTIFS(建筑!A:A, 2011, 建筑!G:G, "新目标") + COUNTIFS(建筑!A:A, 2011, 建筑!G:G, "强化或放宽目标（气候影响不明确）") + COUNTIFS(建筑!A:A, 2011, 建筑!G:G, "强化或放宽目标（积极气候影响）") + COUNTIFS(建筑!A:A, 2011, 建筑!G:G, "强化或放宽目标（消极气候影响）") + COUNTIFS(交通!A:A, 2011, 交通!G:G, "新目标") + COUNTIFS(交通!A:A, 2011, 交通!G:G, "强化或放宽目标（气候影响不明确）") + COUNTIFS(交通!A:A, 2011, 交通!G:G, "强化或放宽目标（积极气候影响）") + COUNTIFS(交通!A:A, 2011, 交通!G:G, "强化或放宽目标（消极气候影响）") + COUNTIFS('土地利用、土地利用变化和林业'!A:A, 2011, '土地利用、土地利用变化和林业'!G:G, "新目标") + COUNTIFS('土地利用、土地利用变化和林业'!A:A, 2011, '土地利用、土地利用变化和林业'!G:G, "强化或放宽目标（气候影响不明确）") + COUNTIFS('土地利用、土地利用变化和林业'!A:A, 2011, '土地利用、土地利用变化和林业'!G:G, "强化或放宽目标（积极气候影响）") + COUNTIFS('土地利用、土地利用变化和林业'!A:A, 2011, '土地利用、土地利用变化和林业'!G:G, "强化或放宽目标（消极气候影响）") + COUNTIFS(循环经济!A:A, 2011, 循环经济!G:G, "新目标") + COUNTIFS(循环经济!A:A, 2011, 循环经济!G:G, "强化或放宽目标（气候影响不明确）") + COUNTIFS(循环经济!A:A, 2011, 循环经济!G:G, "强化或放宽目标（积极气候影响）") + COUNTIFS(循环经济!A:A, 2011, 循环经济!G:G, "强化或放宽目标（消极气候影响）") + COUNTIFS(金融!A:A, 2011, 金融!G:G, "新目标") + COUNTIFS(金融!A:A, 2011, 金融!G:G, "强化或放宽目标（气候影响不明确）") + COUNTIFS(金融!A:A, 2011, 金融!G:G, "强化或放宽目标（积极气候影响）") + COUNTIFS(金融!A:A, 2011, 金融!G:G, "强化或放宽目标（消极气候影响）") | N13: 十二五 | O13: =COUNTIFS(温室气体排放!F:F, "十二五", 温室气体排放!G:G, "新目标") + COUNTIFS(温室气体排放!F:F, "十二五", 温室气体排放!G:G, "强化或放宽目标（气候影响不明确）") + COUNTIFS(温室气体排放!F:F, "十二五", 温室气体排放!G:G, "强化或放宽目标（积极气候影响）") + COUNTIFS(温室气体排放!F:F, "十二五", 温室气体排放!G:G, "强化或放宽目标（消极气候影响）") + COUNTIFS(污染!F:F, "十二五", 污染!G:G, "新目标") + COUNTIFS(污染!F:F, "十二五", 污染!G:G, "强化或放宽目标（气候影响不明确）") + COUNTIFS(污染!F:F, "十二五", 污染!G:G, "强化或放宽目标（积极气候影响）") + COUNTIFS(污染!F:F, "十二五", 污染!G:G, "强化或放宽目标（消极气候影响）") + COUNTIFS('能源|电力'!F:F, "十二五", '能源|电力'!G:G, "新目标") + COUNTIFS('能源|电力'!F:F, "十二五", '能源|电力'!G:G, "强化或放宽目标（气候影响不明确）") + COUNTIFS('能源|电力'!F:F, "十二五", '能源|电力'!G:G, "强化或放宽目标（积极气候影响）") + COUNTIFS('能源|电力'!F:F, "十二五", '能源|电力'!G:G, "强化或放宽目标（消极气候影响）") + COUNTIFS(工业!F:F, "十二五", 工业!G:G, "新目标") + COUNTIFS(工业!F:F, "十二五", 工业!G:G, "强化或放宽目标（气候影响不明确）") + COUNTIFS(工业!F:F, "十二五", 工业!G:G, "强化或放宽目标（积极气候影响）") + COUNTIFS(工业!F:F, "十二五", 工业!G:G, "强化或放宽目标（消极气候影响）") + COUNTIFS(建筑!F:F, "十二五", 建筑!G:G, "新目标") + COUNTIFS(建筑!F:F, "十二五", 建筑!G:G, "强化或放宽目标（气候影响不明确）") + COUNTIFS(建筑!F:F, "十二五", 建筑!G:G, "强化或放宽目标（积极气候影响）") + COUNTIFS(建筑!F:F, "十二五", 建筑!G:G, "强化或放宽目标（消极气候影响）") + COUNTIFS(交通!F:F, "十二五", 交通!G:G, "新目标") + COUNTIFS(交通!F:F, "十二五", 交通!G:G, "强化或放宽目标（气候影响不明确）") + COUNTIFS(交通!F:F, "十二五", 交通!G:G, "强化或放宽目标（积极气候影响）") + COUNTIFS(交通!F:F, "十二五", 交通!G:G, "强化或放宽目标（消极气候影响）") + COUNTIFS('土地利用、土地利用变化和林业'!F:F, "十二五", '土地利用、土地利用变化和林业'!G:G, "新目标") + COUNTIFS('土地利用、土地利用变化和林业'!F:F, "十二五", '土地利用、土地利用变化和林业'!G:G, "强化或放宽目标（气候影响不明确）") + COUNTIFS('土地利用、土地利用变化和林业'!F:F, "十二五", '土地利用、土地利用变化和林业'!G:G, "强化或放宽目标（积极气候影响）") + COUNTIFS('土地利用、土地利用变化和林业'!F:F, "十二五", '土地利用、土地利用变化和林业'!G:G, "强化或放宽目标（消极气候影响）") + COUNTIFS(循环经济!F:F, "十二五", 循环经济!G:G, "新目标") + COUNTIFS(循环经济!F:F, "十二五", 循环经济!G:G, "强化或放宽目标（气候影响不明确）") + COUNTIFS(循环经济!F:F, "十二五", 循环经济!G:G, "强化或放宽目标（积极气候影响）") + COUNTIFS(循环经济!F:F, "十二五", 循环经济!G:G, "强化或放宽目标（消极气候影响）") + COUNTIFS(金融!F:F, "十二五", 金融!G:G, "新目标") + COUNTIFS(金融!F:F, "十二五", 金融!G:G, "强化或放宽目标（气候影响不明确）") + COUNTIFS(金融!F:F, "十二五", 金融!G:G, "强化或放宽目标（积极气候影响）") + COUNTIFS(金融!F:F, "十二五", 金融!G:G, "强化或放宽目标（消极气候影响）") | Q13: 可再生能源 | R13: =COUNTIFS(温室气体排放!H:H, "可再生能源", 温室气体排放!G:G, "新目标") + COUNTIFS(温室气体排放!H:H, "可再生能源", 温室气体排放!G:G, "强化或放宽目标（气候影响不明确）") + COUNTIFS(温室气体排放!H:H, "可再生能源", 温室气体排放!G:G, "强化或放宽目标（积极气候影响）") + COUNTIFS(温室气体排放!H:H, "可再生能源", 温室气体排放!G:G, "强化或放宽目标（消极气候影响）") + COUNTIFS(污染!H:H, "可再生能源", 污染!G:G, "新目标") + COUNTIFS(污染!H:H, "可再生能源", 污染!G:G, "强化或放宽目标（气候影响不明确）") + COUNTIFS(污染!H:H, "可再生能源", 污染!G:G, "强化或放宽目标（积极气候影响）") + COUNTIFS(污染!H:H, "可再生能源", 污染!G:G, "强化或放宽目标（消极气候影响）") + COUNTIFS('能源|电力'!H:H, "可再生能源", '能源|电力'!G:G, "新目标") + COUNTIFS('能源|电力'!H:H, "可再生能源", '能源|电力'!G:G, "强化或放宽目标（气候影响不明确）") + COUNTIFS('能源|电力'!H:H, "可再生能源", '能源|电力'!G:G, "强化或放宽目标（积极气候影响）") + COUNTIFS('能源|电力'!H:H, "可再生能源", '能源|电力'!G:G, "强化或放宽目标（消极气候影响）") + COUNTIFS(工业!H:H, "可再生能源", 工业!G:G, "新目标") + COUNTIFS(工业!H:H, "可再生能源", 工业!G:G, "强化或放宽目标（气候影响不明确）") + COUNTIFS(工业!H:H, "可再生能源", 工业!G:G, "强化或放宽目标（积极气候影响）") + COUNTIFS(工业!H:H, "可再生能源", 工业!G:G, "强化或放宽目标（消极气候影响）") + COUNTIFS(建筑!H:H, "可再生能源", 建筑!G:G, "新目标") + COUNTIFS(建筑!H:H, "可再生能源", 建筑!G:G, "强化或放宽目标（气候影响不明确）") + COUNTIFS(建筑!H:H, "可再生能源", 建筑!G:G, "强化或放宽目标（积极气候影响）") + COUNTIFS(建筑!H:H, "可再生能源", 建筑!G:G, "强化或放宽目标（消极气候影响）") + COUNTIFS(交通!H:H, "可再生能源", 交通!G:G, "新目标") + COUNTIFS(交通!H:H, "可再生能源", 交通!G:G, "强化或放宽目标（气候影响不明确）") + COUNTIFS(交通!H:H, "可再生能源", 交通!G:G, "强化或放宽目标（积极气候影响）") + COUNTIFS(交通!H:H, "可再生能源", 交通!G:G, "强化或放宽目标（消极气候影响）") + COUNTIFS('土地利用、土地利用变化和林业'!H:H, "可再生能源", '土地利用、土地利用变化和林业'!G:G, "新目标") + COUNTIFS('土地利用、土地利用变化和林业'!H:H, "可再生能源", '土地利用、土地利用变化和林业'!G:G, "强化或放宽目标（气候影响不明确）") + COUNTIFS('土地利用、土地利用变化和林业'!H:H, "可再生能源", '土地利用、土地利用变化和林业'!G:G, "强化或放宽目标（积极气候影响）") + COUNTIFS('土地利用、土地利用变化和林业'!H:H, "可再生能源", '土地利用、土地利用变化和林业'!G:G, "强化或放宽目标（消极气候影响）") + COUNTIFS(循环经济!H:H, "可再生能源", 循环经济!G:G, "新目标") + COUNTIFS(循环经济!H:H, "可再生能源", 循环经济!G:G, "强化或放宽目标（气候影响不明确）") + COUNTIFS(循环经济!H:H, "可再生能源", 循环经济!G:G, "强化或放宽目标（积极气候影响）") + COUNTIFS(循环经济!H:H, "可再生能源", 循环经济!G:G, "强化或放宽目标（消极气候影响）") + COUNTIFS(金融!H:H, "可再生能源", 金融!G:G, "新目标") + COUNTIFS(金融!H:H, "可再生能源", 金融!G:G, "强化或放宽目标（气候影响不明确）") + COUNTIFS(金融!H:H, "可再生能源", 金融!G:G, "强化或放宽目标（积极气候影响）") + COUNTIFS(金融!H:H, "可再生能源", 金融!G:G, "强化或放宽目标（消极气候影响）")
B14: 金融 | C14: =COUNTIFS(金融!G:G, "新目标") + COUNTIFS(金融!G:G, "强化或放宽目标（气候影响不明确）") + COUNTIFS(金融!G:G, "强化或放宽目标（积极气候影响）") + COUNTIFS(金融!G:G, "强化或放宽目标（消极气候影响）") | K14: 2012 | L14: =COUNTIFS(温室气体排放!A:A, 2012, 温室气体排放!G:G, "新目标") + COUNTIFS(温室气体排放!A:A, 2012, 温室气体排放!G:G, "强化或放宽目标（气候影响不明确）") + COUNTIFS(温室气体排放!A:A, 2012, 温室气体排放!G:G, "强化或放宽目标（积极气候影响）") + COUNTIFS(温室气体排放!A:A, 2012, 温室气体排放!G:G, "强化或放宽目标（消极气候影响）") + COUNTIFS(污染!A:A, 2012, 污染!G:G, "新目标") + COUNTIFS(污染!A:A, 2012, 污染!G:G, "强化或放宽目标（气候影响不明确）") + COUNTIFS(污染!A:A, 2012, 污染!G:G, "强化或放宽目标（积极气候影响）") + COUNTIFS(污染!A:A, 2012, 污染!G:G, "强化或放宽目标（消极气候影响）") + COUNTIFS('能源|电力'!A:A, 2012, '能源|电力'!G:G, "新目标") + COUNTIFS('能源|电力'!A:A, 2012, '能源|电力'!G:G, "强化或放宽目标（气候影响不明确）") + COUNTIFS('能源|电力'!A:A, 2012, '能源|电力'!G:G, "强化或放宽目标（积极气候影响）") + COUNTIFS('能源|电力'!A:A, 2012, '能源|电力'!G:G, "强化或放宽目标（消极气候影响）") + COUNTIFS(工业!A:A, 2012, 工业!G:G, "新目标") + COUNTIFS(工业!A:A, 2012, 工业!G:G, "强化或放宽目标（气候影响不明确）") + COUNTIFS(工业!A:A, 2012, 工业!G:G, "强化或放宽目标（积极气候影响）") + COUNTIFS(工业!A:A, 2012, 工业!G:G, "强化或放宽目标（消极气候影响）") + COUNTIFS(建筑!A:A, 2012, 建筑!G:G, "新目标") + COUNTIFS(建筑!A:A, 2012, 建筑!G:G, "强化或放宽目标（气候影响不明确）") + COUNTIFS(建筑!A:A, 2012, 建筑!G:G, "强化或放宽目标（积极气候影响）") + COUNTIFS(建筑!A:A, 2012, 建筑!G:G, "强化或放宽目标（消极气候影响）") + COUNTIFS(交通!A:A, 2012, 交通!G:G, "新目标") + COUNTIFS(交通!A:A, 2012, 交通!G:G, "强化或放宽目标（气候影响不明确）") + COUNTIFS(交通!A:A, 2012, 交通!G:G, "强化或放宽目标（积极气候影响）") + COUNTIFS(交通!A:A, 2012, 交通!G:G, "强化或放宽目标（消极气候影响）") + COUNTIFS('土地利用、土地利用变化和林业'!A:A, 2012, '土地利用、土地利用变化和林业'!G:G, "新目标") + COUNTIFS('土地利用、土地利用变化和林业'!A:A, 2012, '土地利用、土地利用变化和林业'!G:G, "强化或放宽目标（气候影响不明确）") + COUNTIFS('土地利用、土地利用变化和林业'!A:A, 2012, '土地利用、土地利用变化和林业'!G:G, "强化或放宽目标（积极气候影响）") + COUNTIFS('土地利用、土地利用变化和林业'!A:A, 2012, '土地利用、土地利用变化和林业'!G:G, "强化或放宽目标（消极气候影响）") + COUNTIFS(循环经济!A:A, 2012, 循环经济!G:G, "新目标") + COUNTIFS(循环经济!A:A, 2012, 循环经济!G:G, "强化或放宽目标（气候影响不明确）") + COUNTIFS(循环经济!A:A, 2012, 循环经济!G:G, "强化或放宽目标（积极气候影响）") + COUNTIFS(循环经济!A:A, 2012, 循环经济!G:G, "强化或放宽目标（消极气候影响）") + COUNTIFS(金融!A:A, 2012, 金融!G:G, "新目标") + COUNTIFS(金融!A:A, 2012, 金融!G:G, "强化或放宽目标（气候影响不明确）") + COUNTIFS(金融!A:A, 2012, 金融!G:G, "强化或放宽目标（积极气候影响）") + COUNTIFS(金融!A:A, 2012, 金融!G:G, "强化或放宽目标（消极气候影响）") | N14: 2016 | O14: =COUNTIFS(温室气体排放!F:F, 2016, 温室气体排放!G:G, "新目标") + COUNTIFS(温室气体排放!F:F, 2016, 温室气体排放!G:G, "强化或放宽目标（气候影响不明确）") + COUNTIFS(温室气体排放!F:F, 2016, 温室气体排放!G:G, "强化或放宽目标（积极气候影响）") + COUNTIFS(温室气体排放!F:F, 2016, 温室气体排放!G:G, "强化或放宽目标（消极气候影响）") + COUNTIFS(污染!F:F, 2016, 污染!G:G, "新目标") + COUNTIFS(污染!F:F, 2016, 污染!G:G, "强化或放宽目标（气候影响不明确）") + COUNTIFS(污染!F:F, 2016, 污染!G:G, "强化或放宽目标（积极气候影响）") + COUNTIFS(污染!F:F, 2016, 污染!G:G, "强化或放宽目标（消极气候影响）") + COUNTIFS('能源|电力'!F:F, 2016, '能源|电力'!G:G, "新目标") + COUNTIFS('能源|电力'!F:F, 2016, '能源|电力'!G:G, "强化或放宽目标（气候影响不明确）") + COUNTIFS('能源|电力'!F:F, 2016, '能源|电力'!G:G, "强化或放宽目标（积极气候影响）") + COUNTIFS('能源|电力'!F:F, 2016, '能源|电力'!G:G, "强化或放宽目标（消极气候影响）") + COUNTIFS(工业!F:F, 2016, 工业!G:G, "新目标") + COUNTIFS(工业!F:F, 2016, 工业!G:G, "强化或放宽目标（气候影响不明确）") + COUNTIFS(工业!F:F, 2016, 工业!G:G, "强化或放宽目标（积极气候影响）") + COUNTIFS(工业!F:F, 2016, 工业!G:G, "强化或放宽目标（消极气候影响）") + COUNTIFS(建筑!F:F, 2016, 建筑!G:G, "新目标") + COUNTIFS(建筑!F:F, 2016, 建筑!G:G, "强化或放宽目标（气候影响不明确）") + COUNTIFS(建筑!F:F, 2016, 建筑!G:G, "强化或放宽目标（积极气候影响）") + COUNTIFS(建筑!F:F, 2016, 建筑!G:G, "强化或放宽目标（消极气候影响）") + COUNTIFS(交通!F:F, 2016, 交通!G:G, "新目标") + COUNTIFS(交通!F:F, 2016, 交通!G:G, "强化或放宽目标（气候影响不明确）") + COUNTIFS(交通!F:F, 2016, 交通!G:G, "强化或放宽目标（积极气候影响）") + COUNTIFS(交通!F:F, 2016, 交通!G:G, "强化或放宽目标（消极气候影响）") + COUNTIFS('土地利用、土地利用变化和林业'!F:F, 2016, '土地利用、土地利用变化和林业'!G:G, "新目标") + COUNTIFS('土地利用、土地利用变化和林业'!F:F, 2016, '土地利用、土地利用变化和林业'!G:G, "强化或放宽目标（气候影响不明确）") + COUNTIFS('土地利用、土地利用变化和林业'!F:F, 2016, '土地利用、土地利用变化和林业'!G:G, "强化或放宽目标（积极气候影响）") + COUNTIFS('土地利用、土地利用变化和林业'!F:F, 2016, '土地利用、土地利用变化和林业'!G:G, "强化或放宽目标（消极气候影响）") + COUNTIFS(循环经济!F:F, 2016, 循环经济!G:G, "新目标") + COUNTIFS(循环经济!F:F, 2016, 循环经济!G:G, "强化或放宽目标（气候影响不明确）") + COUNTIFS(循环经济!F:F, 2016, 循环经济!G:G, "强化或放宽目标（积极气候影响）") + COUNTIFS(循环经济!F:F, 2016, 循环经济!G:G, "强化或放宽目标（消极气候影响）") + COUNTIFS(金融!F:F, 2016, 金融!G:G, "新目标") + COUNTIFS(金融!F:F, 2016, 金融!G:G, "强化或放宽目标（气候影响不明确）") + COUNTIFS(金融!F:F, 2016, 金融!G:G, "强化或放宽目标（积极气候影响）") + COUNTIFS(金融!F:F, 2016, 金融!G:G, "强化或放宽目标（消极气候影响）") | Q14: 过渡能源 | R14: =COUNTIFS(温室气体排放!H:H, "过渡能源", 温室气体排放!G:G, "新目标") + COUNTIFS(温室气体排放!H:H, "过渡能源", 温室气体排放!G:G, "强化或放宽目标（气候影响不明确）") + COUNTIFS(温室气体排放!H:H, "过渡能源", 温室气体排放!G:G, "强化或放宽目标（积极气候影响）") + COUNTIFS(温室气体排放!H:H, "过渡能源", 温室气体排放!G:G, "强化或放宽目标（消极气候影响）") + COUNTIFS(污染!H:H, "过渡能源", 污染!G:G, "新目标") + COUNTIFS(污染!H:H, "过渡能源", 污染!G:G, "强化或放宽目标（气候影响不明确）") + COUNTIFS(污染!H:H, "过渡能源", 污染!G:G, "强化或放宽目标（积极气候影响）") + COUNTIFS(污染!H:H, "过渡能源", 污染!G:G, "强化或放宽目标（消极气候影响）") + COUNTIFS('能源|电力'!H:H, "过渡能源", '能源|电力'!G:G, "新目标") + COUNTIFS('能源|电力'!H:H, "过渡能源", '能源|电力'!G:G, "强化或放宽目标（气候影响不明确）") + COUNTIFS('能源|电力'!H:H, "过渡能源", '能源|电力'!G:G, "强化或放宽目标（积极气候影响）") + COUNTIFS('能源|电力'!H:H, "过渡能源", '能源|电力'!G:G, "强化或放宽目标（消极气候影响）") + COUNTIFS(工业!H:H, "过渡能源", 工业!G:G, "新目标") + COUNTIFS(工业!H:H, "过渡能源", 工业!G:G, "强化或放宽目标（气候影响不明确）") + COUNTIFS(工业!H:H, "过渡能源", 工业!G:G, "强化或放宽目标（积极气候影响）") + COUNTIFS(工业!H:H, "过渡能源", 工业!G:G, "强化或放宽目标（消极气候影响）") + COUNTIFS(建筑!H:H, "过渡能源", 建筑!G:G, "新目标") + COUNTIFS(建筑!H:H, "过渡能源", 建筑!G:G, "强化或放宽目标（气候影响不明确）") + COUNTIFS(建筑!H:H, "过渡能源", 建筑!G:G, "强化或放宽目标（积极气候影响）") + COUNTIFS(建筑!H:H, "过渡能源", 建筑!G:G, "强化或放宽目标（消极气候影响）") + COUNTIFS(交通!H:H, "过渡能源", 交通!G:G, "新目标") + COUNTIFS(交通!H:H, "过渡能源", 交通!G:G, "强化或放宽目标（气候影响不明确）") + COUNTIFS(交通!H:H, "过渡能源", 交通!G:G, "强化或放宽目标（积极气候影响）") + COUNTIFS(交通!H:H, "过渡能源", 交通!G:G, "强化或放宽目标（消极气候影响）") + COUNTIFS('土地利用、土地利用变化和林业'!H:H, "过渡能源", '土地利用、土地利用变化和林业'!G:G, "新目标") + COUNTIFS('土地利用、土地利用变化和林业'!H:H, "过渡能源", '土地利用、土地利用变化和林业'!G:G, "强化或放宽目标（气候影响不明确）") + COUNTIFS('土地利用、土地利用变化和林业'!H:H, "过渡能源", '土地利用、土地利用变化和林业'!G:G, "强化或放宽目标（积极气候影响）") + COUNTIFS('土地利用、土地利用变化和林业'!H:H, "过渡能源", '土地利用、土地利用变化和林业'!G:G, "强化或放宽目标（消极气候影响）") + COUNTIFS(循环经济!H:H, "过渡能源", 循环经济!G:G, "新目标") + COUNTIFS(循环经济!H:H, "过渡能源", 循环经济!G:G, "强化或放宽目标（气候影响不明确）") + COUNTIFS(循环经济!H:H, "过渡能源", 循环经济!G:G, "强化或放宽目标（积极气候影响）") + COUNTIFS(循环经济!H:H, "过渡能源", 循环经济!G:G, "强化或放宽目标（消极气候影响）") + COUNTIFS(金融!H:H, "过渡能源", 金融!G:G, "新目标") + COUNTIFS(金融!H:H, "过渡能源", 金融!G:G, "强化或放宽目标（气候影响不明确）") + COUNTIFS(金融!H:H, "过渡能源", 金融!G:G, "强化或放宽目标（积极气候影响）") + COUNTIFS(金融!H:H, "过渡能源", 金融!G:G, "强化或放宽目标（消极气候影响）")
B15: 合计 | C15: =SUM(C6:C14) | K15: 2013 | L15: =COUNTIFS(温室气体排放!A:A, 2013, 温室气体排放!G:G, "新目标") + COUNTIFS(温室气体排放!A:A, 2013, 温室气体排放!G:G, "强化或放宽目标（气候影响不明确）") + COUNTIFS(温室气体排放!A:A, 2013, 温室气体排放!G:G, "强化或放宽目标（积极气候影响）") + COUNTIFS(温室气体排放!A:A, 2013, 温室气体排放!G:G, "强化或放宽目标（消极气候影响）") + COUNTIFS(污染!A:A, 2013, 污染!G:G, "新目标") + COUNTIFS(污染!A:A, 2013, 污染!G:G, "强化或放宽目标（气候影响不明确）") + COUNTIFS(污染!A:A, 2013, 污染!G:G, "强化或放宽目标（积极气候影响）") + COUNTIFS(污染!A:A, 2013, 污染!G:G, "强化或放宽目标（消极气候影响）") + COUNTIFS('能源|电力'!A:A, 2013, '能源|电力'!G:G, "新目标") + COUNTIFS('能源|电力'!A:A, 2013, '能源|电力'!G:G, "强化或放宽目标（气候影响不明确）") + COUNTIFS('能源|电力'!A:A, 2013, '能源|电力'!G:G, "强化或放宽目标（积极气候影响）") + COUNTIFS('能源|电力'!A:A, 2013, '能源|电力'!G:G, "强化或放宽目标（消极气候影响）") + COUNTIFS(工业!A:A, 2013, 工业!G:G, "新目标") + COUNTIFS(工业!A:A, 2013, 工业!G:G, "强化或放宽目标（气候影响不明确）") + COUNTIFS(工业!A:A, 2013, 工业!G:G, "强化或放宽目标（积极气候影响）") + COUNTIFS(工业!A:A, 2013, 工业!G:G, "强化或放宽目标（消极气候影响）") + COUNTIFS(建筑!A:A, 2013, 建筑!G:G, "新目标") + COUNTIFS(建筑!A:A, 2013, 建筑!G:G, "强化或放宽目标（气候影响不明确）") + COUNTIFS(建筑!A:A, 2013, 建筑!G:G, "强化或放宽目标（积极气候影响）") + COUNTIFS(建筑!A:A, 2013, 建筑!G:G, "强化或放宽目标（消极气候影响）") + COUNTIFS(交通!A:A, 2013, 交通!G:G, "新目标") + COUNTIFS(交通!A:A, 2013, 交通!G:G, "强化或放宽目标（气候影响不明确）") + COUNTIFS(交通!A:A, 2013, 交通!G:G, "强化或放宽目标（积极气候影响）") + COUNTIFS(交通!A:A, 2013, 交通!G:G, "强化或放宽目标（消极气候影响）") + COUNTIFS('土地利用、土地利用变化和林业'!A:A, 2013, '土地利用、土地利用变化和林业'!G:G, "新目标") + COUNTIFS('土地利用、土地利用变化和林业'!A:A, 2013, '土地利用、土地利用变化和林业'!G:G, "强化或放宽目标（气候影响不明确）") + COUNTIFS('土地利用、土地利用变化和林业'!A:A, 2013, '土地利用、土地利用变化和林业'!G:G, "强化或放宽目标（积极气候影响）") + COUNTIFS('土地利用、土地利用变化和林业'!A:A, 2013, '土地利用、土地利用变化和林业'!G:G, "强化或放宽目标（消极气候影响）") + COUNTIFS(循环经济!A:A, 2013, 循环经济!G:G, "新目标") + COUNTIFS(循环经济!A:A, 2013, 循环经济!G:G, "强化或放宽目标（气候影响不明确）") + COUNTIFS(循环经济!A:A, 2013, 循环经济!G:G, "强化或放宽目标（积极气候影响）") + COUNTIFS(循环经济!A:A, 2013, 循环经济!G:G, "强化或放宽目标（消极气候影响）") + COUNTIFS(金融!A:A, 2013, 金融!G:G, "新目标") + COUNTIFS(金融!A:A, 2013, 金融!G:G, "强化或放宽目标（气候影响不明确）") + COUNTIFS(金融!A:A, 2013, 金融!G:G, "强化或放宽目标（积极气候影响）") + COUNTIFS(金融!A:A, 2013, 金融!G:G, "强化或放宽目标（消极气候影响）") | N15: 2017 | O15: =COUNTIFS(温室气体排放!F:F, 2017, 温室气体排放!G:G, "新目标") + COUNTIFS(温室气体排放!F:F, 2017, 温室气体排放!G:G, "强化或放宽目标（气候影响不明确）") + COUNTIFS(温室气体排放!F:F, 2017, 温室气体排放!G:G, "强化或放宽目标（积极气候影响）") + COUNTIFS(温室气体排放!F:F, 2017, 温室气体排放!G:G, "强化或放宽目标（消极气候影响）") + COUNTIFS(污染!F:F, 2017, 污染!G:G, "新目标") + COUNTIFS(污染!F:F, 2017, 污染!G:G, "强化或放宽目标（气候影响不明确）") + COUNTIFS(污染!F:F, 2017, 污染!G:G, "强化或放宽目标（积极气候影响）") + COUNTIFS(污染!F:F, 2017, 污染!G:G, "强化或放宽目标（消极气候影响）") + COUNTIFS('能源|电力'!F:F, 2017, '能源|电力'!G:G, "新目标") + COUNTIFS('能源|电力'!F:F, 2017, '能源|电力'!G:G, "强化或放宽目标（气候影响不明确）") + COUNTIFS('能源|电力'!F:F, 2017, '能源|电力'!G:G, "强化或放宽目标（积极气候影响）") + COUNTIFS('能源|电力'!F:F, 2017, '能源|电力'!G:G, "强化或放宽目标（消极气候影响）") + COUNTIFS(工业!F:F, 2017, 工业!G:G, "新目标") + COUNTIFS(工业!F:F, 2017, 工业!G:G, "强化或放宽目标（气候影响不明确）") + COUNTIFS(工业!F:F, 2017, 工业!G:G, "强化或放宽目标（积极气候影响）") + COUNTIFS(工业!F:F, 2017, 工业!G:G, "强化或放宽目标（消极气候影响）") + COUNTIFS(建筑!F:F, 2017, 建筑!G:G, "新目标") + COUNTIFS(建筑!F:F, 2017, 建筑!G:G, "强化或放宽目标（气候影响不明确）") + COUNTIFS(建筑!F:F, 2017, 建筑!G:G, "强化或放宽目标（积极气候影响）") + COUNTIFS(建筑!F:F, 2017, 建筑!G:G, "强化或放宽目标（消极气候影响）") + COUNTIFS(交通!F:F, 2017, 交通!G:G, "新目标") + COUNTIFS(交通!F:F, 2017, 交通!G:G, "强化或放宽目标（气候影响不明确）") + COUNTIFS(交通!F:F, 2017, 交通!G:G, "强化或放宽目标（积极气候影响）") + COUNTIFS(交通!F:F, 2017, 交通!G:G, "强化或放宽目标（消极气候影响）") + COUNTIFS('土地利用、土地利用变化和林业'!F:F, 2017, '土地利用、土地利用变化和林业'!G:G, "新目标") + COUNTIFS('土地利用、土地利用变化和林业'!F:F, 2017, '土地利用、土地利用变化和林业'!G:G, "强化或放宽目标（气候影响不明确）") + COUNTIFS('土地利用、土地利用变化和林业'!F:F, 2017, '土地利用、土地利用变化和林业'!G:G, "强化或放宽目标（积极气候影响）") + COUNTIFS('土地利用、土地利用变化和林业'!F:F, 2017, '土地利用、土地利用变化和林业'!G:G, "强化或放宽目标（消极气候影响）") + COUNTIFS(循环经济!F:F, 2017, 循环经济!G:G, "新目标") + COUNTIFS(循环经济!F:F, 2017, 循环经济!G:G, "强化或放宽目标（气候影响不明确）") + COUNTIFS(循环经济!F:F, 2017, 循环经济!G:G, "强化或放宽目标（积极气候影响）") + COUNTIFS(循环经济!F:F, 2017, 循环经济!G:G, "强化或放宽目标（消极气候影响）") + COUNTIFS(金融!F:F, 2017, 金融!G:G, "新目标") + COUNTIFS(金融!F:F, 2017, 金融!G:G, "强化或放宽目标（气候影响不明确）") + COUNTIFS(金融!F:F, 2017, 金融!G:G, "强化或放宽目标（积极气候影响）") + COUNTIFS(金融!F:F, 2017, 金融!G:G, "强化或放宽目标（消极气候影响）") | Q15: 电气化 | R15: =COUNTIFS(温室气体排放!H:H, "电气化", 温室气体排放!G:G, "新目标") + COUNTIFS(温室气体排放!H:H, "电气化", 温室气体排放!G:G, "强化或放宽目标（气候影响不明确）") + COUNTIFS(温室气体排放!H:H, "电气化", 温室气体排放!G:G, "强化或放宽目标（积极气候影响）") + COUNTIFS(温室气体排放!H:H, "电气化", 温室气体排放!G:G, "强化或放宽目标（消极气候影响）") + COUNTIFS(污染!H:H, "电气化", 污染!G:G, "新目标") + COUNTIFS(污染!H:H, "电气化", 污染!G:G, "强化或放宽目标（气候影响不明确）") + COUNTIFS(污染!H:H, "电气化", 污染!G:G, "强化或放宽目标（积极气候影响）") + COUNTIFS(污染!H:H, "电气化", 污染!G:G, "强化或放宽目标（消极气候影响）") + COUNTIFS('能源|电力'!H:H, "电气化", '能源|电力'!G:G, "新目标") + COUNTIFS('能源|电力'!H:H, "电气化", '能源|电力'!G:G, "强化或放宽目标（气候影响不明确）") + COUNTIFS('能源|电力'!H:H, "电气化", '能源|电力'!G:G, "强化或放宽目标（积极气候影响）") + COUNTIFS('能源|电力'!H:H, "电气化", '能源|电力'!G:G, "强化或放宽目标（消极气候影响）") + COUNTIFS(工业!H:H, "电气化", 工业!G:G, "新目标") + COUNTIFS(工业!H:H, "电气化", 工业!G:G, "强化或放宽目标（气候影响不明确）") + COUNTIFS(工业!H:H, "电气化", 工业!G:G, "强化或放宽目标（积极气候影响）") + COUNTIFS(工业!H:H, "电气化", 工业!G:G, "强化或放宽目标（消极气候影响）") + COUNTIFS(建筑!H:H, "电气化", 建筑!G:G, "新目标") + COUNTIFS(建筑!H:H, "电气化", 建筑!G:G, "强化或放宽目标（气候影响不明确）") + COUNTIFS(建筑!H:H, "电气化", 建筑!G:G, "强化或放宽目标（积极气候影响）") + COUNTIFS(建筑!H:H, "电气化", 建筑!G:G, "强化或放宽目标（消极气候影响）") + COUNTIFS(交通!H:H, "电气化", 交通!G:G, "新目标") + COUNTIFS(交通!H:H, "电气化", 交通!G:G, "强化或放宽目标（气候影响不明确）") + COUNTIFS(交通!H:H, "电气化", 交通!G:G, "强化或放宽目标（积极气候影响）") + COUNTIFS(交通!H:H, "电气化", 交通!G:G, "强化或放宽目标（消极气候影响）") + COUNTIFS('土地利用、土地利用变化和林业'!H:H, "电气化", '土地利用、土地利用变化和林业'!G:G, "新目标") + COUNTIFS('土地利用、土地利用变化和林业'!H:H, "电气化", '土地利用、土地利用变化和林业'!G:G, "强化或放宽目标（气候影响不明确）") + COUNTIFS('土地利用、土地利用变化和林业'!H:H, "电气化", '土地利用、土地利用变化和林业'!G:G, "强化或放宽目标（积极气候影响）") + COUNTIFS('土地利用、土地利用变化和林业'!H:H, "电气化", '土地利用、土地利用变化和林业'!G:G, "强化或放宽目标（消极气候影响）") + COUNTIFS(循环经济!H:H, "电气化", 循环经济!G:G, "新目标") + COUNTIFS(循环经济!H:H, "电气化", 循环经济!G:G, "强化或放宽目标（气候影响不明确）") + COUNTIFS(循环经济!H:H, "电气化", 循环经济!G:G, "强化或放宽目标（积极气候影响）") + COUNTIFS(循环经济!H:H, "电气化", 循环经济!G:G, "强化或放宽目标（消极气候影响）") + COUNTIFS(金融!H:H, "电气化", 金融!G:G, "新目标") + COUNTIFS(金融!H:H, "电气化", 金融!G:G, "强化或放宽目标（气候影响不明确）") + COUNTIFS(金融!H:H, "电气化", 金融!G:G, "强化或放宽目标（积极气候影响）") + COUNTIFS(金融!H:H, "电气化", 金融!G:G, "强化或放宽目标（消极气候影响）")
K16: 2014 | L16: =COUNTIFS(温室气体排放!A:A, 2014, 温室气体排放!G:G, "新目标") + COUNTIFS(温室气体排放!A:A, 2014, 温室气体排放!G:G, "强化或放宽目标（气候影响不明确）") + COUNTIFS(温室气体排放!A:A, 2014, 温室气体排放!G:G, "强化或放宽目标（积极气候影响）") + COUNTIFS(温室气体排放!A:A, 2014, 温室气体排放!G:G, "强化或放宽目标（消极气候影响）") + COUNTIFS(污染!A:A, 2014, 污染!G:G, "新目标") + COUNTIFS(污染!A:A, 2014, 污染!G:G, "强化或放宽目标（气候影响不明确）") + COUNTIFS(污染!A:A, 2014, 污染!G:G, "强化或放宽目标（积极气候影响）") + COUNTIFS(污染!A:A, 2014, 污染!G:G, "强化或放宽目标（消极气候影响）") + COUNTIFS('能源|电力'!A:A, 2014, '能源|电力'!G:G, "新目标") + COUNTIFS('能源|电力'!A:A, 2014, '能源|电力'!G:G, "强化或放宽目标（气候影响不明确）") + COUNTIFS('能源|电力'!A:A, 2014, '能源|电力'!G:G, "强化或放宽目标（积极气候影响）") + COUNTIFS('能源|电力'!A:A, 2014, '能源|电力'!G:G, "强化或放宽目标（消极气候影响）") + COUNTIFS(工业!A:A, 2014, 工业!G:G, "新目标") + COUNTIFS(工业!A:A, 2014, 工业!G:G, "强化或放宽目标（气候影响不明确）") + COUNTIFS(工业!A:A, 2014, 工业!G:G, "强化或放宽目标（积极气候影响）") + COUNTIFS(工业!A:A, 2014, 工业!G:G, "强化或放宽目标（消极气候影响）") + COUNTIFS(建筑!A:A, 2014, 建筑!G:G, "新目标") + COUNTIFS(建筑!A:A, 2014, 建筑!G:G, "强化或放宽目标（气候影响不明确）") + COUNTIFS(建筑!A:A, 2014, 建筑!G:G, "强化或放宽目标（积极气候影响）") + COUNTIFS(建筑!A:A, 2014, 建筑!G:G, "强化或放宽目标（消极气候影响）") + COUNTIFS(交通!A:A, 2014, 交通!G:G, "新目标") + COUNTIFS(交通!A:A, 2014, 交通!G:G, "强化或放宽目标（气候影响不明确）") + COUNTIFS(交通!A:A, 2014, 交通!G:G, "强化或放宽目标（积极气候影响）") + COUNTIFS(交通!A:A, 2014, 交通!G:G, "强化或放宽目标（消极气候影响）") + COUNTIFS('土地利用、土地利用变化和林业'!A:A, 2014, '土地利用、土地利用变化和林业'!G:G, "新目标") + COUNTIFS('土地利用、土地利用变化和林业'!A:A, 2014, '土地利用、土地利用变化和林业'!G:G, "强化或放宽目标（气候影响不明确）") + COUNTIFS('土地利用、土地利用变化和林业'!A:A, 2014, '土地利用、土地利用变化和林业'!G:G, "强化或放宽目标（积极气候影响）") + COUNTIFS('土地利用、土地利用变化和林业'!A:A, 2014, '土地利用、土地利用变化和林业'!G:G, "强化或放宽目标（消极气候影响）") + COUNTIFS(循环经济!A:A, 2014, 循环经济!G:G, "新目标") + COUNTIFS(循环经济!A:A, 2014, 循环经济!G:G, "强化或放宽目标（气候影响不明确）") + COUNTIFS(循环经济!A:A, 2014, 循环经济!G:G, "强化或放宽目标（积极气候影响）") + COUNTIFS(循环经济!A:A, 2014, 循环经济!G:G, "强化或放宽目标（消极气候影响）") + COUNTIFS(金融!A:A, 2014, 金融!G:G, "新目标") + COUNTIFS(金融!A:A, 2014, 金融!G:G, "强化或放宽目标（气候影响不明确）") + COUNTIFS(金融!A:A, 2014, 金融!G:G, "强化或放宽目标（积极气候影响）") + COUNTIFS(金融!A:A, 2014, 金融!G:G, "强化或放宽目标（消极气候影响）") | N16: 2018 | O16: =COUNTIFS(温室气体排放!F:F, 2018, 温室气体排放!G:G, "新目标") + COUNTIFS(温室气体排放!F:F, 2018, 温室气体排放!G:G, "强化或放宽目标（气候影响不明确）") + COUNTIFS(温室气体排放!F:F, 2018, 温室气体排放!G:G, "强化或放宽目标（积极气候影响）") + COUNTIFS(温室气体排放!F:F, 2018, 温室气体排放!G:G, "强化或放宽目标（消极气候影响）") + COUNTIFS(污染!F:F, 2018, 污染!G:G, "新目标") + COUNTIFS(污染!F:F, 2018, 污染!G:G, "强化或放宽目标（气候影响不明确）") + COUNTIFS(污染!F:F, 2018, 污染!G:G, "强化或放宽目标（积极气候影响）") + COUNTIFS(污染!F:F, 2018, 污染!G:G, "强化或放宽目标（消极气候影响）") + COUNTIFS('能源|电力'!F:F, 2018, '能源|电力'!G:G, "新目标") + COUNTIFS('能源|电力'!F:F, 2018, '能源|电力'!G:G, "强化或放宽目标（气候影响不明确）") + COUNTIFS('能源|电力'!F:F, 2018, '能源|电力'!G:G, "强化或放宽目标（积极气候影响）") + COUNTIFS('能源|电力'!F:F, 2018, '能源|电力'!G:G, "强化或放宽目标（消极气候影响）") + COUNTIFS(工业!F:F, 2018, 工业!G:G, "新目标") + COUNTIFS(工业!F:F, 2018, 工业!G:G, "强化或放宽目标（气候影响不明确）") + COUNTIFS(工业!F:F, 2018, 工业!G:G, "强化或放宽目标（积极气候影响）") + COUNTIFS(工业!F:F, 2018, 工业!G:G, "强化或放宽目标（消极气候影响）") + COUNTIFS(建筑!F:F, 2018, 建筑!G:G, "新目标") + COUNTIFS(建筑!F:F, 2018, 建筑!G:G, "强化或放宽目标（气候影响不明确）") + COUNTIFS(建筑!F:F, 2018, 建筑!G:G, "强化或放宽目标（积极气候影响）") + COUNTIFS(建筑!F:F, 2018, 建筑!G:G, "强化或放宽目标（消极气候影响）") + COUNTIFS(交通!F:F, 2018, 交通!G:G, "新目标") + COUNTIFS(交通!F:F, 2018, 交通!G:G, "强化或放宽目标（气候影响不明确）") + COUNTIFS(交通!F:F, 2018, 交通!G:G, "强化或放宽目标（积极气候影响）") + COUNTIFS(交通!F:F, 2018, 交通!G:G, "强化或放宽目标（消极气候影响）") + COUNTIFS('土地利用、土地利用变化和林业'!F:F, 2018, '土地利用、土地利用变化和林业'!G:G, "新目标") + COUNTIFS('土地利用、土地利用变化和林业'!F:F, 2018, '土地利用、土地利用变化和林业'!G:G, "强化或放宽目标（气候影响不明确）") + COUNTIFS('土地利用、土地利用变化和林业'!F:F, 2018, '土地利用、土地利用变化和林业'!G:G, "强化或放宽目标（积极气候影响）") + COUNTIFS('土地利用、土地利用变化和林业'!F:F, 2018, '土地利用、土地利用变化和林业'!G:G, "强化或放宽目标（消极气候影响）") + COUNTIFS(循环经济!F:F, 2018, 循环经济!G:G, "新目标") + COUNTIFS(循环经济!F:F, 2018, 循环经济!G:G, "强化或放宽目标（气候影响不明确）") + COUNTIFS(循环经济!F:F, 2018, 循环经济!G:G, "强化或放宽目标（积极气候影响）") + COUNTIFS(循环经济!F:F, 2018, 循环经济!G:G, "强化或放宽目标（消极气候影响）") + COUNTIFS(金融!F:F, 2018, 金融!G:G, "新目标") + COUNTIFS(金融!F:F, 2018, 金融!G:G, "强化或放宽目标（气候影响不明确）") + COUNTIFS(金融!F:F, 2018, 金融!G:G, "强化或放宽目标（积极气候影响）") + COUNTIFS(金融!F:F, 2018, 金融!G:G, "强化或放宽目标（消极气候影响）") | Q16: 涉煤 | R16: =COUNTIFS(温室气体排放!H:H, "涉煤", 温室气体排放!G:G, "新目标") + COUNTIFS(温室气体排放!H:H, "涉煤", 温室气体排放!G:G, "强化或放宽目标（气候影响不明确）") + COUNTIFS(温室气体排放!H:H, "涉煤", 温室气体排放!G:G, "强化或放宽目标（积极气候影响）") + COUNTIFS(温室气体排放!H:H, "涉煤", 温室气体排放!G:G, "强化或放宽目标（消极气候影响）") + COUNTIFS(污染!H:H, "涉煤", 污染!G:G, "新目标") + COUNTIFS(污染!H:H, "涉煤", 污染!G:G, "强化或放宽目标（气候影响不明确）") + COUNTIFS(污染!H:H, "涉煤", 污染!G:G, "强化或放宽目标（积极气候影响）") + COUNTIFS(污染!H:H, "涉煤", 污染!G:G, "强化或放宽目标（消极气候影响）") + COUNTIFS('能源|电力'!H:H, "涉煤", '能源|电力'!G:G, "新目标") + COUNTIFS('能源|电力'!H:H, "涉煤", '能源|电力'!G:G, "强化或放宽目标（气候影响不明确）") + COUNTIFS('能源|电力'!H:H, "涉煤", '能源|电力'!G:G, "强化或放宽目标（积极气候影响）") + COUNTIFS('能源|电力'!H:H, "涉煤", '能源|电力'!G:G, "强化或放宽目标（消极气候影响）") + COUNTIFS(工业!H:H, "涉煤", 工业!G:G, "新目标") + COUNTIFS(工业!H:H, "涉煤", 工业!G:G, "强化或放宽目标（气候影响不明确）") + COUNTIFS(工业!H:H, "涉煤", 工业!G:G, "强化或放宽目标（积极气候影响）") + COUNTIFS(工业!H:H, "涉煤", 工业!G:G, "强化或放宽目标（消极气候影响）") + COUNTIFS(建筑!H:H, "涉煤", 建筑!G:G, "新目标") + COUNTIFS(建筑!H:H, "涉煤", 建筑!G:G, "强化或放宽目标（气候影响不明确）") + COUNTIFS(建筑!H:H, "涉煤", 建筑!G:G, "强化或放宽目标（积极气候影响）") + COUNTIFS(建筑!H:H, "涉煤", 建筑!G:G, "强化或放宽目标（消极气候影响）") + COUNTIFS(交通!H:H, "涉煤", 交通!G:G, "新目标") + COUNTIFS(交通!H:H, "涉煤", 交通!G:G, "强化或放宽目标（气候影响不明确）") + COUNTIFS(交通!H:H, "涉煤", 交通!G:G, "强化或放宽目标（积极气候影响）") + COUNTIFS(交通!H:H, "涉煤", 交通!G:G, "强化或放宽目标（消极气候影响）") + COUNTIFS('土地利用、土地利用变化和林业'!H:H, "涉煤", '土地利用、土地利用变化和林业'!G:G, "新目标") + COUNTIFS('土地利用、土地利用变化和林业'!H:H, "涉煤", '土地利用、土地利用变化和林业'!G:G, "强化或放宽目标（气候影响不明确）") + COUNTIFS('土地利用、土地利用变化和林业'!H:H, "涉煤", '土地利用、土地利用变化和林业'!G:G, "强化或放宽目标（积极气候影响）") + COUNTIFS('土地利用、土地利用变化和林业'!H:H, "涉煤", '土地利用、土地利用变化和林业'!G:G, "强化或放宽目标（消极气候影响）") + COUNTIFS(循环经济!H:H, "涉煤", 循环经济!G:G, "新目标") + COUNTIFS(循环经济!H:H, "涉煤", 循环经济!G:G, "强化或放宽目标（气候影响不明确）") + COUNTIFS(循环经济!H:H, "涉煤", 循环经济!G:G, "强化或放宽目标（积极气候影响）") + COUNTIFS(循环经济!H:H, "涉煤", 循环经济!G:G, "强化或放宽目标（消极气候影响）") + COUNTIFS(金融!H:H, "涉煤", 金融!G:G, "新目标") + COUNTIFS(金融!H:H, "涉煤", 金融!G:G, "强化或放宽目标（气候影响不明确）") + COUNTIFS(金融!H:H, "涉煤", 金融!G:G, "强化或放宽目标（积极气候影响）") + COUNTIFS(金融!H:H, "涉煤", 金融!G:G, "强化或放宽目标（消极气候影响）")
K17: 2015 | L17: =COUNTIFS(温室气体排放!A:A, 2015, 温室气体排放!G:G, "新目标") + COUNTIFS(温室气体排放!A:A, 2015, 温室气体排放!G:G, "强化或放宽目标（气候影响不明确）") + COUNTIFS(温室气体排放!A:A, 2015, 温室气体排放!G:G, "强化或放宽目标（积极气候影响）") + COUNTIFS(温室气体排放!A:A, 2015, 温室气体排放!G:G, "强化或放宽目标（消极气候影响）") + COUNTIFS(污染!A:A, 2015, 污染!G:G, "新目标") + COUNTIFS(污染!A:A, 2015, 污染!G:G, "强化或放宽目标（气候影响不明确）") + COUNTIFS(污染!A:A, 2015, 污染!G:G, "强化或放宽目标（积极气候影响）") + COUNTIFS(污染!A:A, 2015, 污染!G:G, "强化或放宽目标（消极气候影响）") + COUNTIFS('能源|电力'!A:A, 2015, '能源|电力'!G:G, "新目标") + COUNTIFS('能源|电力'!A:A, 2015, '能源|电力'!G:G, "强化或放宽目标（气候影响不明确）") + COUNTIFS('能源|电力'!A:A, 2015, '能源|电力'!G:G, "强化或放宽目标（积极气候影响）") + COUNTIFS('能源|电力'!A:A, 2015, '能源|电力'!G:G, "强化或放宽目标（消极气候影响）") + COUNTIFS(工业!A:A, 2015, 工业!G:G, "新目标") + COUNTIFS(工业!A:A, 2015, 工业!G:G, "强化或放宽目标（气候影响不明确）") + COUNTIFS(工业!A:A, 2015, 工业!G:G, "强化或放宽目标（积极气候影响）") + COUNTIFS(工业!A:A, 2015, 工业!G:G, "强化或放宽目标（消极气候影响）") + COUNTIFS(建筑!A:A, 2015, 建筑!G:G, "新目标") + COUNTIFS(建筑!A:A, 2015, 建筑!G:G, "强化或放宽目标（气候影响不明确）") + COUNTIFS(建筑!A:A, 2015, 建筑!G:G, "强化或放宽目标（积极气候影响）") + COUNTIFS(建筑!A:A, 2015, 建筑!G:G, "强化或放宽目标（消极气候影响）") + COUNTIFS(交通!A:A, 2015, 交通!G:G, "新目标") + COUNTIFS(交通!A:A, 2015, 交通!G:G, "强化或放宽目标（气候影响不明确）") + COUNTIFS(交通!A:A, 2015, 交通!G:G, "强化或放宽目标（积极气候影响）") + COUNTIFS(交通!A:A, 2015, 交通!G:G, "强化或放宽目标（消极气候影响）") + COUNTIFS('土地利用、土地利用变化和林业'!A:A, 2015, '土地利用、土地利用变化和林业'!G:G, "新目标") + COUNTIFS('土地利用、土地利用变化和林业'!A:A, 2015, '土地利用、土地利用变化和林业'!G:G, "强化或放宽目标（气候影响不明确）") + COUNTIFS('土地利用、土地利用变化和林业'!A:A, 2015, '土地利用、土地利用变化和林业'!G:G, "强化或放宽目标（积极气候影响）") + COUNTIFS('土地利用、土地利用变化和林业'!A:A, 2015, '土地利用、土地利用变化和林业'!G:G, "强化或放宽目标（消极气候影响）") + COUNTIFS(循环经济!A:A, 2015, 循环经济!G:G, "新目标") + COUNTIFS(循环经济!A:A, 2015, 循环经济!G:G, "强化或放宽目标（气候影响不明确）") + COUNTIFS(循环经济!A:A, 2015, 循环经济!G:G, "强化或放宽目标（积极气候影响）") + COUNTIFS(循环经济!A:A, 2015, 循环经济!G:G, "强化或放宽目标（消极气候影响）") + COUNTIFS(金融!A:A, 2015, 金融!G:G, "新目标") + COUNTIFS(金融!A:A, 2015, 金融!G:G, "强化或放宽目标（气候影响不明确）") + COUNTIFS(金融!A:A, 2015, 金融!G:G, "强化或放宽目标（积极气候影响）") + COUNTIFS(金融!A:A, 2015, 金融!G:G, "强化或放宽目标（消极气候影响）") | N17: 2019 | O17: =COUNTIFS(温室气体排放!F:F, 2019, 温室气体排放!G:G, "新目标") + COUNTIFS(温室气体排放!F:F, 2019, 温室气体排放!G:G, "强化或放宽目标（气候影响不明确）") + COUNTIFS(温室气体排放!F:F, 2019, 温室气体排放!G:G, "强化或放宽目标（积极气候影响）") + COUNTIFS(温室气体排放!F:F, 2019, 温室气体排放!G:G, "强化或放宽目标（消极气候影响）") + COUNTIFS(污染!F:F, 2019, 污染!G:G, "新目标") + COUNTIFS(污染!F:F, 2019, 污染!G:G, "强化或放宽目标（气候影响不明确）") + COUNTIFS(污染!F:F, 2019, 污染!G:G, "强化或放宽目标（积极气候影响）") + COUNTIFS(污染!F:F, 2019, 污染!G:G, "强化或放宽目标（消极气候影响）") + COUNTIFS('能源|电力'!F:F, 2019, '能源|电力'!G:G, "新目标") + COUNTIFS('能源|电力'!F:F, 2019, '能源|电力'!G:G, "强化或放宽目标（气候影响不明确）") + COUNTIFS('能源|电力'!F:F, 2019, '能源|电力'!G:G, "强化或放宽目标（积极气候影响）") + COUNTIFS('能源|电力'!F:F, 2019, '能源|电力'!G:G, "强化或放宽目标（消极气候影响）") + COUNTIFS(工业!F:F, 2019, 工业!G:G, "新目标") + COUNTIFS(工业!F:F, 2019, 工业!G:G, "强化或放宽目标（气候影响不明确）") + COUNTIFS(工业!F:F, 2019, 工业!G:G, "强化或放宽目标（积极气候影响）") + COUNTIFS(工业!F:F, 2019, 工业!G:G, "强化或放宽目标（消极气候影响）") + COUNTIFS(建筑!F:F, 2019, 建筑!G:G, "新目标") + COUNTIFS(建筑!F:F, 2019, 建筑!G:G, "强化或放宽目标（气候影响不明确）") + COUNTIFS(建筑!F:F, 2019, 建筑!G:G, "强化或放宽目标（积极气候影响）") + COUNTIFS(建筑!F:F, 2019, 建筑!G:G, "强化或放宽目标（消极气候影响）") + COUNTIFS(交通!F:F, 2019, 交通!G:G, "新目标") + COUNTIFS(交通!F:F, 2019, 交通!G:G, "强化或放宽目标（气候影响不明确）") + COUNTIFS(交通!F:F, 2019, 交通!G:G, "强化或放宽目标（积极气候影响）") + COUNTIFS(交通!F:F, 2019, 交通!G:G, "强化或放宽目标（消极气候影响）") + COUNTIFS('土地利用、土地利用变化和林业'!F:F, 2019, '土地利用、土地利用变化和林业'!G:G, "新目标") + COUNTIFS('土地利用、土地利用变化和林业'!F:F, 2019, '土地利用、土地利用变化和林业'!G:G, "强化或放宽目标（气候影响不明确）") + COUNTIFS('土地利用、土地利用变化和林业'!F:F, 2019, '土地利用、土地利用变化和林业'!G:G, "强化或放宽目标（积极气候影响）") + COUNTIFS('土地利用、土地利用变化和林业'!F:F, 2019, '土地利用、土地利用变化和林业'!G:G, "强化或放宽目标（消极气候影响）") + COUNTIFS(循环经济!F:F, 2019, 循环经济!G:G, "新目标") + COUNTIFS(循环经济!F:F, 2019, 循环经济!G:G, "强化或放宽目标（气候影响不明确）") + COUNTIFS(循环经济!F:F, 2019, 循环经济!G:G, "强化或放宽目标（积极气候影响）") + COUNTIFS(循环经济!F:F, 2019, 循环经济!G:G, "强化或放宽目标（消极气候影响）") + COUNTIFS(金融!F:F, 2019, 金融!G:G, "新目标") + COUNTIFS(金融!F:F, 2019, 金融!G:G, "强化或放宽目标（气候影响不明确）") + COUNTIFS(金融!F:F, 2019, 金融!G:G, "强化或放宽目标（积极气候影响）") + COUNTIFS(金融!F:F, 2019, 金融!G:G, "强化或放宽目标（消极气候影响）") | Q17: 生产导向 | R17: =COUNTIFS(温室气体排放!H:H, "生产导向", 温室气体排放!G:G, "新目标") + COUNTIFS(温室气体排放!H:H, "生产导向", 温室气体排放!G:G, "强化或放宽目标（气候影响不明确）") + COUNTIFS(温室气体排放!H:H, "生产导向", 温室气体排放!G:G, "强化或放宽目标（积极气候影响）") + COUNTIFS(温室气体排放!H:H, "生产导向", 温室气体排放!G:G, "强化或放宽目标（消极气候影响）") + COUNTIFS(污染!H:H, "生产导向", 污染!G:G, "新目标") + COUNTIFS(污染!H:H, "生产导向", 污染!G:G, "强化或放宽目标（气候影响不明确）") + COUNTIFS(污染!H:H, "生产导向", 污染!G:G, "强化或放宽目标（积极气候影响）") + COUNTIFS(污染!H:H, "生产导向", 污染!G:G, "强化或放宽目标（消极气候影响）") + COUNTIFS('能源|电力'!H:H, "生产导向", '能源|电力'!G:G, "新目标") + COUNTIFS('能源|电力'!H:H, "生产导向", '能源|电力'!G:G, "强化或放宽目标（气候影响不明确）") + COUNTIFS('能源|电力'!H:H, "生产导向", '能源|电力'!G:G, "强化或放宽目标（积极气候影响）") + COUNTIFS('能源|电力'!H:H, "生产导向", '能源|电力'!G:G, "强化或放宽目标（消极气候影响）") + COUNTIFS(工业!H:H, "生产导向", 工业!G:G, "新目标") + COUNTIFS(工业!H:H, "生产导向", 工业!G:G, "强化或放宽目标（气候影响不明确）") + COUNTIFS(工业!H:H, "生产导向", 工业!G:G, "强化或放宽目标（积极气候影响）") + COUNTIFS(工业!H:H, "生产导向", 工业!G:G, "强化或放宽目标（消极气候影响）") + COUNTIFS(建筑!H:H, "生产导向", 建筑!G:G, "新目标") + COUNTIFS(建筑!H:H, "生产导向", 建筑!G:G, "强化或放宽目标（气候影响不明确）") + COUNTIFS(建筑!H:H, "生产导向", 建筑!G:G, "强化或放宽目标（积极气候影响）") + COUNTIFS(建筑!H:H, "生产导向", 建筑!G:G, "强化或放宽目标（消极气候影响）") + COUNTIFS(交通!H:H, "生产导向", 交通!G:G, "新目标") + COUNTIFS(交通!H:H, "生产导向", 交通!G:G, "强化或放宽目标（气候影响不明确）") + COUNTIFS(交通!H:H, "生产导向", 交通!G:G, "强化或放宽目标（积极气候影响）") + COUNTIFS(交通!H:H, "生产导向", 交通!G:G, "强化或放宽目标（消极气候影响）") + COUNTIFS('土地利用、土地利用变化和林业'!H:H, "生产导向", '土地利用、土地利用变化和林业'!G:G, "新目标") + COUNTIFS('土地利用、土地利用变化和林业'!H:H, "生产导向", '土地利用、土地利用变化和林业'!G:G, "强化或放宽目标（气候影响不明确）") + COUNTIFS('土地利用、土地利用变化和林业'!H:H, "生产导向", '土地利用、土地利用变化和林业'!G:G, "强化或放宽目标（积极气候影响）") + COUNTIFS('土地利用、土地利用变化和林业'!H:H, "生产导向", '土地利用、土地利用变化和林业'!G:G, "强化或放宽目标（消极气候影响）") + COUNTIFS(循环经济!H:H, "生产导向", 循环经济!G:G, "新目标") + COUNTIFS(循环经济!H:H, "生产导向", 循环经济!G:G, "强化或放宽目标（气候影响不明确）") + COUNTIFS(循环经济!H:H, "生产导向", 循环经济!G:G, "强化或放宽目标（积极气候影响）") + COUNTIFS(循环经济!H:H, "生产导向", 循环经济!G:G, "强化或放宽目标（消极气候影响）") + COUNTIFS(金融!H:H, "生产导向", 金融!G:G, "新目标") + COUNTIFS(金融!H:H, "生产导向", 金融!G:G, "强化或放宽目标（气候影响不明确）") + COUNTIFS(金融!H:H, "生产导向", 金融!G:G, "强化或放宽目标（积极气候影响）") + COUNTIFS(金融!H:H, "生产导向", 金融!G:G, "强化或放宽目标（消极气候影响）")
K18: 2016 | L18: =COUNTIFS(温室气体排放!A:A, 2016, 温室气体排放!G:G, "新目标") + COUNTIFS(温室气体排放!A:A, 2016, 温室气体排放!G:G, "强化或放宽目标（气候影响不明确）") + COUNTIFS(温室气体排放!A:A, 2016, 温室气体排放!G:G, "强化或放宽目标（积极气候影响）") + COUNTIFS(温室气体排放!A:A, 2016, 温室气体排放!G:G, "强化或放宽目标（消极气候影响）") + COUNTIFS(污染!A:A, 2016, 污染!G:G, "新目标") + COUNTIFS(污染!A:A, 2016, 污染!G:G, "强化或放宽目标（气候影响不明确）") + COUNTIFS(污染!A:A, 2016, 污染!G:G, "强化或放宽目标（积极气候影响）") + COUNTIFS(污染!A:A, 2016, 污染!G:G, "强化或放宽目标（消极气候影响）") + COUNTIFS('能源|电力'!A:A, 2016, '能源|电力'!G:G, "新目标") + COUNTIFS('能源|电力'!A:A, 2016, '能源|电力'!G:G, "强化或放宽目标（气候影响不明确）") + COUNTIFS('能源|电力'!A:A, 2016, '能源|电力'!G:G, "强化或放宽目标（积极气候影响）") + COUNTIFS('能源|电力'!A:A, 2016, '能源|电力'!G:G, "强化或放宽目标（消极气候影响）") + COUNTIFS(工业!A:A, 2016, 工业!G:G, "新目标") + COUNTIFS(工业!A:A, 2016, 工业!G:G, "强化或放宽目标（气候影响不明确）") + COUNTIFS(工业!A:A, 2016, 工业!G:G, "强化或放宽目标（积极气候影响）") + COUNTIFS(工业!A:A, 2016, 工业!G:G, "强化或放宽目标（消极气候影响）") + COUNTIFS(建筑!A:A, 2016, 建筑!G:G, "新目标") + COUNTIFS(建筑!A:A, 2016, 建筑!G:G, "强化或放宽目标（气候影响不明确）") + COUNTIFS(建筑!A:A, 2016, 建筑!G:G, "强化或放宽目标（积极气候影响）") + COUNTIFS(建筑!A:A, 2016, 建筑!G:G, "强化或放宽目标（消极气候影响）") + COUNTIFS(交通!A:A, 2016, 交通!G:G, "新目标") + COUNTIFS(交通!A:A, 2016, 交通!G:G, "强化或放宽目标（气候影响不明确）") + COUNTIFS(交通!A:A, 2016, 交通!G:G, "强化或放宽目标（积极气候影响）") + COUNTIFS(交通!A:A, 2016, 交通!G:G, "强化或放宽目标（消极气候影响）") + COUNTIFS('土地利用、土地利用变化和林业'!A:A, 2016, '土地利用、土地利用变化和林业'!G:G, "新目标") + COUNTIFS('土地利用、土地利用变化和林业'!A:A, 2016, '土地利用、土地利用变化和林业'!G:G, "强化或放宽目标（气候影响不明确）") + COUNTIFS('土地利用、土地利用变化和林业'!A:A, 2016, '土地利用、土地利用变化和林业'!G:G, "强化或放宽目标（积极气候影响）") + COUNTIFS('土地利用、土地利用变化和林业'!A:A, 2016, '土地利用、土地利用变化和林业'!G:G, "强化或放宽目标（消极气候影响）") + COUNTIFS(循环经济!A:A, 2016, 循环经济!G:G, "新目标") + COUNTIFS(循环经济!A:A, 2016, 循环经济!G:G, "强化或放宽目标（气候影响不明确）") + COUNTIFS(循环经济!A:A, 2016, 循环经济!G:G, "强化或放宽目标（积极气候影响）") + COUNTIFS(循环经济!A:A, 2016, 循环经济!G:G, "强化或放宽目标（消极气候影响）") + COUNTIFS(金融!A:A, 2016, 金融!G:G, "新目标") + COUNTIFS(金融!A:A, 2016, 金融!G:G, "强化或放宽目标（气候影响不明确）") + COUNTIFS(金融!A:A, 2016, 金融!G:G, "强化或放宽目标（积极气候影响）") + COUNTIFS(金融!A:A, 2016, 金融!G:G, "强化或放宽目标（消极气候影响）") | N18: 2020 | O18: =COUNTIFS(温室气体排放!F:F, 2020, 温室气体排放!G:G, "新目标") + COUNTIFS(温室气体排放!F:F, 2020, 温室气体排放!G:G, "强化或放宽目标（气候影响不明确）") + COUNTIFS(温室气体排放!F:F, 2020, 温室气体排放!G:G, "强化或放宽目标（积极气候影响）") + COUNTIFS(温室气体排放!F:F, 2020, 温室气体排放!G:G, "强化或放宽目标（消极气候影响）") + COUNTIFS(污染!F:F, 2020, 污染!G:G, "新目标") + COUNTIFS(污染!F:F, 2020, 污染!G:G, "强化或放宽目标（气候影响不明确）") + COUNTIFS(污染!F:F, 2020, 污染!G:G, "强化或放宽目标（积极气候影响）") + COUNTIFS(污染!F:F, 2020, 污染!G:G, "强化或放宽目标（消极气候影响）") + COUNTIFS('能源|电力'!F:F, 2020, '能源|电力'!G:G, "新目标") + COUNTIFS('能源|电力'!F:F, 2020, '能源|电力'!G:G, "强化或放宽目标（气候影响不明确）") + COUNTIFS('能源|电力'!F:F, 2020, '能源|电力'!G:G, "强化或放宽目标（积极气候影响）") + COUNTIFS('能源|电力'!F:F, 2020, '能源|电力'!G:G, "强化或放宽目标（消极气候影响）") + COUNTIFS(工业!F:F, 2020, 工业!G:G, "新目标") + COUNTIFS(工业!F:F, 2020, 工业!G:G, "强化或放宽目标（气候影响不明确）") + COUNTIFS(工业!F:F, 2020, 工业!G:G, "强化或放宽目标（积极气候影响）") + COUNTIFS(工业!F:F, 2020, 工业!G:G, "强化或放宽目标（消极气候影响）") + COUNTIFS(建筑!F:F, 2020, 建筑!G:G, "新目标") + COUNTIFS(建筑!F:F, 2020, 建筑!G:G, "强化或放宽目标（气候影响不明确）") + COUNTIFS(建筑!F:F, 2020, 建筑!G:G, "强化或放宽目标（积极气候影响）") + COUNTIFS(建筑!F:F, 2020, 建筑!G:G, "强化或放宽目标（消极气候影响）") + COUNTIFS(交通!F:F, 2020, 交通!G:G, "新目标") + COUNTIFS(交通!F:F, 2020, 交通!G:G, "强化或放宽目标（气候影响不明确）") + COUNTIFS(交通!F:F, 2020, 交通!G:G, "强化或放宽目标（积极气候影响）") + COUNTIFS(交通!F:F, 2020, 交通!G:G, "强化或放宽目标（消极气候影响）") + COUNTIFS('土地利用、土地利用变化和林业'!F:F, 2020, '土地利用、土地利用变化和林业'!G:G, "新目标") + COUNTIFS('土地利用、土地利用变化和林业'!F:F, 2020, '土地利用、土地利用变化和林业'!G:G, "强化或放宽目标（气候影响不明确）") + COUNTIFS('土地利用、土地利用变化和林业'!F:F, 2020, '土地利用、土地利用变化和林业'!G:G, "强化或放宽目标（积极气候影响）") + COUNTIFS('土地利用、土地利用变化和林业'!F:F, 2020, '土地利用、土地利用变化和林业'!G:G, "强化或放宽目标（消极气候影响）") + COUNTIFS(循环经济!F:F, 2020, 循环经济!G:G, "新目标") + COUNTIFS(循环经济!F:F, 2020, 循环经济!G:G, "强化或放宽目标（气候影响不明确）") + COUNTIFS(循环经济!F:F, 2020, 循环经济!G:G, "强化或放宽目标（积极气候影响）") + COUNTIFS(循环经济!F:F, 2020, 循环经济!G:G, "强化或放宽目标（消极气候影响）") + COUNTIFS(金融!F:F, 2020, 金融!G:G, "新目标") + COUNTIFS(金融!F:F, 2020, 金融!G:G, "强化或放宽目标（气候影响不明确）") + COUNTIFS(金融!F:F, 2020, 金融!G:G, "强化或放宽目标（积极气候影响）") + COUNTIFS(金融!F:F, 2020, 金融!G:G, "强化或放宽目标（消极气候影响）") | Q18: 工业转型 | R18: =COUNTIFS(温室气体排放!H:H, "工业转型", 温室气体排放!G:G, "新目标") + COUNTIFS(温室气体排放!H:H, "工业转型", 温室气体排放!G:G, "强化或放宽目标（气候影响不明确）") + COUNTIFS(温室气体排放!H:H, "工业转型", 温室气体排放!G:G, "强化或放宽目标（积极气候影响）") + COUNTIFS(温室气体排放!H:H, "工业转型", 温室气体排放!G:G, "强化或放宽目标（消极气候影响）") + COUNTIFS(污染!H:H, "工业转型", 污染!G:G, "新目标") + COUNTIFS(污染!H:H, "工业转型", 污染!G:G, "强化或放宽目标（气候影响不明确）") + COUNTIFS(污染!H:H, "工业转型", 污染!G:G, "强化或放宽目标（积极气候影响）") + COUNTIFS(污染!H:H, "工业转型", 污染!G:G, "强化或放宽目标（消极气候影响）") + COUNTIFS('能源|电力'!H:H, "工业转型", '能源|电力'!G:G, "新目标") + COUNTIFS('能源|电力'!H:H, "工业转型", '能源|电力'!G:G, "强化或放宽目标（气候影响不明确）") + COUNTIFS('能源|电力'!H:H, "工业转型", '能源|电力'!G:G, "强化或放宽目标（积极气候影响）") + COUNTIFS('能源|电力'!H:H, "工业转型", '能源|电力'!G:G, "强化或放宽目标（消极气候影响）") + COUNTIFS(工业!H:H, "工业转型", 工业!G:G, "新目标") + COUNTIFS(工业!H:H, "工业转型", 工业!G:G, "强化或放宽目标（气候影响不明确）") + COUNTIFS(工业!H:H, "工业转型", 工业!G:G, "强化或放宽目标（积极气候影响）") + COUNTIFS(工业!H:H, "工业转型", 工业!G:G, "强化或放宽目标（消极气候影响）") + COUNTIFS(建筑!H:H, "工业转型", 建筑!G:G, "新目标") + COUNTIFS(建筑!H:H, "工业转型", 建筑!G:G, "强化或放宽目标（气候影响不明确）") + COUNTIFS(建筑!H:H, "工业转型", 建筑!G:G, "强化或放宽目标（积极气候影响）") + COUNTIFS(建筑!H:H, "工业转型", 建筑!G:G, "强化或放宽目标（消极气候影响）") + COUNTIFS(交通!H:H, "工业转型", 交通!G:G, "新目标") + COUNTIFS(交通!H:H, "工业转型", 交通!G:G, "强化或放宽目标（气候影响不明确）") + COUNTIFS(交通!H:H, "工业转型", 交通!G:G, "强化或放宽目标（积极气候影响）") + COUNTIFS(交通!H:H, "工业转型", 交通!G:G, "强化或放宽目标（消极气候影响）") + COUNTIFS('土地利用、土地利用变化和林业'!H:H, "工业转型", '土地利用、土地利用变化和林业'!G:G, "新目标") + COUNTIFS('土地利用、土地利用变化和林业'!H:H, "工业转型", '土地利用、土地利用变化和林业'!G:G, "强化或放宽目标（气候影响不明确）") + COUNTIFS('土地利用、土地利用变化和林业'!H:H, "工业转型", '土地利用、土地利用变化和林业'!G:G, "强化或放宽目标（积极气候影响）") + COUNTIFS('土地利用、土地利用变化和林业'!H:H, "工业转型", '土地利用、土地利用变化和林业'!G:G, "强化或放宽目标（消极气候影响）") + COUNTIFS(循环经济!H:H, "工业转型", 循环经济!G:G, "新目标") + COUNTIFS(循环经济!H:H, "工业转型", 循环经济!G:G, "强化或放宽目标（气候影响不明确）") + COUNTIFS(循环经济!H:H, "工业转型", 循环经济!G:G, "强化或放宽目标（积极气候影响）") + COUNTIFS(循环经济!H:H, "工业转型", 循环经济!G:G, "强化或放宽目标（消极气候影响）") + COUNTIFS(金融!H:H, "工业转型", 金融!G:G, "新目标") + COUNTIFS(金融!H:H, "工业转型", 金融!G:G, "强化或放宽目标（气候影响不明确）") + COUNTIFS(金融!H:H, "工业转型", 金融!G:G, "强化或放宽目标（积极气候影响）") + COUNTIFS(金融!H:H, "工业转型", 金融!G:G, "强化或放宽目标（消极气候影响）")
K19: 2017 | L19: =COUNTIFS(温室气体排放!A:A, 2017, 温室气体排放!G:G, "新目标") + COUNTIFS(温室气体排放!A:A, 2017, 温室气体排放!G:G, "强化或放宽目标（气候影响不明确）") + COUNTIFS(温室气体排放!A:A, 2017, 温室气体排放!G:G, "强化或放宽目标（积极气候影响）") + COUNTIFS(温室气体排放!A:A, 2017, 温室气体排放!G:G, "强化或放宽目标（消极气候影响）") + COUNTIFS(污染!A:A, 2017, 污染!G:G, "新目标") + COUNTIFS(污染!A:A, 2017, 污染!G:G, "强化或放宽目标（气候影响不明确）") + COUNTIFS(污染!A:A, 2017, 污染!G:G, "强化或放宽目标（积极气候影响）") + COUNTIFS(污染!A:A, 2017, 污染!G:G, "强化或放宽目标（消极气候影响）") + COUNTIFS('能源|电力'!A:A, 2017, '能源|电力'!G:G, "新目标") + COUNTIFS('能源|电力'!A:A, 2017, '能源|电力'!G:G, "强化或放宽目标（气候影响不明确）") + COUNTIFS('能源|电力'!A:A, 2017, '能源|电力'!G:G, "强化或放宽目标（积极气候影响）") + COUNTIFS('能源|电力'!A:A, 2017, '能源|电力'!G:G, "强化或放宽目标（消极气候影响）") + COUNTIFS(工业!A:A, 2017, 工业!G:G, "新目标") + COUNTIFS(工业!A:A, 2017, 工业!G:G, "强化或放宽目标（气候影响不明确）") + COUNTIFS(工业!A:A, 2017, 工业!G:G, "强化或放宽目标（积极气候影响）") + COUNTIFS(工业!A:A, 2017, 工业!G:G, "强化或放宽目标（消极气候影响）") + COUNTIFS(建筑!A:A, 2017, 建筑!G:G, "新目标") + COUNTIFS(建筑!A:A, 2017, 建筑!G:G, "强化或放宽目标（气候影响不明确）") + COUNTIFS(建筑!A:A, 2017, 建筑!G:G, "强化或放宽目标（积极气候影响）") + COUNTIFS(建筑!A:A, 2017, 建筑!G:G, "强化或放宽目标（消极气候影响）") + COUNTIFS(交通!A:A, 2017, 交通!G:G, "新目标") + COUNTIFS(交通!A:A, 2017, 交通!G:G, "强化或放宽目标（气候影响不明确）") + COUNTIFS(交通!A:A, 2017, 交通!G:G, "强化或放宽目标（积极气候影响）") + COUNTIFS(交通!A:A, 2017, 交通!G:G, "强化或放宽目标（消极气候影响）") + COUNTIFS('土地利用、土地利用变化和林业'!A:A, 2017, '土地利用、土地利用变化和林业'!G:G, "新目标") + COUNTIFS('土地利用、土地利用变化和林业'!A:A, 2017, '土地利用、土地利用变化和林业'!G:G, "强化或放宽目标（气候影响不明确）") + COUNTIFS('土地利用、土地利用变化和林业'!A:A, 2017, '土地利用、土地利用变化和林业'!G:G, "强化或放宽目标（积极气候影响）") + COUNTIFS('土地利用、土地利用变化和林业'!A:A, 2017, '土地利用、土地利用变化和林业'!G:G, "强化或放宽目标（消极气候影响）") + COUNTIFS(循环经济!A:A, 2017, 循环经济!G:G, "新目标") + COUNTIFS(循环经济!A:A, 2017, 循环经济!G:G, "强化或放宽目标（气候影响不明确）") + COUNTIFS(循环经济!A:A, 2017, 循环经济!G:G, "强化或放宽目标（积极气候影响）") + COUNTIFS(循环经济!A:A, 2017, 循环经济!G:G, "强化或放宽目标（消极气候影响）") + COUNTIFS(金融!A:A, 2017, 金融!G:G, "新目标") + COUNTIFS(金融!A:A, 2017, 金融!G:G, "强化或放宽目标（气候影响不明确）") + COUNTIFS(金融!A:A, 2017, 金融!G:G, "强化或放宽目标（积极气候影响）") + COUNTIFS(金融!A:A, 2017, 金融!G:G, "强化或放宽目标（消极气候影响）") | N19: 十三五 | O19: =COUNTIFS(温室气体排放!F:F, "十三五", 温室气体排放!G:G, "新目标") + COUNTIFS(温室气体排放!F:F, "十三五", 温室气体排放!G:G, "强化或放宽目标（气候影响不明确）") + COUNTIFS(温室气体排放!F:F, "十三五", 温室气体排放!G:G, "强化或放宽目标（积极气候影响）") + COUNTIFS(温室气体排放!F:F, "十三五", 温室气体排放!G:G, "强化或放宽目标（消极气候影响）") + COUNTIFS(污染!F:F, "十三五", 污染!G:G, "新目标") + COUNTIFS(污染!F:F, "十三五", 污染!G:G, "强化或放宽目标（气候影响不明确）") + COUNTIFS(污染!F:F, "十三五", 污染!G:G, "强化或放宽目标（积极气候影响）") + COUNTIFS(污染!F:F, "十三五", 污染!G:G, "强化或放宽目标（消极气候影响）") + COUNTIFS('能源|电力'!F:F, "十三五", '能源|电力'!G:G, "新目标") + COUNTIFS('能源|电力'!F:F, "十三五", '能源|电力'!G:G, "强化或放宽目标（气候影响不明确）") + COUNTIFS('能源|电力'!F:F, "十三五", '能源|电力'!G:G, "强化或放宽目标（积极气候影响）") + COUNTIFS('能源|电力'!F:F, "十三五", '能源|电力'!G:G, "强化或放宽目标（消极气候影响）") + COUNTIFS(工业!F:F, "十三五", 工业!G:G, "新目标") + COUNTIFS(工业!F:F, "十三五", 工业!G:G, "强化或放宽目标（气候影响不明确）") + COUNTIFS(工业!F:F, "十三五", 工业!G:G, "强化或放宽目标（积极气候影响）") + COUNTIFS(工业!F:F, "十三五", 工业!G:G, "强化或放宽目标（消极气候影响）") + COUNTIFS(建筑!F:F, "十三五", 建筑!G:G, "新目标") + COUNTIFS(建筑!F:F, "十三五", 建筑!G:G, "强化或放宽目标（气候影响不明确）") + COUNTIFS(建筑!F:F, "十三五", 建筑!G:G, "强化或放宽目标（积极气候影响）") + COUNTIFS(建筑!F:F, "十三五", 建筑!G:G, "强化或放宽目标（消极气候影响）") + COUNTIFS(交通!F:F, "十三五", 交通!G:G, "新目标") + COUNTIFS(交通!F:F, "十三五", 交通!G:G, "强化或放宽目标（气候影响不明确）") + COUNTIFS(交通!F:F, "十三五", 交通!G:G, "强化或放宽目标（积极气候影响）") + COUNTIFS(交通!F:F, "十三五", 交通!G:G, "强化或放宽目标（消极气候影响）") + COUNTIFS('土地利用、土地利用变化和林业'!F:F, "十三五", '土地利用、土地利用变化和林业'!G:G, "新目标") + COUNTIFS('土地利用、土地利用变化和林业'!F:F, "十三五", '土地利用、土地利用变化和林业'!G:G, "强化或放宽目标（气候影响不明确）") + COUNTIFS('土地利用、土地利用变化和林业'!F:F, "十三五", '土地利用、土地利用变化和林业'!G:G, "强化或放宽目标（积极气候影响）") + COUNTIFS('土地利用、土地利用变化和林业'!F:F, "十三五", '土地利用、土地利用变化和林业'!G:G, "强化或放宽目标（消极气候影响）") + COUNTIFS(循环经济!F:F, "十三五", 循环经济!G:G, "新目标") + COUNTIFS(循环经济!F:F, "十三五", 循环经济!G:G, "强化或放宽目标（气候影响不明确）") + COUNTIFS(循环经济!F:F, "十三五", 循环经济!G:G, "强化或放宽目标（积极气候影响）") + COUNTIFS(循环经济!F:F, "十三五", 循环经济!G:G, "强化或放宽目标（消极气候影响）") + COUNTIFS(金融!F:F, "十三五", 金融!G:G, "新目标") + COUNTIFS(金融!F:F, "十三五", 金融!G:G, "强化或放宽目标（气候影响不明确）") + COUNTIFS(金融!F:F, "十三五", 金融!G:G, "强化或放宽目标（积极气候影响）") + COUNTIFS(金融!F:F, "十三五", 金融!G:G, "强化或放宽目标（消极气候影响）") | Q19: 技术创新 | R19: =COUNTIFS(温室气体排放!H:H, "技术创新", 温室气体排放!G:G, "新目标") + COUNTIFS(温室气体排放!H:H, "技术创新", 温室气体排放!G:G, "强化或放宽目标（气候影响不明确）") + COUNTIFS(温室气体排放!H:H, "技术创新", 温室气体排放!G:G, "强化或放宽目标（积极气候影响）") + COUNTIFS(温室气体排放!H:H, "技术创新", 温室气体排放!G:G, "强化或放宽目标（消极气候影响）") + COUNTIFS(污染!H:H, "技术创新", 污染!G:G, "新目标") + COUNTIFS(污染!H:H, "技术创新", 污染!G:G, "强化或放宽目标（气候影响不明确）") + COUNTIFS(污染!H:H, "技术创新", 污染!G:G, "强化或放宽目标（积极气候影响）") + COUNTIFS(污染!H:H, "技术创新", 污染!G:G, "强化或放宽目标（消极气候影响）") + COUNTIFS('能源|电力'!H:H, "技术创新", '能源|电力'!G:G, "新目标") + COUNTIFS('能源|电力'!H:H, "技术创新", '能源|电力'!G:G, "强化或放宽目标（气候影响不明确）") + COUNTIFS('能源|电力'!H:H, "技术创新", '能源|电力'!G:G, "强化或放宽目标（积极气候影响）") + COUNTIFS('能源|电力'!H:H, "技术创新", '能源|电力'!G:G, "强化或放宽目标（消极气候影响）") + COUNTIFS(工业!H:H, "技术创新", 工业!G:G, "新目标") + COUNTIFS(工业!H:H, "技术创新", 工业!G:G, "强化或放宽目标（气候影响不明确）") + COUNTIFS(工业!H:H, "技术创新", 工业!G:G, "强化或放宽目标（积极气候影响）") + COUNTIFS(工业!H:H, "技术创新", 工业!G:G, "强化或放宽目标（消极气候影响）") + COUNTIFS(建筑!H:H, "技术创新", 建筑!G:G, "新目标") + COUNTIFS(建筑!H:H, "技术创新", 建筑!G:G, "强化或放宽目标（气候影响不明确）") + COUNTIFS(建筑!H:H, "技术创新", 建筑!G:G, "强化或放宽目标（积极气候影响）") + COUNTIFS(建筑!H:H, "技术创新", 建筑!G:G, "强化或放宽目标（消极气候影响）") + COUNTIFS(交通!H:H, "技术创新", 交通!G:G, "新目标") + COUNTIFS(交通!H:H, "技术创新", 交通!G:G, "强化或放宽目标（气候影响不明确）") + COUNTIFS(交通!H:H, "技术创新", 交通!G:G, "强化或放宽目标（积极气候影响）") + COUNTIFS(交通!H:H, "技术创新", 交通!G:G, "强化或放宽目标（消极气候影响）") + COUNTIFS('土地利用、土地利用变化和林业'!H:H, "技术创新", '土地利用、土地利用变化和林业'!G:G, "新目标") + COUNTIFS('土地利用、土地利用变化和林业'!H:H, "技术创新", '土地利用、土地利用变化和林业'!G:G, "强化或放宽目标（气候影响不明确）") + COUNTIFS('土地利用、土地利用变化和林业'!H:H, "技术创新", '土地利用、土地利用变化和林业'!G:G, "强化或放宽目标（积极气候影响）") + COUNTIFS('土地利用、土地利用变化和林业'!H:H, "技术创新", '土地利用、土地利用变化和林业'!G:G, "强化或放宽目标（消极气候影响）") + COUNTIFS(循环经济!H:H, "技术创新", 循环经济!G:G, "新目标") + COUNTIFS(循环经济!H:H, "技术创新", 循环经济!G:G, "强化或放宽目标（气候影响不明确）") + COUNTIFS(循环经济!H:H, "技术创新", 循环经济!G:G, "强化或放宽目标（积极气候影响）") + COUNTIFS(循环经济!H:H, "技术创新", 循环经济!G:G, "强化或放宽目标（消极气候影响）") + COUNTIFS(金融!H:H, "技术创新", 金融!G:G, "新目标") + COUNTIFS(金融!H:H, "技术创新", 金融!G:G, "强化或放宽目标（气候影响不明确）") + COUNTIFS(金融!H:H, "技术创新", 金融!G:G, "强化或放宽目标（积极气候影响）") + COUNTIFS(金融!H:H, "技术创新", 金融!G:G, "强化或放宽目标（消极气候影响）")
K20: 2018 | L20: =COUNTIFS(温室气体排放!A:A, 2018, 温室气体排放!G:G, "新目标") + COUNTIFS(温室气体排放!A:A, 2018, 温室气体排放!G:G, "强化或放宽目标（气候影响不明确）") + COUNTIFS(温室气体排放!A:A, 2018, 温室气体排放!G:G, "强化或放宽目标（积极气候影响）") + COUNTIFS(温室气体排放!A:A, 2018, 温室气体排放!G:G, "强化或放宽目标（消极气候影响）") + COUNTIFS(污染!A:A, 2018, 污染!G:G, "新目标") + COUNTIFS(污染!A:A, 2018, 污染!G:G, "强化或放宽目标（气候影响不明确）") + COUNTIFS(污染!A:A, 2018, 污染!G:G, "强化或放宽目标（积极气候影响）") + COUNTIFS(污染!A:A, 2018, 污染!G:G, "强化或放宽目标（消极气候影响）") + COUNTIFS('能源|电力'!A:A, 2018, '能源|电力'!G:G, "新目标") + COUNTIFS('能源|电力'!A:A, 2018, '能源|电力'!G:G, "强化或放宽目标（气候影响不明确）") + COUNTIFS('能源|电力'!A:A, 2018, '能源|电力'!G:G, "强化或放宽目标（积极气候影响）") + COUNTIFS('能源|电力'!A:A, 2018, '能源|电力'!G:G, "强化或放宽目标（消极气候影响）") + COUNTIFS(工业!A:A, 2018, 工业!G:G, "新目标") + COUNTIFS(工业!A:A, 2018, 工业!G:G, "强化或放宽目标（气候影响不明确）") + COUNTIFS(工业!A:A, 2018, 工业!G:G, "强化或放宽目标（积极气候影响）") + COUNTIFS(工业!A:A, 2018, 工业!G:G, "强化或放宽目标（消极气候影响）") + COUNTIFS(建筑!A:A, 2018, 建筑!G:G, "新目标") + COUNTIFS(建筑!A:A, 2018, 建筑!G:G, "强化或放宽目标（气候影响不明确）") + COUNTIFS(建筑!A:A, 2018, 建筑!G:G, "强化或放宽目标（积极气候影响）") + COUNTIFS(建筑!A:A, 2018, 建筑!G:G, "强化或放宽目标（消极气候影响）") + COUNTIFS(交通!A:A, 2018, 交通!G:G, "新目标") + COUNTIFS(交通!A:A, 2018, 交通!G:G, "强化或放宽目标（气候影响不明确）") + COUNTIFS(交通!A:A, 2018, 交通!G:G, "强化或放宽目标（积极气候影响）") + COUNTIFS(交通!A:A, 2018, 交通!G:G, "强化或放宽目标（消极气候影响）") + COUNTIFS('土地利用、土地利用变化和林业'!A:A, 2018, '土地利用、土地利用变化和林业'!G:G, "新目标") + COUNTIFS('土地利用、土地利用变化和林业'!A:A, 2018, '土地利用、土地利用变化和林业'!G:G, "强化或放宽目标（气候影响不明确）") + COUNTIFS('土地利用、土地利用变化和林业'!A:A, 2018, '土地利用、土地利用变化和林业'!G:G, "强化或放宽目标（积极气候影响）") + COUNTIFS('土地利用、土地利用变化和林业'!A:A, 2018, '土地利用、土地利用变化和林业'!G:G, "强化或放宽目标（消极气候影响）") + COUNTIFS(循环经济!A:A, 2018, 循环经济!G:G, "新目标") + COUNTIFS(循环经济!A:A, 2018, 循环经济!G:G, "强化或放宽目标（气候影响不明确）") + COUNTIFS(循环经济!A:A, 2018, 循环经济!G:G, "强化或放宽目标（积极气候影响）") + COUNTIFS(循环经济!A:A, 2018, 循环经济!G:G, "强化或放宽目标（消极气候影响）") + COUNTIFS(金融!A:A, 2018, 金融!G:G, "新目标") + COUNTIFS(金融!A:A, 2018, 金融!G:G, "强化或放宽目标（气候影响不明确）") + COUNTIFS(金融!A:A, 2018, 金融!G:G, "强化或放宽目标（积极气候影响）") + COUNTIFS(金融!A:A, 2018, 金融!G:G, "强化或放宽目标（消极气候影响）") | N20: 2021 | O20: =COUNTIFS(温室气体排放!F:F, 2021, 温室气体排放!G:G, "新目标") + COUNTIFS(温室气体排放!F:F, 2021, 温室气体排放!G:G, "强化或放宽目标（气候影响不明确）") + COUNTIFS(温室气体排放!F:F, 2021, 温室气体排放!G:G, "强化或放宽目标（积极气候影响）") + COUNTIFS(温室气体排放!F:F, 2021, 温室气体排放!G:G, "强化或放宽目标（消极气候影响）") + COUNTIFS(污染!F:F, 2021, 污染!G:G, "新目标") + COUNTIFS(污染!F:F, 2021, 污染!G:G, "强化或放宽目标（气候影响不明确）") + COUNTIFS(污染!F:F, 2021, 污染!G:G, "强化或放宽目标（积极气候影响）") + COUNTIFS(污染!F:F, 2021, 污染!G:G, "强化或放宽目标（消极气候影响）") + COUNTIFS('能源|电力'!F:F, 2021, '能源|电力'!G:G, "新目标") + COUNTIFS('能源|电力'!F:F, 2021, '能源|电力'!G:G, "强化或放宽目标（气候影响不明确）") + COUNTIFS('能源|电力'!F:F, 2021, '能源|电力'!G:G, "强化或放宽目标（积极气候影响）") + COUNTIFS('能源|电力'!F:F, 2021, '能源|电力'!G:G, "强化或放宽目标（消极气候影响）") + COUNTIFS(工业!F:F, 2021, 工业!G:G, "新目标") + COUNTIFS(工业!F:F, 2021, 工业!G:G, "强化或放宽目标（气候影响不明确）") + COUNTIFS(工业!F:F, 2021, 工业!G:G, "强化或放宽目标（积极气候影响）") + COUNTIFS(工业!F:F, 2021, 工业!G:G, "强化或放宽目标（消极气候影响）") + COUNTIFS(建筑!F:F, 2021, 建筑!G:G, "新目标") + COUNTIFS(建筑!F:F, 2021, 建筑!G:G, "强化或放宽目标（气候影响不明确）") + COUNTIFS(建筑!F:F, 2021, 建筑!G:G, "强化或放宽目标（积极气候影响）") + COUNTIFS(建筑!F:F, 2021, 建筑!G:G, "强化或放宽目标（消极气候影响）") + COUNTIFS(交通!F:F, 2021, 交通!G:G, "新目标") + COUNTIFS(交通!F:F, 2021, 交通!G:G, "强化或放宽目标（气候影响不明确）") + COUNTIFS(交通!F:F, 2021, 交通!G:G, "强化或放宽目标（积极气候影响）") + COUNTIFS(交通!F:F, 2021, 交通!G:G, "强化或放宽目标（消极气候影响）") + COUNTIFS('土地利用、土地利用变化和林业'!F:F, 2021, '土地利用、土地利用变化和林业'!G:G, "新目标") + COUNTIFS('土地利用、土地利用变化和林业'!F:F, 2021, '土地利用、土地利用变化和林业'!G:G, "强化或放宽目标（气候影响不明确）") + COUNTIFS('土地利用、土地利用变化和林业'!F:F, 2021, '土地利用、土地利用变化和林业'!G:G, "强化或放宽目标（积极气候影响）") + COUNTIFS('土地利用、土地利用变化和林业'!F:F, 2021, '土地利用、土地利用变化和林业'!G:G, "强化或放宽目标（消极气候影响）") + COUNTIFS(循环经济!F:F, 2021, 循环经济!G:G, "新目标") + COUNTIFS(循环经济!F:F, 2021, 循环经济!G:G, "强化或放宽目标（气候影响不明确）") + COUNTIFS(循环经济!F:F, 2021, 循环经济!G:G, "强化或放宽目标（积极气候影响）") + COUNTIFS(循环经济!F:F, 2021, 循环经济!G:G, "强化或放宽目标（消极气候影响）") + COUNTIFS(金融!F:F, 2021, 金融!G:G, "新目标") + COUNTIFS(金融!F:F, 2021, 金融!G:G, "强化或放宽目标（气候影响不明确）") + COUNTIFS(金融!F:F, 2021, 金融!G:G, "强化或放宽目标（积极气候影响）") + COUNTIFS(金融!F:F, 2021, 金融!G:G, "强化或放宽目标（消极气候影响）") | Q20: 绿色交通 | R20: =COUNTIFS(温室气体排放!H:H, "绿色交通", 温室气体排放!G:G, "新目标") + COUNTIFS(温室气体排放!H:H, "绿色交通", 温室气体排放!G:G, "强化或放宽目标（气候影响不明确）") + COUNTIFS(温室气体排放!H:H, "绿色交通", 温室气体排放!G:G, "强化或放宽目标（积极气候影响）") + COUNTIFS(温室气体排放!H:H, "绿色交通", 温室气体排放!G:G, "强化或放宽目标（消极气候影响）") + COUNTIFS(污染!H:H, "绿色交通", 污染!G:G, "新目标") + COUNTIFS(污染!H:H, "绿色交通", 污染!G:G, "强化或放宽目标（气候影响不明确）") + COUNTIFS(污染!H:H, "绿色交通", 污染!G:G, "强化或放宽目标（积极气候影响）") + COUNTIFS(污染!H:H, "绿色交通", 污染!G:G, "强化或放宽目标（消极气候影响）") + COUNTIFS('能源|电力'!H:H, "绿色交通", '能源|电力'!G:G, "新目标") + COUNTIFS('能源|电力'!H:H, "绿色交通", '能源|电力'!G:G, "强化或放宽目标（气候影响不明确）") + COUNTIFS('能源|电力'!H:H, "绿色交通", '能源|电力'!G:G, "强化或放宽目标（积极气候影响）") + COUNTIFS('能源|电力'!H:H, "绿色交通", '能源|电力'!G:G, "强化或放宽目标（消极气候影响）") + COUNTIFS(工业!H:H, "绿色交通", 工业!G:G, "新目标") + COUNTIFS(工业!H:H, "绿色交通", 工业!G:G, "强化或放宽目标（气候影响不明确）") + COUNTIFS(工业!H:H, "绿色交通", 工业!G:G, "强化或放宽目标（积极气候影响）") + COUNTIFS(工业!H:H, "绿色交通", 工业!G:G, "强化或放宽目标（消极气候影响）") + COUNTIFS(建筑!H:H, "绿色交通", 建筑!G:G, "新目标") + COUNTIFS(建筑!H:H, "绿色交通", 建筑!G:G, "强化或放宽目标（气候影响不明确）") + COUNTIFS(建筑!H:H, "绿色交通", 建筑!G:G, "强化或放宽目标（积极气候影响）") + COUNTIFS(建筑!H:H, "绿色交通", 建筑!G:G, "强化或放宽目标（消极气候影响）") + COUNTIFS(交通!H:H, "绿色交通", 交通!G:G, "新目标") + COUNTIFS(交通!H:H, "绿色交通", 交通!G:G, "强化或放宽目标（气候影响不明确）") + COUNTIFS(交通!H:H, "绿色交通", 交通!G:G, "强化或放宽目标（积极气候影响）") + COUNTIFS(交通!H:H, "绿色交通", 交通!G:G, "强化或放宽目标（消极气候影响）") + COUNTIFS('土地利用、土地利用变化和林业'!H:H, "绿色交通", '土地利用、土地利用变化和林业'!G:G, "新目标") + COUNTIFS('土地利用、土地利用变化和林业'!H:H, "绿色交通", '土地利用、土地利用变化和林业'!G:G, "强化或放宽目标（气候影响不明确）") + COUNTIFS('土地利用、土地利用变化和林业'!H:H, "绿色交通", '土地利用、土地利用变化和林业'!G:G, "强化或放宽目标（积极气候影响）") + COUNTIFS('土地利用、土地利用变化和林业'!H:H, "绿色交通", '土地利用、土地利用变化和林业'!G:G, "强化或放宽目标（消极气候影响）") + COUNTIFS(循环经济!H:H, "绿色交通", 循环经济!G:G, "新目标") + COUNTIFS(循环经济!H:H, "绿色交通", 循环经济!G:G, "强化或放宽目标（气候影响不明确）") + COUNTIFS(循环经济!H:H, "绿色交通", 循环经济!G:G, "强化或放宽目标（积极气候影响）") + COUNTIFS(循环经济!H:H, "绿色交通", 循环经济!G:G, "强化或放宽目标（消极气候影响）") + COUNTIFS(金融!H:H, "绿色交通", 金融!G:G, "新目标") + COUNTIFS(金融!H:H, "绿色交通", 金融!G:G, "强化或放宽目标（气候影响不明确）") + COUNTIFS(金融!H:H, "绿色交通", 金融!G:G, "强化或放宽目标（积极气候影响）") + COUNTIFS(金融!H:H, "绿色交通", 金融!G:G, "强化或放宽目标（消极气候影响）")
K21: 2019 | L21: =COUNTIFS(温室气体排放!A:A, 2019, 温室气体排放!G:G, "新目标") + COUNTIFS(温室气体排放!A:A, 2019, 温室气体排放!G:G, "强化或放宽目标（气候影响不明确）") + COUNTIFS(温室气体排放!A:A, 2019, 温室气体排放!G:G, "强化或放宽目标（积极气候影响）") + COUNTIFS(温室气体排放!A:A, 2019, 温室气体排放!G:G, "强化或放宽目标（消极气候影响）") + COUNTIFS(污染!A:A, 2019, 污染!G:G, "新目标") + COUNTIFS(污染!A:A, 2019, 污染!G:G, "强化或放宽目标（气候影响不明确）") + COUNTIFS(污染!A:A, 2019, 污染!G:G, "强化或放宽目标（积极气候影响）") + COUNTIFS(污染!A:A, 2019, 污染!G:G, "强化或放宽目标（消极气候影响）") + COUNTIFS('能源|电力'!A:A, 2019, '能源|电力'!G:G, "新目标") + COUNTIFS('能源|电力'!A:A, 2019, '能源|电力'!G:G, "强化或放宽目标（气候影响不明确）") + COUNTIFS('能源|电力'!A:A, 2019, '能源|电力'!G:G, "强化或放宽目标（积极气候影响）") + COUNTIFS('能源|电力'!A:A, 2019, '能源|电力'!G:G, "强化或放宽目标（消极气候影响）") + COUNTIFS(工业!A:A, 2019, 工业!G:G, "新目标") + COUNTIFS(工业!A:A, 2019, 工业!G:G, "强化或放宽目标（气候影响不明确）") + COUNTIFS(工业!A:A, 2019, 工业!G:G, "强化或放宽目标（积极气候影响）") + COUNTIFS(工业!A:A, 2019, 工业!G:G, "强化或放宽目标（消极气候影响）") + COUNTIFS(建筑!A:A, 2019, 建筑!G:G, "新目标") + COUNTIFS(建筑!A:A, 2019, 建筑!G:G, "强化或放宽目标（气候影响不明确）") + COUNTIFS(建筑!A:A, 2019, 建筑!G:G, "强化或放宽目标（积极气候影响）") + COUNTIFS(建筑!A:A, 2019, 建筑!G:G, "强化或放宽目标（消极气候影响）") + COUNTIFS(交通!A:A, 2019, 交通!G:G, "新目标") + COUNTIFS(交通!A:A, 2019, 交通!G:G, "强化或放宽目标（气候影响不明确）") + COUNTIFS(交通!A:A, 2019, 交通!G:G, "强化或放宽目标（积极气候影响）") + COUNTIFS(交通!A:A, 2019, 交通!G:G, "强化或放宽目标（消极气候影响）") + COUNTIFS('土地利用、土地利用变化和林业'!A:A, 2019, '土地利用、土地利用变化和林业'!G:G, "新目标") + COUNTIFS('土地利用、土地利用变化和林业'!A:A, 2019, '土地利用、土地利用变化和林业'!G:G, "强化或放宽目标（气候影响不明确）") + COUNTIFS('土地利用、土地利用变化和林业'!A:A, 2019, '土地利用、土地利用变化和林业'!G:G, "强化或放宽目标（积极气候影响）") + COUNTIFS('土地利用、土地利用变化和林业'!A:A, 2019, '土地利用、土地利用变化和林业'!G:G, "强化或放宽目标（消极气候影响）") + COUNTIFS(循环经济!A:A, 2019, 循环经济!G:G, "新目标") + COUNTIFS(循环经济!A:A, 2019, 循环经济!G:G, "强化或放宽目标（气候影响不明确）") + COUNTIFS(循环经济!A:A, 2019, 循环经济!G:G, "强化或放宽目标（积极气候影响）") + COUNTIFS(循环经济!A:A, 2019, 循环经济!G:G, "强化或放宽目标（消极气候影响）") + COUNTIFS(金融!A:A, 2019, 金融!G:G, "新目标") + COUNTIFS(金融!A:A, 2019, 金融!G:G, "强化或放宽目标（气候影响不明确）") + COUNTIFS(金融!A:A, 2019, 金融!G:G, "强化或放宽目标（积极气候影响）") + COUNTIFS(金融!A:A, 2019, 金融!G:G, "强化或放宽目标（消极气候影响）") | N21: 2022 | O21: =COUNTIFS(温室气体排放!F:F, 2022, 温室气体排放!G:G, "新目标") + COUNTIFS(温室气体排放!F:F, 2022, 温室气体排放!G:G, "强化或放宽目标（气候影响不明确）") + COUNTIFS(温室气体排放!F:F, 2022, 温室气体排放!G:G, "强化或放宽目标（积极气候影响）") + COUNTIFS(温室气体排放!F:F, 2022, 温室气体排放!G:G, "强化或放宽目标（消极气候影响）") + COUNTIFS(污染!F:F, 2022, 污染!G:G, "新目标") + COUNTIFS(污染!F:F, 2022, 污染!G:G, "强化或放宽目标（气候影响不明确）") + COUNTIFS(污染!F:F, 2022, 污染!G:G, "强化或放宽目标（积极气候影响）") + COUNTIFS(污染!F:F, 2022, 污染!G:G, "强化或放宽目标（消极气候影响）") + COUNTIFS('能源|电力'!F:F, 2022, '能源|电力'!G:G, "新目标") + COUNTIFS('能源|电力'!F:F, 2022, '能源|电力'!G:G, "强化或放宽目标（气候影响不明确）") + COUNTIFS('能源|电力'!F:F, 2022, '能源|电力'!G:G, "强化或放宽目标（积极气候影响）") + COUNTIFS('能源|电力'!F:F, 2022, '能源|电力'!G:G, "强化或放宽目标（消极气候影响）") + COUNTIFS(工业!F:F, 2022, 工业!G:G, "新目标") + COUNTIFS(工业!F:F, 2022, 工业!G:G, "强化或放宽目标（气候影响不明确）") + COUNTIFS(工业!F:F, 2022, 工业!G:G, "强化或放宽目标（积极气候影响）") + COUNTIFS(工业!F:F, 2022, 工业!G:G, "强化或放宽目标（消极气候影响）") + COUNTIFS(建筑!F:F, 2022, 建筑!G:G, "新目标") + COUNTIFS(建筑!F:F, 2022, 建筑!G:G, "强化或放宽目标（气候影响不明确）") + COUNTIFS(建筑!F:F, 2022, 建筑!G:G, "强化或放宽目标（积极气候影响）") + COUNTIFS(建筑!F:F, 2022, 建筑!G:G, "强化或放宽目标（消极气候影响）") + COUNTIFS(交通!F:F, 2022, 交通!G:G, "新目标") + COUNTIFS(交通!F:F, 2022, 交通!G:G, "强化或放宽目标（气候影响不明确）") + COUNTIFS(交通!F:F, 2022, 交通!G:G, "强化或放宽目标（积极气候影响）") + COUNTIFS(交通!F:F, 2022, 交通!G:G, "强化或放宽目标（消极气候影响）") + COUNTIFS('土地利用、土地利用变化和林业'!F:F, 2022, '土地利用、土地利用变化和林业'!G:G, "新目标") + COUNTIFS('土地利用、土地利用变化和林业'!F:F, 2022, '土地利用、土地利用变化和林业'!G:G, "强化或放宽目标（气候影响不明确）") + COUNTIFS('土地利用、土地利用变化和林业'!F:F, 2022, '土地利用、土地利用变化和林业'!G:G, "强化或放宽目标（积极气候影响）") + COUNTIFS('土地利用、土地利用变化和林业'!F:F, 2022, '土地利用、土地利用变化和林业'!G:G, "强化或放宽目标（消极气候影响）") + COUNTIFS(循环经济!F:F, 2022, 循环经济!G:G, "新目标") + COUNTIFS(循环经济!F:F, 2022, 循环经济!G:G, "强化或放宽目标（气候影响不明确）") + COUNTIFS(循环经济!F:F, 2022, 循环经济!G:G, "强化或放宽目标（积极气候影响）") + COUNTIFS(循环经济!F:F, 2022, 循环经济!G:G, "强化或放宽目标（消极气候影响）") + COUNTIFS(金融!F:F, 2022, 金融!G:G, "新目标") + COUNTIFS(金融!F:F, 2022, 金融!G:G, "强化或放宽目标（气候影响不明确）") + COUNTIFS(金融!F:F, 2022, 金融!G:G, "强化或放宽目标（积极气候影响）") + COUNTIFS(金融!F:F, 2022, 金融!G:G, "强化或放宽目标（消极气候影响）") | Q21: 环境质量 | R21: =COUNTIFS(温室气体排放!H:H, "环境质量", 温室气体排放!G:G, "新目标") + COUNTIFS(温室气体排放!H:H, "环境质量", 温室气体排放!G:G, "强化或放宽目标（气候影响不明确）") + COUNTIFS(温室气体排放!H:H, "环境质量", 温室气体排放!G:G, "强化或放宽目标（积极气候影响）") + COUNTIFS(温室气体排放!H:H, "环境质量", 温室气体排放!G:G, "强化或放宽目标（消极气候影响）") + COUNTIFS(污染!H:H, "环境质量", 污染!G:G, "新目标") + COUNTIFS(污染!H:H, "环境质量", 污染!G:G, "强化或放宽目标（气候影响不明确）") + COUNTIFS(污染!H:H, "环境质量", 污染!G:G, "强化或放宽目标（积极气候影响）") + COUNTIFS(污染!H:H, "环境质量", 污染!G:G, "强化或放宽目标（消极气候影响）") + COUNTIFS('能源|电力'!H:H, "环境质量", '能源|电力'!G:G, "新目标") + COUNTIFS('能源|电力'!H:H, "环境质量", '能源|电力'!G:G, "强化或放宽目标（气候影响不明确）") + COUNTIFS('能源|电力'!H:H, "环境质量", '能源|电力'!G:G, "强化或放宽目标（积极气候影响）") + COUNTIFS('能源|电力'!H:H, "环境质量", '能源|电力'!G:G, "强化或放宽目标（消极气候影响）") + COUNTIFS(工业!H:H, "环境质量", 工业!G:G, "新目标") + COUNTIFS(工业!H:H, "环境质量", 工业!G:G, "强化或放宽目标（气候影响不明确）") + COUNTIFS(工业!H:H, "环境质量", 工业!G:G, "强化或放宽目标（积极气候影响）") + COUNTIFS(工业!H:H, "环境质量", 工业!G:G, "强化或放宽目标（消极气候影响）") + COUNTIFS(建筑!H:H, "环境质量", 建筑!G:G, "新目标") + COUNTIFS(建筑!H:H, "环境质量", 建筑!G:G, "强化或放宽目标（气候影响不明确）") + COUNTIFS(建筑!H:H, "环境质量", 建筑!G:G, "强化或放宽目标（积极气候影响）") + COUNTIFS(建筑!H:H, "环境质量", 建筑!G:G, "强化或放宽目标（消极气候影响）") + COUNTIFS(交通!H:H, "环境质量", 交通!G:G, "新目标") + COUNTIFS(交通!H:H, "环境质量", 交通!G:G, "强化或放宽目标（气候影响不明确）") + COUNTIFS(交通!H:H, "环境质量", 交通!G:G, "强化或放宽目标（积极气候影响）") + COUNTIFS(交通!H:H, "环境质量", 交通!G:G, "强化或放宽目标（消极气候影响）") + COUNTIFS('土地利用、土地利用变化和林业'!H:H, "环境质量", '土地利用、土地利用变化和林业'!G:G, "新目标") + COUNTIFS('土地利用、土地利用变化和林业'!H:H, "环境质量", '土地利用、土地利用变化和林业'!G:G, "强化或放宽目标（气候影响不明确）") + COUNTIFS('土地利用、土地利用变化和林业'!H:H, "环境质量", '土地利用、土地利用变化和林业'!G:G, "强化或放宽目标（积极气候影响）") + COUNTIFS('土地利用、土地利用变化和林业'!H:H, "环境质量", '土地利用、土地利用变化和林业'!G:G, "强化或放宽目标（消极气候影响）") + COUNTIFS(循环经济!H:H, "环境质量", 循环经济!G:G, "新目标") + COUNTIFS(循环经济!H:H, "环境质量", 循环经济!G:G, "强化或放宽目标（气候影响不明确）") + COUNTIFS(循环经济!H:H, "环境质量", 循环经济!G:G, "强化或放宽目标（积极气候影响）") + COUNTIFS(循环经济!H:H, "环境质量", 循环经济!G:G, "强化或放宽目标（消极气候影响）") + COUNTIFS(金融!H:H, "环境质量", 金融!G:G, "新目标") + COUNTIFS(金融!H:H, "环境质量", 金融!G:G, "强化或放宽目标（气候影响不明确）") + COUNTIFS(金融!H:H, "环境质量", 金融!G:G, "强化或放宽目标（积极气候影响）") + COUNTIFS(金融!H:H, "环境质量", 金融!G:G, "强化或放宽目标（消极气候影响）")
K22: 2020 | L22: =COUNTIFS(温室气体排放!A:A, 2020, 温室气体排放!G:G, "新目标") + COUNTIFS(温室气体排放!A:A, 2020, 温室气体排放!G:G, "强化或放宽目标（气候影响不明确）") + COUNTIFS(温室气体排放!A:A, 2020, 温室气体排放!G:G, "强化或放宽目标（积极气候影响）") + COUNTIFS(温室气体排放!A:A, 2020, 温室气体排放!G:G, "强化或放宽目标（消极气候影响）") + COUNTIFS(污染!A:A, 2020, 污染!G:G, "新目标") + COUNTIFS(污染!A:A, 2020, 污染!G:G, "强化或放宽目标（气候影响不明确）") + COUNTIFS(污染!A:A, 2020, 污染!G:G, "强化或放宽目标（积极气候影响）") + COUNTIFS(污染!A:A, 2020, 污染!G:G, "强化或放宽目标（消极气候影响）") + COUNTIFS('能源|电力'!A:A, 2020, '能源|电力'!G:G, "新目标") + COUNTIFS('能源|电力'!A:A, 2020, '能源|电力'!G:G, "强化或放宽目标（气候影响不明确）") + COUNTIFS('能源|电力'!A:A, 2020, '能源|电力'!G:G, "强化或放宽目标（积极气候影响）") + COUNTIFS('能源|电力'!A:A, 2020, '能源|电力'!G:G, "强化或放宽目标（消极气候影响）") + COUNTIFS(工业!A:A, 2020, 工业!G:G, "新目标") + COUNTIFS(工业!A:A, 2020, 工业!G:G, "强化或放宽目标（气候影响不明确）") + COUNTIFS(工业!A:A, 2020, 工业!G:G, "强化或放宽目标（积极气候影响）") + COUNTIFS(工业!A:A, 2020, 工业!G:G, "强化或放宽目标（消极气候影响）") + COUNTIFS(建筑!A:A, 2020, 建筑!G:G, "新目标") + COUNTIFS(建筑!A:A, 2020, 建筑!G:G, "强化或放宽目标（气候影响不明确）") + COUNTIFS(建筑!A:A, 2020, 建筑!G:G, "强化或放宽目标（积极气候影响）") + COUNTIFS(建筑!A:A, 2020, 建筑!G:G, "强化或放宽目标（消极气候影响）") + COUNTIFS(交通!A:A, 2020, 交通!G:G, "新目标") + COUNTIFS(交通!A:A, 2020, 交通!G:G, "强化或放宽目标（气候影响不明确）") + COUNTIFS(交通!A:A, 2020, 交通!G:G, "强化或放宽目标（积极气候影响）") + COUNTIFS(交通!A:A, 2020, 交通!G:G, "强化或放宽目标（消极气候影响）") + COUNTIFS('土地利用、土地利用变化和林业'!A:A, 2020, '土地利用、土地利用变化和林业'!G:G, "新目标") + COUNTIFS('土地利用、土地利用变化和林业'!A:A, 2020, '土地利用、土地利用变化和林业'!G:G, "强化或放宽目标（气候影响不明确）") + COUNTIFS('土地利用、土地利用变化和林业'!A:A, 2020, '土地利用、土地利用变化和林业'!G:G, "强化或放宽目标（积极气候影响）") + COUNTIFS('土地利用、土地利用变化和林业'!A:A, 2020, '土地利用、土地利用变化和林业'!G:G, "强化或放宽目标（消极气候影响）") + COUNTIFS(循环经济!A:A, 2020, 循环经济!G:G, "新目标") + COUNTIFS(循环经济!A:A, 2020, 循环经济!G:G, "强化或放宽目标（气候影响不明确）") + COUNTIFS(循环经济!A:A, 2020, 循环经济!G:G, "强化或放宽目标（积极气候影响）") + COUNTIFS(循环经济!A:A, 2020, 循环经济!G:G, "强化或放宽目标（消极气候影响）") + COUNTIFS(金融!A:A, 2020, 金融!G:G, "新目标") + COUNTIFS(金融!A:A, 2020, 金融!G:G, "强化或放宽目标（气候影响不明确）") + COUNTIFS(金融!A:A, 2020, 金融!G:G, "强化或放宽目标（积极气候影响）") + COUNTIFS(金融!A:A, 2020, 金融!G:G, "强化或放宽目标（消极气候影响）") | N22: 2023 | O22: =COUNTIFS(温室气体排放!F:F, 2023, 温室气体排放!G:G, "新目标") + COUNTIFS(温室气体排放!F:F, 2023, 温室气体排放!G:G, "强化或放宽目标（气候影响不明确）") + COUNTIFS(温室气体排放!F:F, 2023, 温室气体排放!G:G, "强化或放宽目标（积极气候影响）") + COUNTIFS(温室气体排放!F:F, 2023, 温室气体排放!G:G, "强化或放宽目标（消极气候影响）") + COUNTIFS(污染!F:F, 2023, 污染!G:G, "新目标") + COUNTIFS(污染!F:F, 2023, 污染!G:G, "强化或放宽目标（气候影响不明确）") + COUNTIFS(污染!F:F, 2023, 污染!G:G, "强化或放宽目标（积极气候影响）") + COUNTIFS(污染!F:F, 2023, 污染!G:G, "强化或放宽目标（消极气候影响）") + COUNTIFS('能源|电力'!F:F, 2023, '能源|电力'!G:G, "新目标") + COUNTIFS('能源|电力'!F:F, 2023, '能源|电力'!G:G, "强化或放宽目标（气候影响不明确）") + COUNTIFS('能源|电力'!F:F, 2023, '能源|电力'!G:G, "强化或放宽目标（积极气候影响）") + COUNTIFS('能源|电力'!F:F, 2023, '能源|电力'!G:G, "强化或放宽目标（消极气候影响）") + COUNTIFS(工业!F:F, 2023, 工业!G:G, "新目标") + COUNTIFS(工业!F:F, 2023, 工业!G:G, "强化或放宽目标（气候影响不明确）") + COUNTIFS(工业!F:F, 2023, 工业!G:G, "强化或放宽目标（积极气候影响）") + COUNTIFS(工业!F:F, 2023, 工业!G:G, "强化或放宽目标（消极气候影响）") + COUNTIFS(建筑!F:F, 2023, 建筑!G:G, "新目标") + COUNTIFS(建筑!F:F, 2023, 建筑!G:G, "强化或放宽目标（气候影响不明确）") + COUNTIFS(建筑!F:F, 2023, 建筑!G:G, "强化或放宽目标（积极气候影响）") + COUNTIFS(建筑!F:F, 2023, 建筑!G:G, "强化或放宽目标（消极气候影响）") + COUNTIFS(交通!F:F, 2023, 交通!G:G, "新目标") + COUNTIFS(交通!F:F, 2023, 交通!G:G, "强化或放宽目标（气候影响不明确）") + COUNTIFS(交通!F:F, 2023, 交通!G:G, "强化或放宽目标（积极气候影响）") + COUNTIFS(交通!F:F, 2023, 交通!G:G, "强化或放宽目标（消极气候影响）") + COUNTIFS('土地利用、土地利用变化和林业'!F:F, 2023, '土地利用、土地利用变化和林业'!G:G, "新目标") + COUNTIFS('土地利用、土地利用变化和林业'!F:F, 2023, '土地利用、土地利用变化和林业'!G:G, "强化或放宽目标（气候影响不明确）") + COUNTIFS('土地利用、土地利用变化和林业'!F:F, 2023, '土地利用、土地利用变化和林业'!G:G, "强化或放宽目标（积极气候影响）") + COUNTIFS('土地利用、土地利用变化和林业'!F:F, 2023, '土地利用、土地利用变化和林业'!G:G, "强化或放宽目标（消极气候影响）") + COUNTIFS(循环经济!F:F, 2023, 循环经济!G:G, "新目标") + COUNTIFS(循环经济!F:F, 2023, 循环经济!G:G, "强化或放宽目标（气候影响不明确）") + COUNTIFS(循环经济!F:F, 2023, 循环经济!G:G, "强化或放宽目标（积极气候影响）") + COUNTIFS(循环经济!F:F, 2023, 循环经济!G:G, "强化或放宽目标（消极气候影响）") + COUNTIFS(金融!F:F, 2023, 金融!G:G, "新目标") + COUNTIFS(金融!F:F, 2023, 金融!G:G, "强化或放宽目标（气候影响不明确）") + COUNTIFS(金融!F:F, 2023, 金融!G:G, "强化或放宽目标（积极气候影响）") + COUNTIFS(金融!F:F, 2023, 金融!G:G, "强化或放宽目标（消极气候影响）") | Q22: 循环利用 | R22: =COUNTIFS(温室气体排放!H:H, "循环利用", 温室气体排放!G:G, "新目标") + COUNTIFS(温室气体排放!H:H, "循环利用", 温室气体排放!G:G, "强化或放宽目标（气候影响不明确）") + COUNTIFS(温室气体排放!H:H, "循环利用", 温室气体排放!G:G, "强化或放宽目标（积极气候影响）") + COUNTIFS(温室气体排放!H:H, "循环利用", 温室气体排放!G:G, "强化或放宽目标（消极气候影响）") + COUNTIFS(污染!H:H, "循环利用", 污染!G:G, "新目标") + COUNTIFS(污染!H:H, "循环利用", 污染!G:G, "强化或放宽目标（气候影响不明确）") + COUNTIFS(污染!H:H, "循环利用", 污染!G:G, "强化或放宽目标（积极气候影响）") + COUNTIFS(污染!H:H, "循环利用", 污染!G:G, "强化或放宽目标（消极气候影响）") + COUNTIFS('能源|电力'!H:H, "循环利用", '能源|电力'!G:G, "新目标") + COUNTIFS('能源|电力'!H:H, "循环利用", '能源|电力'!G:G, "强化或放宽目标（气候影响不明确）") + COUNTIFS('能源|电力'!H:H, "循环利用", '能源|电力'!G:G, "强化或放宽目标（积极气候影响）") + COUNTIFS('能源|电力'!H:H, "循环利用", '能源|电力'!G:G, "强化或放宽目标（消极气候影响）") + COUNTIFS(工业!H:H, "循环利用", 工业!G:G, "新目标") + COUNTIFS(工业!H:H, "循环利用", 工业!G:G, "强化或放宽目标（气候影响不明确）") + COUNTIFS(工业!H:H, "循环利用", 工业!G:G, "强化或放宽目标（积极气候影响）") + COUNTIFS(工业!H:H, "循环利用", 工业!G:G, "强化或放宽目标（消极气候影响）") + COUNTIFS(建筑!H:H, "循环利用", 建筑!G:G, "新目标") + COUNTIFS(建筑!H:H, "循环利用", 建筑!G:G, "强化或放宽目标（气候影响不明确）") + COUNTIFS(建筑!H:H, "循环利用", 建筑!G:G, "强化或放宽目标（积极气候影响）") + COUNTIFS(建筑!H:H, "循环利用", 建筑!G:G, "强化或放宽目标（消极气候影响）") + COUNTIFS(交通!H:H, "循环利用", 交通!G:G, "新目标") + COUNTIFS(交通!H:H, "循环利用", 交通!G:G, "强化或放宽目标（气候影响不明确）") + COUNTIFS(交通!H:H, "循环利用", 交通!G:G, "强化或放宽目标（积极气候影响）") + COUNTIFS(交通!H:H, "循环利用", 交通!G:G, "强化或放宽目标（消极气候影响）") + COUNTIFS('土地利用、土地利用变化和林业'!H:H, "循环利用", '土地利用、土地利用变化和林业'!G:G, "新目标") + COUNTIFS('土地利用、土地利用变化和林业'!H:H, "循环利用", '土地利用、土地利用变化和林业'!G:G, "强化或放宽目标（气候影响不明确）") + COUNTIFS('土地利用、土地利用变化和林业'!H:H, "循环利用", '土地利用、土地利用变化和林业'!G:G, "强化或放宽目标（积极气候影响）") + COUNTIFS('土地利用、土地利用变化和林业'!H:H, "循环利用", '土地利用、土地利用变化和林业'!G:G, "强化或放宽目标（消极气候影响）") + COUNTIFS(循环经济!H:H, "循环利用", 循环经济!G:G, "新目标") + COUNTIFS(循环经济!H:H, "循环利用", 循环经济!G:G, "强化或放宽目标（气候影响不明确）") + COUNTIFS(循环经济!H:H, "循环利用", 循环经济!G:G, "强化或放宽目标（积极气候影响）") + COUNTIFS(循环经济!H:H, "循环利用", 循环经济!G:G, "强化或放宽目标（消极气候影响）") + COUNTIFS(金融!H:H, "循环利用", 金融!G:G, "新目标") + COUNTIFS(金融!H:H, "循环利用", 金融!G:G, "强化或放宽目标（气候影响不明确）") + COUNTIFS(金融!H:H, "循环利用", 金融!G:G, "强化或放宽目标（积极气候影响）") + COUNTIFS(金融!H:H, "循环利用", 金融!G:G, "强化或放宽目标（消极气候影响）")
K23: 2021 | L23: =COUNTIFS(温室气体排放!A:A, 2021, 温室气体排放!G:G, "新目标") + COUNTIFS(温室气体排放!A:A, 2021, 温室气体排放!G:G, "强化或放宽目标（气候影响不明确）") + COUNTIFS(温室气体排放!A:A, 2021, 温室气体排放!G:G, "强化或放宽目标（积极气候影响）") + COUNTIFS(温室气体排放!A:A, 2021, 温室气体排放!G:G, "强化或放宽目标（消极气候影响）") + COUNTIFS(污染!A:A, 2021, 污染!G:G, "新目标") + COUNTIFS(污染!A:A, 2021, 污染!G:G, "强化或放宽目标（气候影响不明确）") + COUNTIFS(污染!A:A, 2021, 污染!G:G, "强化或放宽目标（积极气候影响）") + COUNTIFS(污染!A:A, 2021, 污染!G:G, "强化或放宽目标（消极气候影响）") + COUNTIFS('能源|电力'!A:A, 2021, '能源|电力'!G:G, "新目标") + COUNTIFS('能源|电力'!A:A, 2021, '能源|电力'!G:G, "强化或放宽目标（气候影响不明确）") + COUNTIFS('能源|电力'!A:A, 2021, '能源|电力'!G:G, "强化或放宽目标（积极气候影响）") + COUNTIFS('能源|电力'!A:A, 2021, '能源|电力'!G:G, "强化或放宽目标（消极气候影响）") + COUNTIFS(工业!A:A, 2021, 工业!G:G, "新目标") + COUNTIFS(工业!A:A, 2021, 工业!G:G, "强化或放宽目标（气候影响不明确）") + COUNTIFS(工业!A:A, 2021, 工业!G:G, "强化或放宽目标（积极气候影响）") + COUNTIFS(工业!A:A, 2021, 工业!G:G, "强化或放宽目标（消极气候影响）") + COUNTIFS(建筑!A:A, 2021, 建筑!G:G, "新目标") + COUNTIFS(建筑!A:A, 2021, 建筑!G:G, "强化或放宽目标（气候影响不明确）") + COUNTIFS(建筑!A:A, 2021, 建筑!G:G, "强化或放宽目标（积极气候影响）") + COUNTIFS(建筑!A:A, 2021, 建筑!G:G, "强化或放宽目标（消极气候影响）") + COUNTIFS(交通!A:A, 2021, 交通!G:G, "新目标") + COUNTIFS(交通!A:A, 2021, 交通!G:G, "强化或放宽目标（气候影响不明确）") + COUNTIFS(交通!A:A, 2021, 交通!G:G, "强化或放宽目标（积极气候影响）") + COUNTIFS(交通!A:A, 2021, 交通!G:G, "强化或放宽目标（消极气候影响）") + COUNTIFS('土地利用、土地利用变化和林业'!A:A, 2021, '土地利用、土地利用变化和林业'!G:G, "新目标") + COUNTIFS('土地利用、土地利用变化和林业'!A:A, 2021, '土地利用、土地利用变化和林业'!G:G, "强化或放宽目标（气候影响不明确）") + COUNTIFS('土地利用、土地利用变化和林业'!A:A, 2021, '土地利用、土地利用变化和林业'!G:G, "强化或放宽目标（积极气候影响）") + COUNTIFS('土地利用、土地利用变化和林业'!A:A, 2021, '土地利用、土地利用变化和林业'!G:G, "强化或放宽目标（消极气候影响）") + COUNTIFS(循环经济!A:A, 2021, 循环经济!G:G, "新目标") + COUNTIFS(循环经济!A:A, 2021, 循环经济!G:G, "强化或放宽目标（气候影响不明确）") + COUNTIFS(循环经济!A:A, 2021, 循环经济!G:G, "强化或放宽目标（积极气候影响）") + COUNTIFS(循环经济!A:A, 2021, 循环经济!G:G, "强化或放宽目标（消极气候影响）") + COUNTIFS(金融!A:A, 2021, 金融!G:G, "新目标") + COUNTIFS(金融!A:A, 2021, 金融!G:G, "强化或放宽目标（气候影响不明确）") + COUNTIFS(金融!A:A, 2021, 金融!G:G, "强化或放宽目标（积极气候影响）") + COUNTIFS(金融!A:A, 2021, 金融!G:G, "强化或放宽目标（消极气候影响）") | N23: 2024 | O23: =COUNTIFS(温室气体排放!F:F, 2024, 温室气体排放!G:G, "新目标") + COUNTIFS(温室气体排放!F:F, 2024, 温室气体排放!G:G, "强化或放宽目标（气候影响不明确）") + COUNTIFS(温室气体排放!F:F, 2024, 温室气体排放!G:G, "强化或放宽目标（积极气候影响）") + COUNTIFS(温室气体排放!F:F, 2024, 温室气体排放!G:G, "强化或放宽目标（消极气候影响）") + COUNTIFS(污染!F:F, 2024, 污染!G:G, "新目标") + COUNTIFS(污染!F:F, 2024, 污染!G:G, "强化或放宽目标（气候影响不明确）") + COUNTIFS(污染!F:F, 2024, 污染!G:G, "强化或放宽目标（积极气候影响）") + COUNTIFS(污染!F:F, 2024, 污染!G:G, "强化或放宽目标（消极气候影响）") + COUNTIFS('能源|电力'!F:F, 2024, '能源|电力'!G:G, "新目标") + COUNTIFS('能源|电力'!F:F, 2024, '能源|电力'!G:G, "强化或放宽目标（气候影响不明确）") + COUNTIFS('能源|电力'!F:F, 2024, '能源|电力'!G:G, "强化或放宽目标（积极气候影响）") + COUNTIFS('能源|电力'!F:F, 2024, '能源|电力'!G:G, "强化或放宽目标（消极气候影响）") + COUNTIFS(工业!F:F, 2024, 工业!G:G, "新目标") + COUNTIFS(工业!F:F, 2024, 工业!G:G, "强化或放宽目标（气候影响不明确）") + COUNTIFS(工业!F:F, 2024, 工业!G:G, "强化或放宽目标（积极气候影响）") + COUNTIFS(工业!F:F, 2024, 工业!G:G, "强化或放宽目标（消极气候影响）") + COUNTIFS(建筑!F:F, 2024, 建筑!G:G, "新目标") + COUNTIFS(建筑!F:F, 2024, 建筑!G:G, "强化或放宽目标（气候影响不明确）") + COUNTIFS(建筑!F:F, 2024, 建筑!G:G, "强化或放宽目标（积极气候影响）") + COUNTIFS(建筑!F:F, 2024, 建筑!G:G, "强化或放宽目标（消极气候影响）") + COUNTIFS(交通!F:F, 2024, 交通!G:G, "新目标") + COUNTIFS(交通!F:F, 2024, 交通!G:G, "强化或放宽目标（气候影响不明确）") + COUNTIFS(交通!F:F, 2024, 交通!G:G, "强化或放宽目标（积极气候影响）") + COUNTIFS(交通!F:F, 2024, 交通!G:G, "强化或放宽目标（消极气候影响）") + COUNTIFS('土地利用、土地利用变化和林业'!F:F, 2024, '土地利用、土地利用变化和林业'!G:G, "新目标") + COUNTIFS('土地利用、土地利用变化和林业'!F:F, 2024, '土地利用、土地利用变化和林业'!G:G, "强化或放宽目标（气候影响不明确）") + COUNTIFS('土地利用、土地利用变化和林业'!F:F, 2024, '土地利用、土地利用变化和林业'!G:G, "强化或放宽目标（积极气候影响）") + COUNTIFS('土地利用、土地利用变化和林业'!F:F, 2024, '土地利用、土地利用变化和林业'!G:G, "强化或放宽目标（消极气候影响）") + COUNTIFS(循环经济!F:F, 2024, 循环经济!G:G, "新目标") + COUNTIFS(循环经济!F:F, 2024, 循环经济!G:G, "强化或放宽目标（气候影响不明确）") + COUNTIFS(循环经济!F:F, 2024, 循环经济!G:G, "强化或放宽目标（积极气候影响）") + COUNTIFS(循环经济!F:F, 2024, 循环经济!G:G, "强化或放宽目标（消极气候影响）") + COUNTIFS(金融!F:F, 2024, 金融!G:G, "新目标") + COUNTIFS(金融!F:F, 2024, 金融!G:G, "强化或放宽目标（气候影响不明确）") + COUNTIFS(金融!F:F, 2024, 金融!G:G, "强化或放宽目标（积极气候影响）") + COUNTIFS(金融!F:F, 2024, 金融!G:G, "强化或放宽目标（消极气候影响）") | Q23: 气候金融 | R23: =COUNTIFS(温室气体排放!H:H, "气候金融", 温室气体排放!G:G, "新目标") + COUNTIFS(温室气体排放!H:H, "气候金融", 温室气体排放!G:G, "强化或放宽目标（气候影响不明确）") + COUNTIFS(温室气体排放!H:H, "气候金融", 温室气体排放!G:G, "强化或放宽目标（积极气候影响）") + COUNTIFS(温室气体排放!H:H, "气候金融", 温室气体排放!G:G, "强化或放宽目标（消极气候影响）") + COUNTIFS(污染!H:H, "气候金融", 污染!G:G, "新目标") + COUNTIFS(污染!H:H, "气候金融", 污染!G:G, "强化或放宽目标（气候影响不明确）") + COUNTIFS(污染!H:H, "气候金融", 污染!G:G, "强化或放宽目标（积极气候影响）") + COUNTIFS(污染!H:H, "气候金融", 污染!G:G, "强化或放宽目标（消极气候影响）") + COUNTIFS('能源|电力'!H:H, "气候金融", '能源|电力'!G:G, "新目标") + COUNTIFS('能源|电力'!H:H, "气候金融", '能源|电力'!G:G, "强化或放宽目标（气候影响不明确）") + COUNTIFS('能源|电力'!H:H, "气候金融", '能源|电力'!G:G, "强化或放宽目标（积极气候影响）") + COUNTIFS('能源|电力'!H:H, "气候金融", '能源|电力'!G:G, "强化或放宽目标（消极气候影响）") + COUNTIFS(工业!H:H, "气候金融", 工业!G:G, "新目标") + COUNTIFS(工业!H:H, "气候金融", 工业!G:G, "强化或放宽目标（气候影响不明确）") + COUNTIFS(工业!H:H, "气候金融", 工业!G:G, "强化或放宽目标（积极气候影响）") + COUNTIFS(工业!H:H, "气候金融", 工业!G:G, "强化或放宽目标（消极气候影响）") + COUNTIFS(建筑!H:H, "气候金融", 建筑!G:G, "新目标") + COUNTIFS(建筑!H:H, "气候金融", 建筑!G:G, "强化或放宽目标（气候影响不明确）") + COUNTIFS(建筑!H:H, "气候金融", 建筑!G:G, "强化或放宽目标（积极气候影响）") + COUNTIFS(建筑!H:H, "气候金融", 建筑!G:G, "强化或放宽目标（消极气候影响）") + COUNTIFS(交通!H:H, "气候金融", 交通!G:G, "新目标") + COUNTIFS(交通!H:H, "气候金融", 交通!G:G, "强化或放宽目标（气候影响不明确）") + COUNTIFS(交通!H:H, "气候金融", 交通!G:G, "强化或放宽目标（积极气候影响）") + COUNTIFS(交通!H:H, "气候金融", 交通!G:G, "强化或放宽目标（消极气候影响）") + COUNTIFS('土地利用、土地利用变化和林业'!H:H, "气候金融", '土地利用、土地利用变化和林业'!G:G, "新目标") + COUNTIFS('土地利用、土地利用变化和林业'!H:H, "气候金融", '土地利用、土地利用变化和林业'!G:G, "强化或放宽目标（气候影响不明确）") + COUNTIFS('土地利用、土地利用变化和林业'!H:H, "气候金融", '土地利用、土地利用变化和林业'!G:G, "强化或放宽目标（积极气候影响）") + COUNTIFS('土地利用、土地利用变化和林业'!H:H, "气候金融", '土地利用、土地利用变化和林业'!G:G, "强化或放宽目标（消极气候影响）") + COUNTIFS(循环经济!H:H, "气候金融", 循环经济!G:G, "新目标") + COUNTIFS(循环经济!H:H, "气候金融", 循环经济!G:G, "强化或放宽目标（气候影响不明确）") + COUNTIFS(循环经济!H:H, "气候金融", 循环经济!G:G, "强化或放宽目标（积极气候影响）") + COUNTIFS(循环经济!H:H, "气候金融", 循环经济!G:G, "强化或放宽目标（消极气候影响）") + COUNTIFS(金融!H:H, "气候金融", 金融!G:G, "新目标") + COUNTIFS(金融!H:H, "气候金融", 金融!G:G, "强化或放宽目标（气候影响不明确）") + COUNTIFS(金融!H:H, "气候金融", 金融!G:G, "强化或放宽目标（积极气候影响）") + COUNTIFS(金融!H:H, "气候金融", 金融!G:G, "强化或放宽目标（消极气候影响）")
K24: 2022 | L24: =COUNTIFS(温室气体排放!A:A, 2022, 温室气体排放!G:G, "新目标") + COUNTIFS(温室气体排放!A:A, 2022, 温室气体排放!G:G, "强化或放宽目标（气候影响不明确）") + COUNTIFS(温室气体排放!A:A, 2022, 温室气体排放!G:G, "强化或放宽目标（积极气候影响）") + COUNTIFS(温室气体排放!A:A, 2022, 温室气体排放!G:G, "强化或放宽目标（消极气候影响）") + COUNTIFS(污染!A:A, 2022, 污染!G:G, "新目标") + COUNTIFS(污染!A:A, 2022, 污染!G:G, "强化或放宽目标（气候影响不明确）") + COUNTIFS(污染!A:A, 2022, 污染!G:G, "强化或放宽目标（积极气候影响）") + COUNTIFS(污染!A:A, 2022, 污染!G:G, "强化或放宽目标（消极气候影响）") + COUNTIFS('能源|电力'!A:A, 2022, '能源|电力'!G:G, "新目标") + COUNTIFS('能源|电力'!A:A, 2022, '能源|电力'!G:G, "强化或放宽目标（气候影响不明确）") + COUNTIFS('能源|电力'!A:A, 2022, '能源|电力'!G:G, "强化或放宽目标（积极气候影响）") + COUNTIFS('能源|电力'!A:A, 2022, '能源|电力'!G:G, "强化或放宽目标（消极气候影响）") + COUNTIFS(工业!A:A, 2022, 工业!G:G, "新目标") + COUNTIFS(工业!A:A, 2022, 工业!G:G, "强化或放宽目标（气候影响不明确）") + COUNTIFS(工业!A:A, 2022, 工业!G:G, "强化或放宽目标（积极气候影响）") + COUNTIFS(工业!A:A, 2022, 工业!G:G, "强化或放宽目标（消极气候影响）") + COUNTIFS(建筑!A:A, 2022, 建筑!G:G, "新目标") + COUNTIFS(建筑!A:A, 2022, 建筑!G:G, "强化或放宽目标（气候影响不明确）") + COUNTIFS(建筑!A:A, 2022, 建筑!G:G, "强化或放宽目标（积极气候影响）") + COUNTIFS(建筑!A:A, 2022, 建筑!G:G, "强化或放宽目标（消极气候影响）") + COUNTIFS(交通!A:A, 2022, 交通!G:G, "新目标") + COUNTIFS(交通!A:A, 2022, 交通!G:G, "强化或放宽目标（气候影响不明确）") + COUNTIFS(交通!A:A, 2022, 交通!G:G, "强化或放宽目标（积极气候影响）") + COUNTIFS(交通!A:A, 2022, 交通!G:G, "强化或放宽目标（消极气候影响）") + COUNTIFS('土地利用、土地利用变化和林业'!A:A, 2022, '土地利用、土地利用变化和林业'!G:G, "新目标") + COUNTIFS('土地利用、土地利用变化和林业'!A:A, 2022, '土地利用、土地利用变化和林业'!G:G, "强化或放宽目标（气候影响不明确）") + COUNTIFS('土地利用、土地利用变化和林业'!A:A, 2022, '土地利用、土地利用变化和林业'!G:G, "强化或放宽目标（积极气候影响）") + COUNTIFS('土地利用、土地利用变化和林业'!A:A, 2022, '土地利用、土地利用变化和林业'!G:G, "强化或放宽目标（消极气候影响）") + COUNTIFS(循环经济!A:A, 2022, 循环经济!G:G, "新目标") + COUNTIFS(循环经济!A:A, 2022, 循环经济!G:G, "强化或放宽目标（气候影响不明确）") + COUNTIFS(循环经济!A:A, 2022, 循环经济!G:G, "强化或放宽目标（积极气候影响）") + COUNTIFS(循环经济!A:A, 2022, 循环经济!G:G, "强化或放宽目标（消极气候影响）") + COUNTIFS(金融!A:A, 2022, 金融!G:G, "新目标") + COUNTIFS(金融!A:A, 2022, 金融!G:G, "强化或放宽目标（气候影响不明确）") + COUNTIFS(金融!A:A, 2022, 金融!G:G, "强化或放宽目标（积极气候影响）") + COUNTIFS(金融!A:A, 2022, 金融!G:G, "强化或放宽目标（消极气候影响）") | N24: 2025 | O24: =COUNTIFS(温室气体排放!F:F, 2025, 温室气体排放!G:G, "新目标") + COUNTIFS(温室气体排放!F:F, 2025, 温室气体排放!G:G, "强化或放宽目标（气候影响不明确）") + COUNTIFS(温室气体排放!F:F, 2025, 温室气体排放!G:G, "强化或放宽目标（积极气候影响）") + COUNTIFS(温室气体排放!F:F, 2025, 温室气体排放!G:G, "强化或放宽目标（消极气候影响）") + COUNTIFS(污染!F:F, 2025, 污染!G:G, "新目标") + COUNTIFS(污染!F:F, 2025, 污染!G:G, "强化或放宽目标（气候影响不明确）") + COUNTIFS(污染!F:F, 2025, 污染!G:G, "强化或放宽目标（积极气候影响）") + COUNTIFS(污染!F:F, 2025, 污染!G:G, "强化或放宽目标（消极气候影响）") + COUNTIFS('能源|电力'!F:F, 2025, '能源|电力'!G:G, "新目标") + COUNTIFS('能源|电力'!F:F, 2025, '能源|电力'!G:G, "强化或放宽目标（气候影响不明确）") + COUNTIFS('能源|电力'!F:F, 2025, '能源|电力'!G:G, "强化或放宽目标（积极气候影响）") + COUNTIFS('能源|电力'!F:F, 2025, '能源|电力'!G:G, "强化或放宽目标（消极气候影响）") + COUNTIFS(工业!F:F, 2025, 工业!G:G, "新目标") + COUNTIFS(工业!F:F, 2025, 工业!G:G, "强化或放宽目标（气候影响不明确）") + COUNTIFS(工业!F:F, 2025, 工业!G:G, "强化或放宽目标（积极气候影响）") + COUNTIFS(工业!F:F, 2025, 工业!G:G, "强化或放宽目标（消极气候影响）") + COUNTIFS(建筑!F:F, 2025, 建筑!G:G, "新目标") + COUNTIFS(建筑!F:F, 2025, 建筑!G:G, "强化或放宽目标（气候影响不明确）") + COUNTIFS(建筑!F:F, 2025, 建筑!G:G, "强化或放宽目标（积极气候影响）") + COUNTIFS(建筑!F:F, 2025, 建筑!G:G, "强化或放宽目标（消极气候影响）") + COUNTIFS(交通!F:F, 2025, 交通!G:G, "新目标") + COUNTIFS(交通!F:F, 2025, 交通!G:G, "强化或放宽目标（气候影响不明确）") + COUNTIFS(交通!F:F, 2025, 交通!G:G, "强化或放宽目标（积极气候影响）") + COUNTIFS(交通!F:F, 2025, 交通!G:G, "强化或放宽目标（消极气候影响）") + COUNTIFS('土地利用、土地利用变化和林业'!F:F, 2025, '土地利用、土地利用变化和林业'!G:G, "新目标") + COUNTIFS('土地利用、土地利用变化和林业'!F:F, 2025, '土地利用、土地利用变化和林业'!G:G, "强化或放宽目标（气候影响不明确）") + COUNTIFS('土地利用、土地利用变化和林业'!F:F, 2025, '土地利用、土地利用变化和林业'!G:G, "强化或放宽目标（积极气候影响）") + COUNTIFS('土地利用、土地利用变化和林业'!F:F, 2025, '土地利用、土地利用变化和林业'!G:G, "强化或放宽目标（消极气候影响）") + COUNTIFS(循环经济!F:F, 2025, 循环经济!G:G, "新目标") + COUNTIFS(循环经济!F:F, 2025, 循环经济!G:G, "强化或放宽目标（气候影响不明确）") + COUNTIFS(循环经济!F:F, 2025, 循环经济!G:G, "强化或放宽目标（积极气候影响）") + COUNTIFS(循环经济!F:F, 2025, 循环经济!G:G, "强化或放宽目标（消极气候影响）") + COUNTIFS(金融!F:F, 2025, 金融!G:G, "新目标") + COUNTIFS(金融!F:F, 2025, 金融!G:G, "强化或放宽目标（气候影响不明确）") + COUNTIFS(金融!F:F, 2025, 金融!G:G, "强化或放宽目标（积极气候影响）") + COUNTIFS(金融!F:F, 2025, 金融!G:G, "强化或放宽目标（消极气候影响）")
K25: 2023 | L25: =COUNTIFS(温室气体排放!A:A, 2023, 温室气体排放!G:G, "新目标") + COUNTIFS(温室气体排放!A:A, 2023, 温室气体排放!G:G, "强化或放宽目标（气候影响不明确）") + COUNTIFS(温室气体排放!A:A, 2023, 温室气体排放!G:G, "强化或放宽目标（积极气候影响）") + COUNTIFS(温室气体排放!A:A, 2023, 温室气体排放!G:G, "强化或放宽目标（消极气候影响）") + COUNTIFS(污染!A:A, 2023, 污染!G:G, "新目标") + COUNTIFS(污染!A:A, 2023, 污染!G:G, "强化或放宽目标（气候影响不明确）") + COUNTIFS(污染!A:A, 2023, 污染!G:G, "强化或放宽目标（积极气候影响）") + COUNTIFS(污染!A:A, 2023, 污染!G:G, "强化或放宽目标（消极气候影响）") + COUNTIFS('能源|电力'!A:A, 2023, '能源|电力'!G:G, "新目标") + COUNTIFS('能源|电力'!A:A, 2023, '能源|电力'!G:G, "强化或放宽目标（气候影响不明确）") + COUNTIFS('能源|电力'!A:A, 2023, '能源|电力'!G:G, "强化或放宽目标（积极气候影响）") + COUNTIFS('能源|电力'!A:A, 2023, '能源|电力'!G:G, "强化或放宽目标（消极气候影响）") + COUNTIFS(工业!A:A, 2023, 工业!G:G, "新目标") + COUNTIFS(工业!A:A, 2023, 工业!G:G, "强化或放宽目标（气候影响不明确）") + COUNTIFS(工业!A:A, 2023, 工业!G:G, "强化或放宽目标（积极气候影响）") + COUNTIFS(工业!A:A, 2023, 工业!G:G, "强化或放宽目标（消极气候影响）") + COUNTIFS(建筑!A:A, 2023, 建筑!G:G, "新目标") + COUNTIFS(建筑!A:A, 2023, 建筑!G:G, "强化或放宽目标（气候影响不明确）") + COUNTIFS(建筑!A:A, 2023, 建筑!G:G, "强化或放宽目标（积极气候影响）") + COUNTIFS(建筑!A:A, 2023, 建筑!G:G, "强化或放宽目标（消极气候影响）") + COUNTIFS(交通!A:A, 2023, 交通!G:G, "新目标") + COUNTIFS(交通!A:A, 2023, 交通!G:G, "强化或放宽目标（气候影响不明确）") + COUNTIFS(交通!A:A, 2023, 交通!G:G, "强化或放宽目标（积极气候影响）") + COUNTIFS(交通!A:A, 2023, 交通!G:G, "强化或放宽目标（消极气候影响）") + COUNTIFS('土地利用、土地利用变化和林业'!A:A, 2023, '土地利用、土地利用变化和林业'!G:G, "新目标") + COUNTIFS('土地利用、土地利用变化和林业'!A:A, 2023, '土地利用、土地利用变化和林业'!G:G, "强化或放宽目标（气候影响不明确）") + COUNTIFS('土地利用、土地利用变化和林业'!A:A, 2023, '土地利用、土地利用变化和林业'!G:G, "强化或放宽目标（积极气候影响）") + COUNTIFS('土地利用、土地利用变化和林业'!A:A, 2023, '土地利用、土地利用变化和林业'!G:G, "强化或放宽目标（消极气候影响）") + COUNTIFS(循环经济!A:A, 2023, 循环经济!G:G, "新目标") + COUNTIFS(循环经济!A:A, 2023, 循环经济!G:G, "强化或放宽目标（气候影响不明确）") + COUNTIFS(循环经济!A:A, 2023, 循环经济!G:G, "强化或放宽目标（积极气候影响）") + COUNTIFS(循环经济!A:A, 2023, 循环经济!G:G, "强化或放宽目标（消极气候影响）") + COUNTIFS(金融!A:A, 2023, 金融!G:G, "新目标") + COUNTIFS(金融!A:A, 2023, 金融!G:G, "强化或放宽目标（气候影响不明确）") + COUNTIFS(金融!A:A, 2023, 金融!G:G, "强化或放宽目标（积极气候影响）") + COUNTIFS(金融!A:A, 2023, 金融!G:G, "强化或放宽目标（消极气候影响）") | N25: 十四五 | O25: =COUNTIFS(温室气体排放!F:F, "十四五", 温室气体排放!G:G, "新目标") + COUNTIFS(温室气体排放!F:F, "十四五", 温室气体排放!G:G, "强化或放宽目标（气候影响不明确）") + COUNTIFS(温室气体排放!F:F, "十四五", 温室气体排放!G:G, "强化或放宽目标（积极气候影响）") + COUNTIFS(温室气体排放!F:F, "十四五", 温室气体排放!G:G, "强化或放宽目标（消极气候影响）") + COUNTIFS(污染!F:F, "十四五", 污染!G:G, "新目标") + COUNTIFS(污染!F:F, "十四五", 污染!G:G, "强化或放宽目标（气候影响不明确）") + COUNTIFS(污染!F:F, "十四五", 污染!G:G, "强化或放宽目标（积极气候影响）") + COUNTIFS(污染!F:F, "十四五", 污染!G:G, "强化或放宽目标（消极气候影响）") + COUNTIFS('能源|电力'!F:F, "十四五", '能源|电力'!G:G, "新目标") + COUNTIFS('能源|电力'!F:F, "十四五", '能源|电力'!G:G, "强化或放宽目标（气候影响不明确）") + COUNTIFS('能源|电力'!F:F, "十四五", '能源|电力'!G:G, "强化或放宽目标（积极气候影响）") + COUNTIFS('能源|电力'!F:F, "十四五", '能源|电力'!G:G, "强化或放宽目标（消极气候影响）") + COUNTIFS(工业!F:F, "十四五", 工业!G:G, "新目标") + COUNTIFS(工业!F:F, "十四五", 工业!G:G, "强化或放宽目标（气候影响不明确）") + COUNTIFS(工业!F:F, "十四五", 工业!G:G, "强化或放宽目标（积极气候影响）") + COUNTIFS(工业!F:F, "十四五", 工业!G:G, "强化或放宽目标（消极气候影响）") + COUNTIFS(建筑!F:F, "十四五", 建筑!G:G, "新目标") + COUNTIFS(建筑!F:F, "十四五", 建筑!G:G, "强化或放宽目标（气候影响不明确）") + COUNTIFS(建筑!F:F, "十四五", 建筑!G:G, "强化或放宽目标（积极气候影响）") + COUNTIFS(建筑!F:F, "十四五", 建筑!G:G, "强化或放宽目标（消极气候影响）") + COUNTIFS(交通!F:F, "十四五", 交通!G:G, "新目标") + COUNTIFS(交通!F:F, "十四五", 交通!G:G, "强化或放宽目标（气候影响不明确）") + COUNTIFS(交通!F:F, "十四五", 交通!G:G, "强化或放宽目标（积极气候影响）") + COUNTIFS(交通!F:F, "十四五", 交通!G:G, "强化或放宽目标（消极气候影响）") + COUNTIFS('土地利用、土地利用变化和林业'!F:F, "十四五", '土地利用、土地利用变化和林业'!G:G, "新目标") + COUNTIFS('土地利用、土地利用变化和林业'!F:F, "十四五", '土地利用、土地利用变化和林业'!G:G, "强化或放宽目标（气候影响不明确）") + COUNTIFS('土地利用、土地利用变化和林业'!F:F, "十四五", '土地利用、土地利用变化和林业'!G:G, "强化或放宽目标（积极气候影响）") + COUNTIFS('土地利用、土地利用变化和林业'!F:F, "十四五", '土地利用、土地利用变化和林业'!G:G, "强化或放宽目标（消极气候影响）") + COUNTIFS(循环经济!F:F, "十四五", 循环经济!G:G, "新目标") + COUNTIFS(循环经济!F:F, "十四五", 循环经济!G:G, "强化或放宽目标（气候影响不明确）") + COUNTIFS(循环经济!F:F, "十四五", 循环经济!G:G, "强化或放宽目标（积极气候影响）") + COUNTIFS(循环经济!F:F, "十四五", 循环经济!G:G, "强化或放宽目标（消极气候影响）") + COUNTIFS(金融!F:F, "十四五", 金融!G:G, "新目标") + COUNTIFS(金融!F:F, "十四五", 金融!G:G, "强化或放宽目标（气候影响不明确）") + COUNTIFS(金融!F:F, "十四五", 金融!G:G, "强化或放宽目标（积极气候影响）") + COUNTIFS(金融!F:F, "十四五", 金融!G:G, "强化或放宽目标（消极气候影响）")
K26: 2024 | L26: =COUNTIFS(温室气体排放!A:A, 2024, 温室气体排放!G:G, "新目标") + COUNTIFS(温室气体排放!A:A, 2024, 温室气体排放!G:G, "强化或放宽目标（气候影响不明确）") + COUNTIFS(温室气体排放!A:A, 2024, 温室气体排放!G:G, "强化或放宽目标（积极气候影响）") + COUNTIFS(温室气体排放!A:A, 2024, 温室气体排放!G:G, "强化或放宽目标（消极气候影响）") + COUNTIFS(污染!A:A, 2024, 污染!G:G, "新目标") + COUNTIFS(污染!A:A, 2024, 污染!G:G, "强化或放宽目标（气候影响不明确）") + COUNTIFS(污染!A:A, 2024, 污染!G:G, "强化或放宽目标（积极气候影响）") + COUNTIFS(污染!A:A, 2024, 污染!G:G, "强化或放宽目标（消极气候影响）") + COUNTIFS('能源|电力'!A:A, 2024, '能源|电力'!G:G, "新目标") + COUNTIFS('能源|电力'!A:A, 2024, '能源|电力'!G:G, "强化或放宽目标（气候影响不明确）") + COUNTIFS('能源|电力'!A:A, 2024, '能源|电力'!G:G, "强化或放宽目标（积极气候影响）") + COUNTIFS('能源|电力'!A:A, 2024, '能源|电力'!G:G, "强化或放宽目标（消极气候影响）") + COUNTIFS(工业!A:A, 2024, 工业!G:G, "新目标") + COUNTIFS(工业!A:A, 2024, 工业!G:G, "强化或放宽目标（气候影响不明确）") + COUNTIFS(工业!A:A, 2024, 工业!G:G, "强化或放宽目标（积极气候影响）") + COUNTIFS(工业!A:A, 2024, 工业!G:G, "强化或放宽目标（消极气候影响）") + COUNTIFS(建筑!A:A, 2024, 建筑!G:G, "新目标") + COUNTIFS(建筑!A:A, 2024, 建筑!G:G, "强化或放宽目标（气候影响不明确）") + COUNTIFS(建筑!A:A, 2024, 建筑!G:G, "强化或放宽目标（积极气候影响）") + COUNTIFS(建筑!A:A, 2024, 建筑!G:G, "强化或放宽目标（消极气候影响）") + COUNTIFS(交通!A:A, 2024, 交通!G:G, "新目标") + COUNTIFS(交通!A:A, 2024, 交通!G:G, "强化或放宽目标（气候影响不明确）") + COUNTIFS(交通!A:A, 2024, 交通!G:G, "强化或放宽目标（积极气候影响）") + COUNTIFS(交通!A:A, 2024, 交通!G:G, "强化或放宽目标（消极气候影响）") + COUNTIFS('土地利用、土地利用变化和林业'!A:A, 2024, '土地利用、土地利用变化和林业'!G:G, "新目标") + COUNTIFS('土地利用、土地利用变化和林业'!A:A, 2024, '土地利用、土地利用变化和林业'!G:G, "强化或放宽目标（气候影响不明确）") + COUNTIFS('土地利用、土地利用变化和林业'!A:A, 2024, '土地利用、土地利用变化和林业'!G:G, "强化或放宽目标（积极气候影响）") + COUNTIFS('土地利用、土地利用变化和林业'!A:A, 2024, '土地利用、土地利用变化和林业'!G:G, "强化或放宽目标（消极气候影响）") + COUNTIFS(循环经济!A:A, 2024, 循环经济!G:G, "新目标") + COUNTIFS(循环经济!A:A, 2024, 循环经济!G:G, "强化或放宽目标（气候影响不明确）") + COUNTIFS(循环经济!A:A, 2024, 循环经济!G:G, "强化或放宽目标（积极气候影响）") + COUNTIFS(循环经济!A:A, 2024, 循环经济!G:G, "强化或放宽目标（消极气候影响）") + COUNTIFS(金融!A:A, 2024, 金融!G:G, "新目标") + COUNTIFS(金融!A:A, 2024, 金融!G:G, "强化或放宽目标（气候影响不明确）") + COUNTIFS(金融!A:A, 2024, 金融!G:G, "强化或放宽目标（积极气候影响）") + COUNTIFS(金融!A:A, 2024, 金融!G:G, "强化或放宽目标（消极气候影响）") | N26: 2027 | O26: =COUNTIFS(温室气体排放!F:F, 2027, 温室气体排放!G:G, "新目标") + COUNTIFS(温室气体排放!F:F, 2027, 温室气体排放!G:G, "强化或放宽目标（气候影响不明确）") + COUNTIFS(温室气体排放!F:F, 2027, 温室气体排放!G:G, "强化或放宽目标（积极气候影响）") + COUNTIFS(温室气体排放!F:F, 2027, 温室气体排放!G:G, "强化或放宽目标（消极气候影响）") + COUNTIFS(污染!F:F, 2027, 污染!G:G, "新目标") + COUNTIFS(污染!F:F, 2027, 污染!G:G, "强化或放宽目标（气候影响不明确）") + COUNTIFS(污染!F:F, 2027, 污染!G:G, "强化或放宽目标（积极气候影响）") + COUNTIFS(污染!F:F, 2027, 污染!G:G, "强化或放宽目标（消极气候影响）") + COUNTIFS('能源|电力'!F:F, 2027, '能源|电力'!G:G, "新目标") + COUNTIFS('能源|电力'!F:F, 2027, '能源|电力'!G:G, "强化或放宽目标（气候影响不明确）") + COUNTIFS('能源|电力'!F:F, 2027, '能源|电力'!G:G, "强化或放宽目标（积极气候影响）") + COUNTIFS('能源|电力'!F:F, 2027, '能源|电力'!G:G, "强化或放宽目标（消极气候影响）") + COUNTIFS(工业!F:F, 2027, 工业!G:G, "新目标") + COUNTIFS(工业!F:F, 2027, 工业!G:G, "强化或放宽目标（气候影响不明确）") + COUNTIFS(工业!F:F, 2027, 工业!G:G, "强化或放宽目标（积极气候影响）") + COUNTIFS(工业!F:F, 2027, 工业!G:G, "强化或放宽目标（消极气候影响）") + COUNTIFS(建筑!F:F, 2027, 建筑!G:G, "新目标") + COUNTIFS(建筑!F:F, 2027, 建筑!G:G, "强化或放宽目标（气候影响不明确）") + COUNTIFS(建筑!F:F, 2027, 建筑!G:G, "强化或放宽目标（积极气候影响）") + COUNTIFS(建筑!F:F, 2027, 建筑!G:G, "强化或放宽目标（消极气候影响）") + COUNTIFS(交通!F:F, 2027, 交通!G:G, "新目标") + COUNTIFS(交通!F:F, 2027, 交通!G:G, "强化或放宽目标（气候影响不明确）") + COUNTIFS(交通!F:F, 2027, 交通!G:G, "强化或放宽目标（积极气候影响）") + COUNTIFS(交通!F:F, 2027, 交通!G:G, "强化或放宽目标（消极气候影响）") + COUNTIFS('土地利用、土地利用变化和林业'!F:F, 2027, '土地利用、土地利用变化和林业'!G:G, "新目标") + COUNTIFS('土地利用、土地利用变化和林业'!F:F, 2027, '土地利用、土地利用变化和林业'!G:G, "强化或放宽目标（气候影响不明确）") + COUNTIFS('土地利用、土地利用变化和林业'!F:F, 2027, '土地利用、土地利用变化和林业'!G:G, "强化或放宽目标（积极气候影响）") + COUNTIFS('土地利用、土地利用变化和林业'!F:F, 2027, '土地利用、土地利用变化和林业'!G:G, "强化或放宽目标（消极气候影响）") + COUNTIFS(循环经济!F:F, 2027, 循环经济!G:G, "新目标") + COUNTIFS(循环经济!F:F, 2027, 循环经济!G:G, "强化或放宽目标（气候影响不明确）") + COUNTIFS(循环经济!F:F, 2027, 循环经济!G:G, "强化或放宽目标（积极气候影响）") + COUNTIFS(循环经济!F:F, 2027, 循环经济!G:G, "强化或放宽目标（消极气候影响）") + COUNTIFS(金融!F:F, 2027, 金融!G:G, "新目标") + COUNTIFS(金融!F:F, 2027, 金融!G:G, "强化或放宽目标（气候影响不明确）") + COUNTIFS(金融!F:F, 2027, 金融!G:G, "强化或放宽目标（积极气候影响）") + COUNTIFS(金融!F:F, 2027, 金融!G:G, "强化或放宽目标（消极气候影响）")
K27: 2025 | L27: =COUNTIFS(温室气体排放!B:B, 2025, 温室气体排放!G:G, "新目标") + COUNTIFS(温室气体排放!B:B, 2025, 温室气体排放!G:G, "强化或放宽目标（气候影响不明确）") + COUNTIFS(温室气体排放!B:B, 2025, 温室气体排放!G:G, "强化或放宽目标（积极气候影响）") + COUNTIFS(温室气体排放!B:B, 2025, 温室气体排放!G:G, "强化或放宽目标（消极气候影响）") + COUNTIFS(污染!A:A, 2025, 污染!G:G, "新目标") + COUNTIFS(污染!A:A, 2025, 污染!G:G, "强化或放宽目标（气候影响不明确）") + COUNTIFS(污染!A:A, 2025, 污染!G:G, "强化或放宽目标（积极气候影响）") + COUNTIFS(污染!A:A, 2025, 污染!G:G, "强化或放宽目标（消极气候影响）") + COUNTIFS('能源|电力'!A:A, 2025, '能源|电力'!G:G, "新目标") + COUNTIFS('能源|电力'!A:A, 2025, '能源|电力'!G:G, "强化或放宽目标（气候影响不明确）") + COUNTIFS('能源|电力'!A:A, 2025, '能源|电力'!G:G, "强化或放宽目标（积极气候影响）") + COUNTIFS('能源|电力'!A:A, 2025, '能源|电力'!G:G, "强化或放宽目标（消极气候影响）") + COUNTIFS(工业!A:A, 2025, 工业!G:G, "新目标") + COUNTIFS(工业!A:A, 2025, 工业!G:G, "强化或放宽目标（气候影响不明确）") + COUNTIFS(工业!A:A, 2025, 工业!G:G, "强化或放宽目标（积极气候影响）") + COUNTIFS(工业!A:A, 2025, 工业!G:G, "强化或放宽目标（消极气候影响）") + COUNTIFS(建筑!B:B, 2025, 建筑!G:G, "新目标") + COUNTIFS(建筑!B:B, 2025, 建筑!G:G, "强化或放宽目标（气候影响不明确）") + COUNTIFS(建筑!B:B, 2025, 建筑!G:G, "强化或放宽目标（积极气候影响）") + COUNTIFS(建筑!B:B, 2025, 建筑!G:G, "强化或放宽目标（消极气候影响）") + COUNTIFS(交通!A:A, 2025, 交通!G:G, "新目标") + COUNTIFS(交通!A:A, 2025, 交通!G:G, "强化或放宽目标（气候影响不明确）") + COUNTIFS(交通!A:A, 2025, 交通!G:G, "强化或放宽目标（积极气候影响）") + COUNTIFS(交通!A:A, 2025, 交通!G:G, "强化或放宽目标（消极气候影响）") + COUNTIFS('土地利用、土地利用变化和林业'!A:A, 2025, '土地利用、土地利用变化和林业'!G:G, "新目标") + COUNTIFS('土地利用、土地利用变化和林业'!A:A, 2025, '土地利用、土地利用变化和林业'!G:G, "强化或放宽目标（气候影响不明确）") + COUNTIFS('土地利用、土地利用变化和林业'!A:A, 2025, '土地利用、土地利用变化和林业'!G:G, "强化或放宽目标（积极气候影响）") + COUNTIFS('土地利用、土地利用变化和林业'!A:A, 2025, '土地利用、土地利用变化和林业'!G:G, "强化或放宽目标（消极气候影响）") + COUNTIFS(循环经济!A:A, 2025, 循环经济!G:G, "新目标") + COUNTIFS(循环经济!A:A, 2025, 循环经济!G:G, "强化或放宽目标（气候影响不明确）") + COUNTIFS(循环经济!A:A, 2025, 循环经济!G:G, "强化或放宽目标（积极气候影响）") + COUNTIFS(循环经济!A:A, 2025, 循环经济!G:G, "强化或放宽目标（消极气候影响）") + COUNTIFS(金融!A:A, 2025, 金融!G:G, "新目标") + COUNTIFS(金融!A:A, 2025, 金融!G:G, "强化或放宽目标（气候影响不明确）") + COUNTIFS(金融!A:A, 2025, 金融!G:G, "强化或放宽目标（积极气候影响）") + COUNTIFS(金融!A:A, 2025, 金融!G:G, "强化或放宽目标（消极气候影响）") | N27: 2030 | O27: =COUNTIFS(温室气体排放!F:F, 2030, 温室气体排放!G:G, "新目标") + COUNTIFS(温室气体排放!F:F, 2030, 温室气体排放!G:G, "强化或放宽目标（气候影响不明确）") + COUNTIFS(温室气体排放!F:F, 2030, 温室气体排放!G:G, "强化或放宽目标（积极气候影响）") + COUNTIFS(温室气体排放!F:F, 2030, 温室气体排放!G:G, "强化或放宽目标（消极气候影响）") + COUNTIFS(污染!F:F, 2030, 污染!G:G, "新目标") + COUNTIFS(污染!F:F, 2030, 污染!G:G, "强化或放宽目标（气候影响不明确）") + COUNTIFS(污染!F:F, 2030, 污染!G:G, "强化或放宽目标（积极气候影响）") + COUNTIFS(污染!F:F, 2030, 污染!G:G, "强化或放宽目标（消极气候影响）") + COUNTIFS('能源|电力'!F:F, 2030, '能源|电力'!G:G, "新目标") + COUNTIFS('能源|电力'!F:F, 2030, '能源|电力'!G:G, "强化或放宽目标（气候影响不明确）") + COUNTIFS('能源|电力'!F:F, 2030, '能源|电力'!G:G, "强化或放宽目标（积极气候影响）") + COUNTIFS('能源|电力'!F:F, 2030, '能源|电力'!G:G, "强化或放宽目标（消极气候影响）") + COUNTIFS(工业!F:F, 2030, 工业!G:G, "新目标") + COUNTIFS(工业!F:F, 2030, 工业!G:G, "强化或放宽目标（气候影响不明确）") + COUNTIFS(工业!F:F, 2030, 工业!G:G, "强化或放宽目标（积极气候影响）") + COUNTIFS(工业!F:F, 2030, 工业!G:G, "强化或放宽目标（消极气候影响）") + COUNTIFS(建筑!F:F, 2030, 建筑!G:G, "新目标") + COUNTIFS(建筑!F:F, 2030, 建筑!G:G, "强化或放宽目标（气候影响不明确）") + COUNTIFS(建筑!F:F, 2030, 建筑!G:G, "强化或放宽目标（积极气候影响）") + COUNTIFS(建筑!F:F, 2030, 建筑!G:G, "强化或放宽目标（消极气候影响）") + COUNTIFS(交通!F:F, 2030, 交通!G:G, "新目标") + COUNTIFS(交通!F:F, 2030, 交通!G:G, "强化或放宽目标（气候影响不明确）") + COUNTIFS(交通!F:F, 2030, 交通!G:G, "强化或放宽目标（积极气候影响）") + COUNTIFS(交通!F:F, 2030, 交通!G:G, "强化或放宽目标（消极气候影响）") + COUNTIFS('土地利用、土地利用变化和林业'!F:F, 2030, '土地利用、土地利用变化和林业'!G:G, "新目标") + COUNTIFS('土地利用、土地利用变化和林业'!F:F, 2030, '土地利用、土地利用变化和林业'!G:G, "强化或放宽目标（气候影响不明确）") + COUNTIFS('土地利用、土地利用变化和林业'!F:F, 2030, '土地利用、土地利用变化和林业'!G:G, "强化或放宽目标（积极气候影响）") + COUNTIFS('土地利用、土地利用变化和林业'!F:F, 2030, '土地利用、土地利用变化和林业'!G:G, "强化或放宽目标（消极气候影响）") + COUNTIFS(循环经济!F:F, 2030, 循环经济!G:G, "新目标") + COUNTIFS(循环经济!F:F, 2030, 循环经济!G:G, "强化或放宽目标（气候影响不明确）") + COUNTIFS(循环经济!F:F, 2030, 循环经济!G:G, "强化或放宽目标（积极气候影响）") + COUNTIFS(循环经济!F:F, 2030, 循环经济!G:G, "强化或放宽目标（消极气候影响）") + COUNTIFS(金融!F:F, 2030, 金融!G:G, "新目标") + COUNTIFS(金融!F:F, 2030, 金融!G:G, "强化或放宽目标（气候影响不明确）") + COUNTIFS(金融!F:F, 2030, 金融!G:G, "强化或放宽目标（积极气候影响）") + COUNTIFS(金融!F:F, 2030, 金融!G:G, "强化或放宽目标（消极气候影响）")
K28: 2026 | L28: =COUNTIFS(温室气体排放!B:B, 2026, 温室气体排放!G:G, "新目标") + COUNTIFS(温室气体排放!B:B, 2026, 温室气体排放!G:G, "强化或放宽目标（气候影响不明确）") + COUNTIFS(温室气体排放!B:B, 2026, 温室气体排放!G:G, "强化或放宽目标（积极气候影响）") + COUNTIFS(温室气体排放!B:B, 2026, 温室气体排放!G:G, "强化或放宽目标（消极气候影响）") + COUNTIFS(污染!A:A, 2026, 污染!G:G, "新目标") + COUNTIFS(污染!A:A, 2026, 污染!G:G, "强化或放宽目标（气候影响不明确）") + COUNTIFS(污染!A:A, 2026, 污染!G:G, "强化或放宽目标（积极气候影响）") + COUNTIFS(污染!A:A, 2026, 污染!G:G, "强化或放宽目标（消极气候影响）") + COUNTIFS('能源|电力'!A:A, 2026, '能源|电力'!G:G, "新目标") + COUNTIFS('能源|电力'!A:A, 2026, '能源|电力'!G:G, "强化或放宽目标（气候影响不明确）") + COUNTIFS('能源|电力'!A:A, 2026, '能源|电力'!G:G, "强化或放宽目标（积极气候影响）") + COUNTIFS('能源|电力'!A:A, 2026, '能源|电力'!G:G, "强化或放宽目标（消极气候影响）") + COUNTIFS(工业!A:A, 2026, 工业!G:G, "新目标") + COUNTIFS(工业!A:A, 2026, 工业!G:G, "强化或放宽目标（气候影响不明确）") + COUNTIFS(工业!A:A, 2026, 工业!G:G, "强化或放宽目标（积极气候影响）") + COUNTIFS(工业!A:A, 2026, 工业!G:G, "强化或放宽目标（消极气候影响）") + COUNTIFS(建筑!B:B, 2026, 建筑!G:G, "新目标") + COUNTIFS(建筑!B:B, 2026, 建筑!G:G, "强化或放宽目标（气候影响不明确）") + COUNTIFS(建筑!B:B, 2026, 建筑!G:G, "强化或放宽目标（积极气候影响）") + COUNTIFS(建筑!B:B, 2026, 建筑!G:G, "强化或放宽目标（消极气候影响）") + COUNTIFS(交通!A:A, 2026, 交通!G:G, "新目标") + COUNTIFS(交通!A:A, 2026, 交通!G:G, "强化或放宽目标（气候影响不明确）") + COUNTIFS(交通!A:A, 2026, 交通!G:G, "强化或放宽目标（积极气候影响）") + COUNTIFS(交通!A:A, 2026, 交通!G:G, "强化或放宽目标（消极气候影响）") + COUNTIFS('土地利用、土地利用变化和林业'!A:A, 2026, '土地利用、土地利用变化和林业'!G:G, "新目标") + COUNTIFS('土地利用、土地利用变化和林业'!A:A, 2026, '土地利用、土地利用变化和林业'!G:G, "强化或放宽目标（气候影响不明确）") + COUNTIFS('土地利用、土地利用变化和林业'!A:A, 2026, '土地利用、土地利用变化和林业'!G:G, "强化或放宽目标（积极气候影响）") + COUNTIFS('土地利用、土地利用变化和林业'!A:A, 2026, '土地利用、土地利用变化和林业'!G:G, "强化或放宽目标（消极气候影响）") + COUNTIFS(循环经济!A:A, 2026, 循环经济!G:G, "新目标") + COUNTIFS(循环经济!A:A, 2026, 循环经济!G:G, "强化或放宽目标（气候影响不明确）") + COUNTIFS(循环经济!A:A, 2026, 循环经济!G:G, "强化或放宽目标（积极气候影响）") + COUNTIFS(循环经济!A:A, 2026, 循环经济!G:G, "强化或放宽目标（消极气候影响）") + COUNTIFS(金融!A:A, 2026, 金融!G:G, "新目标") + COUNTIFS(金融!A:A, 2026, 金融!G:G, "强化或放宽目标（气候影响不明确）") + COUNTIFS(金融!A:A, 2026, 金融!G:G, "强化或放宽目标（积极气候影响）") + COUNTIFS(金融!A:A, 2026, 金融!G:G, "强化或放宽目标（消极气候影响）") | N28: 2030年前 | O28: =COUNTIFS(温室气体排放!F:F, "2030年前", 温室气体排放!G:G, "新目标") + COUNTIFS(温室气体排放!F:F, "2030年前", 温室气体排放!G:G, "强化或放宽目标（气候影响不明确）") + COUNTIFS(温室气体排放!F:F, "2030年前", 温室气体排放!G:G, "强化或放宽目标（积极气候影响）") + COUNTIFS(温室气体排放!F:F, "2030年前", 温室气体排放!G:G, "强化或放宽目标（消极气候影响）") + COUNTIFS(污染!F:F, "2030年前", 污染!G:G, "新目标") + COUNTIFS(污染!F:F, "2030年前", 污染!G:G, "强化或放宽目标（气候影响不明确）") + COUNTIFS(污染!F:F, "2030年前", 污染!G:G, "强化或放宽目标（积极气候影响）") + COUNTIFS(污染!F:F, "2030年前", 污染!G:G, "强化或放宽目标（消极气候影响）") + COUNTIFS('能源|电力'!F:F, "2030年前", '能源|电力'!G:G, "新目标") + COUNTIFS('能源|电力'!F:F, "2030年前", '能源|电力'!G:G, "强化或放宽目标（气候影响不明确）") + COUNTIFS('能源|电力'!F:F, "2030年前", '能源|电力'!G:G, "强化或放宽目标（积极气候影响）") + COUNTIFS('能源|电力'!F:F, "2030年前", '能源|电力'!G:G, "强化或放宽目标（消极气候影响）") + COUNTIFS(工业!F:F, "2030年前", 工业!G:G, "新目标") + COUNTIFS(工业!F:F, "2030年前", 工业!G:G, "强化或放宽目标（气候影响不明确）") + COUNTIFS(工业!F:F, "2030年前", 工业!G:G, "强化或放宽目标（积极气候影响）") + COUNTIFS(工业!F:F, "2030年前", 工业!G:G, "强化或放宽目标（消极气候影响）") + COUNTIFS(建筑!F:F, "2030年前", 建筑!G:G, "新目标") + COUNTIFS(建筑!F:F, "2030年前", 建筑!G:G, "强化或放宽目标（气候影响不明确）") + COUNTIFS(建筑!F:F, "2030年前", 建筑!G:G, "强化或放宽目标（积极气候影响）") + COUNTIFS(建筑!F:F, "2030年前", 建筑!G:G, "强化或放宽目标（消极气候影响）") + COUNTIFS(交通!F:F, "2030年前", 交通!G:G, "新目标") + COUNTIFS(交通!F:F, "2030年前", 交通!G:G, "强化或放宽目标（气候影响不明确）") + COUNTIFS(交通!F:F, "2030年前", 交通!G:G, "强化或放宽目标（积极气候影响）") + COUNTIFS(交通!F:F, "2030年前", 交通!G:G, "强化或放宽目标（消极气候影响）") + COUNTIFS('土地利用、土地利用变化和林业'!F:F, "2030年前", '土地利用、土地利用变化和林业'!G:G, "新目标") + COUNTIFS('土地利用、土地利用变化和林业'!F:F, "2030年前", '土地利用、土地利用变化和林业'!G:G, "强化或放宽目标（气候影响不明确）") + COUNTIFS('土地利用、土地利用变化和林业'!F:F, "2030年前", '土地利用、土地利用变化和林业'!G:G, "强化或放宽目标（积极气候影响）") + COUNTIFS('土地利用、土地利用变化和林业'!F:F, "2030年前", '土地利用、土地利用变化和林业'!G:G, "强化或放宽目标（消极气候影响）") + COUNTIFS(循环经济!F:F, "2030年前", 循环经济!G:G, "新目标") + COUNTIFS(循环经济!F:F, "2030年前", 循环经济!G:G, "强化或放宽目标（气候影响不明确）") + COUNTIFS(循环经济!F:F, "2030年前", 循环经济!G:G, "强化或放宽目标（积极气候影响）") + COUNTIFS(循环经济!F:F, "2030年前", 循环经济!G:G, "强化或放宽目标（消极气候影响）") + COUNTIFS(金融!F:F, "2030年前", 金融!G:G, "新目标") + COUNTIFS(金融!F:F, "2030年前", 金融!G:G, "强化或放宽目标（气候影响不明确）") + COUNTIFS(金融!F:F, "2030年前", 金融!G:G, "强化或放宽目标（积极气候影响）") + COUNTIFS(金融!F:F, "2030年前", 金融!G:G, "强化或放宽目标（消极气候影响）")
N29: 2030年左右 | O29: =COUNTIFS(温室气体排放!F:F, "2030年左右", 温室气体排放!G:G, "新目标") + COUNTIFS(温室气体排放!F:F, "2030年左右", 温室气体排放!G:G, "强化或放宽目标（气候影响不明确）") + COUNTIFS(温室气体排放!F:F, "2030年左右", 温室气体排放!G:G, "强化或放宽目标（积极气候影响）") + COUNTIFS(温室气体排放!F:F, "2030年左右", 温室气体排放!G:G, "强化或放宽目标（消极气候影响）") + COUNTIFS(污染!F:F, "2030年左右", 污染!G:G, "新目标") + COUNTIFS(污染!F:F, "2030年左右", 污染!G:G, "强化或放宽目标（气候影响不明确）") + COUNTIFS(污染!F:F, "2030年左右", 污染!G:G, "强化或放宽目标（积极气候影响）") + COUNTIFS(污染!F:F, "2030年左右", 污染!G:G, "强化或放宽目标（消极气候影响）") + COUNTIFS('能源|电力'!F:F, "2030年左右", '能源|电力'!G:G, "新目标") + COUNTIFS('能源|电力'!F:F, "2030年左右", '能源|电力'!G:G, "强化或放宽目标（气候影响不明确）") + COUNTIFS('能源|电力'!F:F, "2030年左右", '能源|电力'!G:G, "强化或放宽目标（积极气候影响）") + COUNTIFS('能源|电力'!F:F, "2030年左右", '能源|电力'!G:G, "强化或放宽目标（消极气候影响）") + COUNTIFS(工业!F:F, "2030年左右", 工业!G:G, "新目标") + COUNTIFS(工业!F:F, "2030年左右", 工业!G:G, "强化或放宽目标（气候影响不明确）") + COUNTIFS(工业!F:F, "2030年左右", 工业!G:G, "强化或放宽目标（积极气候影响）") + COUNTIFS(工业!F:F, "2030年左右", 工业!G:G, "强化或放宽目标（消极气候影响）") + COUNTIFS(建筑!F:F, "2030年左右", 建筑!G:G, "新目标") + COUNTIFS(建筑!F:F, "2030年左右", 建筑!G:G, "强化或放宽目标（气候影响不明确）") + COUNTIFS(建筑!F:F, "2030年左右", 建筑!G:G, "强化或放宽目标（积极气候影响）") + COUNTIFS(建筑!F:F, "2030年左右", 建筑!G:G, "强化或放宽目标（消极气候影响）") + COUNTIFS(交通!F:F, "2030年左右", 交通!G:G, "新目标") + COUNTIFS(交通!F:F, "2030年左右", 交通!G:G, "强化或放宽目标（气候影响不明确）") + COUNTIFS(交通!F:F, "2030年左右", 交通!G:G, "强化或放宽目标（积极气候影响）") + COUNTIFS(交通!F:F, "2030年左右", 交通!G:G, "强化或放宽目标（消极气候影响）") + COUNTIFS('土地利用、土地利用变化和林业'!F:F, "2030年左右", '土地利用、土地利用变化和林业'!G:G, "新目标") + COUNTIFS('土地利用、土地利用变化和林业'!F:F, "2030年左右", '土地利用、土地利用变化和林业'!G:G, "强化或放宽目标（气候影响不明确）") + COUNTIFS('土地利用、土地利用变化和林业'!F:F, "2030年左右", '土地利用、土地利用变化和林业'!G:G, "强化或放宽目标（积极气候影响）") + COUNTIFS('土地利用、土地利用变化和林业'!F:F, "2030年左右", '土地利用、土地利用变化和林业'!G:G, "强化或放宽目标（消极气候影响）") + COUNTIFS(循环经济!F:F, "2030年左右", 循环经济!G:G, "新目标") + COUNTIFS(循环经济!F:F, "2030年左右", 循环经济!G:G, "强化或放宽目标（气候影响不明确）") + COUNTIFS(循环经济!F:F, "2030年左右", 循环经济!G:G, "强化或放宽目标（积极气候影响）") + COUNTIFS(循环经济!F:F, "2030年左右", 循环经济!G:G, "强化或放宽目标（消极气候影响）") + COUNTIFS(金融!F:F, "2030年左右", 金融!G:G, "新目标") + COUNTIFS(金融!F:F, "2030年左右", 金融!G:G, "强化或放宽目标（气候影响不明确）") + COUNTIFS(金融!F:F, "2030年左右", 金融!G:G, "强化或放宽目标（积极气候影响）") + COUNTIFS(金融!F:F, "2030年左右", 金融!G:G, "强化或放宽目标（消极气候影响）")
N30: （2030年/2030年前） | O30: =SUM(O27:O29)
N31: 十五五 | O31: =COUNTIFS(温室气体排放!F:F, "十五五", 温室气体排放!G:G, "新目标") + COUNTIFS(温室气体排放!F:F, "十五五", 温室气体排放!G:G, "强化或放宽目标（气候影响不明确）") + COUNTIFS(温室气体排放!F:F, "十五五", 温室气体排放!G:G, "强化或放宽目标（积极气候影响）") + COUNTIFS(温室气体排放!F:F, "十五五", 温室气体排放!G:G, "强化或放宽目标（消极气候影响）") + COUNTIFS(污染!F:F, "十五五", 污染!G:G, "新目标") + COUNTIFS(污染!F:F, "十五五", 污染!G:G, "强化或放宽目标（气候影响不明确）") + COUNTIFS(污染!F:F, "十五五", 污染!G:G, "强化或放宽目标（积极气候影响）") + COUNTIFS(污染!F:F, "十五五", 污染!G:G, "强化或放宽目标（消极气候影响）") + COUNTIFS('能源|电力'!F:F, "十五五", '能源|电力'!G:G, "新目标") + COUNTIFS('能源|电力'!F:F, "十五五", '能源|电力'!G:G, "强化或放宽目标（气候影响不明确）") + COUNTIFS('能源|电力'!F:F, "十五五", '能源|电力'!G:G, "强化或放宽目标（积极气候影响）") + COUNTIFS('能源|电力'!F:F, "十五五", '能源|电力'!G:G, "强化或放宽目标（消极气候影响）") + COUNTIFS(工业!F:F, "十五五", 工业!G:G, "新目标") + COUNTIFS(工业!F:F, "十五五", 工业!G:G, "强化或放宽目标（气候影响不明确）") + COUNTIFS(工业!F:F, "十五五", 工业!G:G, "强化或放宽目标（积极气候影响）") + COUNTIFS(工业!F:F, "十五五", 工业!G:G, "强化或放宽目标（消极气候影响）") + COUNTIFS(建筑!F:F, "十五五", 建筑!G:G, "新目标") + COUNTIFS(建筑!F:F, "十五五", 建筑!G:G, "强化或放宽目标（气候影响不明确）") + COUNTIFS(建筑!F:F, "十五五", 建筑!G:G, "强化或放宽目标（积极气候影响）") + COUNTIFS(建筑!F:F, "十五五", 建筑!G:G, "强化或放宽目标（消极气候影响）") + COUNTIFS(交通!F:F, "十五五", 交通!G:G, "新目标") + COUNTIFS(交通!F:F, "十五五", 交通!G:G, "强化或放宽目标（气候影响不明确）") + COUNTIFS(交通!F:F, "十五五", 交通!G:G, "强化或放宽目标（积极气候影响）") + COUNTIFS(交通!F:F, "十五五", 交通!G:G, "强化或放宽目标（消极气候影响）") + COUNTIFS('土地利用、土地利用变化和林业'!F:F, "十五五", '土地利用、土地利用变化和林业'!G:G, "新目标") + COUNTIFS('土地利用、土地利用变化和林业'!F:F, "十五五", '土地利用、土地利用变化和林业'!G:G, "强化或放宽目标（气候影响不明确）") + COUNTIFS('土地利用、土地利用变化和林业'!F:F, "十五五", '土地利用、土地利用变化和林业'!G:G, "强化或放宽目标（积极气候影响）") + COUNTIFS('土地利用、土地利用变化和林业'!F:F, "十五五", '土地利用、土地利用变化和林业'!G:G, "强化或放宽目标（消极气候影响）") + COUNTIFS(循环经济!F:F, "十五五", 循环经济!G:G, "新目标") + COUNTIFS(循环经济!F:F, "十五五", 循环经济!G:G, "强化或放宽目标（气候影响不明确）") + COUNTIFS(循环经济!F:F, "十五五", 循环经济!G:G, "强化或放宽目标（积极气候影响）") + COUNTIFS(循环经济!F:F, "十五五", 循环经济!G:G, "强化或放宽目标（消极气候影响）") + COUNTIFS(金融!F:F, "十五五", 金融!G:G, "新目标") + COUNTIFS(金融!F:F, "十五五", 金融!G:G, "强化或放宽目标（气候影响不明确）") + COUNTIFS(金融!F:F, "十五五", 金融!G:G, "强化或放宽目标（积极气候影响）") + COUNTIFS(金融!F:F, "十五五", 金融!G:G, "强化或放宽目标（消极气候影响）")
N32: 2035 | O32: =COUNTIFS(温室气体排放!F:F, 2035, 温室气体排放!G:G, "新目标") + COUNTIFS(温室气体排放!F:F, 2035, 温室气体排放!G:G, "强化或放宽目标（气候影响不明确）") + COUNTIFS(温室气体排放!F:F, 2035, 温室气体排放!G:G, "强化或放宽目标（积极气候影响）") + COUNTIFS(温室气体排放!F:F, 2035, 温室气体排放!G:G, "强化或放宽目标（消极气候影响）") + COUNTIFS(污染!F:F, 2035, 污染!G:G, "新目标") + COUNTIFS(污染!F:F, 2035, 污染!G:G, "强化或放宽目标（气候影响不明确）") + COUNTIFS(污染!F:F, 2035, 污染!G:G, "强化或放宽目标（积极气候影响）") + COUNTIFS(污染!F:F, 2035, 污染!G:G, "强化或放宽目标（消极气候影响）") + COUNTIFS('能源|电力'!F:F, 2035, '能源|电力'!G:G, "新目标") + COUNTIFS('能源|电力'!F:F, 2035, '能源|电力'!G:G, "强化或放宽目标（气候影响不明确）") + COUNTIFS('能源|电力'!F:F, 2035, '能源|电力'!G:G, "强化或放宽目标（积极气候影响）") + COUNTIFS('能源|电力'!F:F, 2035, '能源|电力'!G:G, "强化或放宽目标（消极气候影响）") + COUNTIFS(工业!F:F, 2035, 工业!G:G, "新目标") + COUNTIFS(工业!F:F, 2035, 工业!G:G, "强化或放宽目标（气候影响不明确）") + COUNTIFS(工业!F:F, 2035, 工业!G:G, "强化或放宽目标（积极气候影响）") + COUNTIFS(工业!F:F, 2035, 工业!G:G, "强化或放宽目标（消极气候影响）") + COUNTIFS(建筑!F:F, 2035, 建筑!G:G, "新目标") + COUNTIFS(建筑!F:F, 2035, 建筑!G:G, "强化或放宽目标（气候影响不明确）") + COUNTIFS(建筑!F:F, 2035, 建筑!G:G, "强化或放宽目标（积极气候影响）") + COUNTIFS(建筑!F:F, 2035, 建筑!G:G, "强化或放宽目标（消极气候影响）") + COUNTIFS(交通!F:F, 2035, 交通!G:G, "新目标") + COUNTIFS(交通!F:F, 2035, 交通!G:G, "强化或放宽目标（气候影响不明确）") + COUNTIFS(交通!F:F, 2035, 交通!G:G, "强化或放宽目标（积极气候影响）") + COUNTIFS(交通!F:F, 2035, 交通!G:G, "强化或放宽目标（消极气候影响）") + COUNTIFS('土地利用、土地利用变化和林业'!F:F, 2035, '土地利用、土地利用变化和林业'!G:G, "新目标") + COUNTIFS('土地利用、土地利用变化和林业'!F:F, 2035, '土地利用、土地利用变化和林业'!G:G, "强化或放宽目标（气候影响不明确）") + COUNTIFS('土地利用、土地利用变化和林业'!F:F, 2035, '土地利用、土地利用变化和林业'!G:G, "强化或放宽目标（积极气候影响）") + COUNTIFS('土地利用、土地利用变化和林业'!F:F, 2035, '土地利用、土地利用变化和林业'!G:G, "强化或放宽目标（消极气候影响）") + COUNTIFS(循环经济!F:F, 2035, 循环经济!G:G, "新目标") + COUNTIFS(循环经济!F:F, 2035, 循环经济!G:G, "强化或放宽目标（气候影响不明确）") + COUNTIFS(循环经济!F:F, 2035, 循环经济!G:G, "强化或放宽目标（积极气候影响）") + COUNTIFS(循环经济!F:F, 2035, 循环经济!G:G, "强化或放宽目标（消极气候影响）") + COUNTIFS(金融!F:F, 2035, 金融!G:G, "新目标") + COUNTIFS(金融!F:F, 2035, 金融!G:G, "强化或放宽目标（气候影响不明确）") + COUNTIFS(金融!F:F, 2035, 金融!G:G, "强化或放宽目标（积极气候影响）") + COUNTIFS(金融!F:F, 2035, 金融!G:G, "强化或放宽目标（消极气候影响）")
N33: 2060年前 | O33: =COUNTIFS(温室气体排放!F:F, "2060年前", 温室气体排放!G:G, "新目标") + COUNTIFS(温室气体排放!F:F, "2060年前", 温室气体排放!G:G, "强化或放宽目标（气候影响不明确）") + COUNTIFS(温室气体排放!F:F, "2060年前", 温室气体排放!G:G, "强化或放宽目标（积极气候影响）") + COUNTIFS(温室气体排放!F:F, "2060年前", 温室气体排放!G:G, "强化或放宽目标（消极气候影响）") + COUNTIFS(污染!F:F, "2060年前", 污染!G:G, "新目标") + COUNTIFS(污染!F:F, "2060年前", 污染!G:G, "强化或放宽目标（气候影响不明确）") + COUNTIFS(污染!F:F, "2060年前", 污染!G:G, "强化或放宽目标（积极气候影响）") + COUNTIFS(污染!F:F, "2060年前", 污染!G:G, "强化或放宽目标（消极气候影响）") + COUNTIFS('能源|电力'!F:F, "2060年前", '能源|电力'!G:G, "新目标") + COUNTIFS('能源|电力'!F:F, "2060年前", '能源|电力'!G:G, "强化或放宽目标（气候影响不明确）") + COUNTIFS('能源|电力'!F:F, "2060年前", '能源|电力'!G:G, "强化或放宽目标（积极气候影响）") + COUNTIFS('能源|电力'!F:F, "2060年前", '能源|电力'!G:G, "强化或放宽目标（消极气候影响）") + COUNTIFS(工业!F:F, "2060年前", 工业!G:G, "新目标") + COUNTIFS(工业!F:F, "2060年前", 工业!G:G, "强化或放宽目标（气候影响不明确）") + COUNTIFS(工业!F:F, "2060年前", 工业!G:G, "强化或放宽目标（积极气候影响）") + COUNTIFS(工业!F:F, "2060年前", 工业!G:G, "强化或放宽目标（消极气候影响）") + COUNTIFS(建筑!F:F, "2060年前", 建筑!G:G, "新目标") + COUNTIFS(建筑!F:F, "2060年前", 建筑!G:G, "强化或放宽目标（气候影响不明确）") + COUNTIFS(建筑!F:F, "2060年前", 建筑!G:G, "强化或放宽目标（积极气候影响）") + COUNTIFS(建筑!F:F, "2060年前", 建筑!G:G, "强化或放宽目标（消极气候影响）") + COUNTIFS(交通!F:F, "2060年前", 交通!G:G, "新目标") + COUNTIFS(交通!F:F, "2060年前", 交通!G:G, "强化或放宽目标（气候影响不明确）") + COUNTIFS(交通!F:F, "2060年前", 交通!G:G, "强化或放宽目标（积极气候影响）") + COUNTIFS(交通!F:F, "2060年前", 交通!G:G, "强化或放宽目标（消极气候影响）") + COUNTIFS('土地利用、土地利用变化和林业'!F:F, "2060年前", '土地利用、土地利用变化和林业'!G:G, "新目标") + COUNTIFS('土地利用、土地利用变化和林业'!F:F, "2060年前", '土地利用、土地利用变化和林业'!G:G, "强化或放宽目标（气候影响不明确）") + COUNTIFS('土地利用、土地利用变化和林业'!F:F, "2060年前", '土地利用、土地利用变化和林业'!G:G, "强化或放宽目标（积极气候影响）") + COUNTIFS('土地利用、土地利用变化和林业'!F:F, "2060年前", '土地利用、土地利用变化和林业'!G:G, "强化或放宽目标（消极气候影响）") + COUNTIFS(循环经济!F:F, "2060年前", 循环经济!G:G, "新目标") + COUNTIFS(循环经济!F:F, "2060年前", 循环经济!G:G, "强化或放宽目标（气候影响不明确）") + COUNTIFS(循环经济!F:F, "2060年前", 循环经济!G:G, "强化或放宽目标（积极气候影响）") + COUNTIFS(循环经济!F:F, "2060年前", 循环经济!G:G, "强化或放宽目标（消极气候影响）") + COUNTIFS(金融!F:F, "2060年前", 金融!G:G, "新目标") + COUNTIFS(金融!F:F, "2060年前", 金融!G:G, "强化或放宽目标（气候影响不明确）") + COUNTIFS(金融!F:F, "2060年前", 金融!G:G, "强化或放宽目标（积极气候影响）") + COUNTIFS(金融!F:F, "2060年前", 金融!G:G, "强化或放宽目标（消极气候影响）")
N34: 2003-2020 | O34: =COUNTIFS(温室气体排放!F:F, "2003-2020", 温室气体排放!G:G, "新目标") + COUNTIFS(温室气体排放!F:F, "2003-2020", 温室气体排放!G:G, "强化或放宽目标（气候影响不明确）") + COUNTIFS(温室气体排放!F:F, "2003-2020", 温室气体排放!G:G, "强化或放宽目标（积极气候影响）") + COUNTIFS(温室气体排放!F:F, "2003-2020", 温室气体排放!G:G, "强化或放宽目标（消极气候影响）") + COUNTIFS(污染!F:F, "2003-2020", 污染!G:G, "新目标") + COUNTIFS(污染!F:F, "2003-2020", 污染!G:G, "强化或放宽目标（气候影响不明确）") + COUNTIFS(污染!F:F, "2003-2020", 污染!G:G, "强化或放宽目标（积极气候影响）") + COUNTIFS(污染!F:F, "2003-2020", 污染!G:G, "强化或放宽目标（消极气候影响）") + COUNTIFS('能源|电力'!F:F, "2003-2020", '能源|电力'!G:G, "新目标") + COUNTIFS('能源|电力'!F:F, "2003-2020", '能源|电力'!G:G, "强化或放宽目标（气候影响不明确）") + COUNTIFS('能源|电力'!F:F, "2003-2020", '能源|电力'!G:G, "强化或放宽目标（积极气候影响）") + COUNTIFS('能源|电力'!F:F, "2003-2020", '能源|电力'!G:G, "强化或放宽目标（消极气候影响）") + COUNTIFS(工业!F:F, "2003-2020", 工业!G:G, "新目标") + COUNTIFS(工业!F:F, "2003-2020", 工业!G:G, "强化或放宽目标（气候影响不明确）") + COUNTIFS(工业!F:F, "2003-2020", 工业!G:G, "强化或放宽目标（积极气候影响）") + COUNTIFS(工业!F:F, "2003-2020", 工业!G:G, "强化或放宽目标（消极气候影响）") + COUNTIFS(建筑!F:F, "2003-2020", 建筑!G:G, "新目标") + COUNTIFS(建筑!F:F, "2003-2020", 建筑!G:G, "强化或放宽目标（气候影响不明确）") + COUNTIFS(建筑!F:F, "2003-2020", 建筑!G:G, "强化或放宽目标（积极气候影响）") + COUNTIFS(建筑!F:F, "2003-2020", 建筑!G:G, "强化或放宽目标（消极气候影响）") + COUNTIFS(交通!F:F, "2003-2020", 交通!G:G, "新目标") + COUNTIFS(交通!F:F, "2003-2020", 交通!G:G, "强化或放宽目标（气候影响不明确）") + COUNTIFS(交通!F:F, "2003-2020", 交通!G:G, "强化或放宽目标（积极气候影响）") + COUNTIFS(交通!F:F, "2003-2020", 交通!G:G, "强化或放宽目标（消极气候影响）") + COUNTIFS('土地利用、土地利用变化和林业'!F:F, "2003-2020", '土地利用、土地利用变化和林业'!G:G, "新目标") + COUNTIFS('土地利用、土地利用变化和林业'!F:F, "2003-2020", '土地利用、土地利用变化和林业'!G:G, "强化或放宽目标（气候影响不明确）") + COUNTIFS('土地利用、土地利用变化和林业'!F:F, "2003-2020", '土地利用、土地利用变化和林业'!G:G, "强化或放宽目标（积极气候影响）") + COUNTIFS('土地利用、土地利用变化和林业'!F:F, "2003-2020", '土地利用、土地利用变化和林业'!G:G, "强化或放宽目标（消极气候影响）") + COUNTIFS(循环经济!F:F, "2003-2020", 循环经济!G:G, "新目标") + COUNTIFS(循环经济!F:F, "2003-2020", 循环经济!G:G, "强化或放宽目标（气候影响不明确）") + COUNTIFS(循环经济!F:F, "2003-2020", 循环经济!G:G, "强化或放宽目标（积极气候影响）") + COUNTIFS(循环经济!F:F, "2003-2020", 循环经济!G:G, "强化或放宽目标（消极气候影响）") + COUNTIFS(金融!F:F, "2003-2020", 金融!G:G, "新目标") + COUNTIFS(金融!F:F, "2003-2020", 金融!G:G, "强化或放宽目标（气候影响不明确）") + COUNTIFS(金融!F:F, "2003-2020", 金融!G:G, "强化或放宽目标（积极气候影响）") + COUNTIFS(金融!F:F, "2003-2020", 金融!G:G, "强化或放宽目标（消极气候影响）")
N35: 2007-2010 | O35: =COUNTIFS(温室气体排放!F:F, "2007-2010", 温室气体排放!G:G, "新目标") + COUNTIFS(温室气体排放!F:F, "2007-2010", 温室气体排放!G:G, "强化或放宽目标（气候影响不明确）") + COUNTIFS(温室气体排放!F:F, "2007-2010", 温室气体排放!G:G, "强化或放宽目标（积极气候影响）") + COUNTIFS(温室气体排放!F:F, "2007-2010", 温室气体排放!G:G, "强化或放宽目标（消极气候影响）") + COUNTIFS(污染!F:F, "2007-2010", 污染!G:G, "新目标") + COUNTIFS(污染!F:F, "2007-2010", 污染!G:G, "强化或放宽目标（气候影响不明确）") + COUNTIFS(污染!F:F, "2007-2010", 污染!G:G, "强化或放宽目标（积极气候影响）") + COUNTIFS(污染!F:F, "2007-2010", 污染!G:G, "强化或放宽目标（消极气候影响）") + COUNTIFS('能源|电力'!F:F, "2007-2010", '能源|电力'!G:G, "新目标") + COUNTIFS('能源|电力'!F:F, "2007-2010", '能源|电力'!G:G, "强化或放宽目标（气候影响不明确）") + COUNTIFS('能源|电力'!F:F, "2007-2010", '能源|电力'!G:G, "强化或放宽目标（积极气候影响）") + COUNTIFS('能源|电力'!F:F, "2007-2010", '能源|电力'!G:G, "强化或放宽目标（消极气候影响）") + COUNTIFS(工业!F:F, "2007-2010", 工业!G:G, "新目标") + COUNTIFS(工业!F:F, "2007-2010", 工业!G:G, "强化或放宽目标（气候影响不明确）") + COUNTIFS(工业!F:F, "2007-2010", 工业!G:G, "强化或放宽目标（积极气候影响）") + COUNTIFS(工业!F:F, "2007-2010", 工业!G:G, "强化或放宽目标（消极气候影响）") + COUNTIFS(建筑!F:F, "2007-2010", 建筑!G:G, "新目标") + COUNTIFS(建筑!F:F, "2007-2010", 建筑!G:G, "强化或放宽目标（气候影响不明确）") + COUNTIFS(建筑!F:F, "2007-2010", 建筑!G:G, "强化或放宽目标（积极气候影响）") + COUNTIFS(建筑!F:F, "2007-2010", 建筑!G:G, "强化或放宽目标（消极气候影响）") + COUNTIFS(交通!F:F, "2007-2010", 交通!G:G, "新目标") + COUNTIFS(交通!F:F, "2007-2010", 交通!G:G, "强化或放宽目标（气候影响不明确）") + COUNTIFS(交通!F:F, "2007-2010", 交通!G:G, "强化或放宽目标（积极气候影响）") + COUNTIFS(交通!F:F, "2007-2010", 交通!G:G, "强化或放宽目标（消极气候影响）") + COUNTIFS('土地利用、土地利用变化和林业'!F:F, "2007-2010", '土地利用、土地利用变化和林业'!G:G, "新目标") + COUNTIFS('土地利用、土地利用变化和林业'!F:F, "2007-2010", '土地利用、土地利用变化和林业'!G:G, "强化或放宽目标（气候影响不明确）") + COUNTIFS('土地利用、土地利用变化和林业'!F:F, "2007-2010", '土地利用、土地利用变化和林业'!G:G, "强化或放宽目标（积极气候影响）") + COUNTIFS('土地利用、土地利用变化和林业'!F:F, "2007-2010", '土地利用、土地利用变化和林业'!G:G, "强化或放宽目标（消极气候影响）") + COUNTIFS(循环经济!F:F, "2007-2010", 循环经济!G:G, "新目标") + COUNTIFS(循环经济!F:F, "2007-2010", 循环经济!G:G, "强化或放宽目标（气候影响不明确）") + COUNTIFS(循环经济!F:F, "2007-2010", 循环经济!G:G, "强化或放宽目标（积极气候影响）") + COUNTIFS(循环经济!F:F, "2007-2010", 循环经济!G:G, "强化或放宽目标（消极气候影响）") + COUNTIFS(金融!F:F, "2007-2010", 金融!G:G, "新目标") + COUNTIFS(金融!F:F, "2007-2010", 金融!G:G, "强化或放宽目标（气候影响不明确）") + COUNTIFS(金融!F:F, "2007-2010", 金融!G:G, "强化或放宽目标（积极气候影响）") + COUNTIFS(金融!F:F, "2007-2010", 金融!G:G, "强化或放宽目标（消极气候影响）")
N36: 2007-2020 | O36: =COUNTIFS(温室气体排放!F:F, "2007-2020", 温室气体排放!G:G, "新目标") + COUNTIFS(温室气体排放!F:F, "2007-2020", 温室气体排放!G:G, "强化或放宽目标（气候影响不明确）") + COUNTIFS(温室气体排放!F:F, "2007-2020", 温室气体排放!G:G, "强化或放宽目标（积极气候影响）") + COUNTIFS(温室气体排放!F:F, "2007-2020", 温室气体排放!G:G, "强化或放宽目标（消极气候影响）") + COUNTIFS(污染!F:F, "2007-2020", 污染!G:G, "新目标") + COUNTIFS(污染!F:F, "2007-2020", 污染!G:G, "强化或放宽目标（气候影响不明确）") + COUNTIFS(污染!F:F, "2007-2020", 污染!G:G, "强化或放宽目标（积极气候影响）") + COUNTIFS(污染!F:F, "2007-2020", 污染!G:G, "强化或放宽目标（消极气候影响）") + COUNTIFS('能源|电力'!F:F, "2007-2020", '能源|电力'!G:G, "新目标") + COUNTIFS('能源|电力'!F:F, "2007-2020", '能源|电力'!G:G, "强化或放宽目标（气候影响不明确）") + COUNTIFS('能源|电力'!F:F, "2007-2020", '能源|电力'!G:G, "强化或放宽目标（积极气候影响）") + COUNTIFS('能源|电力'!F:F, "2007-2020", '能源|电力'!G:G, "强化或放宽目标（消极气候影响）") + COUNTIFS(工业!F:F, "2007-2020", 工业!G:G, "新目标") + COUNTIFS(工业!F:F, "2007-2020", 工业!G:G, "强化或放宽目标（气候影响不明确）") + COUNTIFS(工业!F:F, "2007-2020", 工业!G:G, "强化或放宽目标（积极气候影响）") + COUNTIFS(工业!F:F, "2007-2020", 工业!G:G, "强化或放宽目标（消极气候影响）") + COUNTIFS(建筑!F:F, "2007-2020", 建筑!G:G, "新目标") + COUNTIFS(建筑!F:F, "2007-2020", 建筑!G:G, "强化或放宽目标（气候影响不明确）") + COUNTIFS(建筑!F:F, "2007-2020", 建筑!G:G, "强化或放宽目标（积极气候影响）") + COUNTIFS(建筑!F:F, "2007-2020", 建筑!G:G, "强化或放宽目标（消极气候影响）") + COUNTIFS(交通!F:F, "2007-2020", 交通!G:G, "新目标") + COUNTIFS(交通!F:F, "2007-2020", 交通!G:G, "强化或放宽目标（气候影响不明确）") + COUNTIFS(交通!F:F, "2007-2020", 交通!G:G, "强化或放宽目标（积极气候影响）") + COUNTIFS(交通!F:F, "2007-2020", 交通!G:G, "强化或放宽目标（消极气候影响）") + COUNTIFS('土地利用、土地利用变化和林业'!F:F, "2007-2020", '土地利用、土地利用变化和林业'!G:G, "新目标") + COUNTIFS('土地利用、土地利用变化和林业'!F:F, "2007-2020", '土地利用、土地利用变化和林业'!G:G, "强化或放宽目标（气候影响不明确）") + COUNTIFS('土地利用、土地利用变化和林业'!F:F, "2007-2020", '土地利用、土地利用变化和林业'!G:G, "强化或放宽目标（积极气候影响）") + COUNTIFS('土地利用、土地利用变化和林业'!F:F, "2007-2020", '土地利用、土地利用变化和林业'!G:G, "强化或放宽目标（消极气候影响）") + COUNTIFS(循环经济!F:F, "2007-2020", 循环经济!G:G, "新目标") + COUNTIFS(循环经济!F:F, "2007-2020", 循环经济!G:G, "强化或放宽目标（气候影响不明确）") + COUNTIFS(循环经济!F:F, "2007-2020", 循环经济!G:G, "强化或放宽目标（积极气候影响）") + COUNTIFS(循环经济!F:F, "2007-2020", 循环经济!G:G, "强化或放宽目标（消极气候影响）") + COUNTIFS(金融!F:F, "2007-2020", 金融!G:G, "新目标") + COUNTIFS(金融!F:F, "2007-2020", 金融!G:G, "强化或放宽目标（气候影响不明确）") + COUNTIFS(金融!F:F, "2007-2020", 金融!G:G, "强化或放宽目标（积极气候影响）") + COUNTIFS(金融!F:F, "2007-2020", 金融!G:G, "强化或放宽目标（消极气候影响）")
N37: 2014-2015 | O37: =COUNTIFS(温室气体排放!F:F, "2014-2015", 温室气体排放!G:G, "新目标") + COUNTIFS(温室气体排放!F:F, "2014-2015", 温室气体排放!G:G, "强化或放宽目标（气候影响不明确）") + COUNTIFS(温室气体排放!F:F, "2014-2015", 温室气体排放!G:G, "强化或放宽目标（积极气候影响）") + COUNTIFS(温室气体排放!F:F, "2014-2015", 温室气体排放!G:G, "强化或放宽目标（消极气候影响）") + COUNTIFS(污染!F:F, "2014-2015", 污染!G:G, "新目标") + COUNTIFS(污染!F:F, "2014-2015", 污染!G:G, "强化或放宽目标（气候影响不明确）") + COUNTIFS(污染!F:F, "2014-2015", 污染!G:G, "强化或放宽目标（积极气候影响）") + COUNTIFS(污染!F:F, "2014-2015", 污染!G:G, "强化或放宽目标（消极气候影响）") + COUNTIFS('能源|电力'!F:F, "2014-2015", '能源|电力'!G:G, "新目标") + COUNTIFS('能源|电力'!F:F, "2014-2015", '能源|电力'!G:G, "强化或放宽目标（气候影响不明确）") + COUNTIFS('能源|电力'!F:F, "2014-2015", '能源|电力'!G:G, "强化或放宽目标（积极气候影响）") + COUNTIFS('能源|电力'!F:F, "2014-2015", '能源|电力'!G:G, "强化或放宽目标（消极气候影响）") + COUNTIFS(工业!F:F, "2014-2015", 工业!G:G, "新目标") + COUNTIFS(工业!F:F, "2014-2015", 工业!G:G, "强化或放宽目标（气候影响不明确）") + COUNTIFS(工业!F:F, "2014-2015", 工业!G:G, "强化或放宽目标（积极气候影响）") + COUNTIFS(工业!F:F, "2014-2015", 工业!G:G, "强化或放宽目标（消极气候影响）") + COUNTIFS(建筑!F:F, "2014-2015", 建筑!G:G, "新目标") + COUNTIFS(建筑!F:F, "2014-2015", 建筑!G:G, "强化或放宽目标（气候影响不明确）") + COUNTIFS(建筑!F:F, "2014-2015", 建筑!G:G, "强化或放宽目标（积极气候影响）") + COUNTIFS(建筑!F:F, "2014-2015", 建筑!G:G, "强化或放宽目标（消极气候影响）") + COUNTIFS(交通!F:F, "2014-2015", 交通!G:G, "新目标") + COUNTIFS(交通!F:F, "2014-2015", 交通!G:G, "强化或放宽目标（气候影响不明确）") + COUNTIFS(交通!F:F, "2014-2015", 交通!G:G, "强化或放宽目标（积极气候影响）") + COUNTIFS(交通!F:F, "2014-2015", 交通!G:G, "强化或放宽目标（消极气候影响）") + COUNTIFS('土地利用、土地利用变化和林业'!F:F, "2014-2015", '土地利用、土地利用变化和林业'!G:G, "新目标") + COUNTIFS('土地利用、土地利用变化和林业'!F:F, "2014-2015", '土地利用、土地利用变化和林业'!G:G, "强化或放宽目标（气候影响不明确）") + COUNTIFS('土地利用、土地利用变化和林业'!F:F, "2014-2015", '土地利用、土地利用变化和林业'!G:G, "强化或放宽目标（积极气候影响）") + COUNTIFS('土地利用、土地利用变化和林业'!F:F, "2014-2015", '土地利用、土地利用变化和林业'!G:G, "强化或放宽目标（消极气候影响）") + COUNTIFS(循环经济!F:F, "2014-2015", 循环经济!G:G, "新目标") + COUNTIFS(循环经济!F:F, "2014-2015", 循环经济!G:G, "强化或放宽目标（气候影响不明确）") + COUNTIFS(循环经济!F:F, "2014-2015", 循环经济!G:G, "强化或放宽目标（积极气候影响）") + COUNTIFS(循环经济!F:F, "2014-2015", 循环经济!G:G, "强化或放宽目标（消极气候影响）") + COUNTIFS(金融!F:F, "2014-2015", 金融!G:G, "新目标") + COUNTIFS(金融!F:F, "2014-2015", 金融!G:G, "强化或放宽目标（气候影响不明确）") + COUNTIFS(金融!F:F, "2014-2015", 金融!G:G, "强化或放宽目标（积极气候影响）") + COUNTIFS(金融!F:F, "2014-2015", 金融!G:G, "强化或放宽目标（消极气候影响）")
N38: 2014-2016 | O38: =COUNTIFS(温室气体排放!F:F, "2014-2016", 温室气体排放!G:G, "新目标") + COUNTIFS(温室气体排放!F:F, "2014-2016", 温室气体排放!G:G, "强化或放宽目标（气候影响不明确）") + COUNTIFS(温室气体排放!F:F, "2014-2016", 温室气体排放!G:G, "强化或放宽目标（积极气候影响）") + COUNTIFS(温室气体排放!F:F, "2014-2016", 温室气体排放!G:G, "强化或放宽目标（消极气候影响）") + COUNTIFS(污染!F:F, "2014-2016", 污染!G:G, "新目标") + COUNTIFS(污染!F:F, "2014-2016", 污染!G:G, "强化或放宽目标（气候影响不明确）") + COUNTIFS(污染!F:F, "2014-2016", 污染!G:G, "强化或放宽目标（积极气候影响）") + COUNTIFS(污染!F:F, "2014-2016", 污染!G:G, "强化或放宽目标（消极气候影响）") + COUNTIFS('能源|电力'!F:F, "2014-2016", '能源|电力'!G:G, "新目标") + COUNTIFS('能源|电力'!F:F, "2014-2016", '能源|电力'!G:G, "强化或放宽目标（气候影响不明确）") + COUNTIFS('能源|电力'!F:F, "2014-2016", '能源|电力'!G:G, "强化或放宽目标（积极气候影响）") + COUNTIFS('能源|电力'!F:F, "2014-2016", '能源|电力'!G:G, "强化或放宽目标（消极气候影响）") + COUNTIFS(工业!F:F, "2014-2016", 工业!G:G, "新目标") + COUNTIFS(工业!F:F, "2014-2016", 工业!G:G, "强化或放宽目标（气候影响不明确）") + COUNTIFS(工业!F:F, "2014-2016", 工业!G:G, "强化或放宽目标（积极气候影响）") + COUNTIFS(工业!F:F, "2014-2016", 工业!G:G, "强化或放宽目标（消极气候影响）") + COUNTIFS(建筑!F:F, "2014-2016", 建筑!G:G, "新目标") + COUNTIFS(建筑!F:F, "2014-2016", 建筑!G:G, "强化或放宽目标（气候影响不明确）") + COUNTIFS(建筑!F:F, "2014-2016", 建筑!G:G, "强化或放宽目标（积极气候影响）") + COUNTIFS(建筑!F:F, "2014-2016", 建筑!G:G, "强化或放宽目标（消极气候影响）") + COUNTIFS(交通!F:F, "2014-2016", 交通!G:G, "新目标") + COUNTIFS(交通!F:F, "2014-2016", 交通!G:G, "强化或放宽目标（气候影响不明确）") + COUNTIFS(交通!F:F, "2014-2016", 交通!G:G, "强化或放宽目标（积极气候影响）") + COUNTIFS(交通!F:F, "2014-2016", 交通!G:G, "强化或放宽目标（消极气候影响）") + COUNTIFS('土地利用、土地利用变化和林业'!F:F, "2014-2016", '土地利用、土地利用变化和林业'!G:G, "新目标") + COUNTIFS('土地利用、土地利用变化和林业'!F:F, "2014-2016", '土地利用、土地利用变化和林业'!G:G, "强化或放宽目标（气候影响不明确）") + COUNTIFS('土地利用、土地利用变化和林业'!F:F, "2014-2016", '土地利用、土地利用变化和林业'!G:G, "强化或放宽目标（积极气候影响）") + COUNTIFS('土地利用、土地利用变化和林业'!F:F, "2014-2016", '土地利用、土地利用变化和林业'!G:G, "强化或放宽目标（消极气候影响）") + COUNTIFS(循环经济!F:F, "2014-2016", 循环经济!G:G, "新目标") + COUNTIFS(循环经济!F:F, "2014-2016", 循环经济!G:G, "强化或放宽目标（气候影响不明确）") + COUNTIFS(循环经济!F:F, "2014-2016", 循环经济!G:G, "强化或放宽目标（积极气候影响）") + COUNTIFS(循环经济!F:F, "2014-2016", 循环经济!G:G, "强化或放宽目标（消极气候影响）") + COUNTIFS(金融!F:F, "2014-2016", 金融!G:G, "新目标") + COUNTIFS(金融!F:F, "2014-2016", 金融!G:G, "强化或放宽目标（气候影响不明确）") + COUNTIFS(金融!F:F, "2014-2016", 金融!G:G, "强化或放宽目标（积极气候影响）") + COUNTIFS(金融!F:F, "2014-2016", 金融!G:G, "强化或放宽目标（消极气候影响）")
N39: 2016-2020 | O39: =COUNTIFS(温室气体排放!F:F, "2016-2020", 温室气体排放!G:G, "新目标") + COUNTIFS(温室气体排放!F:F, "2016-2020", 温室气体排放!G:G, "强化或放宽目标（气候影响不明确）") + COUNTIFS(温室气体排放!F:F, "2016-2020", 温室气体排放!G:G, "强化或放宽目标（积极气候影响）") + COUNTIFS(温室气体排放!F:F, "2016-2020", 温室气体排放!G:G, "强化或放宽目标（消极气候影响）") + COUNTIFS(污染!F:F, "2016-2020", 污染!G:G, "新目标") + COUNTIFS(污染!F:F, "2016-2020", 污染!G:G, "强化或放宽目标（气候影响不明确）") + COUNTIFS(污染!F:F, "2016-2020", 污染!G:G, "强化或放宽目标（积极气候影响）") + COUNTIFS(污染!F:F, "2016-2020", 污染!G:G, "强化或放宽目标（消极气候影响）") + COUNTIFS('能源|电力'!F:F, "2016-2020", '能源|电力'!G:G, "新目标") + COUNTIFS('能源|电力'!F:F, "2016-2020", '能源|电力'!G:G, "强化或放宽目标（气候影响不明确）") + COUNTIFS('能源|电力'!F:F, "2016-2020", '能源|电力'!G:G, "强化或放宽目标（积极气候影响）") + COUNTIFS('能源|电力'!F:F, "2016-2020", '能源|电力'!G:G, "强化或放宽目标（消极气候影响）") + COUNTIFS(工业!F:F, "2016-2020", 工业!G:G, "新目标") + COUNTIFS(工业!F:F, "2016-2020", 工业!G:G, "强化或放宽目标（气候影响不明确）") + COUNTIFS(工业!F:F, "2016-2020", 工业!G:G, "强化或放宽目标（积极气候影响）") + COUNTIFS(工业!F:F, "2016-2020", 工业!G:G, "强化或放宽目标（消极气候影响）") + COUNTIFS(建筑!F:F, "2016-2020", 建筑!G:G, "新目标") + COUNTIFS(建筑!F:F, "2016-2020", 建筑!G:G, "强化或放宽目标（气候影响不明确）") + COUNTIFS(建筑!F:F, "2016-2020", 建筑!G:G, "强化或放宽目标（积极气候影响）") + COUNTIFS(建筑!F:F, "2016-2020", 建筑!G:G, "强化或放宽目标（消极气候影响）") + COUNTIFS(交通!F:F, "2016-2020", 交通!G:G, "新目标") + COUNTIFS(交通!F:F, "2016-2020", 交通!G:G, "强化或放宽目标（气候影响不明确）") + COUNTIFS(交通!F:F, "2016-2020", 交通!G:G, "强化或放宽目标（积极气候影响）") + COUNTIFS(交通!F:F, "2016-2020", 交通!G:G, "强化或放宽目标（消极气候影响）") + COUNTIFS('土地利用、土地利用变化和林业'!F:F, "2016-2020", '土地利用、土地利用变化和林业'!G:G, "新目标") + COUNTIFS('土地利用、土地利用变化和林业'!F:F, "2016-2020", '土地利用、土地利用变化和林业'!G:G, "强化或放宽目标（气候影响不明确）") + COUNTIFS('土地利用、土地利用变化和林业'!F:F, "2016-2020", '土地利用、土地利用变化和林业'!G:G, "强化或放宽目标（积极气候影响）") + COUNTIFS('土地利用、土地利用变化和林业'!F:F, "2016-2020", '土地利用、土地利用变化和林业'!G:G, "强化或放宽目标（消极气候影响）") + COUNTIFS(循环经济!F:F, "2016-2020", 循环经济!G:G, "新目标") + COUNTIFS(循环经济!F:F, "2016-2020", 循环经济!G:G, "强化或放宽目标（气候影响不明确）") + COUNTIFS(循环经济!F:F, "2016-2020", 循环经济!G:G, "强化或放宽目标（积极气候影响）") + COUNTIFS(循环经济!F:F, "2016-2020", 循环经济!G:G, "强化或放宽目标（消极气候影响）") + COUNTIFS(金融!F:F, "2016-2020", 金融!G:G, "新目标") + COUNTIFS(金融!F:F, "2016-2020", 金融!G:G, "强化或放宽目标（气候影响不明确）") + COUNTIFS(金融!F:F, "2016-2020", 金融!G:G, "强化或放宽目标（积极气候影响）") + COUNTIFS(金融!F:F, "2016-2020", 金融!G:G, "强化或放宽目标（消极气候影响）")
N40: 2016-2030 | O40: =COUNTIFS(温室气体排放!F:F, "2016-2030", 温室气体排放!G:G, "新目标") + COUNTIFS(温室气体排放!F:F, "2016-2030", 温室气体排放!G:G, "强化或放宽目标（气候影响不明确）") + COUNTIFS(温室气体排放!F:F, "2016-2030", 温室气体排放!G:G, "强化或放宽目标（积极气候影响）") + COUNTIFS(温室气体排放!F:F, "2016-2030", 温室气体排放!G:G, "强化或放宽目标（消极气候影响）") + COUNTIFS(污染!F:F, "2016-2030", 污染!G:G, "新目标") + COUNTIFS(污染!F:F, "2016-2030", 污染!G:G, "强化或放宽目标（气候影响不明确）") + COUNTIFS(污染!F:F, "2016-2030", 污染!G:G, "强化或放宽目标（积极气候影响）") + COUNTIFS(污染!F:F, "2016-2030", 污染!G:G, "强化或放宽目标（消极气候影响）") + COUNTIFS('能源|电力'!F:F, "2016-2030", '能源|电力'!G:G, "新目标") + COUNTIFS('能源|电力'!F:F, "2016-2030", '能源|电力'!G:G, "强化或放宽目标（气候影响不明确）") + COUNTIFS('能源|电力'!F:F, "2016-2030", '能源|电力'!G:G, "强化或放宽目标（积极气候影响）") + COUNTIFS('能源|电力'!F:F, "2016-2030", '能源|电力'!G:G, "强化或放宽目标（消极气候影响）") + COUNTIFS(工业!F:F, "2016-2030", 工业!G:G, "新目标") + COUNTIFS(工业!F:F, "2016-2030", 工业!G:G, "强化或放宽目标（气候影响不明确）") + COUNTIFS(工业!F:F, "2016-2030", 工业!G:G, "强化或放宽目标（积极气候影响）") + COUNTIFS(工业!F:F, "2016-2030", 工业!G:G, "强化或放宽目标（消极气候影响）") + COUNTIFS(建筑!F:F, "2016-2030", 建筑!G:G, "新目标") + COUNTIFS(建筑!F:F, "2016-2030", 建筑!G:G, "强化或放宽目标（气候影响不明确）") + COUNTIFS(建筑!F:F, "2016-2030", 建筑!G:G, "强化或放宽目标（积极气候影响）") + COUNTIFS(建筑!F:F, "2016-2030", 建筑!G:G, "强化或放宽目标（消极气候影响）") + COUNTIFS(交通!F:F, "2016-2030", 交通!G:G, "新目标") + COUNTIFS(交通!F:F, "2016-2030", 交通!G:G, "强化或放宽目标（气候影响不明确）") + COUNTIFS(交通!F:F, "2016-2030", 交通!G:G, "强化或放宽目标（积极气候影响）") + COUNTIFS(交通!F:F, "2016-2030", 交通!G:G, "强化或放宽目标（消极气候影响）") + COUNTIFS('土地利用、土地利用变化和林业'!F:F, "2016-2030", '土地利用、土地利用变化和林业'!G:G, "新目标") + COUNTIFS('土地利用、土地利用变化和林业'!F:F, "2016-2030", '土地利用、土地利用变化和林业'!G:G, "强化或放宽目标（气候影响不明确）") + COUNTIFS('土地利用、土地利用变化和林业'!F:F, "2016-2030", '土地利用、土地利用变化和林业'!G:G, "强化或放宽目标（积极气候影响）") + COUNTIFS('土地利用、土地利用变化和林业'!F:F, "2016-2030", '土地利用、土地利用变化和林业'!G:G, "强化或放宽目标（消极气候影响）") + COUNTIFS(循环经济!F:F, "2016-2030", 循环经济!G:G, "新目标") + COUNTIFS(循环经济!F:F, "2016-2030", 循环经济!G:G, "强化或放宽目标（气候影响不明确）") + COUNTIFS(循环经济!F:F, "2016-2030", 循环经济!G:G, "强化或放宽目标（积极气候影响）") + COUNTIFS(循环经济!F:F, "2016-2030", 循环经济!G:G, "强化或放宽目标（消极气候影响）") + COUNTIFS(金融!F:F, "2016-2030", 金融!G:G, "新目标") + COUNTIFS(金融!F:F, "2016-2030", 金融!G:G, "强化或放宽目标（气候影响不明确）") + COUNTIFS(金融!F:F, "2016-2030", 金融!G:G, "强化或放宽目标（积极气候影响）") + COUNTIFS(金融!F:F, "2016-2030", 金融!G:G, "强化或放宽目标（消极气候影响）")
N41: 2021-2030 | O41: =COUNTIFS(温室气体排放!F:F, "2021-2030", 温室气体排放!G:G, "新目标") + COUNTIFS(温室气体排放!F:F, "2021-2030", 温室气体排放!G:G, "强化或放宽目标（气候影响不明确）") + COUNTIFS(温室气体排放!F:F, "2021-2030", 温室气体排放!G:G, "强化或放宽目标（积极气候影响）") + COUNTIFS(温室气体排放!F:F, "2021-2030", 温室气体排放!G:G, "强化或放宽目标（消极气候影响）") + COUNTIFS(污染!F:F, "2021-2030", 污染!G:G, "新目标") + COUNTIFS(污染!F:F, "2021-2030", 污染!G:G, "强化或放宽目标（气候影响不明确）") + COUNTIFS(污染!F:F, "2021-2030", 污染!G:G, "强化或放宽目标（积极气候影响）") + COUNTIFS(污染!F:F, "2021-2030", 污染!G:G, "强化或放宽目标（消极气候影响）") + COUNTIFS('能源|电力'!F:F, "2021-2030", '能源|电力'!G:G, "新目标") + COUNTIFS('能源|电力'!F:F, "2021-2030", '能源|电力'!G:G, "强化或放宽目标（气候影响不明确）") + COUNTIFS('能源|电力'!F:F, "2021-2030", '能源|电力'!G:G, "强化或放宽目标（积极气候影响）") + COUNTIFS('能源|电力'!F:F, "2021-2030", '能源|电力'!G:G, "强化或放宽目标（消极气候影响）") + COUNTIFS(工业!F:F, "2021-2030", 工业!G:G, "新目标") + COUNTIFS(工业!F:F, "2021-2030", 工业!G:G, "强化或放宽目标（气候影响不明确）") + COUNTIFS(工业!F:F, "2021-2030", 工业!G:G, "强化或放宽目标（积极气候影响）") + COUNTIFS(工业!F:F, "2021-2030", 工业!G:G, "强化或放宽目标（消极气候影响）") + COUNTIFS(建筑!F:F, "2021-2030", 建筑!G:G, "新目标") + COUNTIFS(建筑!F:F, "2021-2030", 建筑!G:G, "强化或放宽目标（气候影响不明确）") + COUNTIFS(建筑!F:F, "2021-2030", 建筑!G:G, "强化或放宽目标（积极气候影响）") + COUNTIFS(建筑!F:F, "2021-2030", 建筑!G:G, "强化或放宽目标（消极气候影响）") + COUNTIFS(交通!F:F, "2021-2030", 交通!G:G, "新目标") + COUNTIFS(交通!F:F, "2021-2030", 交通!G:G, "强化或放宽目标（气候影响不明确）") + COUNTIFS(交通!F:F, "2021-2030", 交通!G:G, "强化或放宽目标（积极气候影响）") + COUNTIFS(交通!F:F, "2021-2030", 交通!G:G, "强化或放宽目标（消极气候影响）") + COUNTIFS('土地利用、土地利用变化和林业'!F:F, "2021-2030", '土地利用、土地利用变化和林业'!G:G, "新目标") + COUNTIFS('土地利用、土地利用变化和林业'!F:F, "2021-2030", '土地利用、土地利用变化和林业'!G:G, "强化或放宽目标（气候影响不明确）") + COUNTIFS('土地利用、土地利用变化和林业'!F:F, "2021-2030", '土地利用、土地利用变化和林业'!G:G, "强化或放宽目标（积极气候影响）") + COUNTIFS('土地利用、土地利用变化和林业'!F:F, "2021-2030", '土地利用、土地利用变化和林业'!G:G, "强化或放宽目标（消极气候影响）") + COUNTIFS(循环经济!F:F, "2021-2030", 循环经济!G:G, "新目标") + COUNTIFS(循环经济!F:F, "2021-2030", 循环经济!G:G, "强化或放宽目标（气候影响不明确）") + COUNTIFS(循环经济!F:F, "2021-2030", 循环经济!G:G, "强化或放宽目标（积极气候影响）") + COUNTIFS(循环经济!F:F, "2021-2030", 循环经济!G:G, "强化或放宽目标（消极气候影响）") + COUNTIFS(金融!F:F, "2021-2030", 金融!G:G, "新目标") + COUNTIFS(金融!F:F, "2021-2030", 金融!G:G, "强化或放宽目标（气候影响不明确）") + COUNTIFS(金融!F:F, "2021-2030", 金融!G:G, "强化或放宽目标（积极气候影响）") + COUNTIFS(金融!F:F, "2021-2030", 金融!G:G, "强化或放宽目标（消极气候影响）")
N42: 2021-2060 | O42: =COUNTIFS(温室气体排放!F:F, "2021-2060", 温室气体排放!G:G, "新目标") + COUNTIFS(温室气体排放!F:F, "2021-2060", 温室气体排放!G:G, "强化或放宽目标（气候影响不明确）") + COUNTIFS(温室气体排放!F:F, "2021-2060", 温室气体排放!G:G, "强化或放宽目标（积极气候影响）") + COUNTIFS(温室气体排放!F:F, "2021-2060", 温室气体排放!G:G, "强化或放宽目标（消极气候影响）") + COUNTIFS(污染!F:F, "2021-2060", 污染!G:G, "新目标") + COUNTIFS(污染!F:F, "2021-2060", 污染!G:G, "强化或放宽目标（气候影响不明确）") + COUNTIFS(污染!F:F, "2021-2060", 污染!G:G, "强化或放宽目标（积极气候影响）") + COUNTIFS(污染!F:F, "2021-2060", 污染!G:G, "强化或放宽目标（消极气候影响）") + COUNTIFS('能源|电力'!F:F, "2021-2060", '能源|电力'!G:G, "新目标") + COUNTIFS('能源|电力'!F:F, "2021-2060", '能源|电力'!G:G, "强化或放宽目标（气候影响不明确）") + COUNTIFS('能源|电力'!F:F, "2021-2060", '能源|电力'!G:G, "强化或放宽目标（积极气候影响）") + COUNTIFS('能源|电力'!F:F, "2021-2060", '能源|电力'!G:G, "强化或放宽目标（消极气候影响）") + COUNTIFS(工业!F:F, "2021-2060", 工业!G:G, "新目标") + COUNTIFS(工业!F:F, "2021-2060", 工业!G:G, "强化或放宽目标（气候影响不明确）") + COUNTIFS(工业!F:F, "2021-2060", 工业!G:G, "强化或放宽目标（积极气候影响）") + COUNTIFS(工业!F:F, "2021-2060", 工业!G:G, "强化或放宽目标（消极气候影响）") + COUNTIFS(建筑!F:F, "2021-2060", 建筑!G:G, "新目标") + COUNTIFS(建筑!F:F, "2021-2060", 建筑!G:G, "强化或放宽目标（气候影响不明确）") + COUNTIFS(建筑!F:F, "2021-2060", 建筑!G:G, "强化或放宽目标（积极气候影响）") + COUNTIFS(建筑!F:F, "2021-2060", 建筑!G:G, "强化或放宽目标（消极气候影响）") + COUNTIFS(交通!F:F, "2021-2060", 交通!G:G, "新目标") + COUNTIFS(交通!F:F, "2021-2060", 交通!G:G, "强化或放宽目标（气候影响不明确）") + COUNTIFS(交通!F:F, "2021-2060", 交通!G:G, "强化或放宽目标（积极气候影响）") + COUNTIFS(交通!F:F, "2021-2060", 交通!G:G, "强化或放宽目标（消极气候影响）") + COUNTIFS('土地利用、土地利用变化和林业'!F:F, "2021-2060", '土地利用、土地利用变化和林业'!G:G, "新目标") + COUNTIFS('土地利用、土地利用变化和林业'!F:F, "2021-2060", '土地利用、土地利用变化和林业'!G:G, "强化或放宽目标（气候影响不明确）") + COUNTIFS('土地利用、土地利用变化和林业'!F:F, "2021-2060", '土地利用、土地利用变化和林业'!G:G, "强化或放宽目标（积极气候影响）") + COUNTIFS('土地利用、土地利用变化和林业'!F:F, "2021-2060", '土地利用、土地利用变化和林业'!G:G, "强化或放宽目标（消极气候影响）") + COUNTIFS(循环经济!F:F, "2021-2060", 循环经济!G:G, "新目标") + COUNTIFS(循环经济!F:F, "2021-2060", 循环经济!G:G, "强化或放宽目标（气候影响不明确）") + COUNTIFS(循环经济!F:F, "2021-2060", 循环经济!G:G, "强化或放宽目标（积极气候影响）") + COUNTIFS(循环经济!F:F, "2021-2060", 循环经济!G:G, "强化或放宽目标（消极气候影响）") + COUNTIFS(金融!F:F, "2021-2060", 金融!G:G, "新目标") + COUNTIFS(金融!F:F, "2021-2060", 金融!G:G, "强化或放宽目标（气候影响不明确）") + COUNTIFS(金融!F:F, "2021-2060", 金融!G:G, "强化或放宽目标（积极气候影响）") + COUNTIFS(金融!F:F, "2021-2060", 金融!G:G, "强化或放宽目标（消极气候影响）")
N44: 2010年合计 | O44: =O8+O9+O35
N45: 2015年合计 | O45: =O12+O13+O37
N46: 2020年合计 | O46: =O18+O19+O34+O36+O39
N47: 2025年合计 | O47: =O24+O25
N48: 2030年合计 | O48: =O30+O31+O40+O41

Sheet 温室气体排放
A1: 公布年份 | B1: 指标 | C1: 方向 | D1: 目标值 | E1: 基线 | F1: 目标年份/时期 | G1: 计数 | H1: 目标类别 | I1: 责任主体 | J1: 政策原文 | K1: 文件 | L1: 主题标签
A2: 2024 | B2: 重点领域和行业年度温室气体减排量 | C2: 实现 | D2: 1.3亿吨 | F2: 2024 | G2: 新目标 | H2: 碳减排 | I2: 地区 | J2: 重点领域和行业节能降碳改造形成减排二氧化碳约1.3亿吨 | K2: AP2405.htm | L2: 温室气体排放
A3: 2024 | B3: 重点领域和行业节能降碳改造形成的温室气体年减排量 | C3: 实现 | D3: 1.3亿吨 | F3: 2025 | G3: 新目标 | H3: 碳减排 | I3: 地区 | J3: 到2025年，非化石能源消费占比达到20%左右，重点领域和行业节能降碳改造形成节能量约5000万吨标准煤、减排二氧化碳约1.3亿吨。 | K3: AP2405.htm | L3: 温室气体排放
A4: 2026 | B4: 重点行业节能降碳改造形成的二氧化碳减排量 | C4: 实现 | D4: 2亿吨以上 | F4: 2028 | G4: 新目标 | H4: 碳减排 | I4: 全社会经济 | J4: ……累计形成节能量 1 亿吨标准煤以上、减排二氧化碳 2 亿吨以上。 | K4: AP2607.htm | L4: 温室气体排放
A5: 2026 | B5: 国际航行船舶二氧化碳排放强度 | C5: 降低 | D5: 超过15% | E5: 2025 | F5: 2030 | G5: 新目标 | H5: 碳强度 | I5: 行业 | J5: 到2030年，国际航行船舶碳排放强度相比2025年下降超过15%。 | K5: O2602.htm | L5: 温室气体排放
A6: 2020 | B6: 二氧化碳排放碳中和 | C6: 实现 | F6: 2060年前 | G6: 重申目标 | H6: 碳减排 | I6: 全社会经济 | J6: 2020年9月21日，习近平主席在第七十六届联合国大会一般性辩论上宣布，中国将力争于2030年前实现碳达峰、2060年前实现碳中和。 | K6: HL2105.pdf | L6: 温室气体排放
A7: 2020 | B7: 二氧化碳排放碳中和 | C7: 实现 | F7: 2060年前 | G7: 新目标 | H7: 碳减排 | I7: 全社会经济 | J7: 2020年9月22日，习近平主席在第七十五届联合国大会一般性辩论上宣布，中国将提高国家自主贡献力度，采取更加有力的政策和措施，力争于2030年前二氧化碳排放达到峰值，努力争取于2060年前实现碳中和。 | K7: GO2102.htm | L7: 温室气体排放
A8: 2016 | B8: 大型发电集团单位供电二氧化碳排放 | C8: 控制在…以内 | D8: 550克二氧化碳/千瓦时 | F8: 2020 | G8: 新目标 | H8: 碳强度 | I8: 不明确 | J8: 到2020年，大型发电集团单位供电二氧化碳排放控制在550克二氧化碳/千瓦时以内。 | K8: FYP1615.htm | L8: 温室气体排放
A9: 2015 | B9: 二氧化碳排放达峰 | C9: 实现 | F9: 2030年左右 | G9: 新目标 | H9: 碳减排 | I9: 全社会经济 | J9: 二氧化碳排放2030年左右达到峰值并争取尽早达峰 | K9: HL1601.pdf | L9: 温室气体排放
A10: 2020 | B10: 二氧化碳排放达峰 | C10: 实现 | F10: 2030年前 | G10: 强化或放宽目标（积极气候影响） | H10: 碳减排 | I10: 全社会经济 | J10: 习近平总书记在第七十五届联合国大会一般性辩论上宣布我国力争于2030年前二氧化碳排放达到峰值的目标与努力争取于2060年前实现碳中和的愿景，并在气候雄心峰会上进一步宣布国家自主贡献最新举措。 | K10: GO2102.htm | L10: 温室气体排放
A11: 2022 | B11: 建材行业二氧化碳排放达峰 | C11: 实现 | F11: 2030年前 | G11: 新目标 | H11: 碳减排 | I11: 行业 | J11: 确保2030年前建材行业实现碳达峰 | K11: IP2220.htm | L11: 温室气体排放
A12: 2022 | B12: 工业领域二氧化碳排放达峰 | C12: 实现 | D12: 2030年前 | F12: 2030年前 | G12: 新目标 | H12: 碳减排 | I12: 行业 | J12: 确保工业领域二氧化碳排放在2030年前达峰 | K12: IP2206.pdf | L12: 温室气体排放
A13: 2022 | B13: 有色金属行业二氧化碳排放达峰 | C13: 实现 | F13: 2030年前 | G13: 新目标 | H13: 碳减排 | I13: 行业 | J13: 确保2030年前有色金属行业实现碳达峰 | K13: IP2221.htm | L13: 温室气体排放
A14: 2022 | B14: 钢铁行业二氧化碳排放达峰 | C14: 实现 | F14: 2030年前 | G14: 新目标 | H14: 碳减排 | I14: 行业 | J14: 确保2030年前钢铁行业实现碳达峰 | K14: GO2204.htm | L14: 温室气体排放
A15: 2024 | B15: 煤电低碳化改造建设项目的单位供电二氧化碳排放量 | C15: 降低 | D15: 约20% | E15: 2023 | F15: 2025 | G15: 新目标 | H15: 碳强度 | I15: 企业 | J15: 到2025年，相关煤电低碳化改造建设项目的单位供电碳排放量较2023年同类煤电机组平均碳排放水平降低约20%。 | K15: AP2406.pdf | L15: 温室气体排放
A16: 2024 | B16: 煤电低碳化改造建设项目单位千瓦时二氧化碳排放量 | C16: 降低 | D16: 约50% | E16: 2023 | F16: 2027 | G16: 新目标 | H16: 碳强度 | I16: 企业 | J16: 到2027年，相关煤电低碳化改造建设项目单位千瓦时二氧化碳排放量较2023年同类煤电机组平均碳排放水平降低约50% | K16: AP2406.pdf | L16: 温室气体排放
A17: 2010 | B17: 单位国内生产总值二氧化碳排放量 | C17: 降低 | D17: 40%-45% | E17: 2005 | F17: 2020 | G17: 重申目标 | H17: 碳强度 | I17: 全社会经济 | J17: 到2020年，中国政府将实现单位国内生产总值二氧化碳排放比2005年下降40%至45%。 | K17: N1001.htm | L17: 温室气体排放
A18: 2011 | B18: 单位国内生产总值二氧化碳排放 | C18: 降低 | D18: 40%-45% | E18: 2005 | F18: 2020 | G18: 重申目标 | H18: 碳强度 | I18: 全社会经济 | J18: 对此，党中央、国务院明确提出要大力发展绿色经济，积极发展低碳经济和循环经济，将应对气候变化纳入经济社会发展规划，并向世界郑重承诺到2020年单位国内生产总值二氧化碳排放比2005年下降40%～45%的减排目标。 | K18: FYP1102.htm | L18: 温室气体排放
A19: 2011 | B19: 单位国内生产总值二氧化碳排放 | C19: 降低 | D19: 17% | E19: 2010 | F19: 2015 | G19: 重申目标 | H19: 碳强度 | I19: 全社会经济 | J19: 要围绕到2015年全国单位国内生产总值二氧化碳排放比2010年下降17%的目标，大力开展节能降耗，优化能源结构，努力增加碳汇，加快形成以低碳为特征的产业体系和生活方式。 | K19: FYP1101.htm | L19: 温室气体排放
A20: 2012 | B20: 单位国内生产总值二氧化碳排放量 | C20: 降低 | D20: 40%-45% | E20: 2005 | F20: 2020 | G20: 重申目标 | H20: 碳强度 | I20: 全社会经济 | J20: 中国政府宣布，到2020年，单位国内生产总值二氧化碳排放量将比2005年下降40%-45%。 | K20: HL1201.pdf | L20: 温室气体排放
A21: 2012 | B21: 单位国内生产总值二氧化碳排放 | C21: 降低 | D21: 17% | F21: 十二五 | G21: 重申目标 | H21: 碳强度 | I21: 全社会经济 | J21: “十二五”规划纲要明确将单位国内生产总值二氧化碳排放降低17%作为约束性指标。 | K21: HL1201.pdf | L21: 温室气体排放
A22: 2012 | B22: 单位国内生产总值二氧化碳排放量 | C22: 降低 | D22: 17% | F22: 十二五 | G22: 重申目标 | H22: 碳强度 | I22: 全社会经济 | J22: 中华人民共和国国民经济和社会发展第十二个五年规划纲要首次将单位国内生产总值二氧化碳排放降低17%作为约束性指标。 | K22: HL1201.pdf | L22: 温室气体排放
A23: 2012 | B23: 单位国内生产总值二氧化碳排放 | C23: 降低 | D23: 40%-45% | E23: 2005 | F23: 2020 | G23: 重申目标 | H23: 碳强度 | I23: 全社会经济 | J23: 中国单位国内生产总值二氧化碳排放到2020年将比2005年下降40%-45%，并将其作为约束性指标纳入国民经济和社会发展中长期规划，并制定相应的国内统计、监测、考核办法加以落实。 | K23: HL1201.pdf | L23: 温室气体排放
A24: 2012 | B24: 单位国内生产总值二氧化碳排放 | C24: 降低 | D24: 40%-45% | E24: 2005 | F24: 2020 | G24: 重申目标 | H24: 碳强度 | I24: 全社会经济 | J24: 中国政府承诺，到2020年单位国内生产总值二氧化碳排放比2005年下降40%—45%。 | K24: WP1201.htm | L24: 温室气体排放
A25: 2013 | B25: 单位国内生产总值二氧化碳排放 | C25: 降低 | D25: 17% | F25: 2015 | G25: 重申目标 | H25: 碳强度 | I25: 全社会经济 | J25: 到2015年，单位国内生产总值二氧化碳排放比2010年下降17%。 | K25: FYP1302.htm | L25: 温室气体排放
A26: 2016 | B26: 单位国内生产总值二氧化碳排放 | C26: 降低 | D26: 18% | F26: 2020 | G26: 重申目标 | H26: 碳强度 | I26: 全社会经济 | J26: 到2020年，单位国内生产总值二氧化碳排放比2015年下降18%，碳排放总量得到有效控制。 | K26: FYP1615.htm | L26: 温室气体排放
A27: 2016 | B27: 单位国内生产总值二氧化碳排放量 | C27: 降低 | D27: 3.9%以上 | E27: 2015 | F27: 2016 | G27: 新目标 | H27: 碳强度 | I27: 全社会经济 | J27: 单位国内生产总值能耗和二氧化碳排放量分别下降3.4%以上、3.9%以上 | K27: HL1604.htm | L27: 温室气体排放
A28: 2017 | B28: 单位国内生产总值二氧化碳排放量 | C28: 降低 | D28: 40%-45% | E28: 2005 | F28: 2020 | G28: 重申目标 | H28: 碳强度 | I28: 全社会经济 | J28: 从国家层面看，为实现我国到2020年碳强度降低40%－45%的约束性目标以及2030年左右二氧化碳排放达到峰值、且将努力早日达峰的目标，国家生态文明制度体系建设将迈向新高度，环境保护与节能减排领域的硬约束将不断强化。 | K28: FYP1702.pdf | L28: 温室气体排放
A29: 2017 | B29: 单位国内生产总值二氧化碳排放 | C29: 降低 | D29: 40%-45% | E29: 2005 | F29: 十二五 | G29: 重申目标 | H29: 碳强度 | I29: 全社会经济 | J29: 根据中国政府提出的国家适当减缓行动，例如“十二五”期间单位国内生产总值二氧化碳排放比2005年下降40%-45% | K29: HL1701.pdf | L29: 温室气体排放
A30: 2019 | B30: 单位国内生产总值二氧化碳排放量 | C30: 降低 | D30: 18% | E30: 2015 | F30: 2020 | G30: 重申目标 | H30: 碳强度 | I30: 全社会经济 | J30: 进一步强调中国确定的减缓行动，明确提出有效控制碳排放，到2020年碳强度比2015年下降18%；加大力度控制二氧化碳以外的温室气体排放，包括氢氟碳化物、甲烷、氧化亚氮、全氟化碳和六氟化硫；大幅提升碳汇能力。 | K30: HL1901.pdf | L30: 温室气体排放
A31: 2019 | B31: 单位国内生产总值二氧化碳排放量 | C31: 降低 | D31: 40%-45% | E31: 2005 | F31: 2020 | G31: 重申目标 | H31: 碳强度 | I31: 全社会经济 | J31: 到2020年，单位国内生产总值二氧化碳排放量（以下简称碳强度）将比2005年降低40%至45% | K31: HL1902.pdf | L31: 温室气体排放
A32: 2019 | B32: 单位国内生产总值二氧化碳排放量 | C32: 降低 | D32: 60%-65% | E32: 2005 | F32: 2030 | G32: 重申目标 | H32: 碳强度 | I32: 全社会经济 | J32: 到2030年，单位国内生产总值二氧化碳排放量将比2005年下降60%至65% | K32: HL1902.pdf | L32: 温室气体排放
A33: 2019 | B33: 单位国内生产总值二氧化碳排放 | C33: 降低 | D33: 18% | E33: 2015 | F33: 2020 | G33: 重申目标 | H33: 碳强度 | I33: 全社会经济 | J33: 到2020年，单位国内生产总值二氧化碳排放比2015年下降18% | K33: HL1902.pdf | L33: 温室气体排放
A34: 2021 | B34: 单位国内生产总值二氧化碳排放 | C34: 降低 | D34: 60%-65% | E34: 2005 | F34: 2030 | G34: 重申目标 | H34: 碳强度 | I34: 全社会经济 | J34: 目标包括：到2030年，单位国内生产总值二氧化碳排放比2005年下降60%至65%。 | K34: HL2105.pdf | L34: 温室气体排放
A35: 2021 | B35: 单位国内生产总值二氧化碳排放 | C35: 降低 | D35: 65%以上 | E35: 2005 | F35: 2030 | G35: 重申目标 | H35: 碳强度 | I35: 全社会经济 | J35: 中国更新后的国家自主贡献目标如下：到2030年，单位国内生产总值二氧化碳排放将比2005年下降65%以上。 | K35: HL2105.pdf | L35: 温室气体排放
A36: 2021 | B36: 单位国内生产总值二氧化碳排放量（碳强度） | C36: 降低 | D36: 18% | E36: 2020 | F36: 2025 | G36: 重申目标 | H36: 碳强度 | I36: 全社会经济 | J36: “十四五”时期（2021-2025年）单位国内生产总值二氧化碳排放降低18%的约束性指标 | K36: HL2107.pdf | L36: 温室气体排放
A37: 2021 | B37: 单位国内生产总值二氧化碳排放量 | C37: 降低 | D37: 超过65% | E37: 2005 | F37: 2030 | G37: 重申目标 | H37: 碳强度 | I37: 全社会经济 | J37: 中国力争在2030年前实现单位国内生产总值二氧化碳排放量较2005年下降超过65%的目标。 | K37: HL2107.htm | L37: 温室气体排放
A38: 2021 | B38: 单位国内生产总值二氧化碳排放 | C38: 降低 | D38: 18% | E38: 2020 | F38: 2025 | G38: 重申目标 | H38: 碳强度 | I38: 全社会经济 | J38: 到2025年，单位国内生产总值二氧化碳排放比2020年下降18%。 | K38: HL2101.htm | L38: 温室气体排放
A39: 2021 | B39: 单位国内生产总值二氧化碳排放 | C39: 降低 | D39: 65%以上 | E39: 2005 | F39: 2030 | G39: 重申目标 | H39: 碳强度 | I39: 全社会经济 | J39: 到2030年，单位国内生产总值二氧化碳排放比2005年下降65%以上。 | K39: HL2101.htm | L39: 温室气体排放
A40: 2021 | B40: 单位国内生产总值二氧化碳排放量 | C40: 降低 | D40: 18% | E40: 2020 | F40: 2025 | G40: 重申目标 | H40: 碳强度 | I40: 全社会经济 | J40: 到2025年，单位国内生产总值二氧化碳排放较2020年下降18% | K40: HL2102.pdf | L40: 温室气体排放
A41: 2021 | B41: 单位国内生产总值二氧化碳排放 | C41: 降低 | D41: 65%以上 | E41: 2005 | F41: 2030 | G41: 重申目标 | H41: 碳强度 | I41: 全社会经济 | J41: 到2030年，单位国内生产总值二氧化碳排放比2005年下降65%以上，顺利实现2030年前碳达峰目标。 | K41: HL2102.pdf | L41: 温室气体排放
A42: 2015 | B42: 单位国内生产总值二氧化碳排放强度 | C42: 降低 | D42: 40%-45% | E42: 2005 | F42: 2020 | G42: 重申目标 | H42: 碳强度 | I42: 全社会经济 | J42: 到2020年，单位国内生产总值二氧化碳排放强度比2005年下降40%－45% | K42: HL1503.htm | L42: 温室气体排放
A43: 2014 | B43: 单位国内生产总值二氧化碳排放量 | C43: 降低 | D43: 4% | E43: 2013 | F43: 2014 | G43: 新目标 | H43: 碳强度 | I43: 全社会经济 | J43: 2014-2015年，单位GDP二氧化碳排放量两年分别下降4%、3.5%以上。 | K43: AP1404.htm | L43: 温室气体排放
A44: 2011 | B44: 单位国内生产总值二氧化碳排放 | C44: 降低 | D44: 17% | E44: 2010 | F44: 2015 | G44: 新目标 | H44: 碳强度 | I44: 全社会经济 | J44: 到2015年，单位国内生产总值二氧化碳排放比2010年下降17%，单位国内生产总值能耗比2010年下降16%。 | K44: HL1101.pdf | L44: 温室气体排放
A45: 2015 | B45: 单位国内生产总值二氧化碳排放量 | C45: 降低 | D45: 3.1%以上 | E45: 2014 | F45: 2015 | G45: 强化或放宽目标（消极气候影响） | H45: 碳强度 | I45: 全社会经济 | J45: 单位国内生产总值二氧化碳排放降低3.1%以上。 | K45: HL1506.pdf | L45: 温室气体排放
A46: 2014 | B46: 单位国内生产总值二氧化碳排放量 | C46: 降低 | D46: 3.5% | E46: 2014 | F46: 2015 | G46: 新目标 | H46: 碳强度 | I46: 全社会经济 | J46: 2014-2015年，单位GDP能耗、化学需氧量、二氧化硫、氨氮、氮氧化物排放量分别逐年下降3.9%、2%、2%、2%、5%以上，单位GDP二氧化碳排放量两年分别下降4%、3.5%以上。 | K46: AP1404.htm | L46: 温室气体排放
A47: 2009 | B47: 单位国内生产总值二氧化碳排放量 | C47: 降低 | D47: 40%-45% | E47: 2005 | F47: 2020 | G47: 新目标 | H47: 碳强度 | I47: 全社会经济 | J47: 中国于2009年提出，作为其适合本国的减缓行动，到2020年，在2005年水平基础上，将单位国内生产总值二氧化碳排放量降低40%至45%。 | K47: HL2401.pdf | L47: 温室气体排放
A48: 2016 | B48: 单位国内生产总值二氧化碳排放 | C48: 降低 | D48: 18% | E48: 2015 | F48: 2020 | G48: 新目标 | H48: 碳强度 | I48: 全社会经济 | J48: 2016年，中国提出到2020年，单位国内生产总值二氧化碳排放比2015年下降18%的目标。 | K48: HL2302.pdf | L48: 温室气体排放
A49: 2024 | B49: 单位国内生产总值二氧化碳排放 | C49: 降低 | D49: 3.9% | E49: 2023 | F49: 2024 | G49: 新目标 | H49: 碳强度 | I49: 全社会经济 | J49: 到2024年，单位国内生产总值能源消耗和二氧化碳排放分别降低2.5%左右、3.9%左右，规模以上工业单位增加值能源消耗降低3.5%左右 | K49: AP2405.htm | L49: 温室气体排放
A50: 2021 | B50: 单位国内生产总值二氧化碳排放 | C50: 降低 | D50: 18% | E50: 2020 | F50: 2025 | G50: 新目标 | H50: 碳强度 | I50: 全社会经济 | J50: 值得注意的是，文件设定了量化目标，即到2025年，单位国内生产总值二氧化碳排放比2020年降低18%。 | K50: HL2401.pdf | L50: 温室气体排放
A51: 2021 | B51: 单位国内生产总值二氧化碳排放 | C51: 降低 | D51: 65%以上 | E51: 2005 | F51: 2030 | G51: 强化或放宽目标（积极气候影响） | H51: 碳强度 | I51: 全社会经济 | J51: 到2030年，中国单位国内生产总值二氧化碳排放将比2005年下降65%以上。 | K51: HL2105.pdf | L51: 温室气体排放
A52: 2015 | B52: 单位国内生产总值二氧化碳排放 | C52: 降低 | D52: 60%-65% | E52: 2005 | F52: 2030 | G52: 新目标 | H52: 碳强度 | I52: 全社会经济 | J52: 到2030年，单位国内生产总值二氧化碳排放比2005年下降60%－65% | K52: HL1601.pdf | L52: 温室气体排放
A53: 2011 | B53: 单位国内生产总值二氧化碳排放 | C53: 降低 | D53: 17% | E53: 2010 | F53: 2015 | G53: 重申目标 | H53: 碳强度 | I53: 全社会经济 | J53: 国家“十二五”规划纲要提出，到2015年，单位国内生产总值二氧化碳排放比2010年降低17%。 | K53: FYP1102.htm | L53: 温室气体排放
A54: 2026 | B54: 单位国内生产总值二氧化碳排放 | C54: 降低 | D54: 3.8%左右 | E54: 2025 | F54: 2026 | G54: 新目标 | H54: 碳强度 | I54: 全社会经济 | J54: 单位国内生产总值二氧化碳排放降低3.8%左右 | K54: HL2602.htm | L54: 温室气体排放
A55: 2026 | B55: 单位国内生产总值二氧化碳排放 | C55: 降低 | D55: 17% | F55: 十五五 | G55: 新目标 | H55: 碳强度 | I55: 全社会经济 | J55: “十五五”时期，单位国内生产总值二氧化碳排放降低17%。 | K55: HL2601.pdf | L55: 温室气体排放
A56: 2019 | B56: 单位国内生产总值二氧化碳排放量 | C56: 降低 | D56: 约3.6% | E56: 2018 | F56: 2019 | G56: 新目标 | H56: 碳强度 | I56: 全社会经济 | J56: 单位国内生产总值二氧化碳排放量降低百分之三点六 | K56: HL2003.pdf | L56: 温室气体排放
A57: 2011 | B57: 单位国内生产总值二氧化碳排放量 | C57: 降低 | D57: 3.5%左右 | E57: 2010 | F57: 2011 | G57: 新目标 | H57: 碳强度 | I57: 全社会经济 | J57: 二氧化碳排放强度下降3.5%左右。 | K57: HL1103.htm | L57: 温室气体排放
A58: 2012 | B58: 单位国内生产总值二氧化碳排放量 | C58: 降低 | D58: 超过3.5% | E58: 2011 | F58: 2012 | G58: 新目标 | H58: 碳强度 | I58: 全社会经济 | J58: 单位国内生产总值能耗下降约3.5%，二氧化碳排放强度降幅更大一些 | K58: HL1204.htm | L58: 温室气体排放
A59: 2018 | B59: 单位国内生产总值二氧化碳排放量 | C59: 降低 | D59: 3.9% | E59: 2017 | F59: 2018 | G59: 新目标 | H59: 碳强度 | I59: 全社会经济 | J59: 单位国内生产总值二氧化碳排放量降低3.9% | K59: HL1803.htm | L59: 温室气体排放
A60: 2026 | B60: 单位国内生产总值二氧化碳排放 | C60: 降低 | D60: 17% | E60: 2025 | F60: 2030 | G60: 新目标 | H60: 碳强度 | I60: 全社会经济 | J60: 到2030年，我国单位国内生产总值二氧化碳排放比2025年降低17%，非化石能源消费占比达到25%，确保如期实现碳达峰目标，…… | K60: HL2604.htm | L60: 温室气体排放
A61: 2026 | B61: 单位国内生产总值二氧化碳排放 | C61: 降低 | D61: 17% | E61: 2025 | F61: 2030 | G61: 重申目标 | H61: 碳强度 | I61: 全社会经济 | J61: 到 2030 年，单位国内生产总值二氧化碳排放较 2025 年降低 17%，…… | K61: HL2603.pdf | L61: 温室气体排放
A62: 2016 | B62: 单位工业增加值二氧化碳排放量 | C62: 降低 | D62: 22% | E62: 2015 | F62: 2020 | G62: 新目标 | H62: 碳强度 | I62: 行业 | J62: 2020年单位工业增加值二氧化碳排放量比2015年下降22%，工业领域二氧化碳排放总量趋于稳定，钢铁、建材等重点行业二氧化碳排放总量得到有效控制。 | K62: FYP1615.htm | L62: 温室气体排放
A63: 2012 | B63: 单位工业增加值二氧化碳排放量 | C63: 降低 | D63: 50%左右 | E63: 2005 | F63: 2020 | G63: 新目标 | H63: 碳强度 | I63: 行业 | J63: 到2020年，单位工业增加值二氧化碳排放量比2005年下降50%左右，基本形成以低碳排放为特征的工业体系。 | K63: AP1201.pdf | L63: 温室气体排放
A64: 2012 | B64: 单位工业增加值二氧化碳排放量 | C64: 降低 | D64: 21%以上 | E64: 2010 | F64: 2015 | G64: 新目标 | H64: 碳强度 | I64: 行业 | J64: 到2015年，全面落实国家温室气体排放控制目标，单位工业增加值二氧化碳排放量比2010年下降21%以上。 | K64: AP1201.pdf | L64: 温室气体排放
A65: 2021 | B65: 单位工业增加值二氧化碳排放量年均削减率 | C65: 达到 | D65: 4%以上 | F65: 2025 | G65: 新目标 | H65: 碳强度 | I65: 行业 | J65: 到2025年，单位工业增加值二氧化碳排放量年均削减率高于4%。 | K65: IP2102.htm | L65: 温室气体排放
A66: 2012 | B66: 单位工业增加值二氧化碳排放量（建材工业） | C66: 降低 | D66: 18% | E66: 2010 | F66: 2015 | G66: 新目标 | H66: 碳强度 | I66: 行业 | J66: 到2015年，建材工业单位工业增加值二氧化碳排放量比2010年下降18%以上。 | K66: AP1201.pdf | L66: 温室气体排放
A67: 2012 | B67: 化工行业单位工业增加值二氧化碳排放量 | C67: 降低 | D67: 17% | E67: 2010 | F67: 2015 | G67: 新目标 | H67: 碳强度 | I67: 行业 | J67: 到2015年，化工行业单位工业增加值二氧化碳排放量比2010年下降17%以上。 | K67: AP1201.pdf | L67: 温室气体排放
A68: 2012 | B68: 电子信息行业单位工业增加值二氧化碳排放量 | C68: 降低 | D68: 18%以上 | E68: 2010 | F68: 2015 | G68: 新目标 | H68: 碳强度 | I68: 行业 | J68: 到2015年，电子信息行业单位工业增加值二氧化碳排放量比2010年下降18%以上。 | K68: AP1201.pdf | L68: 温室气体排放
A69: 2012 | B69: 轻工业单位工业增加值二氧化碳排放量 | C69: 降低 | D69: 20% | E69: 2010 | F69: 2015 | G69: 新目标 | H69: 碳强度 | I69: 行业 | J69: 到2015年，轻工业单位工业增加值二氧化碳排放量比2010年下降20%。 | K69: AP1201.pdf | L69: 温室气体排放
A70: 2012 | B70: 机械行业单位工业增加值二氧化碳排放量 | C70: 降低 | D70: 22% | E70: 2010 | F70: 2015 | G70: 新目标 | H70: 碳强度 | I70: 行业 | J70: 到2015年，机械行业单位工业增加值二氧化碳排放量比2010年下降22%。 | K70: AP1201.pdf | L70: 温室气体排放
A71: 2012 | B71: 有色金属行业单位工业增加值二氧化碳排放量 | C71: 降低 | D71: 18% | E71: 2010 | F71: 2015 | G71: 新目标 | H71: 碳强度 | I71: 行业 | J71: 到2015年，有色金属行业单位工业增加值二氧化碳排放量比2010年下降18%。 | K71: AP1201.pdf | L71: 温室气体排放
A72: 2012 | B72: 石化行业单位工业增加值二氧化碳排放量 | C72: 降低 | D72: 18% | E72: 2010 | F72: 2015 | G72: 新目标 | H72: 碳强度 | I72: 行业 | J72: 到2015年，石化行业单位工业增加值二氧化碳排放量比2010年下降18%。 | K72: AP1201.pdf | L72: 温室气体排放
A73: 2012 | B73: 钢铁行业单位工业增加值二氧化碳排放量 | C73: 降低 | D73: 18% | E73: 2010 | F73: 2015 | G73: 新目标 | H73: 碳强度 | I73: 行业 | J73: 到2015年，钢铁行业单位工业增加值二氧化碳排放量比2010年下降18%以上。 | K73: AP1201.pdf | L73: 温室气体排放
A74: 2012 | B74: 纺织行业单位工业增加值二氧化碳排放量 | C74: 降低 | D74: 20% | E74: 2010 | F74: 2015 | G74: 新目标 | H74: 碳强度 | I74: 行业 | J74: 到2015年，纺织行业单位工业增加值二氧化碳排放量比2010年下降20%。 | K74: AP1201.pdf | L74: 温室气体排放
A75: 2026 | B75: 全国碳排放权交易市场覆盖行业单位产品二氧化碳排放 | C75: 下降 | D75: 3%左右 | E75: 2025 | F75: 2030 | G75: 重申目标 | H75: 碳强度 | I75: 行业 | J75: ……全国碳排放权交易市场覆盖行业单位产品二氧化碳排放比 2025 年下降3%左右，建成诚信透明、方法统一、参与广泛、与国际接轨的全国温室气体自愿减排交易市场，…… | K75: HL2603.pdf | L75: 温室气体排放
A76: 2022 | B76: 交通运输单位周转量二氧化碳排放强度 | C76: 降低 | D76: 9.5% | E76: 2020 | F76: 2030 | G76: 重申目标 | H76: 碳强度 | I76: 行业 | J76: 力争到2030年，营运交通工具单位周转量碳排放强度比2020年下降约9.5% | K76: HL2404.pdf | L76: 温室气体排放
A77: 2016 | B77: 营运客车单位运输周转量二氧化碳排放 | C77: 降低 | D77: 2.6% | E77: 2015 | F77: 2020 | G77: 新目标 | H77: 碳强度 | I77: 行业 | J77: 到2020年，营运客车单位运输周转量二氧化碳排放比2015年下降2.6%。 | K77: FYP1615.htm | L77: 温室气体排放
A78: 2016 | B78: 营运船舶单位运输周转量二氧化碳排放 | C78: 降低 | D78: 7% | E78: 2015 | F78: 2020 | G78: 新目标 | H78: 碳强度 | I78: 行业 | J78: 到2020年，中国营运船舶单位运输周转量二氧化碳排放比2015年下降7%。 | K78: FYP1615.htm | L78: 温室气体排放
A79: 2016 | B79: 营运货车单位运输周转量二氧化碳排放 | C79: 降低 | D79: 8% | E79: 2015 | F79: 2020 | G79: 新目标 | H79: 碳强度 | I79: 行业 | J79: 到2020年，营运货车单位运输周转量二氧化碳排放比2015年下降8%。 | K79: FYP1615.htm | L79: 温室气体排放
A80: 2022 | B80: 营运车辆单位运输周转量二氧化碳排放 | C80: 降低 | D80: 5% | E80: 2020 | F80: 2025 | G80: 新目标 | H80: 碳强度 | I80: 行业 | J80: 到2025年，营运车辆和船舶的单位运输周转量二氧化碳排放量较2020年分别下降5%和3.5%。 | K80: HL2401.pdf | L80: 温室气体排放
A81: 2022 | B81: 营运船舶单位运输周转量二氧化碳排放量 | C81: 降低 | D81: 3.5% | E81: 2020 | F81: 2025 | G81: 新目标 | H81: 碳强度 | I81: 行业 | J81: 到2025年，营运车辆和船舶单位运输周转量二氧化碳排放量较2020年分别下降5%和3.5%。 | K81: HL2401.pdf | L81: 温室气体排放
A82: 2024 | B82: 交通运输领域单位周转量二氧化碳排放 | C82: 降低 | D82: 5% | E82: 2020 | F82: 2025 | G82: 新目标 | H82: 碳强度 | I82: 行业 | J82: 到2025年底，交通运输领域二氧化碳排放强度较2020年降低5%。 | K82: AP2405.htm | L82: 温室气体排放
A83: 2021 | B83: 营运车辆单位运输周转量二氧化碳排放强度 | C83: 降低 | D83: 约9.5% | E83: 2020 | F83: 2030 | G83: 新目标 | H83: 碳强度 | I83: 不明确 | J83: 到2030年，营运车辆单位换算周转量碳排放强度较2020年下降约9.5%。 | K83: HL2102.pdf | L83: 温室气体排放
A84: 2021 | B84: 公共交通单位周转量二氧化碳排放强度 | C84: 降低 | D84: 约9.5% | E84: 2020 | F84: 2030 | G84: 新目标 | H84: 碳强度 | I84: 不明确 | J84: 到2030年，公共交通单位周转量二氧化碳排放强度较2020年下降约9.5%。 | K84: HL2302.pdf | L84: 温室气体排放
A85: 2016 | B85: 城市客运单位客运量二氧化碳排放 | C85: 降低 | D85: 12.5% | E85: 2015 | F85: 2020 | G85: 新目标 | H85: 碳强度 | I85: 城市 | J85: 到2020年，城市客运单位客运量二氧化碳排放比2015年下降12.5%。 | K85: FYP1615.htm | L85: 温室气体排放
A86: 2024 | B86: 建材行业节能降碳改造形成的二氧化碳减排量 | C86: 达到 | D86: 2600万吨二氧化碳 | F86: 2024-2025 | G86: 新目标 | H86: 碳减排 | I86: 行业 | J86: 2024—2025年，建材行业节能降碳改造形成减排二氧化碳约2600万吨。 | K86: AP2405.htm | L86: 温室气体排放
A87: 2024 | B87: 水泥行业节能降碳改造形成的二氧化碳减排量 | C87: 达到 | D87: 约1300万吨 | F87: 2024-2025 | G87: 新目标 | H87: 碳减排 | I87: 行业 | J87: 2024—2025年，通过实施水泥行业节能降碳改造和用能设备更新形成节能量约500万吨标准煤、减排二氧化碳约1300万吨。 | K87: AP2412.pdf | L87: 温室气体排放
A88: 2024 | B88: 有色金属行业节能降碳改造二氧化碳减排量 | C88: 达到 | D88: 1300万吨 | F88: 2024-2025 | G88: 新目标 | H88: 碳减排 | I88: 行业 | J88: 2024—2025年，有色金属行业节能降碳改造形成减排二氧化碳约1300万吨。 | K88: AP2405.htm | L88: 温室气体排放
A89: 2024 | B89: 石化化工行业节能降碳改造形成的二氧化碳减排量 | C89: 达到 | D89: 1.1亿吨 | F89: 2024-2025 | G89: 新目标 | H89: 碳减排 | I89: 行业 | J89: 2024—2025年，石化化工行业节能降碳改造形成减排二氧化碳约1.1亿吨。 | K89: AP2405.htm | L89: 温室气体排放
A90: 2024 | B90: 钢铁行业节能降碳改造形成的二氧化碳减排量 | C90: 达到 | D90: 5300万吨二氧化碳 | F90: 2024-2025 | G90: 新目标 | H90: 碳减排 | I90: 行业 | J90: 2024—2025年，钢铁行业节能降碳改造形成节能量约2000万吨标准煤、减排二氧化碳约5300万吨。 | K90: AP2405.htm | L90: 温室气体排放
A91: 2013 | B91: 节能型内燃机产品减少二氧化碳排放量 | C91: 降低 | D91: 6200万吨 | E91: 2010 | F91: 2015 | G91: 新目标 | H91: 碳减排 | I91: 不明确 | J91: 到2015年，通过节能型内燃机产品实现减少二氧化碳排放6200万吨。 | K91: O1301.htm | L91: 温室气体排放
A92: 2007 | B92: 可再生能源新增装机带来的二氧化碳减排量 | C92: 节约 | D92: 6亿吨二氧化碳 | F92: 2007-2010 | G92: 新目标 | H92: 碳减排 | I92: 全社会经济 | J92: 达到2010年发展目标时，可再生能源年利用量相当于减少二氧化硫年排放量约400万吨，减少氮氧化物年排放量约150万吨，减少烟尘年排放量约200万吨，减少二氧化碳年排放量约6亿吨，年节约用水约15亿立方米，可使约1.5亿亩林地免遭破坏。 | K92: MLT0701.htm | L92: 温室气体排放
A93: 2007 | B93: 可再生能源新增量带来的二氧化碳减排量 | C93: 节约 | D93: 约12亿吨二氧化碳 | F93: 2007-2020 | G93: 新目标 | H93: 碳减排 | I93: 不明确 | J93: 到2020年发展目标实现时，可再生能源年利用量相当于减少二氧化硫年排放量约800万吨，减少氮氧化物年排放量约300万吨，减少烟尘年排放量约400万吨，减少二氧化碳年排放量约12亿吨，年节约用水约20亿立方米，可使约3亿亩林地免遭破坏。 | K93: MLT0701.htm | L93: 温室气体排放
A94: 2022 | B94: 焦化行业碳排放量 | C94: 降低 | D94: 30% | E94: 2025 | F94: 2035 | G94: 新目标 | H94: 碳减排 | I94: 行业 | J94: 通过采取有效的技术与管理措施，到2035年具备在2025年实现碳达峰基础上减碳30%的能力。 | K94: AP2206.pdf | L94: 温室气体排放
A95: 2024 | B95: 公共机构单位建筑面积碳排放 | C95: 降低 | D95: 7% | E95: 2020 | F95: 2025 | G95: 新目标 | H95: 碳强度 | I95: 公共机构 | J95: 到2025年底，公共机构单位建筑面积碳排放较2020年降低7%。 | K95: AP2405.htm | L95: 温室气体排放
A96: 2021 | B96: 营运车辆单位运输周转量二氧化碳排放 | C96: 降低 | D96: 9.5% | E96: 2020 | F96: 2030 | G96: 重申目标 | H96: 碳强度 | I96: 不明确 | J96: 到2030年，营运车辆换算周转量碳排放强度较2020年下降约9.5% | K96: HL2104.pdf | L96: 温室气体排放
A97: 2024 | B97: 营运交通工具单位换算周转量碳排放强度 | C97: 降低 | D97: 约9.5% | E97: 2020 | F97: 2030 | G97: 重申目标 | H97: 碳强度 | I97: 不明确 | J97: 到2030年，营运交通工具单位换算周转量碳排放强度比2020年下降9.5%左右。 | K97: O2407.htm | L97: 温室气体排放
A98: 2026 | B98: 公共机构单位建筑面积碳排放 | C98: 降低 | D98: 8.5% | F98: 十五五 | G98: 重申目标 | H98: 碳强度 | I98: 企事业单位 | J98: “十五五”期间，公共机构单位建筑面积能耗降低5%、碳排放降低8.5%。 | K98: HL2604.htm | L98: 温室气体排放
A99: 2026 | B99: 公共机构单位建筑面积碳排放 | C99: 降低 | D99: 8.5% | E99: 2025 | F99: 2030 | G99: 新目标 | H99: 碳强度 | I99: 企事业单位 | J99: 以2025年碳排放、能源资源消费为基数，到2030年统计范围内公共机构单位建筑面积碳排放下降8.5%，…… | K99: WOP2601.htm | L99: 温室气体排放
A100: 2026 | B100: 全国碳排放权交易市场覆盖行业单位产品碳排放 | C100: 降低 | D100: 3%左右 | F100: 十五五 | G100: 新目标 | H100: 碳强度 | I100: 行业 | J100: “十五五”期间，全国碳排放权交易市场覆盖行业的单位产品碳排放降低3%左右，重点排放单位碳排放配额清缴完成率稳定在较高水平。 | K100: HL2604.htm | L100: 温室气体排放
...

Sheet 能源|电力
A1: 公布年份 | B1: 指标 | C1: 方向 | D1: 目标值 | E1: 基线 | F1: 目标年份/时期 | G1: 计数 | H1: 目标类别 | I1: 责任主体 | J1: 政策原文 | K1: 文件 | L1: 主题标签 | M1: 子主题标签
A2: 2018 | B2: “三北”地区可再生能源跨区消纳 | C2: 实现 | D2: 4000万千瓦以上 | F2: 十三五 | G2: 新目标 | H2: 可再生能源 | I2: 不明确 | J2: 调整和放缓配套火电建设的跨区输电通道，富余容量优先安排新能源外送，力争“十三五”期间，“三北地区”可再生能源跨区消纳4000万千瓦以上。 | K2: GO1801.htm | L2: 能源|电力 | M2: 能源消费
A3: 2016 | B3: “三北”地区煤电机组灵活性改造 | C3: 达到 | D3: 约1.33亿千瓦 | F3: 十三五 | G3: 新目标 | H3: 涉煤 | I3: 地区 | J3: “十三五”期间，“三北”地区热电机组灵活性改造约1.33亿千瓦。 | K3: FYP1607.pdf | L3: 能源|电力 | M3: 煤电
A4: 2013 | B4: 330千伏及以上输电线路建设规模 | C4: 达到 | D4: 20万公里 | F4: 2015 | G4: 新目标 | H4: 可再生能源 | I4: 不明确 | J4: 到2015年，建成330千伏及以上输电线路20万公里。 | K4: FYP1302.htm | L4: 能源|电力 | M4: 电力传输/能源运输
A5: 2023 | B5: PM2.5未达标城市每小时10蒸吨及以下燃煤锅炉 | C5: 基本淘汰 | D5: 基本淘汰 | F5: 2025 | G5: 新目标 | H5: 涉煤 | I5: 行业 | J5: 到2025年，PM2.5未达标城市基本淘汰10蒸吨/小时及以下燃煤锅炉。 | K5: AP2304.htm | L5: 能源|电力 | M5: 煤电
A6: 2014 | B6: 一次能源消费中煤炭占比 | C6: 降低 | D6: 62% | F6: 2020 | G6: 重申目标 | H6: 涉煤 | I6: 全社会经济 | J6: 到2020年，全国煤炭消费比重降至62%以内。 | K6: AP1401.htm | L6: 能源|电力 | M6: 能源消费
A7: 2013 | B7: 一次能源消费总量 | C7: 达到 | D7: 40亿吨标准煤 | F7: 2015 | G7: 新目标 | H7: 能源效率 | I7: 全社会经济 | J7: 到2015年，全国能源消费总量控制在40亿吨标准煤左右。 | K7: FYP1302.htm | L7: 能源|电力 | M7: 能源消费
A8: 2018 | B8: 上海市、江苏省、浙江省、安徽省及汾渭平原地区煤炭消费总量 | C8: 降低 | D8: 比2015年下降5%左右 | E8: 2015 | F8: 2020 | G8: 新目标 | H8: 涉煤 | I8: 地区 | J8: 到2020年，上海、江苏、浙江、安徽及汾渭平原煤炭消费总量均下降5%左右 | K8: O1802.htm | L8: 能源|电力 | M8: 煤电
A9: 2016 | B9: 东部11省市现役30万千瓦及以上公用煤电机组、10万千瓦及以上自备煤电机组超低排放改造 | C9: 完成 | F9: 2017 | G9: 新目标 | H9: 涉煤 | I9: 行业 | J9: 2017年前总体完成东部11省市现役30万千瓦及以上公用煤电机组、10万千瓦及以上自备煤电机组超低排放改造。 | K9: FYP1603.pdf | L9: 能源|电力 | M9: 煤电
A10: 2021 | B10: 东部和中部地区新增非化石能源年生产能力 | C10: 新增 | D10: 1.5亿吨标准煤 | F10: 十四五 | G10: 新目标 | H10: 可再生能源 | I10: 全社会经济 | J10: “十四五”期间，东部和中部地区新增非化石能源年生产能力1.5亿吨标准煤以上。 | K10: FYP2105.pdf | L10: 能源|电力 | M10: 电力供应
A11: 2014 | B11: 中厚煤层采区回采率 | C11: 达到 | D11: 85% | F11: 2020 | G11: 新目标 | H11: 涉煤 | I11: 不明确 | J11: 到2020年，中厚煤层采区回采率达到85%。 | K11: O1401.htm | L11: 能源|电力 | M11: 煤电
A12: 2016 | B12: 中部八省现役30万千瓦及以上煤电机组超低排放改造 | C12: 基本完成 | F12: 2018 | G12: 新目标 | H12: 涉煤 | I12: 行业 | J12: 2018年前基本完成中部八省现役30万千瓦及以上煤电机组超低排放改造 | K12: FYP1603.pdf | L12: 能源|电力 | M12: 煤电
A13: 2023 | B13: 京津冀及周边地区煤炭消费总量 | C13: 降低 | D13: 10% | E13: 2020 | F13: 2025 | G13: 新目标 | H13: 涉煤 | I13: 地区 | J13: 到2025年，京津冀及周边地区煤炭消费量较2020年下降10%左右 | K13: AP2304.htm | L13: 能源|电力 | M13: 煤电
A14: 2014 | B14: 京津冀鲁四省市煤炭消费总量 | C14: 降低 | D14: 1亿吨 | E14: 2012 | F14: 2020 | G14: 新目标 | H14: 涉煤 | I14: 地区 | J14: 到2020年，京津冀鲁四省市煤炭消费比2012年净削减1亿吨，长三角和珠三角地区煤炭消费总量负增长。 | K14: AP1401.htm | L14: 能源|电力 | M14: 煤电
A15: 2013 | B15: 以分布式可再生能源为主的新能源示范城市 | C15: 建设 | D15: 100个 | F15: 2015 | G15: 新目标 | H15: 可再生能源 | I15: 全社会经济 | J15: 到2015年，建成100个以分布式可再生能源应用为主的新能源示范城市。 | K15: FYP1302.htm | L15: 能源|电力 | M15: 电力供应
A16: 2004 | B16: 低温余热发电装置 | C16: 建设 | D16: 30套 | F16: 十一五 | G16: 新目标 | H16: 能源效率 | I16: 不明确 | J16: “十一五”期间，在日产2000吨以上水泥生产线上建设低温余热发电装置30套，形成年节能300万吨标准煤。 | K16: MLT0401.htm | L16: 能源|电力 | M16: 电力供应
A17: 2013 | B17: 低热值煤炭资源综合利用发电装机容量 | C17: 达到 | D17: 7600万千瓦 | F17: 2015 | G17: 新目标 | H17: 涉煤 | I17: 全社会经济 | J17: 到2015年，低热值煤炭资源综合利用发电装机容量达到7600万千瓦。 | K17: DP1301.htm | L17: 能源|电力 | M17: 煤电
A18: 2012 | B18: 余热发电比例 | C18: 提高至 | D18: 30%以上 | F18: 2015 | G18: 新目标 | H18: 能源效率 | I18: 全社会经济 | J18: 推进玻璃生产线余热发电，到2015年余热发电比例提高到30%以上。 | K18: FYP1201.htm | L18: 能源|电力 | M18: 电力供应
A19: 2007 | B19: 保留小型煤矿产量 | C19: 控制在…以内 | D19: 2亿吨 | F19: 2010 | G19: 重申目标 | H19: 涉煤 | I19: 行业 | J19: 到2010年，保留的小型煤矿产量控制在2亿吨以内。 | K19: FYP0701.htm | L19: 能源|电力 | M19: 煤电
A20: 2013 | B20: 光伏电站太阳能发电装机容量 | C20: 达到 | D20: 3500万千瓦以上 | F20: 2015 | G20: 新目标 | H20: 可再生能源 | I20: 全社会经济 | J20: 到2015年，光伏发电总装机容量达到3500万千瓦以上。 | K20: O1303.htm | L20: 能源|电力 | M20: 电力供应
A21: 2018 | B21: 全国光伏发电利用率 | C21: 超过 | D21: 95% | F21: 2018 | G21: 新目标 | H21: 可再生能源 | I21: 全社会经济 | J21: 2018年，确保光伏发电利用率高于95%，弃光率低于5%，确保弃风、弃光电量比2017年进一步下降。 | K21: AP1804.pdf | L21: 能源|电力 | M21: 电力供应
A22: 2018 | B22: 全国光伏发电利用率 | C22: 超过 | D22: 95% | F22: 2019 | G22: 新目标 | H22: 可再生能源 | I22: 全社会经济 | J22: 2019年，确保光伏发电利用率高于95%，弃光率低于5%。 | K22: AP1804.pdf | L22: 能源|电力 | M22: 电力供应
A23: 2018 | B23: 全国光伏发电利用率 | C23: 超过 | D23: 95% | F23: 2020 | G23: 新目标 | H23: 可再生能源 | I23: 全社会经济 | J23: 到2020年，确保光伏发电利用率高于95%，弃光率低于5%。 | K23: AP1804.pdf | L23: 能源|电力 | M23: 电力供应
A24: 2018 | B24: 全国光伏弃光率 | C24: 低于 | D24: 5% | F24: 2020 | G24: 新目标 | H24: 可再生能源 | I24: 全社会经济 | J24: 2020年，光伏发电利用率高于95%，弃光率低于5%。 | K24: AP1804.pdf | L24: 能源|电力 | M24: 电力供应
A25: 2012 | B25: 全国可再生能源利用量 | C25: 达到 | D25: 3亿吨标准煤 | F25: 十一五 | G25: 新目标 | H25: 可再生能源 | I25: 全社会经济 | J25: 《可再生能源发展“十一五”规划》提出的主要发展指标包括：全国可再生能源利用量达到3亿吨标准煤。 | K25: HL1201.pdf | L25: 能源|电力 | M25: 能源消费
A26: 2018 | B26: 全国太阳能弃光率 | C26: 低于 | D26: 5% | F26: 2019 | G26: 新目标 | H26: 可再生能源 | I26: 全社会经济 | J26: 2019年，确保光伏发电利用率高于95%，弃光率低于5%。 | K26: AP1804.pdf | L26: 能源|电力 | M26: 电力供应
A27: 2018 | B27: 全国平均弃风率 | C27: 低于 | D27: 12% | F27: 2018 | G27: 新目标 | H27: 可再生能源 | I27: 全社会经济 | J27: 2018年，确保全国平均风电利用率高于88%（力争达到90%以上），弃风率低于12%（力争控制在10%以内）。 | K27: AP1804.pdf | L27: 能源|电力 | M27: 电力供应
A28: 2018 | B28: 全国平均弃风率 | C28: 低于 | D28: 10% | F28: 2019 | G28: 新目标 | H28: 可再生能源 | I28: 全社会经济 | J28: 2019年，确保全国平均风电利用率高于90%（力争达到92%左右），弃风率低于10%（力争控制在8%左右）。 | K28: AP1804.pdf | L28: 能源|电力 | M28: 电力供应
A29: 2018 | B29: 全国平均弃风率 | C29: 控制在…以内 | D29: 5% | F29: 2020 | G29: 新目标 | H29: 可再生能源 | I29: 全社会经济 | J29: 到2020年，确保全国平均风电利用率达到国际先进水平（力争达到95%左右），弃风率控制在合理水平（力争控制在5%左右）。 | K29: AP1804.pdf | L29: 能源|电力 | M29: 电力供应
A30: 2018 | B30: 全国平均风电利用率 | C30: 超过 | D30: 88% | F30: 2018 | G30: 新目标 | H30: 可再生能源 | I30: 全社会经济 | J30: 2018年，确保全国平均风电利用率高于88%（力争达到90%以上），弃风率低于12%（力争控制在10%以内）。 | K30: AP1804.pdf | L30: 能源|电力 | M30: 电力供应
A31: 2018 | B31: 全国平均风电利用率 | C31: 超过 | D31: 90% | F31: 2019 | G31: 新目标 | H31: 可再生能源 | I31: 全社会经济 | J31: 2019年，确保全国平均风电利用率高于90%（力争达到92%左右），弃风率低于10%（力争控制在8%左右）。 | K31: AP1804.pdf | L31: 能源|电力 | M31: 电力供应
A32: 2018 | B32: 全国平均风电利用率 | C32: 超过 | D32: 95% | F32: 2020 | G32: 新目标 | H32: 可再生能源 | I32: 全社会经济 | J32: 2020年，确保全国平均风电利用率达到国际先进水平（力争达到95%左右），弃风率控制在合理水平（力争控制在5%左右）。 | K32: AP1804.pdf | L32: 能源|电力 | M32: 电力供应
A33: 2018 | B33: 全国弃光率 | C33: 低于 | D33: 5% | F33: 2018 | G33: 新目标 | H33: 可再生能源 | I33: 全社会经济 | J33: 2018年，确保光伏发电利用率高于95%，弃光率低于5%，确保弃风、弃光电量比2017年进一步下降。 | K33: AP1804.pdf | L33: 能源|电力 | M33: 电力供应
A34: 2018 | B34: 全国水能利用率 | C34: 超过 | D34: 95% | F34: 2018 | G34: 新目标 | H34: 可再生能源 | I34: 全社会经济 | J34: 二零一八年，确保全国水能利用率达到百分之九十五以上。 | K34: AP1804.pdf | L34: 能源|电力 | M34: 电力供应
A35: 2018 | B35: 全国水能利用率 | C35: 超过 | D35: 95% | F35: 2019 | G35: 新目标 | H35: 可再生能源 | I35: 全社会经济 | J35: 2019年，全国水能利用率应高于95%。 | K35: AP1804.pdf | L35: 能源|电力 | M35: 电力供应
A36: 2018 | B36: 全国水能利用率 | C36: 超过 | D36: 95% | F36: 2020 | G36: 新目标 | H36: 可再生能源 | I36: 全社会经济 | J36: 2020年，全国水能利用率确保达到95%以上。 | K36: AP1804.pdf | L36: 能源|电力 | M36: 电力供应
A37: 2014 | B37: 全国煤炭铁路运输能力 | C37: 达到 | D37: 30亿吨 | F37: 2020 | G37: 新目标 | H37: 涉煤 | I37: 全社会经济 | J37: 到2020年，全国煤炭铁路运输能力达到30亿吨。 | K37: AP1401.htm | L37: 能源|电力 | M37: 电力传输/能源运输
A38: 2025 | B38: 全国虚拟电厂调节能力 | C38: 达到 | D38: 5000万千瓦以上 | F38: 2030 | G38: 新目标 | H38: 可再生能源 | I38: 全社会经济 | J38: 到2030年，虚拟电厂应用场景进一步拓展，各类商业模式创新发展，全国虚拟电厂调节能力达到5000万千瓦以上。 | K38: GO2501.htm | L38: 能源|电力 | M38: 电力传输/能源运输
A39: 2025 | B39: 全国虚拟电厂调节能力 | C39: 达到 | D39: 2000万千瓦以上 | F39: 2027 | G39: 新目标 | H39: 可再生能源 | I39: 全社会经济 | J39: 到2027年，虚拟电厂建设运行管理机制成熟规范，参与电力市场的机制健全完善，全国虚拟电厂调节能力达到2000万千瓦以上。 | K39: GO2501.htm | L39: 能源|电力 | M39: 电力传输/能源运输
