Workbook

Sheet README
B2: China's National Climate Targets Database (v1.0.0) | S2: CC BY 4.0
B3: This dataset compiles quantified climate-related targets set by the Chinese central government from 2004 through mid-2026, drawn from official policy documents and government website entries, and organized into distinct thematic areas. | R3: Author | S3: Florian Wengel
B4: In China, targets have a directive character in practice and serve as important guidance for government bodies. | S4: SOAS University of London
B5: Last update | C5: 46272 | Q5: Disclaimer: All errors are the author's. | S5: 705404@soas.ac.uk
B6: 2026-09-07: Unified percentage notation across the English version ("X percent" → "X%").
B7: 2026-09-07: Added 1 target from the Implementation Plan for Promoting Coordinated Digital and Green Transformation (2026-2030) (IP2604): renewable electricity consumption level in computing facilities and other key areas reaching the provincial renewable electricity consumption responsibility weight (2030).
B8: 2026-09-07: Simplified target category names by removing the "target" suffix (e.g. "Renewable energy target" → "Renewable energy"), in sync with the Chinese version.
B9: 2026-09-04: Per the inclusion criteria (directly reducing GHG emissions, indirectly promoting mitigation, or significantly affecting the emission pathway), 62 indicators without a direct climate link were screened and removed (travel convenience, security screening procedures, vehicle technical parameters, employment/revenue, biodiversity, etc.). 2026-09-04: Added 169 targets from 17 new 2026 policy documents (98 new targets, 63 reiterated targets, 8 strengthened or loosened targets), and added 26 policy documents to the Sources sheet.
B10: Source information
B11: Climate targets are extracted from Chinese climate strategies issued by various agencies of the Chinese central government. These text documents were found on government agencies' websites, the online encyclopaedia Baidu Baike, Chinese state-owned media outlets, or other websites.
B13: Climate target definition
B14: For the purpose of compiling this data set, we define climate targets in a broad sense as quantified commitments aimed at directly reducing GHG emissions, contributing indirectly to emission reduction, or significantly influencing GHG emission pathways.
B15: The dataset includes both hard targets and softer indicative targets.
B17: Scope & coverage
B18: This dataset only covers national level climate targets. It does not provide information on targets set at the subnational level. Targets are extracted from policy documents that were issued since 2004.
B19: The dataset was compiled to be as comprehensive as possible, yet some targets may not have been captured.
B21: Dataset structure
B22: Sheet | C22: Explanation
B23: Overview | C23: Summary statistics
B24: GHG Emissions | C24: All targets addressing greenhouse gas emissions, economy-wide or for specific sectors, systems or processes
B25: Energy|Power | C25: All targets related to energy supply (including targets related to coal power) and consumption
B26: Industry | C26: All targets related to the industrial sector, particularly carbon-intensive industrial processes
B27: Buildings | C27: All targets related to buildings and infrastructure
B28: Transport | C28: All targets related to transportation and logistics
B29: LULUCF | C29: All targets related to land use, agriculture and forestry
B30: Circular Economy | C30: All targets related to waste and water management and recycling
B31: Pollution | C31: All targets addressing air or water pollutants, economy-wide or for specific sectors, systems or processes
B32: Finance | C32: All targets related to the financing to achieve decarbonisation goals
B33: Sources | C33: Code identifying climate policy document used to source target data. Codes and the corresponding full titles of policy documents can be found in the 'Sources' sheet.
B35: Column Descriptions
B36: Announcement_Year | C36: The year in which the source document in which the target was found was officially released or published.
B37: Metric | C37: The core indicator the target is about (what is being measured).
B38: Direction | C38: The intended direction or type of change expressed by the target
B39: Target_Magnitude | C39: The target level or change magnitude (the numeric value together with its unit)
C40: The level or year from which progress toward the target is measured, if specified in the source document. This is the starting reference year for the change magnitude.
C41: The year or period in which the target is meant to be achieved.
C42: A code indicating whether the target is new, repeated, strengthened, or loosened:
C43: n = New target (appears for the first time)
C44: r = Repeated target (same target level and same target year appears in multiple policy documents)
C45: s/l = Strengthened or loosened target (same target year or period, but target level is made more or less ambitious)
D46: s/l-UNC | E46: Strengthened or loosened target with unclear climate impact
D47: s/l-POS | E47: Strengthened or loosened target with positive climate impact
D48: s/l-NEG | E48: Strengthened or loosened target with negative climate impact
C49: An attribute categorising targets based on the underlying mechanism through which they aim to contribute to climate mitigation or environmental outcomes:
C50: Carbon reduction | E50: absolute reduction in emissions
C51: Carbon intensity | E51: relative reduction in emissions per unit of output
C52: Carbon sink | E52: increase in forest cover or carbon sink capacity
C53: Energy saving | E53: reduction of energy consumption
C54: Energy efficiency | E54: enhancing energy use efficiency
C55: Resource efficiency | E55: enhancing resource use efficiency
C56: Renewable energy | E56: expanding renewable energy
C57: Electrification | E57: enhancing electrification
C58: Transitional energy | E58: shift from coal to other fossil fuels and nuclear power
C59: Coal-related | E59: transformation and phase out of coal power
C60: Production-oriented | E60: expansion of production in green sectors or restriction of carbon intensive production
C61: Industrial transformation | E61: decarbonising carbon-intensive industries
... C67: Climate finance | E67: mobilization of funds to mitigate and adapt to climate change
C68: An attribute indicating the accountable implementation unit to which a climate target applies:
C69: enterprises | E69: applies to specific firms/plants/institutions
C70: areas | E70: applies to specific cities/regions/zones
C71: sectors | E71: applies to a defined industry or economic activity (e.g., steel)
C72: whole economy | E72: applies nationally across all economic activity
C73: unclear | E73: scope/accountable unit not specified
B74: Sentence | C74: The sentence from the source document containing the quantified target with minor edits for clarity or completeness that do not alter meaning. Translated into English where applicable.
B75: Document | C75: The file name of the source document from which the target was extracted. The prefix typically indicates the policy type (e.g., “AP” = Action Plan, “FYP” = Five‑Year Plan) followed by the year of publication (21 = 2021) and an internal identifier.
B76: Topic_Label | C76: The thematic area or category that the target falls under.
B77: Subtopic_Label (in "Energy|Power" sheet only) | C77: A more granular categorisation within the main topic label, used to refine the thematic classification.

Sheet Overview
B2: Descriptive Statistics
B4: Number of Targets by Sector/Topic | E4: Number of "Energy/Power" Targets by Subtopic | H4: Number of Targets by Count | K4: Number of Targets by Announcement Year | N4: Number of Targets by Target Year | Q4: Number of Targets by Category | T4: Targets by Accountability
B6: GHG Emissions | C6: =COUNTIFS('GHG Emissions'!G:G, "n") + COUNTIFS('GHG Emissions'!G:G, "s/l-UNC") + COUNTIFS('GHG Emissions'!G:G, "s/l-POS") + COUNTIFS('GHG Emissions'!G:G, "s/l-NEG") | E6: Energy consumption | F6: =COUNTIFS('Energy|Power'!M:M, "Energy consumption") | H6: New target | I6: =COUNTIF('GHG Emissions'!G:G,"n") +COUNTIF(Pollution!G:G,"n") +COUNTIF('Energy|Power'!G:G,"n") +COUNTIF(Industry!G:G,"n") +COUNTIF(Buildings!G:G,"n") +COUNTIF(Transport!G:G,"n") +COUNTIF(LULUCF!G:G,"n") +COUNTIF('Circular Economy'!G:G,"n") +COUNTIF(Finance!G:G,"n") | K6: 2004 | L6: =COUNTIFS('GHG Emissions'!A:A, 2004, 'GHG Emissions'!G:G, "n") + COUNTIFS('GHG Emissions'!A:A, 2004, 'GHG Emissions'!G:G, "s/l-UNC") + COUNTIFS('GHG Emissions'!A:A, 2004, 'GHG Emissions'!G:G, "s/l-POS") + COUNTIFS('GHG Emissions'!A:A, 2004, 'GHG Emissions'!G:G, "s/l-NEG") + COUNTIFS(Pollution!A:A, 2004, Pollution!G:G, "n") + COUNTIFS(Pollution!A:A, 2004, Pollution!G:G, "s/l-UNC") + COUNTIFS(Pollution!A:A, 2004, Pollution!G:G, "s/l-POS") + COUNTIFS(Pollution!A:A, 2004, Pollution!G:G, "s/l-NEG") + COUNTIFS('Energy|Power'!A:A, 2004, 'Energy|Power'!G:G, "n") + COUNTIFS('Energy|Power'!A:A, 2004, 'Energy|Power'!G:G, "s/l-UNC") + COUNTIFS('Energy|Power'!A:A, 2004, 'Energy|Power'!G:G, "s/l-POS") + COUNTIFS('Energy|Power'!A:A, 2004, 'Energy|Power'!G:G, "s/l-NEG") + COUNTIFS(Industry!A:A, 2004, Industry!G:G, "n") + COUNTIFS(Industry!A:A, 2004, Industry!G:G, "s/l-UNC") + COUNTIFS(Industry!A:A, 2004, Industry!G:G, "s/l-POS") + COUNTIFS(Industry!A:A, 2004, Industry!G:G, "s/l-NEG") + COUNTIFS(Buildings!A:A, 2004, Buildings!G:G, "n") + COUNTIFS(Buildings!A:A, 2004, Buildings!G:G, "s/l-UNC") + COUNTIFS(Buildings!A:A, 2004, Buildings!G:G, "s/l-POS") + COUNTIFS(Buildings!A:A, 2004, Buildings!G:G, "s/l-NEG") + COUNTIFS(Transport!A:A, 2004, Transport!G:G, "n") + COUNTIFS(Transport!A:A, 2004, Transport!G:G, "s/l-UNC") + COUNTIFS(Transport!A:A, 2004, Transport!G:G, "s/l-POS") + COUNTIFS(Transport!A:A, 2004, Transport!G:G, "s/l-NEG") + COUNTIFS(LULUCF!A:A, 2004, LULUCF!G:G, "n") + COUNTIFS(LULUCF!A:A, 2004, LULUCF!G:G, "s/l-UNC") + COUNTIFS(LULUCF!A:A, 2004, LULUCF!G:G, "s/l-POS") + COUNTIFS(LULUCF!A:A, 2004, LULUCF!G:G, "s/l-NEG") + COUNTIFS('Circular Economy'!A:A, 2004, 'Circular Economy'!G:G, "n") + COUNTIFS('Circular Economy'!A:A, 2004, 'Circular Economy'!G:G, "s/l-UNC") + COUNTIFS('Circular Economy'!A:A, 2004, 'Circular Economy'!G:G, "s/l-POS") + COUNTIFS('Circular Economy'!A:A, 2004, 'Circular Economy'!G:G, "s/l-NEG") + COUNTIFS(Finance!A:A, 2004, Finance!G:G, "n") + COUNTIFS(Finance!A:A, 2004, Finance!G:G, "s/l-UNC") + COUNTIFS(Finance!A:A, 2004, Finance!G:G, "s/l-POS") + COUNTIFS(Finance!A:A, 2004, Finance!G:G, "s/l-NEG") | N6: 2007 | O6: =COUNTIFS('GHG Emissions'!F:F, 2007, 'GHG Emissions'!G:G, "n") + COUNTIFS('GHG Emissions'!F:F, 2007, 'GHG Emissions'!G:G, "s/l-UNC") + COUNTIFS('GHG Emissions'!F:F, 2007, 'GHG Emissions'!G:G, "s/l-POS") + COUNTIFS('GHG Emissions'!F:F, 2007, 'GHG Emissions'!G:G, "s/l-NEG") + COUNTIFS(Pollution!F:F, 2007, Pollution!G:G, "n") + COUNTIFS(Pollution!F:F, 2007, Pollution!G:G, "s/l-UNC") + COUNTIFS(Pollution!F:F, 2007, Pollution!G:G, "s/l-POS") + COUNTIFS(Pollution!F:F, 2007, Pollution!G:G, "s/l-NEG") + COUNTIFS('Energy|Power'!F:F, 2007, 'Energy|Power'!G:G, "n") + COUNTIFS('Energy|Power'!F:F, 2007, 'Energy|Power'!G:G, "s/l-UNC") + COUNTIFS('Energy|Power'!F:F, 2007, 'Energy|Power'!G:G, "s/l-POS") + COUNTIFS('Energy|Power'!F:F, 2007, 'Energy|Power'!G:G, "s/l-NEG") + COUNTIFS(Industry!F:F, 2007, Industry!G:G, "n") + COUNTIFS(Industry!F:F, 2007, Industry!G:G, "s/l-UNC") + COUNTIFS(Industry!F:F, 2007, Industry!G:G, "s/l-POS") + COUNTIFS(Industry!F:F, 2007, Industry!G:G, "s/l-NEG") + COUNTIFS(Buildings!F:F, 2007, Buildings!G:G, "n") + COUNTIFS(Buildings!F:F, 2007, Buildings!G:G, "s/l-UNC") + COUNTIFS(Buildings!F:F, 2007, Buildings!G:G, "s/l-POS") + COUNTIFS(Buildings!F:F, 2007, Buildings!G:G, "s/l-NEG") + COUNTIFS(Transport!F:F, 2007, Transport!G:G, "n") + COUNTIFS(Transport!F:F, 2007, Transport!G:G, "s/l-UNC") + COUNTIFS(Transport!F:F, 2007, Transport!G:G, "s/l-POS") + COUNTIFS(Transport!F:F, 2007, Transport!G:G, "s/l-NEG") + COUNTIFS(LULUCF!F:F, 2007, LULUCF!G:G, "n") + COUNTIFS(LULUCF!F:F, 2007, LULUCF!G:G, "s/l-UNC") + COUNTIFS(LULUCF!F:F, 2007, LULUCF!G:G, "s/l-POS") + COUNTIFS(LULUCF!F:F, 2007, LULUCF!G:G, "s/l-NEG") + COUNTIFS('Circular Economy'!F:F, 2007, 'Circular Economy'!G:G, "n") + COUNTIFS('Circular Economy'!F:F, 2007, 'Circular Economy'!G:G, "s/l-UNC") + COUNTIFS('Circular Economy'!F:F, 2007, 'Circular Economy'!G:G, "s/l-POS") + COUNTIFS('Circular Economy'!F:F, 2007, 'Circular Economy'!G:G, "s/l-NEG") + COUNTIFS(Finance!F:F, 2007, Finance!G:G, "n") + COUNTIFS(Finance!F:F, 2007, Finance!G:G, "s/l-UNC") + COUNTIFS(Finance!F:F, 2007, Finance!G:G, "s/l-POS") + COUNTIFS(Finance!F:F, 2007, Finance!G:G, "s/l-NEG") | Q6: Carbon reduction | R6: =COUNTIFS('GHG Emissions'!H:H, "Carbon reduction", 'GHG Emissions'!G:G, "n") + COUNTIFS('GHG Emissions'!H:H, "Carbon reduction", 'GHG Emissions'!G:G, "s/l-UNC") + COUNTIFS('GHG Emissions'!H:H, "Carbon reduction", 'GHG Emissions'!G:G, "s/l-POS") + COUNTIFS('GHG Emissions'!H:H, "Carbon reduction", 'GHG Emissions'!G:G, "s/l-NEG") + COUNTIFS(Pollution!H:H, "Carbon reduction", Pollution!G:G, "n") + COUNTIFS(Pollution!H:H, "Carbon reduction", Pollution!G:G, "s/l-UNC") + COUNTIFS(Pollution!H:H, "Carbon reduction", Pollution!G:G, "s/l-POS") + COUNTIFS(Pollution!H:H, "Carbon reduction", Pollution!G:G, "s/l-NEG") + COUNTIFS('Energy|Power'!H:H, "Carbon reduction", 'Energy|Power'!G:G, "n") + COUNTIFS('Energy|Power'!H:H, "Carbon reduction", 'Energy|Power'!G:G, "s/l-UNC") + COUNTIFS('Energy|Power'!H:H, "Carbon reduction", 'Energy|Power'!G:G, "s/l-POS") + COUNTIFS('Energy|Power'!H:H, "Carbon reduction", 'Energy|Power'!G:G, "s/l-NEG") + COUNTIFS(Industry!H:H, "Carbon reduction", Industry!G:G, "n") + COUNTIFS(Industry!H:H, "Carbon reduction", Industry!G:G, "s/l-UNC") + COUNTIFS(Industry!H:H, "Carbon reduction", Industry!G:G, "s/l-POS") + COUNTIFS(Industry!H:H, "Carbon reduction", Industry!G:G, "s/l-NEG") + COUNTIFS(Buildings!H:H, "Carbon reduction", Buildings!G:G, "n") + COUNTIFS(Buildings!H:H, "Carbon reduction", Buildings!G:G, "s/l-UNC") + COUNTIFS(Buildings!H:H, "Carbon reduction", Buildings!G:G, "s/l-POS") + COUNTIFS(Buildings!H:H, "Carbon reduction", Buildings!G:G, "s/l-NEG") + COUNTIFS(Transport!H:H, "Carbon reduction", Transport!G:G, "n") + COUNTIFS(Transport!H:H, "Carbon reduction", Transport!G:G, "s/l-UNC") + COUNTIFS(Transport!H:H, "Carbon reduction", Transport!G:G, "s/l-POS") + COUNTIFS(Transport!H:H, "Carbon reduction", Transport!G:G, "s/l-NEG") + COUNTIFS(LULUCF!H:H, "Carbon reduction", LULUCF!G:G, "n") + COUNTIFS(LULUCF!H:H, "Carbon reduction", LULUCF!G:G, "s/l-UNC") + COUNTIFS(LULUCF!H:H, "Carbon reduction", LULUCF!G:G, "s/l-POS") + COUNTIFS(LULUCF!H:H, "Carbon reduction", LULUCF!G:G, "s/l-NEG") + COUNTIFS('Circular Economy'!H:H, "Carbon reduction", 'Circular Economy'!G:G, "n") + COUNTIFS('Circular Economy'!H:H, "Carbon reduction", 'Circular Economy'!G:G, "s/l-UNC") + COUNTIFS('Circular Economy'!H:H, "Carbon reduction", 'Circular Economy'!G:G, "s/l-POS") + COUNTIFS('Circular Economy'!H:H, "Carbon reduction", 'Circular Economy'!G:G, "s/l-NEG") + COUNTIFS(Finance!H:H, "Carbon reduction", Finance!G:G, "n") + COUNTIFS(Finance!H:H, "Carbon reduction", Finance!G:G, "s/l-UNC") + COUNTIFS(Finance!H:H, "Carbon reduction", Finance!G:G, "s/l-POS") + COUNTIFS(Finance!H:H, "Carbon reduction", Finance!G:G, "s/l-NEG") | T6: Enterprises & institutions | U6: =COUNTIFS('GHG Emissions'!I:I,"enterprises",'GHG Emissions'!G:G,"n") +COUNTIFS('GHG Emissions'!I:I,"enterprises",'GHG Emissions'!G:G,"s/l-UNC") +COUNTIFS('GHG Emissions'!I:I,"enterprises",'GHG Emissions'!G:G,"s/l-POS") +COUNTIFS('GHG Emissions'!I:I,"enterprises",'GHG Emissions'!G:G,"s/l-NEG") +COUNTIFS(Pollution!I:I,"enterprises",Pollution!G:G,"n") +COUNTIFS(Pollution!I:I,"enterprises",Pollution!G:G,"s/l-UNC") +COUNTIFS(Pollution!I:I,"enterprises",Pollution!G:G,"s/l-POS") +COUNTIFS(Pollution!I:I,"enterprises",Pollution!G:G,"s/l-NEG") +COUNTIFS('Energy|Power'!I:I,"enterprises",'Energy|Power'!G:G,"n") +COUNTIFS('Energy|Power'!I:I,"enterprises",'Energy|Power'!G:G,"s/l-UNC") +COUNTIFS('Energy|Power'!I:I,"enterprises",'Energy|Power'!G:G,"s/l-POS") +COUNTIFS('Energy|Power'!I:I,"enterprises",'Energy|Power'!G:G,"s/l-NEG") +COUNTIFS(Industry!I:I,"enterprises",Industry!G:G,"n") +COUNTIFS(Industry!I:I,"enterprises",Industry!G:G,"s/l-UNC") +COUNTIFS(Industry!I:I,"enterprises",Industry!G:G,"s/l-POS") +COUNTIFS(Industry!I:I,"enterprises",Industry!G:G,"s/l-NEG") +COUNTIFS(Buildings!I:I,"enterprises",Buildings!G:G,"n") +COUNTIFS(Buildings!I:I,"enterprises",Buildings!G:G,"s/l-UNC") +COUNTIFS(Buildings!I:I,"enterprises",Buildings!G:G,"s/l-POS") +COUNTIFS(Buildings!I:I,"enterprises",Buildings!G:G,"s/l-NEG") +COUNTIFS(Transport!I:I,"enterprises",Transport!G:G,"n") +COUNTIFS(Transport!I:I,"enterprises",Transport!G:G,"s/l-UNC") +COUNTIFS(Transport!I:I,"enterprises",Transport!G:G,"s/l-POS") +COUNTIFS(Transport!I:I,"enterprises",Transport!G:G,"s/l-NEG") +COUNTIFS(LULUCF!I:I,"enterprises",LULUCF!G:G,"n") +COUNTIFS(LULUCF!I:I,"enterprises",LULUCF!G:G,"s/l-UNC") +COUNTIFS(LULUCF!I:I,"enterprises",LULUCF!G:G,"s/l-POS") +COUNTIFS(LULUCF!I:I,"enterprises",LULUCF!G:G,"s/l-NEG") +COUNTIFS('Circular Economy'!I:I,"enterprises",'Circular Economy'!G:G,"n") +COUNTIFS('Circular Economy'!I:I,"enterprises",'Circular Economy'!G:G,"s/l-UNC") +COUNTIFS('Circular Economy'!I:I,"enterprises",'Circular Economy'!G:G,"s/l-POS") +COUNTIFS('Circular Economy'!I:I,"enterprises",'Circular Economy'!G:G,"s/l-NEG") +COUNTIFS(Finance!I:I,"enterprises",Finance!G:G,"n") +COUNTIFS(Finance!I:I,"enterprises",Finance!G:G,"s/l-UNC") +COUNTIFS(Finance!I:I,"enterprises",Finance!G:G,"s/l-POS") +COUNTIFS(Finance!I:I,"enterprises",Finance!G:G,"s/l-NEG")
B7: Pollution | C7: =COUNTIFS(Pollution!G:G, "n") + COUNTIFS(Pollution!G:G, "s/l-UNC") + COUNTIFS(Pollution!G:G, "s/l-POS") + COUNTIFS(Pollution!G:G, "s/l-NEG") | E7: Power supply | F7: =COUNTIFS('Energy|Power'!M:M, "Power supply") | H7: Strengthened or loosened target with unclear climate impact | I7: =COUNTIF('GHG Emissions'!G:G,"s/l-UNC") +COUNTIF(Pollution!G:G,"s/l-UNC") +COUNTIF('Energy|Power'!G:G,"s/l-UNC") +COUNTIF(Industry!G:G,"s/l-UNC") +COUNTIF(Buildings!G:G,"s/l-UNC") +COUNTIF(Transport!G:G,"s/l-UNC") +COUNTIF(LULUCF!G:G,"s/l-UNC") +COUNTIF('Circular Economy'!G:G,"s/l-UNC") +COUNTIF(Finance!G:G,"s/l-UNC") | K7: 2005 | L7: =COUNTIFS('GHG Emissions'!A:A, 2005, 'GHG Emissions'!G:G, "n") + COUNTIFS('GHG Emissions'!A:A, 2005, 'GHG Emissions'!G:G, "s/l-UNC") + COUNTIFS('GHG Emissions'!A:A, 2005, 'GHG Emissions'!G:G, "s/l-POS") + COUNTIFS('GHG Emissions'!A:A, 2005, 'GHG Emissions'!G:G, "s/l-NEG") + COUNTIFS(Pollution!A:A, 2005, Pollution!G:G, "n") + COUNTIFS(Pollution!A:A, 2005, Pollution!G:G, "s/l-UNC") + COUNTIFS(Pollution!A:A, 2005, Pollution!G:G, "s/l-POS") + COUNTIFS(Pollution!A:A, 2005, Pollution!G:G, "s/l-NEG") + COUNTIFS('Energy|Power'!A:A, 2005, 'Energy|Power'!G:G, "n") + COUNTIFS('Energy|Power'!A:A, 2005, 'Energy|Power'!G:G, "s/l-UNC") + COUNTIFS('Energy|Power'!A:A, 2005, 'Energy|Power'!G:G, "s/l-POS") + COUNTIFS('Energy|Power'!A:A, 2005, 'Energy|Power'!G:G, "s/l-NEG") + COUNTIFS(Industry!A:A, 2005, Industry!G:G, "n") + COUNTIFS(Industry!A:A, 2005, Industry!G:G, "s/l-UNC") + COUNTIFS(Industry!A:A, 2005, Industry!G:G, "s/l-POS") + COUNTIFS(Industry!A:A, 2005, Industry!G:G, "s/l-NEG") + COUNTIFS(Buildings!A:A, 2005, Buildings!G:G, "n") + COUNTIFS(Buildings!A:A, 2005, Buildings!G:G, "s/l-UNC") + COUNTIFS(Buildings!A:A, 2005, Buildings!G:G, "s/l-POS") + COUNTIFS(Buildings!A:A, 2005, Buildings!G:G, "s/l-NEG") + COUNTIFS(Transport!A:A, 2005, Transport!G:G, "n") + COUNTIFS(Transport!A:A, 2005, Transport!G:G, "s/l-UNC") + COUNTIFS(Transport!A:A, 2005, Transport!G:G, "s/l-POS") + COUNTIFS(Transport!A:A, 2005, Transport!G:G, "s/l-NEG") + COUNTIFS(LULUCF!A:A, 2005, LULUCF!G:G, "n") + COUNTIFS(LULUCF!A:A, 2005, LULUCF!G:G, "s/l-UNC") + COUNTIFS(LULUCF!A:A, 2005, LULUCF!G:G, "s/l-POS") + COUNTIFS(LULUCF!A:A, 2005, LULUCF!G:G, "s/l-NEG") + COUNTIFS('Circular Economy'!A:A, 2005, 'Circular Economy'!G:G, "n") + COUNTIFS('Circular Economy'!A:A, 2005, 'Circular Economy'!G:G, "s/l-UNC") + COUNTIFS('Circular Economy'!A:A, 2005, 'Circular Economy'!G:G, "s/l-POS") + COUNTIFS('Circular Economy'!A:A, 2005, 'Circular Economy'!G:G, "s/l-NEG") + COUNTIFS(Finance!A:A, 2005, Finance!G:G, "n") + COUNTIFS(Finance!A:A, 2005, Finance!G:G, "s/l-UNC") + COUNTIFS(Finance!A:A, 2005, Finance!G:G, "s/l-POS") + COUNTIFS(Finance!A:A, 2005, Finance!G:G, "s/l-NEG") | N7: 2008 | O7: =COUNTIFS('GHG Emissions'!F:F, 2008, 'GHG Emissions'!G:G, "n") + COUNTIFS('GHG Emissions'!F:F, 2008, 'GHG Emissions'!G:G, "s/l-UNC") + COUNTIFS('GHG Emissions'!F:F, 2008, 'GHG Emissions'!G:G, "s/l-POS") + COUNTIFS('GHG Emissions'!F:F, 2008, 'GHG Emissions'!G:G, "s/l-NEG") + COUNTIFS(Pollution!F:F, 2008, Pollution!G:G, "n") + COUNTIFS(Pollution!F:F, 2008, Pollution!G:G, "s/l-UNC") + COUNTIFS(Pollution!F:F, 2008, Pollution!G:G, "s/l-POS") + COUNTIFS(Pollution!F:F, 2008, Pollution!G:G, "s/l-NEG") + COUNTIFS('Energy|Power'!F:F, 2008, 'Energy|Power'!G:G, "n") + COUNTIFS('Energy|Power'!F:F, 2008, 'Energy|Power'!G:G, "s/l-UNC") + COUNTIFS('Energy|Power'!F:F, 2008, 'Energy|Power'!G:G, "s/l-POS") + COUNTIFS('Energy|Power'!F:F, 2008, 'Energy|Power'!G:G, "s/l-NEG") + COUNTIFS(Industry!F:F, 2008, Industry!G:G, "n") + COUNTIFS(Industry!F:F, 2008, Industry!G:G, "s/l-UNC") + COUNTIFS(Industry!F:F, 2008, Industry!G:G, "s/l-POS") + COUNTIFS(Industry!F:F, 2008, Industry!G:G, "s/l-NEG") + COUNTIFS(Buildings!F:F, 2008, Buildings!G:G, "n") + COUNTIFS(Buildings!F:F, 2008, Buildings!G:G, "s/l-UNC") + COUNTIFS(Buildings!F:F, 2008, Buildings!G:G, "s/l-POS") + COUNTIFS(Buildings!F:F, 2008, Buildings!G:G, "s/l-NEG") + COUNTIFS(Transport!F:F, 2008, Transport!G:G, "n") + COUNTIFS(Transport!F:F, 2008, Transport!G:G, "s/l-UNC") + COUNTIFS(Transport!F:F, 2008, Transport!G:G, "s/l-POS") + COUNTIFS(Transport!F:F, 2008, Transport!G:G, "s/l-NEG") + COUNTIFS(LULUCF!F:F, 2008, LULUCF!G:G, "n") + COUNTIFS(LULUCF!F:F, 2008, LULUCF!G:G, "s/l-UNC") + COUNTIFS(LULUCF!F:F, 2008, LULUCF!G:G, "s/l-POS") + COUNTIFS(LULUCF!F:F, 2008, LULUCF!G:G, "s/l-NEG") + COUNTIFS('Circular Economy'!F:F, 2008, 'Circular Economy'!G:G, "n") + COUNTIFS('Circular Economy'!F:F, 2008, 'Circular Economy'!G:G, "s/l-UNC") + COUNTIFS('Circular Economy'!F:F, 2008, 'Circular Economy'!G:G, "s/l-POS") + COUNTIFS('Circular Economy'!F:F, 2008, 'Circular Economy'!G:G, "s/l-NEG") + COUNTIFS(Finance!F:F, 2008, Finance!G:G, "n") + COUNTIFS(Finance!F:F, 2008, Finance!G:G, "s/l-UNC") + COUNTIFS(Finance!F:F, 2008, Finance!G:G, "s/l-POS") + COUNTIFS(Finance!F:F, 2008, Finance!G:G, "s/l-NEG") | Q7: Carbon intensity | R7: =COUNTIFS('GHG Emissions'!H:H, "Carbon intensity", 'GHG Emissions'!G:G, "n") + COUNTIFS('GHG Emissions'!H:H, "Carbon intensity", 'GHG Emissions'!G:G, "s/l-UNC") + COUNTIFS('GHG Emissions'!H:H, "Carbon intensity", 'GHG Emissions'!G:G, "s/l-POS") + COUNTIFS('GHG Emissions'!H:H, "Carbon intensity", 'GHG Emissions'!G:G, "s/l-NEG") + COUNTIFS(Pollution!H:H, "Carbon intensity", Pollution!G:G, "n") + COUNTIFS(Pollution!H:H, "Carbon intensity", Pollution!G:G, "s/l-UNC") + COUNTIFS(Pollution!H:H, "Carbon intensity", Pollution!G:G, "s/l-POS") + COUNTIFS(Pollution!H:H, "Carbon intensity", Pollution!G:G, "s/l-NEG") + COUNTIFS('Energy|Power'!H:H, "Carbon intensity", 'Energy|Power'!G:G, "n") + COUNTIFS('Energy|Power'!H:H, "Carbon intensity", 'Energy|Power'!G:G, "s/l-UNC") + COUNTIFS('Energy|Power'!H:H, "Carbon intensity", 'Energy|Power'!G:G, "s/l-POS") + COUNTIFS('Energy|Power'!H:H, "Carbon intensity", 'Energy|Power'!G:G, "s/l-NEG") + COUNTIFS(Industry!H:H, "Carbon intensity", Industry!G:G, "n") + COUNTIFS(Industry!H:H, "Carbon intensity", Industry!G:G, "s/l-UNC") + COUNTIFS(Industry!H:H, "Carbon intensity", Industry!G:G, "s/l-POS") + COUNTIFS(Industry!H:H, "Carbon intensity", Industry!G:G, "s/l-NEG") + COUNTIFS(Buildings!H:H, "Carbon intensity", Buildings!G:G, "n") + COUNTIFS(Buildings!H:H, "Carbon intensity", Buildings!G:G, "s/l-UNC") + COUNTIFS(Buildings!H:H, "Carbon intensity", Buildings!G:G, "s/l-POS") + COUNTIFS(Buildings!H:H, "Carbon intensity", Buildings!G:G, "s/l-NEG") + COUNTIFS(Transport!H:H, "Carbon intensity", Transport!G:G, "n") + COUNTIFS(Transport!H:H, "Carbon intensity", Transport!G:G, "s/l-UNC") + COUNTIFS(Transport!H:H, "Carbon intensity", Transport!G:G, "s/l-POS") + COUNTIFS(Transport!H:H, "Carbon intensity", Transport!G:G, "s/l-NEG") + COUNTIFS(LULUCF!H:H, "Carbon intensity", LULUCF!G:G, "n") + COUNTIFS(LULUCF!H:H, "Carbon intensity", LULUCF!G:G, "s/l-UNC") + COUNTIFS(LULUCF!H:H, "Carbon intensity", LULUCF!G:G, "s/l-POS") + COUNTIFS(LULUCF!H:H, "Carbon intensity", LULUCF!G:G, "s/l-NEG") + COUNTIFS('Circular Economy'!H:H, "Carbon intensity", 'Circular Economy'!G:G, "n") + COUNTIFS('Circular Economy'!H:H, "Carbon intensity", 'Circular Economy'!G:G, "s/l-UNC") + COUNTIFS('Circular Economy'!H:H, "Carbon intensity", 'Circular Economy'!G:G, "s/l-POS") + COUNTIFS('Circular Economy'!H:H, "Carbon intensity", 'Circular Economy'!G:G, "s/l-NEG") + COUNTIFS(Finance!H:H, "Carbon intensity", Finance!G:G, "n") + COUNTIFS(Finance!H:H, "Carbon intensity", Finance!G:G, "s/l-UNC") + COUNTIFS(Finance!H:H, "Carbon intensity", Finance!G:G, "s/l-POS") + COUNTIFS(Finance!H:H, "Carbon intensity", Finance!G:G, "s/l-NEG") | T7: Cities & areas | U7: =COUNTIFS('GHG Emissions'!I:I,"areas",'GHG Emissions'!G:G,"n") +COUNTIFS('GHG Emissions'!I:I,"areas",'GHG Emissions'!G:G,"s/l-UNC") +COUNTIFS('GHG Emissions'!I:I,"areas",'GHG Emissions'!G:G,"s/l-POS") +COUNTIFS('GHG Emissions'!I:I,"areas",'GHG Emissions'!G:G,"s/l-NEG") +COUNTIFS(Pollution!I:I,"areas",Pollution!G:G,"n") +COUNTIFS(Pollution!I:I,"areas",Pollution!G:G,"s/l-UNC") +COUNTIFS(Pollution!I:I,"areas",Pollution!G:G,"s/l-POS") +COUNTIFS(Pollution!I:I,"areas",Pollution!G:G,"s/l-NEG") +COUNTIFS('Energy|Power'!I:I,"areas",'Energy|Power'!G:G,"n") +COUNTIFS('Energy|Power'!I:I,"areas",'Energy|Power'!G:G,"s/l-UNC") +COUNTIFS('Energy|Power'!I:I,"areas",'Energy|Power'!G:G,"s/l-POS") +COUNTIFS('Energy|Power'!I:I,"areas",'Energy|Power'!G:G,"s/l-NEG") +COUNTIFS(Industry!I:I,"areas",Industry!G:G,"n") +COUNTIFS(Industry!I:I,"areas",Industry!G:G,"s/l-UNC") +COUNTIFS(Industry!I:I,"areas",Industry!G:G,"s/l-POS") +COUNTIFS(Industry!I:I,"areas",Industry!G:G,"s/l-NEG") +COUNTIFS(Buildings!I:I,"areas",Buildings!G:G,"n") +COUNTIFS(Buildings!I:I,"areas",Buildings!G:G,"s/l-UNC") +COUNTIFS(Buildings!I:I,"areas",Buildings!G:G,"s/l-POS") +COUNTIFS(Buildings!I:I,"areas",Buildings!G:G,"s/l-NEG") +COUNTIFS(Transport!I:I,"areas",Transport!G:G,"n") +COUNTIFS(Transport!I:I,"areas",Transport!G:G,"s/l-UNC") +COUNTIFS(Transport!I:I,"areas",Transport!G:G,"s/l-POS") +COUNTIFS(Transport!I:I,"areas",Transport!G:G,"s/l-NEG") +COUNTIFS(LULUCF!I:I,"areas",LULUCF!G:G,"n") +COUNTIFS(LULUCF!I:I,"areas",LULUCF!G:G,"s/l-UNC") +COUNTIFS(LULUCF!I:I,"areas",LULUCF!G:G,"s/l-POS") +COUNTIFS(LULUCF!I:I,"areas",LULUCF!G:G,"s/l-NEG") +COUNTIFS('Circular Economy'!I:I,"areas",'Circular Economy'!G:G,"n") +COUNTIFS('Circular Economy'!I:I,"areas",'Circular Economy'!G:G,"s/l-UNC") +COUNTIFS('Circular Economy'!I:I,"areas",'Circular Economy'!G:G,"s/l-POS") +COUNTIFS('Circular Economy'!I:I,"areas",'Circular Economy'!G:G,"s/l-NEG") +COUNTIFS(Finance!I:I,"areas",Finance!G:G,"n") +COUNTIFS(Finance!I:I,"areas",Finance!G:G,"s/l-UNC") +COUNTIFS(Finance!I:I,"areas",Finance!G:G,"s/l-POS") +COUNTIFS(Finance!I:I,"areas",Finance!G:G,"s/l-NEG")
B8: Energy/Power | C8: =COUNTIFS('Energy|Power'!G:G, "n") + COUNTIFS('Energy|Power'!G:G, "s/l-UNC") + COUNTIFS('Energy|Power'!G:G, "s/l-POS") + COUNTIFS('Energy|Power'!G:G, "s/l-NEG") | E8: Power transmission/Energy transportation | F8: =COUNTIFS('Energy|Power'!M:M, "Power transmission/Energy transportation") | H8: Strengthened or loosened target with positive climate impact | I8: =COUNTIF('GHG Emissions'!G:G,"s/l-POS") +COUNTIF(Pollution!G:G,"s/l-POS") +COUNTIF('Energy|Power'!G:G,"s/l-POS") +COUNTIF(Industry!G:G,"s/l-POS") +COUNTIF(Buildings!G:G,"s/l-POS") +COUNTIF(Transport!G:G,"s/l-POS") +COUNTIF(LULUCF!G:G,"s/l-POS") +COUNTIF('Circular Economy'!G:G,"s/l-POS") +COUNTIF(Finance!G:G,"s/l-POS") | K8: 2006 | L8: =COUNTIFS('GHG Emissions'!A:A, 2006, 'GHG Emissions'!G:G, "n") + COUNTIFS('GHG Emissions'!A:A, 2006, 'GHG Emissions'!G:G, "s/l-UNC") + COUNTIFS('GHG Emissions'!A:A, 2006, 'GHG Emissions'!G:G, "s/l-POS") + COUNTIFS('GHG Emissions'!A:A, 2006, 'GHG Emissions'!G:G, "s/l-NEG") + COUNTIFS(Pollution!A:A, 2006, Pollution!G:G, "n") + COUNTIFS(Pollution!A:A, 2006, Pollution!G:G, "s/l-UNC") + COUNTIFS(Pollution!A:A, 2006, Pollution!G:G, "s/l-POS") + COUNTIFS(Pollution!A:A, 2006, Pollution!G:G, "s/l-NEG") + COUNTIFS('Energy|Power'!A:A, 2006, 'Energy|Power'!G:G, "n") + COUNTIFS('Energy|Power'!A:A, 2006, 'Energy|Power'!G:G, "s/l-UNC") + COUNTIFS('Energy|Power'!A:A, 2006, 'Energy|Power'!G:G, "s/l-POS") + COUNTIFS('Energy|Power'!A:A, 2006, 'Energy|Power'!G:G, "s/l-NEG") + COUNTIFS(Industry!A:A, 2006, Industry!G:G, "n") + COUNTIFS(Industry!A:A, 2006, Industry!G:G, "s/l-UNC") + COUNTIFS(Industry!A:A, 2006, Industry!G:G, "s/l-POS") + COUNTIFS(Industry!A:A, 2006, Industry!G:G, "s/l-NEG") + COUNTIFS(Buildings!A:A, 2006, Buildings!G:G, "n") + COUNTIFS(Buildings!A:A, 2006, Buildings!G:G, "s/l-UNC") + COUNTIFS(Buildings!A:A, 2006, Buildings!G:G, "s/l-POS") + COUNTIFS(Buildings!A:A, 2006, Buildings!G:G, "s/l-NEG") + COUNTIFS(Transport!A:A, 2006, Transport!G:G, "n") + COUNTIFS(Transport!A:A, 2006, Transport!G:G, "s/l-UNC") + COUNTIFS(Transport!A:A, 2006, Transport!G:G, "s/l-POS") + COUNTIFS(Transport!A:A, 2006, Transport!G:G, "s/l-NEG") + COUNTIFS(LULUCF!A:A, 2006, LULUCF!G:G, "n") + COUNTIFS(LULUCF!A:A, 2006, LULUCF!G:G, "s/l-UNC") + COUNTIFS(LULUCF!A:A, 2006, LULUCF!G:G, "s/l-POS") + COUNTIFS(LULUCF!A:A, 2006, LULUCF!G:G, "s/l-NEG") + COUNTIFS('Circular Economy'!A:A, 2006, 'Circular Economy'!G:G, "n") + COUNTIFS('Circular Economy'!A:A, 2006, 'Circular Economy'!G:G, "s/l-UNC") + COUNTIFS('Circular Economy'!A:A, 2006, 'Circular Economy'!G:G, "s/l-POS") + COUNTIFS('Circular Economy'!A:A, 2006, 'Circular Economy'!G:G, "s/l-NEG") + COUNTIFS(Finance!A:A, 2006, Finance!G:G, "n") + COUNTIFS(Finance!A:A, 2006, Finance!G:G, "s/l-UNC") + COUNTIFS(Finance!A:A, 2006, Finance!G:G, "s/l-POS") + COUNTIFS(Finance!A:A, 2006, Finance!G:G, "s/l-NEG") | N8: 2010 | O8: =COUNTIFS('GHG Emissions'!F:F, 2010, 'GHG Emissions'!G:G, "n") + COUNTIFS('GHG Emissions'!F:F, 2010, 'GHG Emissions'!G:G, "s/l-UNC") + COUNTIFS('GHG Emissions'!F:F, 2010, 'GHG Emissions'!G:G, "s/l-POS") + COUNTIFS('GHG Emissions'!F:F, 2010, 'GHG Emissions'!G:G, "s/l-NEG") + COUNTIFS(Pollution!F:F, 2010, Pollution!G:G, "n") + COUNTIFS(Pollution!F:F, 2010, Pollution!G:G, "s/l-UNC") + COUNTIFS(Pollution!F:F, 2010, Pollution!G:G, "s/l-POS") + COUNTIFS(Pollution!F:F, 2010, Pollution!G:G, "s/l-NEG") + COUNTIFS('Energy|Power'!F:F, 2010, 'Energy|Power'!G:G, "n") + COUNTIFS('Energy|Power'!F:F, 2010, 'Energy|Power'!G:G, "s/l-UNC") + COUNTIFS('Energy|Power'!F:F, 2010, 'Energy|Power'!G:G, "s/l-POS") + COUNTIFS('Energy|Power'!F:F, 2010, 'Energy|Power'!G:G, "s/l-NEG") + COUNTIFS(Industry!F:F, 2010, Industry!G:G, "n") + COUNTIFS(Industry!F:F, 2010, Industry!G:G, "s/l-UNC") + COUNTIFS(Industry!F:F, 2010, Industry!G:G, "s/l-POS") + COUNTIFS(Industry!F:F, 2010, Industry!G:G, "s/l-NEG") + COUNTIFS(Buildings!F:F, 2010, Buildings!G:G, "n") + COUNTIFS(Buildings!F:F, 2010, Buildings!G:G, "s/l-UNC") + COUNTIFS(Buildings!F:F, 2010, Buildings!G:G, "s/l-POS") + COUNTIFS(Buildings!F:F, 2010, Buildings!G:G, "s/l-NEG") + COUNTIFS(Transport!F:F, 2010, Transport!G:G, "n") + COUNTIFS(Transport!F:F, 2010, Transport!G:G, "s/l-UNC") + COUNTIFS(Transport!F:F, 2010, Transport!G:G, "s/l-POS") + COUNTIFS(Transport!F:F, 2010, Transport!G:G, "s/l-NEG") + COUNTIFS(LULUCF!F:F, 2010, LULUCF!G:G, "n") + COUNTIFS(LULUCF!F:F, 2010, LULUCF!G:G, "s/l-UNC") + COUNTIFS(LULUCF!F:F, 2010, LULUCF!G:G, "s/l-POS") + COUNTIFS(LULUCF!F:F, 2010, LULUCF!G:G, "s/l-NEG") + COUNTIFS('Circular Economy'!F:F, 2010, 'Circular Economy'!G:G, "n") + COUNTIFS('Circular Economy'!F:F, 2010, 'Circular Economy'!G:G, "s/l-UNC") + COUNTIFS('Circular Economy'!F:F, 2010, 'Circular Economy'!G:G, "s/l-POS") + COUNTIFS('Circular Economy'!F:F, 2010, 'Circular Economy'!G:G, "s/l-NEG") + COUNTIFS(Finance!F:F, 2010, Finance!G:G, "n") + COUNTIFS(Finance!F:F, 2010, Finance!G:G, "s/l-UNC") + COUNTIFS(Finance!F:F, 2010, Finance!G:G, "s/l-POS") + COUNTIFS(Finance!F:F, 2010, Finance!G:G, "s/l-NEG") | Q8: Carbon sink | R8: =COUNTIFS('GHG Emissions'!H:H, "Carbon sink", 'GHG Emissions'!G:G, "n") + COUNTIFS('GHG Emissions'!H:H, "Carbon sink", 'GHG Emissions'!G:G, "s/l-UNC") + COUNTIFS('GHG Emissions'!H:H, "Carbon sink", 'GHG Emissions'!G:G, "s/l-POS") + COUNTIFS('GHG Emissions'!H:H, "Carbon sink", 'GHG Emissions'!G:G, "s/l-NEG") + COUNTIFS(Pollution!H:H, "Carbon sink", Pollution!G:G, "n") + COUNTIFS(Pollution!H:H, "Carbon sink", Pollution!G:G, "s/l-UNC") + COUNTIFS(Pollution!H:H, "Carbon sink", Pollution!G:G, "s/l-POS") + COUNTIFS(Pollution!H:H, "Carbon sink", Pollution!G:G, "s/l-NEG") + COUNTIFS('Energy|Power'!H:H, "Carbon sink", 'Energy|Power'!G:G, "n") + COUNTIFS('Energy|Power'!H:H, "Carbon sink", 'Energy|Power'!G:G, "s/l-UNC") + COUNTIFS('Energy|Power'!H:H, "Carbon sink", 'Energy|Power'!G:G, "s/l-POS") + COUNTIFS('Energy|Power'!H:H, "Carbon sink", 'Energy|Power'!G:G, "s/l-NEG") + COUNTIFS(Industry!H:H, "Carbon sink", Industry!G:G, "n") + COUNTIFS(Industry!H:H, "Carbon sink", Industry!G:G, "s/l-UNC") + COUNTIFS(Industry!H:H, "Carbon sink", Industry!G:G, "s/l-POS") + COUNTIFS(Industry!H:H, "Carbon sink", Industry!G:G, "s/l-NEG") + COUNTIFS(Buildings!H:H, "Carbon sink", Buildings!G:G, "n") + COUNTIFS(Buildings!H:H, "Carbon sink", Buildings!G:G, "s/l-UNC") + COUNTIFS(Buildings!H:H, "Carbon sink", Buildings!G:G, "s/l-POS") + COUNTIFS(Buildings!H:H, "Carbon sink", Buildings!G:G, "s/l-NEG") + COUNTIFS(Transport!H:H, "Carbon sink", Transport!G:G, "n") + COUNTIFS(Transport!H:H, "Carbon sink", Transport!G:G, "s/l-UNC") + COUNTIFS(Transport!H:H, "Carbon sink", Transport!G:G, "s/l-POS") + COUNTIFS(Transport!H:H, "Carbon sink", Transport!G:G, "s/l-NEG") + COUNTIFS(LULUCF!H:H, "Carbon sink", LULUCF!G:G, "n") + COUNTIFS(LULUCF!H:H, "Carbon sink", LULUCF!G:G, "s/l-UNC") + COUNTIFS(LULUCF!H:H, "Carbon sink", LULUCF!G:G, "s/l-POS") + COUNTIFS(LULUCF!H:H, "Carbon sink", LULUCF!G:G, "s/l-NEG") + COUNTIFS('Circular Economy'!H:H, "Carbon sink", 'Circular Economy'!G:G, "n") + COUNTIFS('Circular Economy'!H:H, "Carbon sink", 'Circular Economy'!G:G, "s/l-UNC") + COUNTIFS('Circular Economy'!H:H, "Carbon sink", 'Circular Economy'!G:G, "s/l-POS") + COUNTIFS('Circular Economy'!H:H, "Carbon sink", 'Circular Economy'!G:G, "s/l-NEG") + COUNTIFS(Finance!H:H, "Carbon sink", Finance!G:G, "n") + COUNTIFS(Finance!H:H, "Carbon sink", Finance!G:G, "s/l-UNC") + COUNTIFS(Finance!H:H, "Carbon sink", Finance!G:G, "s/l-POS") + COUNTIFS(Finance!H:H, "Carbon sink", Finance!G:G, "s/l-NEG") | T8: Sectors | U8: =COUNTIFS('GHG Emissions'!I:I,"sectors",'GHG Emissions'!G:G,"n") +COUNTIFS('GHG Emissions'!I:I,"sectors",'GHG Emissions'!G:G,"s/l-UNC") +COUNTIFS('GHG Emissions'!I:I,"sectors",'GHG Emissions'!G:G,"s/l-POS") +COUNTIFS('GHG Emissions'!I:I,"sectors",'GHG Emissions'!G:G,"s/l-NEG") +COUNTIFS(Pollution!I:I,"sectors",Pollution!G:G,"n") +COUNTIFS(Pollution!I:I,"sectors",Pollution!G:G,"s/l-UNC") +COUNTIFS(Pollution!I:I,"sectors",Pollution!G:G,"s/l-POS") +COUNTIFS(Pollution!I:I,"sectors",Pollution!G:G,"s/l-NEG") +COUNTIFS('Energy|Power'!I:I,"sectors",'Energy|Power'!G:G,"n") +COUNTIFS('Energy|Power'!I:I,"sectors",'Energy|Power'!G:G,"s/l-UNC") +COUNTIFS('Energy|Power'!I:I,"sectors",'Energy|Power'!G:G,"s/l-POS") +COUNTIFS('Energy|Power'!I:I,"sectors",'Energy|Power'!G:G,"s/l-NEG") +COUNTIFS(Industry!I:I,"sectors",Industry!G:G,"n") +COUNTIFS(Industry!I:I,"sectors",Industry!G:G,"s/l-UNC") +COUNTIFS(Industry!I:I,"sectors",Industry!G:G,"s/l-POS") +COUNTIFS(Industry!I:I,"sectors",Industry!G:G,"s/l-NEG") +COUNTIFS(Buildings!I:I,"sectors",Buildings!G:G,"n") +COUNTIFS(Buildings!I:I,"sectors",Buildings!G:G,"s/l-UNC") +COUNTIFS(Buildings!I:I,"sectors",Buildings!G:G,"s/l-POS") +COUNTIFS(Buildings!I:I,"sectors",Buildings!G:G,"s/l-NEG") +COUNTIFS(Transport!I:I,"sectors",Transport!G:G,"n") +COUNTIFS(Transport!I:I,"sectors",Transport!G:G,"s/l-UNC") +COUNTIFS(Transport!I:I,"sectors",Transport!G:G,"s/l-POS") +COUNTIFS(Transport!I:I,"sectors",Transport!G:G,"s/l-NEG") +COUNTIFS(LULUCF!I:I,"sectors",LULUCF!G:G,"n") +COUNTIFS(LULUCF!I:I,"sectors",LULUCF!G:G,"s/l-UNC") +COUNTIFS(LULUCF!I:I,"sectors",LULUCF!G:G,"s/l-POS") +COUNTIFS(LULUCF!I:I,"sectors",LULUCF!G:G,"s/l-NEG") +COUNTIFS('Circular Economy'!I:I,"sectors",'Circular Economy'!G:G,"n") +COUNTIFS('Circular Economy'!I:I,"sectors",'Circular Economy'!G:G,"s/l-UNC") +COUNTIFS('Circular Economy'!I:I,"sectors",'Circular Economy'!G:G,"s/l-POS") +COUNTIFS('Circular Economy'!I:I,"sectors",'Circular Economy'!G:G,"s/l-NEG") +COUNTIFS(Finance!I:I,"sectors",Finance!G:G,"n") +COUNTIFS(Finance!I:I,"sectors",Finance!G:G,"s/l-UNC") +COUNTIFS(Finance!I:I,"sectors",Finance!G:G,"s/l-POS") +COUNTIFS(Finance!I:I,"sectors",Finance!G:G,"s/l-NEG")
B9: Industry | C9: =COUNTIFS(Industry!G:G, "n") + COUNTIFS(Industry!G:G, "s/l-UNC") + COUNTIFS(Industry!G:G, "s/l-POS") + COUNTIFS(Industry!G:G, "s/l-NEG") | E9: Coal power | F9: =COUNTIFS('Energy|Power'!M:M, "Coal power") | H9: Strengthened or loosened target with negative climate impact | I9: =COUNTIF('GHG Emissions'!G:G,"s/l-NEG") +COUNTIF(Pollution!G:G,"s/l-NEG") +COUNTIF('Energy|Power'!G:G,"s/l-NEG") +COUNTIF(Industry!G:G,"s/l-NEG") +COUNTIF(Buildings!G:G,"s/l-NEG") +COUNTIF(Transport!G:G,"s/l-NEG") +COUNTIF(LULUCF!G:G,"s/l-NEG") +COUNTIF('Circular Economy'!G:G,"s/l-NEG") +COUNTIF(Finance!G:G,"s/l-NEG") | K9: 2007 | L9: =COUNTIFS('GHG Emissions'!A:A, 2007, 'GHG Emissions'!G:G, "n") + COUNTIFS('GHG Emissions'!A:A, 2007, 'GHG Emissions'!G:G, "s/l-UNC") + COUNTIFS('GHG Emissions'!A:A, 2007, 'GHG Emissions'!G:G, "s/l-POS") + COUNTIFS('GHG Emissions'!A:A, 2007, 'GHG Emissions'!G:G, "s/l-NEG") + COUNTIFS(Pollution!A:A, 2007, Pollution!G:G, "n") + COUNTIFS(Pollution!A:A, 2007, Pollution!G:G, "s/l-UNC") + COUNTIFS(Pollution!A:A, 2007, Pollution!G:G, "s/l-POS") + COUNTIFS(Pollution!A:A, 2007, Pollution!G:G, "s/l-NEG") + COUNTIFS('Energy|Power'!A:A, 2007, 'Energy|Power'!G:G, "n") + COUNTIFS('Energy|Power'!A:A, 2007, 'Energy|Power'!G:G, "s/l-UNC") + COUNTIFS('Energy|Power'!A:A, 2007, 'Energy|Power'!G:G, "s/l-POS") + COUNTIFS('Energy|Power'!A:A, 2007, 'Energy|Power'!G:G, "s/l-NEG") + COUNTIFS(Industry!A:A, 2007, Industry!G:G, "n") + COUNTIFS(Industry!A:A, 2007, Industry!G:G, "s/l-UNC") + COUNTIFS(Industry!A:A, 2007, Industry!G:G, "s/l-POS") + COUNTIFS(Industry!A:A, 2007, Industry!G:G, "s/l-NEG") + COUNTIFS(Buildings!A:A, 2007, Buildings!G:G, "n") + COUNTIFS(Buildings!A:A, 2007, Buildings!G:G, "s/l-UNC") + COUNTIFS(Buildings!A:A, 2007, Buildings!G:G, "s/l-POS") + COUNTIFS(Buildings!A:A, 2007, Buildings!G:G, "s/l-NEG") + COUNTIFS(Transport!A:A, 2007, Transport!G:G, "n") + COUNTIFS(Transport!A:A, 2007, Transport!G:G, "s/l-UNC") + COUNTIFS(Transport!A:A, 2007, Transport!G:G, "s/l-POS") + COUNTIFS(Transport!A:A, 2007, Transport!G:G, "s/l-NEG") + COUNTIFS(LULUCF!A:A, 2007, LULUCF!G:G, "n") + COUNTIFS(LULUCF!A:A, 2007, LULUCF!G:G, "s/l-UNC") + COUNTIFS(LULUCF!A:A, 2007, LULUCF!G:G, "s/l-POS") + COUNTIFS(LULUCF!A:A, 2007, LULUCF!G:G, "s/l-NEG") + COUNTIFS('Circular Economy'!A:A, 2007, 'Circular Economy'!G:G, "n") + COUNTIFS('Circular Economy'!A:A, 2007, 'Circular Economy'!G:G, "s/l-UNC") + COUNTIFS('Circular Economy'!A:A, 2007, 'Circular Economy'!G:G, "s/l-POS") + COUNTIFS('Circular Economy'!A:A, 2007, 'Circular Economy'!G:G, "s/l-NEG") + COUNTIFS(Finance!A:A, 2007, Finance!G:G, "n") + COUNTIFS(Finance!A:A, 2007, Finance!G:G, "s/l-UNC") + COUNTIFS(Finance!A:A, 2007, Finance!G:G, "s/l-POS") + COUNTIFS(Finance!A:A, 2007, Finance!G:G, "s/l-NEG") | N9: 11th FYP | O9: =COUNTIFS('GHG Emissions'!F:F, "11th FYP", 'GHG Emissions'!G:G, "n") + COUNTIFS('GHG Emissions'!F:F, "11th FYP", 'GHG Emissions'!G:G, "s/l-UNC") + COUNTIFS('GHG Emissions'!F:F, "11th FYP", 'GHG Emissions'!G:G, "s/l-POS") + COUNTIFS('GHG Emissions'!F:F, "11th FYP", 'GHG Emissions'!G:G, "s/l-NEG") + COUNTIFS(Pollution!F:F, "11th FYP", Pollution!G:G, "n") + COUNTIFS(Pollution!F:F, "11th FYP", Pollution!G:G, "s/l-UNC") + COUNTIFS(Pollution!F:F, "11th FYP", Pollution!G:G, "s/l-POS") + COUNTIFS(Pollution!F:F, "11th FYP", Pollution!G:G, "s/l-NEG") + COUNTIFS('Energy|Power'!F:F, "11th FYP", 'Energy|Power'!G:G, "n") + COUNTIFS('Energy|Power'!F:F, "11th FYP", 'Energy|Power'!G:G, "s/l-UNC") + COUNTIFS('Energy|Power'!F:F, "11th FYP", 'Energy|Power'!G:G, "s/l-POS") + COUNTIFS('Energy|Power'!F:F, "11th FYP", 'Energy|Power'!G:G, "s/l-NEG") + COUNTIFS(Industry!F:F, "11th FYP", Industry!G:G, "n") + COUNTIFS(Industry!F:F, "11th FYP", Industry!G:G, "s/l-UNC") + COUNTIFS(Industry!F:F, "11th FYP", Industry!G:G, "s/l-POS") + COUNTIFS(Industry!F:F, "11th FYP", Industry!G:G, "s/l-NEG") + COUNTIFS(Buildings!F:F, "11th FYP", Buildings!G:G, "n") + COUNTIFS(Buildings!F:F, "11th FYP", Buildings!G:G, "s/l-UNC") + COUNTIFS(Buildings!F:F, "11th FYP", Buildings!G:G, "s/l-POS") + COUNTIFS(Buildings!F:F, "11th FYP", Buildings!G:G, "s/l-NEG") + COUNTIFS(Transport!F:F, "11th FYP", Transport!G:G, "n") + COUNTIFS(Transport!F:F, "11th FYP", Transport!G:G, "s/l-UNC") + COUNTIFS(Transport!F:F, "11th FYP", Transport!G:G, "s/l-POS") + COUNTIFS(Transport!F:F, "11th FYP", Transport!G:G, "s/l-NEG") + COUNTIFS(LULUCF!F:F, "11th FYP", LULUCF!G:G, "n") + COUNTIFS(LULUCF!F:F, "11th FYP", LULUCF!G:G, "s/l-UNC") + COUNTIFS(LULUCF!F:F, "11th FYP", LULUCF!G:G, "s/l-POS") + COUNTIFS(LULUCF!F:F, "11th FYP", LULUCF!G:G, "s/l-NEG") + COUNTIFS('Circular Economy'!F:F, "11th FYP", 'Circular Economy'!G:G, "n") + COUNTIFS('Circular Economy'!F:F, "11th FYP", 'Circular Economy'!G:G, "s/l-UNC") + COUNTIFS('Circular Economy'!F:F, "11th FYP", 'Circular Economy'!G:G, "s/l-POS") + COUNTIFS('Circular Economy'!F:F, "11th FYP", 'Circular Economy'!G:G, "s/l-NEG") + COUNTIFS(Finance!F:F, "11th FYP", Finance!G:G, "n") + COUNTIFS(Finance!F:F, "11th FYP", Finance!G:G, "s/l-UNC") + COUNTIFS(Finance!F:F, "11th FYP", Finance!G:G, "s/l-POS") + COUNTIFS(Finance!F:F, "11th FYP", Finance!G:G, "s/l-NEG") | Q9: Pollution control | R9: =COUNTIFS('GHG Emissions'!H:H, "Pollution control", 'GHG Emissions'!G:G, "n") + COUNTIFS('GHG Emissions'!H:H, "Pollution control", 'GHG Emissions'!G:G, "s/l-UNC") + COUNTIFS('GHG Emissions'!H:H, "Pollution control", 'GHG Emissions'!G:G, "s/l-POS") + COUNTIFS('GHG Emissions'!H:H, "Pollution control", 'GHG Emissions'!G:G, "s/l-NEG") + COUNTIFS(Pollution!H:H, "Pollution control", Pollution!G:G, "n") + COUNTIFS(Pollution!H:H, "Pollution control", Pollution!G:G, "s/l-UNC") + COUNTIFS(Pollution!H:H, "Pollution control", Pollution!G:G, "s/l-POS") + COUNTIFS(Pollution!H:H, "Pollution control", Pollution!G:G, "s/l-NEG") + COUNTIFS('Energy|Power'!H:H, "Pollution control", 'Energy|Power'!G:G, "n") + COUNTIFS('Energy|Power'!H:H, "Pollution control", 'Energy|Power'!G:G, "s/l-UNC") + COUNTIFS('Energy|Power'!H:H, "Pollution control", 'Energy|Power'!G:G, "s/l-POS") + COUNTIFS('Energy|Power'!H:H, "Pollution control", 'Energy|Power'!G:G, "s/l-NEG") + COUNTIFS(Industry!H:H, "Pollution control", Industry!G:G, "n") + COUNTIFS(Industry!H:H, "Pollution control", Industry!G:G, "s/l-UNC") + COUNTIFS(Industry!H:H, "Pollution control", Industry!G:G, "s/l-POS") + COUNTIFS(Industry!H:H, "Pollution control", Industry!G:G, "s/l-NEG") + COUNTIFS(Buildings!H:H, "Pollution control", Buildings!G:G, "n") + COUNTIFS(Buildings!H:H, "Pollution control", Buildings!G:G, "s/l-UNC") + COUNTIFS(Buildings!H:H, "Pollution control", Buildings!G:G, "s/l-POS") + COUNTIFS(Buildings!H:H, "Pollution control", Buildings!G:G, "s/l-NEG") + COUNTIFS(Transport!H:H, "Pollution control", Transport!G:G, "n") + COUNTIFS(Transport!H:H, "Pollution control", Transport!G:G, "s/l-UNC") + COUNTIFS(Transport!H:H, "Pollution control", Transport!G:G, "s/l-POS") + COUNTIFS(Transport!H:H, "Pollution control", Transport!G:G, "s/l-NEG") + COUNTIFS(LULUCF!H:H, "Pollution control", LULUCF!G:G, "n") + COUNTIFS(LULUCF!H:H, "Pollution control", LULUCF!G:G, "s/l-UNC") + COUNTIFS(LULUCF!H:H, "Pollution control", LULUCF!G:G, "s/l-POS") + COUNTIFS(LULUCF!H:H, "Pollution control", LULUCF!G:G, "s/l-NEG") + COUNTIFS('Circular Economy'!H:H, "Pollution control", 'Circular Economy'!G:G, "n") + COUNTIFS('Circular Economy'!H:H, "Pollution control", 'Circular Economy'!G:G, "s/l-UNC") + COUNTIFS('Circular Economy'!H:H, "Pollution control", 'Circular Economy'!G:G, "s/l-POS") + COUNTIFS('Circular Economy'!H:H, "Pollution control", 'Circular Economy'!G:G, "s/l-NEG") + COUNTIFS(Finance!H:H, "Pollution control", Finance!G:G, "n") + COUNTIFS(Finance!H:H, "Pollution control", Finance!G:G, "s/l-UNC") + COUNTIFS(Finance!H:H, "Pollution control", Finance!G:G, "s/l-POS") + COUNTIFS(Finance!H:H, "Pollution control", Finance!G:G, "s/l-NEG") | T9: Whole economy | U9: =COUNTIFS('GHG Emissions'!I:I,"whole economy",'GHG Emissions'!G:G,"n") +COUNTIFS('GHG Emissions'!I:I,"whole economy",'GHG Emissions'!G:G,"s/l-UNC") +COUNTIFS('GHG Emissions'!I:I,"whole economy",'GHG Emissions'!G:G,"s/l-POS") +COUNTIFS('GHG Emissions'!I:I,"whole economy",'GHG Emissions'!G:G,"s/l-NEG") +COUNTIFS(Pollution!I:I,"whole economy",Pollution!G:G,"n") +COUNTIFS(Pollution!I:I,"whole economy",Pollution!G:G,"s/l-UNC") +COUNTIFS(Pollution!I:I,"whole economy",Pollution!G:G,"s/l-POS") +COUNTIFS(Pollution!I:I,"whole economy",Pollution!G:G,"s/l-NEG") +COUNTIFS('Energy|Power'!I:I,"whole economy",'Energy|Power'!G:G,"n") +COUNTIFS('Energy|Power'!I:I,"whole economy",'Energy|Power'!G:G,"s/l-UNC") +COUNTIFS('Energy|Power'!I:I,"whole economy",'Energy|Power'!G:G,"s/l-POS") +COUNTIFS('Energy|Power'!I:I,"whole economy",'Energy|Power'!G:G,"s/l-NEG") +COUNTIFS(Industry!I:I,"whole economy",Industry!G:G,"n") +COUNTIFS(Industry!I:I,"whole economy",Industry!G:G,"s/l-UNC") +COUNTIFS(Industry!I:I,"whole economy",Industry!G:G,"s/l-POS") +COUNTIFS(Industry!I:I,"whole economy",Industry!G:G,"s/l-NEG") +COUNTIFS(Buildings!I:I,"whole economy",Buildings!G:G,"n") +COUNTIFS(Buildings!I:I,"whole economy",Buildings!G:G,"s/l-UNC") +COUNTIFS(Buildings!I:I,"whole economy",Buildings!G:G,"s/l-POS") +COUNTIFS(Buildings!I:I,"whole economy",Buildings!G:G,"s/l-NEG") +COUNTIFS(Transport!I:I,"whole economy",Transport!G:G,"n") +COUNTIFS(Transport!I:I,"whole economy",Transport!G:G,"s/l-UNC") +COUNTIFS(Transport!I:I,"whole economy",Transport!G:G,"s/l-POS") +COUNTIFS(Transport!I:I,"whole economy",Transport!G:G,"s/l-NEG") +COUNTIFS(LULUCF!I:I,"whole economy",LULUCF!G:G,"n") +COUNTIFS(LULUCF!I:I,"whole economy",LULUCF!G:G,"s/l-UNC") +COUNTIFS(LULUCF!I:I,"whole economy",LULUCF!G:G,"s/l-POS") +COUNTIFS(LULUCF!I:I,"whole economy",LULUCF!G:G,"s/l-NEG") +COUNTIFS('Circular Economy'!I:I,"whole economy",'Circular Economy'!G:G,"n") +COUNTIFS('Circular Economy'!I:I,"whole economy",'Circular Economy'!G:G,"s/l-UNC") +COUNTIFS('Circular Economy'!I:I,"whole economy",'Circular Economy'!G:G,"s/l-POS") +COUNTIFS('Circular Economy'!I:I,"whole economy",'Circular Economy'!G:G,"s/l-NEG") +COUNTIFS(Finance!I:I,"whole economy",Finance!G:G,"n") +COUNTIFS(Finance!I:I,"whole economy",Finance!G:G,"s/l-UNC") +COUNTIFS(Finance!I:I,"whole economy",Finance!G:G,"s/l-POS") +COUNTIFS(Finance!I:I,"whole economy",Finance!G:G,"s/l-NEG")
B10: Buildings | C10: =COUNTIFS(Buildings!G:G, "n") + COUNTIFS(Buildings!G:G, "s/l-UNC") + COUNTIFS(Buildings!G:G, "s/l-POS") + COUNTIFS(Buildings!G:G, "s/l-NEG") | E10: Fossil fuel reserves | F10: =COUNTIFS('Energy|Power'!M:M, "Reserves") | K10: 2008 | L10: =COUNTIFS('GHG Emissions'!A:A, 2008, 'GHG Emissions'!G:G, "n") + COUNTIFS('GHG Emissions'!A:A, 2008, 'GHG Emissions'!G:G, "s/l-UNC") + COUNTIFS('GHG Emissions'!A:A, 2008, 'GHG Emissions'!G:G, "s/l-POS") + COUNTIFS('GHG Emissions'!A:A, 2008, 'GHG Emissions'!G:G, "s/l-NEG") + COUNTIFS(Pollution!A:A, 2008, Pollution!G:G, "n") + COUNTIFS(Pollution!A:A, 2008, Pollution!G:G, "s/l-UNC") + COUNTIFS(Pollution!A:A, 2008, Pollution!G:G, "s/l-POS") + COUNTIFS(Pollution!A:A, 2008, Pollution!G:G, "s/l-NEG") + COUNTIFS('Energy|Power'!A:A, 2008, 'Energy|Power'!G:G, "n") + COUNTIFS('Energy|Power'!A:A, 2008, 'Energy|Power'!G:G, "s/l-UNC") + COUNTIFS('Energy|Power'!A:A, 2008, 'Energy|Power'!G:G, "s/l-POS") + COUNTIFS('Energy|Power'!A:A, 2008, 'Energy|Power'!G:G, "s/l-NEG") + COUNTIFS(Industry!A:A, 2008, Industry!G:G, "n") + COUNTIFS(Industry!A:A, 2008, Industry!G:G, "s/l-UNC") + COUNTIFS(Industry!A:A, 2008, Industry!G:G, "s/l-POS") + COUNTIFS(Industry!A:A, 2008, Industry!G:G, "s/l-NEG") + COUNTIFS(Buildings!A:A, 2008, Buildings!G:G, "n") + COUNTIFS(Buildings!A:A, 2008, Buildings!G:G, "s/l-UNC") + COUNTIFS(Buildings!A:A, 2008, Buildings!G:G, "s/l-POS") + COUNTIFS(Buildings!A:A, 2008, Buildings!G:G, "s/l-NEG") + COUNTIFS(Transport!A:A, 2008, Transport!G:G, "n") + COUNTIFS(Transport!A:A, 2008, Transport!G:G, "s/l-UNC") + COUNTIFS(Transport!A:A, 2008, Transport!G:G, "s/l-POS") + COUNTIFS(Transport!A:A, 2008, Transport!G:G, "s/l-NEG") + COUNTIFS(LULUCF!A:A, 2008, LULUCF!G:G, "n") + COUNTIFS(LULUCF!A:A, 2008, LULUCF!G:G, "s/l-UNC") + COUNTIFS(LULUCF!A:A, 2008, LULUCF!G:G, "s/l-POS") + COUNTIFS(LULUCF!A:A, 2008, LULUCF!G:G, "s/l-NEG") + COUNTIFS('Circular Economy'!A:A, 2008, 'Circular Economy'!G:G, "n") + COUNTIFS('Circular Economy'!A:A, 2008, 'Circular Economy'!G:G, "s/l-UNC") + COUNTIFS('Circular Economy'!A:A, 2008, 'Circular Economy'!G:G, "s/l-POS") + COUNTIFS('Circular Economy'!A:A, 2008, 'Circular Economy'!G:G, "s/l-NEG") + COUNTIFS(Finance!A:A, 2008, Finance!G:G, "n") + COUNTIFS(Finance!A:A, 2008, Finance!G:G, "s/l-UNC") + COUNTIFS(Finance!A:A, 2008, Finance!G:G, "s/l-POS") + COUNTIFS(Finance!A:A, 2008, Finance!G:G, "s/l-NEG") | N10: 2011 | O10: =COUNTIFS('GHG Emissions'!F:F, 2011, 'GHG Emissions'!G:G, "n") + COUNTIFS('GHG Emissions'!F:F, 2011, 'GHG Emissions'!G:G, "s/l-UNC") + COUNTIFS('GHG Emissions'!F:F, 2011, 'GHG Emissions'!G:G, "s/l-POS") + COUNTIFS('GHG Emissions'!F:F, 2011, 'GHG Emissions'!G:G, "s/l-NEG") + COUNTIFS(Pollution!F:F, 2011, Pollution!G:G, "n") + COUNTIFS(Pollution!F:F, 2011, Pollution!G:G, "s/l-UNC") + COUNTIFS(Pollution!F:F, 2011, Pollution!G:G, "s/l-POS") + COUNTIFS(Pollution!F:F, 2011, Pollution!G:G, "s/l-NEG") + COUNTIFS('Energy|Power'!F:F, 2011, 'Energy|Power'!G:G, "n") + COUNTIFS('Energy|Power'!F:F, 2011, 'Energy|Power'!G:G, "s/l-UNC") + COUNTIFS('Energy|Power'!F:F, 2011, 'Energy|Power'!G:G, "s/l-POS") + COUNTIFS('Energy|Power'!F:F, 2011, 'Energy|Power'!G:G, "s/l-NEG") + COUNTIFS(Industry!F:F, 2011, Industry!G:G, "n") + COUNTIFS(Industry!F:F, 2011, Industry!G:G, "s/l-UNC") + COUNTIFS(Industry!F:F, 2011, Industry!G:G, "s/l-POS") + COUNTIFS(Industry!F:F, 2011, Industry!G:G, "s/l-NEG") + COUNTIFS(Buildings!F:F, 2011, Buildings!G:G, "n") + COUNTIFS(Buildings!F:F, 2011, Buildings!G:G, "s/l-UNC") + COUNTIFS(Buildings!F:F, 2011, Buildings!G:G, "s/l-POS") + COUNTIFS(Buildings!F:F, 2011, Buildings!G:G, "s/l-NEG") + COUNTIFS(Transport!F:F, 2011, Transport!G:G, "n") + COUNTIFS(Transport!F:F, 2011, Transport!G:G, "s/l-UNC") + COUNTIFS(Transport!F:F, 2011, Transport!G:G, "s/l-POS") + COUNTIFS(Transport!F:F, 2011, Transport!G:G, "s/l-NEG") + COUNTIFS(LULUCF!F:F, 2011, LULUCF!G:G, "n") + COUNTIFS(LULUCF!F:F, 2011, LULUCF!G:G, "s/l-UNC") + COUNTIFS(LULUCF!F:F, 2011, LULUCF!G:G, "s/l-POS") + COUNTIFS(LULUCF!F:F, 2011, LULUCF!G:G, "s/l-NEG") + COUNTIFS('Circular Economy'!F:F, 2011, 'Circular Economy'!G:G, "n") + COUNTIFS('Circular Economy'!F:F, 2011, 'Circular Economy'!G:G, "s/l-UNC") + COUNTIFS('Circular Economy'!F:F, 2011, 'Circular Economy'!G:G, "s/l-POS") + COUNTIFS('Circular Economy'!F:F, 2011, 'Circular Economy'!G:G, "s/l-NEG") + COUNTIFS(Finance!F:F, 2011, Finance!G:G, "n") + COUNTIFS(Finance!F:F, 2011, Finance!G:G, "s/l-UNC") + COUNTIFS(Finance!F:F, 2011, Finance!G:G, "s/l-POS") + COUNTIFS(Finance!F:F, 2011, Finance!G:G, "s/l-NEG") | Q10: Energy saving | R10: =COUNTIFS('GHG Emissions'!H:H, "Energy saving", 'GHG Emissions'!G:G, "n") + COUNTIFS('GHG Emissions'!H:H, "Energy saving", 'GHG Emissions'!G:G, "s/l-UNC") + COUNTIFS('GHG Emissions'!H:H, "Energy saving", 'GHG Emissions'!G:G, "s/l-POS") + COUNTIFS('GHG Emissions'!H:H, "Energy saving", 'GHG Emissions'!G:G, "s/l-NEG") + COUNTIFS(Pollution!H:H, "Energy saving", Pollution!G:G, "n") + COUNTIFS(Pollution!H:H, "Energy saving", Pollution!G:G, "s/l-UNC") + COUNTIFS(Pollution!H:H, "Energy saving", Pollution!G:G, "s/l-POS") + COUNTIFS(Pollution!H:H, "Energy saving", Pollution!G:G, "s/l-NEG") + COUNTIFS('Energy|Power'!H:H, "Energy saving", 'Energy|Power'!G:G, "n") + COUNTIFS('Energy|Power'!H:H, "Energy saving", 'Energy|Power'!G:G, "s/l-UNC") + COUNTIFS('Energy|Power'!H:H, "Energy saving", 'Energy|Power'!G:G, "s/l-POS") + COUNTIFS('Energy|Power'!H:H, "Energy saving", 'Energy|Power'!G:G, "s/l-NEG") + COUNTIFS(Industry!H:H, "Energy saving", Industry!G:G, "n") + COUNTIFS(Industry!H:H, "Energy saving", Industry!G:G, "s/l-UNC") + COUNTIFS(Industry!H:H, "Energy saving", Industry!G:G, "s/l-POS") + COUNTIFS(Industry!H:H, "Energy saving", Industry!G:G, "s/l-NEG") + COUNTIFS(Buildings!H:H, "Energy saving", Buildings!G:G, "n") + COUNTIFS(Buildings!H:H, "Energy saving", Buildings!G:G, "s/l-UNC") + COUNTIFS(Buildings!H:H, "Energy saving", Buildings!G:G, "s/l-POS") + COUNTIFS(Buildings!H:H, "Energy saving", Buildings!G:G, "s/l-NEG") + COUNTIFS(Transport!H:H, "Energy saving", Transport!G:G, "n") + COUNTIFS(Transport!H:H, "Energy saving", Transport!G:G, "s/l-UNC") + COUNTIFS(Transport!H:H, "Energy saving", Transport!G:G, "s/l-POS") + COUNTIFS(Transport!H:H, "Energy saving", Transport!G:G, "s/l-NEG") + COUNTIFS(LULUCF!H:H, "Energy saving", LULUCF!G:G, "n") + COUNTIFS(LULUCF!H:H, "Energy saving", LULUCF!G:G, "s/l-UNC") + COUNTIFS(LULUCF!H:H, "Energy saving", LULUCF!G:G, "s/l-POS") + COUNTIFS(LULUCF!H:H, "Energy saving", LULUCF!G:G, "s/l-NEG") + COUNTIFS('Circular Economy'!H:H, "Energy saving", 'Circular Economy'!G:G, "n") + COUNTIFS('Circular Economy'!H:H, "Energy saving", 'Circular Economy'!G:G, "s/l-UNC") + COUNTIFS('Circular Economy'!H:H, "Energy saving", 'Circular Economy'!G:G, "s/l-POS") + COUNTIFS('Circular Economy'!H:H, "Energy saving", 'Circular Economy'!G:G, "s/l-NEG") + COUNTIFS(Finance!H:H, "Energy saving", Finance!G:G, "n") + COUNTIFS(Finance!H:H, "Energy saving", Finance!G:G, "s/l-UNC") + COUNTIFS(Finance!H:H, "Energy saving", Finance!G:G, "s/l-POS") + COUNTIFS(Finance!H:H, "Energy saving", Finance!G:G, "s/l-NEG") | T10: Unclear | U10: =COUNTIFS('GHG Emissions'!I:I,"unclear",'GHG Emissions'!G:G,"n") +COUNTIFS('GHG Emissions'!I:I,"unclear",'GHG Emissions'!G:G,"s/l-UNC") +COUNTIFS('GHG Emissions'!I:I,"unclear",'GHG Emissions'!G:G,"s/l-POS") +COUNTIFS('GHG Emissions'!I:I,"unclear",'GHG Emissions'!G:G,"s/l-NEG") +COUNTIFS(Pollution!I:I,"unclear",Pollution!G:G,"n") +COUNTIFS(Pollution!I:I,"unclear",Pollution!G:G,"s/l-UNC") +COUNTIFS(Pollution!I:I,"unclear",Pollution!G:G,"s/l-POS") +COUNTIFS(Pollution!I:I,"unclear",Pollution!G:G,"s/l-NEG") +COUNTIFS('Energy|Power'!I:I,"unclear",'Energy|Power'!G:G,"n") +COUNTIFS('Energy|Power'!I:I,"unclear",'Energy|Power'!G:G,"s/l-UNC") +COUNTIFS('Energy|Power'!I:I,"unclear",'Energy|Power'!G:G,"s/l-POS") +COUNTIFS('Energy|Power'!I:I,"unclear",'Energy|Power'!G:G,"s/l-NEG") +COUNTIFS(Industry!I:I,"unclear",Industry!G:G,"n") +COUNTIFS(Industry!I:I,"unclear",Industry!G:G,"s/l-UNC") +COUNTIFS(Industry!I:I,"unclear",Industry!G:G,"s/l-POS") +COUNTIFS(Industry!I:I,"unclear",Industry!G:G,"s/l-NEG") +COUNTIFS(Buildings!I:I,"unclear",Buildings!G:G,"n") +COUNTIFS(Buildings!I:I,"unclear",Buildings!G:G,"s/l-UNC") +COUNTIFS(Buildings!I:I,"unclear",Buildings!G:G,"s/l-POS") +COUNTIFS(Buildings!I:I,"unclear",Buildings!G:G,"s/l-NEG") +COUNTIFS(Transport!I:I,"unclear",Transport!G:G,"n") +COUNTIFS(Transport!I:I,"unclear",Transport!G:G,"s/l-UNC") +COUNTIFS(Transport!I:I,"unclear",Transport!G:G,"s/l-POS") +COUNTIFS(Transport!I:I,"unclear",Transport!G:G,"s/l-NEG") +COUNTIFS(LULUCF!I:I,"unclear",LULUCF!G:G,"n") +COUNTIFS(LULUCF!I:I,"unclear",LULUCF!G:G,"s/l-UNC") +COUNTIFS(LULUCF!I:I,"unclear",LULUCF!G:G,"s/l-POS") +COUNTIFS(LULUCF!I:I,"unclear",LULUCF!G:G,"s/l-NEG") +COUNTIFS('Circular Economy'!I:I,"unclear",'Circular Economy'!G:G,"n") +COUNTIFS('Circular Economy'!I:I,"unclear",'Circular Economy'!G:G,"s/l-UNC") +COUNTIFS('Circular Economy'!I:I,"unclear",'Circular Economy'!G:G,"s/l-POS") +COUNTIFS('Circular Economy'!I:I,"unclear",'Circular Economy'!G:G,"s/l-NEG") +COUNTIFS(Finance!I:I,"unclear",Finance!G:G,"n") +COUNTIFS(Finance!I:I,"unclear",Finance!G:G,"s/l-UNC") +COUNTIFS(Finance!I:I,"unclear",Finance!G:G,"s/l-POS") +COUNTIFS(Finance!I:I,"unclear",Finance!G:G,"s/l-NEG")
B11: Transport | C11: =COUNTIFS(Transport!G:G, "n") + COUNTIFS(Transport!G:G, "s/l-UNC") + COUNTIFS(Transport!G:G, "s/l-POS") + COUNTIFS(Transport!G:G, "s/l-NEG") | E11: Other | F11: =COUNTIFS('Energy|Power'!M:M, "Other") | K11: 2009 | L11: =COUNTIFS('GHG Emissions'!A:A, 2009, 'GHG Emissions'!G:G, "n") + COUNTIFS('GHG Emissions'!A:A, 2009, 'GHG Emissions'!G:G, "s/l-UNC") + COUNTIFS('GHG Emissions'!A:A, 2009, 'GHG Emissions'!G:G, "s/l-POS") + COUNTIFS('GHG Emissions'!A:A, 2009, 'GHG Emissions'!G:G, "s/l-NEG") + COUNTIFS(Pollution!A:A, 2009, Pollution!G:G, "n") + COUNTIFS(Pollution!A:A, 2009, Pollution!G:G, "s/l-UNC") + COUNTIFS(Pollution!A:A, 2009, Pollution!G:G, "s/l-POS") + COUNTIFS(Pollution!A:A, 2009, Pollution!G:G, "s/l-NEG") + COUNTIFS('Energy|Power'!A:A, 2009, 'Energy|Power'!G:G, "n") + COUNTIFS('Energy|Power'!A:A, 2009, 'Energy|Power'!G:G, "s/l-UNC") + COUNTIFS('Energy|Power'!A:A, 2009, 'Energy|Power'!G:G, "s/l-POS") + COUNTIFS('Energy|Power'!A:A, 2009, 'Energy|Power'!G:G, "s/l-NEG") + COUNTIFS(Industry!A:A, 2009, Industry!G:G, "n") + COUNTIFS(Industry!A:A, 2009, Industry!G:G, "s/l-UNC") + COUNTIFS(Industry!A:A, 2009, Industry!G:G, "s/l-POS") + COUNTIFS(Industry!A:A, 2009, Industry!G:G, "s/l-NEG") + COUNTIFS(Buildings!A:A, 2009, Buildings!G:G, "n") + COUNTIFS(Buildings!A:A, 2009, Buildings!G:G, "s/l-UNC") + COUNTIFS(Buildings!A:A, 2009, Buildings!G:G, "s/l-POS") + COUNTIFS(Buildings!A:A, 2009, Buildings!G:G, "s/l-NEG") + COUNTIFS(Transport!A:A, 2009, Transport!G:G, "n") + COUNTIFS(Transport!A:A, 2009, Transport!G:G, "s/l-UNC") + COUNTIFS(Transport!A:A, 2009, Transport!G:G, "s/l-POS") + COUNTIFS(Transport!A:A, 2009, Transport!G:G, "s/l-NEG") + COUNTIFS(LULUCF!A:A, 2009, LULUCF!G:G, "n") + COUNTIFS(LULUCF!A:A, 2009, LULUCF!G:G, "s/l-UNC") + COUNTIFS(LULUCF!A:A, 2009, LULUCF!G:G, "s/l-POS") + COUNTIFS(LULUCF!A:A, 2009, LULUCF!G:G, "s/l-NEG") + COUNTIFS('Circular Economy'!A:A, 2009, 'Circular Economy'!G:G, "n") + COUNTIFS('Circular Economy'!A:A, 2009, 'Circular Economy'!G:G, "s/l-UNC") + COUNTIFS('Circular Economy'!A:A, 2009, 'Circular Economy'!G:G, "s/l-POS") + COUNTIFS('Circular Economy'!A:A, 2009, 'Circular Economy'!G:G, "s/l-NEG") + COUNTIFS(Finance!A:A, 2009, Finance!G:G, "n") + COUNTIFS(Finance!A:A, 2009, Finance!G:G, "s/l-UNC") + COUNTIFS(Finance!A:A, 2009, Finance!G:G, "s/l-POS") + COUNTIFS(Finance!A:A, 2009, Finance!G:G, "s/l-NEG") | N11: 2014 | O11: =COUNTIFS('GHG Emissions'!F:F, 2014, 'GHG Emissions'!G:G, "n") + COUNTIFS('GHG Emissions'!F:F, 2014, 'GHG Emissions'!G:G, "s/l-UNC") + COUNTIFS('GHG Emissions'!F:F, 2014, 'GHG Emissions'!G:G, "s/l-POS") + COUNTIFS('GHG Emissions'!F:F, 2014, 'GHG Emissions'!G:G, "s/l-NEG") + COUNTIFS(Pollution!F:F, 2014, Pollution!G:G, "n") + COUNTIFS(Pollution!F:F, 2014, Pollution!G:G, "s/l-UNC") + COUNTIFS(Pollution!F:F, 2014, Pollution!G:G, "s/l-POS") + COUNTIFS(Pollution!F:F, 2014, Pollution!G:G, "s/l-NEG") + COUNTIFS('Energy|Power'!F:F, 2014, 'Energy|Power'!G:G, "n") + COUNTIFS('Energy|Power'!F:F, 2014, 'Energy|Power'!G:G, "s/l-UNC") + COUNTIFS('Energy|Power'!F:F, 2014, 'Energy|Power'!G:G, "s/l-POS") + COUNTIFS('Energy|Power'!F:F, 2014, 'Energy|Power'!G:G, "s/l-NEG") + COUNTIFS(Industry!F:F, 2014, Industry!G:G, "n") + COUNTIFS(Industry!F:F, 2014, Industry!G:G, "s/l-UNC") + COUNTIFS(Industry!F:F, 2014, Industry!G:G, "s/l-POS") + COUNTIFS(Industry!F:F, 2014, Industry!G:G, "s/l-NEG") + COUNTIFS(Buildings!F:F, 2014, Buildings!G:G, "n") + COUNTIFS(Buildings!F:F, 2014, Buildings!G:G, "s/l-UNC") + COUNTIFS(Buildings!F:F, 2014, Buildings!G:G, "s/l-POS") + COUNTIFS(Buildings!F:F, 2014, Buildings!G:G, "s/l-NEG") + COUNTIFS(Transport!F:F, 2014, Transport!G:G, "n") + COUNTIFS(Transport!F:F, 2014, Transport!G:G, "s/l-UNC") + COUNTIFS(Transport!F:F, 2014, Transport!G:G, "s/l-POS") + COUNTIFS(Transport!F:F, 2014, Transport!G:G, "s/l-NEG") + COUNTIFS(LULUCF!F:F, 2014, LULUCF!G:G, "n") + COUNTIFS(LULUCF!F:F, 2014, LULUCF!G:G, "s/l-UNC") + COUNTIFS(LULUCF!F:F, 2014, LULUCF!G:G, "s/l-POS") + COUNTIFS(LULUCF!F:F, 2014, LULUCF!G:G, "s/l-NEG") + COUNTIFS('Circular Economy'!F:F, 2014, 'Circular Economy'!G:G, "n") + COUNTIFS('Circular Economy'!F:F, 2014, 'Circular Economy'!G:G, "s/l-UNC") + COUNTIFS('Circular Economy'!F:F, 2014, 'Circular Economy'!G:G, "s/l-POS") + COUNTIFS('Circular Economy'!F:F, 2014, 'Circular Economy'!G:G, "s/l-NEG") + COUNTIFS(Finance!F:F, 2014, Finance!G:G, "n") + COUNTIFS(Finance!F:F, 2014, Finance!G:G, "s/l-UNC") + COUNTIFS(Finance!F:F, 2014, Finance!G:G, "s/l-POS") + COUNTIFS(Finance!F:F, 2014, Finance!G:G, "s/l-NEG") | Q11: Energy efficiency | R11: =COUNTIFS('GHG Emissions'!H:H, "Energy efficiency", 'GHG Emissions'!G:G, "n") + COUNTIFS('GHG Emissions'!H:H, "Energy efficiency", 'GHG Emissions'!G:G, "s/l-UNC") + COUNTIFS('GHG Emissions'!H:H, "Energy efficiency", 'GHG Emissions'!G:G, "s/l-POS") + COUNTIFS('GHG Emissions'!H:H, "Energy efficiency", 'GHG Emissions'!G:G, "s/l-NEG") + COUNTIFS(Pollution!H:H, "Energy efficiency", Pollution!G:G, "n") + COUNTIFS(Pollution!H:H, "Energy efficiency", Pollution!G:G, "s/l-UNC") + COUNTIFS(Pollution!H:H, "Energy efficiency", Pollution!G:G, "s/l-POS") + COUNTIFS(Pollution!H:H, "Energy efficiency", Pollution!G:G, "s/l-NEG") + COUNTIFS('Energy|Power'!H:H, "Energy efficiency", 'Energy|Power'!G:G, "n") + COUNTIFS('Energy|Power'!H:H, "Energy efficiency", 'Energy|Power'!G:G, "s/l-UNC") + COUNTIFS('Energy|Power'!H:H, "Energy efficiency", 'Energy|Power'!G:G, "s/l-POS") + COUNTIFS('Energy|Power'!H:H, "Energy efficiency", 'Energy|Power'!G:G, "s/l-NEG") + COUNTIFS(Industry!H:H, "Energy efficiency", Industry!G:G, "n") + COUNTIFS(Industry!H:H, "Energy efficiency", Industry!G:G, "s/l-UNC") + COUNTIFS(Industry!H:H, "Energy efficiency", Industry!G:G, "s/l-POS") + COUNTIFS(Industry!H:H, "Energy efficiency", Industry!G:G, "s/l-NEG") + COUNTIFS(Buildings!H:H, "Energy efficiency", Buildings!G:G, "n") + COUNTIFS(Buildings!H:H, "Energy efficiency", Buildings!G:G, "s/l-UNC") + COUNTIFS(Buildings!H:H, "Energy efficiency", Buildings!G:G, "s/l-POS") + COUNTIFS(Buildings!H:H, "Energy efficiency", Buildings!G:G, "s/l-NEG") + COUNTIFS(Transport!H:H, "Energy efficiency", Transport!G:G, "n") + COUNTIFS(Transport!H:H, "Energy efficiency", Transport!G:G, "s/l-UNC") + COUNTIFS(Transport!H:H, "Energy efficiency", Transport!G:G, "s/l-POS") + COUNTIFS(Transport!H:H, "Energy efficiency", Transport!G:G, "s/l-NEG") + COUNTIFS(LULUCF!H:H, "Energy efficiency", LULUCF!G:G, "n") + COUNTIFS(LULUCF!H:H, "Energy efficiency", LULUCF!G:G, "s/l-UNC") + COUNTIFS(LULUCF!H:H, "Energy efficiency", LULUCF!G:G, "s/l-POS") + COUNTIFS(LULUCF!H:H, "Energy efficiency", LULUCF!G:G, "s/l-NEG") + COUNTIFS('Circular Economy'!H:H, "Energy efficiency", 'Circular Economy'!G:G, "n") + COUNTIFS('Circular Economy'!H:H, "Energy efficiency", 'Circular Economy'!G:G, "s/l-UNC") + COUNTIFS('Circular Economy'!H:H, "Energy efficiency", 'Circular Economy'!G:G, "s/l-POS") + COUNTIFS('Circular Economy'!H:H, "Energy efficiency", 'Circular Economy'!G:G, "s/l-NEG") + COUNTIFS(Finance!H:H, "Energy efficiency", Finance!G:G, "n") + COUNTIFS(Finance!H:H, "Energy efficiency", Finance!G:G, "s/l-UNC") + COUNTIFS(Finance!H:H, "Energy efficiency", Finance!G:G, "s/l-POS") + COUNTIFS(Finance!H:H, "Energy efficiency", Finance!G:G, "s/l-NEG")
B12: LULUCF | C12: =COUNTIFS(LULUCF!G:G, "n") + COUNTIFS(LULUCF!G:G, "s/l-UNC") + COUNTIFS(LULUCF!G:G, "s/l-POS") + COUNTIFS(LULUCF!G:G, "s/l-NEG") | K12: 2010 | L12: =COUNTIFS('GHG Emissions'!A:A, 2010, 'GHG Emissions'!G:G, "n") + COUNTIFS('GHG Emissions'!A:A, 2010, 'GHG Emissions'!G:G, "s/l-UNC") + COUNTIFS('GHG Emissions'!A:A, 2010, 'GHG Emissions'!G:G, "s/l-POS") + COUNTIFS('GHG Emissions'!A:A, 2010, 'GHG Emissions'!G:G, "s/l-NEG") + COUNTIFS(Pollution!A:A, 2010, Pollution!G:G, "n") + COUNTIFS(Pollution!A:A, 2010, Pollution!G:G, "s/l-UNC") + COUNTIFS(Pollution!A:A, 2010, Pollution!G:G, "s/l-POS") + COUNTIFS(Pollution!A:A, 2010, Pollution!G:G, "s/l-NEG") + COUNTIFS('Energy|Power'!A:A, 2010, 'Energy|Power'!G:G, "n") + COUNTIFS('Energy|Power'!A:A, 2010, 'Energy|Power'!G:G, "s/l-UNC") + COUNTIFS('Energy|Power'!A:A, 2010, 'Energy|Power'!G:G, "s/l-POS") + COUNTIFS('Energy|Power'!A:A, 2010, 'Energy|Power'!G:G, "s/l-NEG") + COUNTIFS(Industry!A:A, 2010, Industry!G:G, "n") + COUNTIFS(Industry!A:A, 2010, Industry!G:G, "s/l-UNC") + COUNTIFS(Industry!A:A, 2010, Industry!G:G, "s/l-POS") + COUNTIFS(Industry!A:A, 2010, Industry!G:G, "s/l-NEG") + COUNTIFS(Buildings!A:A, 2010, Buildings!G:G, "n") + COUNTIFS(Buildings!A:A, 2010, Buildings!G:G, "s/l-UNC") + COUNTIFS(Buildings!A:A, 2010, Buildings!G:G, "s/l-POS") + COUNTIFS(Buildings!A:A, 2010, Buildings!G:G, "s/l-NEG") + COUNTIFS(Transport!A:A, 2010, Transport!G:G, "n") + COUNTIFS(Transport!A:A, 2010, Transport!G:G, "s/l-UNC") + COUNTIFS(Transport!A:A, 2010, Transport!G:G, "s/l-POS") + COUNTIFS(Transport!A:A, 2010, Transport!G:G, "s/l-NEG") + COUNTIFS(LULUCF!A:A, 2010, LULUCF!G:G, "n") + COUNTIFS(LULUCF!A:A, 2010, LULUCF!G:G, "s/l-UNC") + COUNTIFS(LULUCF!A:A, 2010, LULUCF!G:G, "s/l-POS") + COUNTIFS(LULUCF!A:A, 2010, LULUCF!G:G, "s/l-NEG") + COUNTIFS('Circular Economy'!A:A, 2010, 'Circular Economy'!G:G, "n") + COUNTIFS('Circular Economy'!A:A, 2010, 'Circular Economy'!G:G, "s/l-UNC") + COUNTIFS('Circular Economy'!A:A, 2010, 'Circular Economy'!G:G, "s/l-POS") + COUNTIFS('Circular Economy'!A:A, 2010, 'Circular Economy'!G:G, "s/l-NEG") + COUNTIFS(Finance!A:A, 2010, Finance!G:G, "n") + COUNTIFS(Finance!A:A, 2010, Finance!G:G, "s/l-UNC") + COUNTIFS(Finance!A:A, 2010, Finance!G:G, "s/l-POS") + COUNTIFS(Finance!A:A, 2010, Finance!G:G, "s/l-NEG") | N12: 2015 | O12: =COUNTIFS('GHG Emissions'!F:F, 2015, 'GHG Emissions'!G:G, "n") + COUNTIFS('GHG Emissions'!F:F, 2015, 'GHG Emissions'!G:G, "s/l-UNC") + COUNTIFS('GHG Emissions'!F:F, 2015, 'GHG Emissions'!G:G, "s/l-POS") + COUNTIFS('GHG Emissions'!F:F, 2015, 'GHG Emissions'!G:G, "s/l-NEG") + COUNTIFS(Pollution!F:F, 2015, Pollution!G:G, "n") + COUNTIFS(Pollution!F:F, 2015, Pollution!G:G, "s/l-UNC") + COUNTIFS(Pollution!F:F, 2015, Pollution!G:G, "s/l-POS") + COUNTIFS(Pollution!F:F, 2015, Pollution!G:G, "s/l-NEG") + COUNTIFS('Energy|Power'!F:F, 2015, 'Energy|Power'!G:G, "n") + COUNTIFS('Energy|Power'!F:F, 2015, 'Energy|Power'!G:G, "s/l-UNC") + COUNTIFS('Energy|Power'!F:F, 2015, 'Energy|Power'!G:G, "s/l-POS") + COUNTIFS('Energy|Power'!F:F, 2015, 'Energy|Power'!G:G, "s/l-NEG") + COUNTIFS(Industry!F:F, 2015, Industry!G:G, "n") + COUNTIFS(Industry!F:F, 2015, Industry!G:G, "s/l-UNC") + COUNTIFS(Industry!F:F, 2015, Industry!G:G, "s/l-POS") + COUNTIFS(Industry!F:F, 2015, Industry!G:G, "s/l-NEG") + COUNTIFS(Buildings!F:F, 2015, Buildings!G:G, "n") + COUNTIFS(Buildings!F:F, 2015, Buildings!G:G, "s/l-UNC") + COUNTIFS(Buildings!F:F, 2015, Buildings!G:G, "s/l-POS") + COUNTIFS(Buildings!F:F, 2015, Buildings!G:G, "s/l-NEG") + COUNTIFS(Transport!F:F, 2015, Transport!G:G, "n") + COUNTIFS(Transport!F:F, 2015, Transport!G:G, "s/l-UNC") + COUNTIFS(Transport!F:F, 2015, Transport!G:G, "s/l-POS") + COUNTIFS(Transport!F:F, 2015, Transport!G:G, "s/l-NEG") + COUNTIFS(LULUCF!F:F, 2015, LULUCF!G:G, "n") + COUNTIFS(LULUCF!F:F, 2015, LULUCF!G:G, "s/l-UNC") + COUNTIFS(LULUCF!F:F, 2015, LULUCF!G:G, "s/l-POS") + COUNTIFS(LULUCF!F:F, 2015, LULUCF!G:G, "s/l-NEG") + COUNTIFS('Circular Economy'!F:F, 2015, 'Circular Economy'!G:G, "n") + COUNTIFS('Circular Economy'!F:F, 2015, 'Circular Economy'!G:G, "s/l-UNC") + COUNTIFS('Circular Economy'!F:F, 2015, 'Circular Economy'!G:G, "s/l-POS") + COUNTIFS('Circular Economy'!F:F, 2015, 'Circular Economy'!G:G, "s/l-NEG") + COUNTIFS(Finance!F:F, 2015, Finance!G:G, "n") + COUNTIFS(Finance!F:F, 2015, Finance!G:G, "s/l-UNC") + COUNTIFS(Finance!F:F, 2015, Finance!G:G, "s/l-POS") + COUNTIFS(Finance!F:F, 2015, Finance!G:G, "s/l-NEG") | Q12: Resource efficiency | R12: =COUNTIFS('GHG Emissions'!H:H, "Resource efficiency", 'GHG Emissions'!G:G, "n") + COUNTIFS('GHG Emissions'!H:H, "Resource efficiency", 'GHG Emissions'!G:G, "s/l-UNC") + COUNTIFS('GHG Emissions'!H:H, "Resource efficiency", 'GHG Emissions'!G:G, "s/l-POS") + COUNTIFS('GHG Emissions'!H:H, "Resource efficiency", 'GHG Emissions'!G:G, "s/l-NEG") + COUNTIFS(Pollution!H:H, "Resource efficiency", Pollution!G:G, "n") + COUNTIFS(Pollution!H:H, "Resource efficiency", Pollution!G:G, "s/l-UNC") + COUNTIFS(Pollution!H:H, "Resource efficiency", Pollution!G:G, "s/l-POS") + COUNTIFS(Pollution!H:H, "Resource efficiency", Pollution!G:G, "s/l-NEG") + COUNTIFS('Energy|Power'!H:H, "Resource efficiency", 'Energy|Power'!G:G, "n") + COUNTIFS('Energy|Power'!H:H, "Resource efficiency", 'Energy|Power'!G:G, "s/l-UNC") + COUNTIFS('Energy|Power'!H:H, "Resource efficiency", 'Energy|Power'!G:G, "s/l-POS") + COUNTIFS('Energy|Power'!H:H, "Resource efficiency", 'Energy|Power'!G:G, "s/l-NEG") + COUNTIFS(Industry!H:H, "Resource efficiency", Industry!G:G, "n") + COUNTIFS(Industry!H:H, "Resource efficiency", Industry!G:G, "s/l-UNC") + COUNTIFS(Industry!H:H, "Resource efficiency", Industry!G:G, "s/l-POS") + COUNTIFS(Industry!H:H, "Resource efficiency", Industry!G:G, "s/l-NEG") + COUNTIFS(Buildings!H:H, "Resource efficiency", Buildings!G:G, "n") + COUNTIFS(Buildings!H:H, "Resource efficiency", Buildings!G:G, "s/l-UNC") + COUNTIFS(Buildings!H:H, "Resource efficiency", Buildings!G:G, "s/l-POS") + COUNTIFS(Buildings!H:H, "Resource efficiency", Buildings!G:G, "s/l-NEG") + COUNTIFS(Transport!H:H, "Resource efficiency", Transport!G:G, "n") + COUNTIFS(Transport!H:H, "Resource efficiency", Transport!G:G, "s/l-UNC") + COUNTIFS(Transport!H:H, "Resource efficiency", Transport!G:G, "s/l-POS") + COUNTIFS(Transport!H:H, "Resource efficiency", Transport!G:G, "s/l-NEG") + COUNTIFS(LULUCF!H:H, "Resource efficiency", LULUCF!G:G, "n") + COUNTIFS(LULUCF!H:H, "Resource efficiency", LULUCF!G:G, "s/l-UNC") + COUNTIFS(LULUCF!H:H, "Resource efficiency", LULUCF!G:G, "s/l-POS") + COUNTIFS(LULUCF!H:H, "Resource efficiency", LULUCF!G:G, "s/l-NEG") + COUNTIFS('Circular Economy'!H:H, "Resource efficiency", 'Circular Economy'!G:G, "n") + COUNTIFS('Circular Economy'!H:H, "Resource efficiency", 'Circular Economy'!G:G, "s/l-UNC") + COUNTIFS('Circular Economy'!H:H, "Resource efficiency", 'Circular Economy'!G:G, "s/l-POS") + COUNTIFS('Circular Economy'!H:H, "Resource efficiency", 'Circular Economy'!G:G, "s/l-NEG") + COUNTIFS(Finance!H:H, "Resource efficiency", Finance!G:G, "n") + COUNTIFS(Finance!H:H, "Resource efficiency", Finance!G:G, "s/l-UNC") + COUNTIFS(Finance!H:H, "Resource efficiency", Finance!G:G, "s/l-POS") + COUNTIFS(Finance!H:H, "Resource efficiency", Finance!G:G, "s/l-NEG")
B13: Circular Economy | C13: =COUNTIFS('Circular Economy'!G:G, "n") + COUNTIFS('Circular Economy'!G:G, "s/l-UNC") + COUNTIFS('Circular Economy'!G:G, "s/l-POS") + COUNTIFS('Circular Economy'!G:G, "s/l-NEG") | K13: 2011 | L13: =COUNTIFS('GHG Emissions'!A:A, 2011, 'GHG Emissions'!G:G, "n") + COUNTIFS('GHG Emissions'!A:A, 2011, 'GHG Emissions'!G:G, "s/l-UNC") + COUNTIFS('GHG Emissions'!A:A, 2011, 'GHG Emissions'!G:G, "s/l-POS") + COUNTIFS('GHG Emissions'!A:A, 2011, 'GHG Emissions'!G:G, "s/l-NEG") + COUNTIFS(Pollution!A:A, 2011, Pollution!G:G, "n") + COUNTIFS(Pollution!A:A, 2011, Pollution!G:G, "s/l-UNC") + COUNTIFS(Pollution!A:A, 2011, Pollution!G:G, "s/l-POS") + COUNTIFS(Pollution!A:A, 2011, Pollution!G:G, "s/l-NEG") + COUNTIFS('Energy|Power'!A:A, 2011, 'Energy|Power'!G:G, "n") + COUNTIFS('Energy|Power'!A:A, 2011, 'Energy|Power'!G:G, "s/l-UNC") + COUNTIFS('Energy|Power'!A:A, 2011, 'Energy|Power'!G:G, "s/l-POS") + COUNTIFS('Energy|Power'!A:A, 2011, 'Energy|Power'!G:G, "s/l-NEG") + COUNTIFS(Industry!A:A, 2011, Industry!G:G, "n") + COUNTIFS(Industry!A:A, 2011, Industry!G:G, "s/l-UNC") + COUNTIFS(Industry!A:A, 2011, Industry!G:G, "s/l-POS") + COUNTIFS(Industry!A:A, 2011, Industry!G:G, "s/l-NEG") + COUNTIFS(Buildings!A:A, 2011, Buildings!G:G, "n") + COUNTIFS(Buildings!A:A, 2011, Buildings!G:G, "s/l-UNC") + COUNTIFS(Buildings!A:A, 2011, Buildings!G:G, "s/l-POS") + COUNTIFS(Buildings!A:A, 2011, Buildings!G:G, "s/l-NEG") + COUNTIFS(Transport!A:A, 2011, Transport!G:G, "n") + COUNTIFS(Transport!A:A, 2011, Transport!G:G, "s/l-UNC") + COUNTIFS(Transport!A:A, 2011, Transport!G:G, "s/l-POS") + COUNTIFS(Transport!A:A, 2011, Transport!G:G, "s/l-NEG") + COUNTIFS(LULUCF!A:A, 2011, LULUCF!G:G, "n") + COUNTIFS(LULUCF!A:A, 2011, LULUCF!G:G, "s/l-UNC") + COUNTIFS(LULUCF!A:A, 2011, LULUCF!G:G, "s/l-POS") + COUNTIFS(LULUCF!A:A, 2011, LULUCF!G:G, "s/l-NEG") + COUNTIFS('Circular Economy'!A:A, 2011, 'Circular Economy'!G:G, "n") + COUNTIFS('Circular Economy'!A:A, 2011, 'Circular Economy'!G:G, "s/l-UNC") + COUNTIFS('Circular Economy'!A:A, 2011, 'Circular Economy'!G:G, "s/l-POS") + COUNTIFS('Circular Economy'!A:A, 2011, 'Circular Economy'!G:G, "s/l-NEG") + COUNTIFS(Finance!A:A, 2011, Finance!G:G, "n") + COUNTIFS(Finance!A:A, 2011, Finance!G:G, "s/l-UNC") + COUNTIFS(Finance!A:A, 2011, Finance!G:G, "s/l-POS") + COUNTIFS(Finance!A:A, 2011, Finance!G:G, "s/l-NEG") | N13: 12th FYP | O13: =COUNTIFS('GHG Emissions'!F:F, "12th FYP", 'GHG Emissions'!G:G, "n") + COUNTIFS('GHG Emissions'!F:F, "12th FYP", 'GHG Emissions'!G:G, "s/l-UNC") + COUNTIFS('GHG Emissions'!F:F, "12th FYP", 'GHG Emissions'!G:G, "s/l-POS") + COUNTIFS('GHG Emissions'!F:F, "12th FYP", 'GHG Emissions'!G:G, "s/l-NEG") + COUNTIFS(Pollution!F:F, "12th FYP", Pollution!G:G, "n") + COUNTIFS(Pollution!F:F, "12th FYP", Pollution!G:G, "s/l-UNC") + COUNTIFS(Pollution!F:F, "12th FYP", Pollution!G:G, "s/l-POS") + COUNTIFS(Pollution!F:F, "12th FYP", Pollution!G:G, "s/l-NEG") + COUNTIFS('Energy|Power'!F:F, "12th FYP", 'Energy|Power'!G:G, "n") + COUNTIFS('Energy|Power'!F:F, "12th FYP", 'Energy|Power'!G:G, "s/l-UNC") + COUNTIFS('Energy|Power'!F:F, "12th FYP", 'Energy|Power'!G:G, "s/l-POS") + COUNTIFS('Energy|Power'!F:F, "12th FYP", 'Energy|Power'!G:G, "s/l-NEG") + COUNTIFS(Industry!F:F, "12th FYP", Industry!G:G, "n") + COUNTIFS(Industry!F:F, "12th FYP", Industry!G:G, "s/l-UNC") + COUNTIFS(Industry!F:F, "12th FYP", Industry!G:G, "s/l-POS") + COUNTIFS(Industry!F:F, "12th FYP", Industry!G:G, "s/l-NEG") + COUNTIFS(Buildings!F:F, "12th FYP", Buildings!G:G, "n") + COUNTIFS(Buildings!F:F, "12th FYP", Buildings!G:G, "s/l-UNC") + COUNTIFS(Buildings!F:F, "12th FYP", Buildings!G:G, "s/l-POS") + COUNTIFS(Buildings!F:F, "12th FYP", Buildings!G:G, "s/l-NEG") + COUNTIFS(Transport!F:F, "12th FYP", Transport!G:G, "n") + COUNTIFS(Transport!F:F, "12th FYP", Transport!G:G, "s/l-UNC") + COUNTIFS(Transport!F:F, "12th FYP", Transport!G:G, "s/l-POS") + COUNTIFS(Transport!F:F, "12th FYP", Transport!G:G, "s/l-NEG") + COUNTIFS(LULUCF!F:F, "12th FYP", LULUCF!G:G, "n") + COUNTIFS(LULUCF!F:F, "12th FYP", LULUCF!G:G, "s/l-UNC") + COUNTIFS(LULUCF!F:F, "12th FYP", LULUCF!G:G, "s/l-POS") + COUNTIFS(LULUCF!F:F, "12th FYP", LULUCF!G:G, "s/l-NEG") + COUNTIFS('Circular Economy'!F:F, "12th FYP", 'Circular Economy'!G:G, "n") + COUNTIFS('Circular Economy'!F:F, "12th FYP", 'Circular Economy'!G:G, "s/l-UNC") + COUNTIFS('Circular Economy'!F:F, "12th FYP", 'Circular Economy'!G:G, "s/l-POS") + COUNTIFS('Circular Economy'!F:F, "12th FYP", 'Circular Economy'!G:G, "s/l-NEG") + COUNTIFS(Finance!F:F, "12th FYP", Finance!G:G, "n") + COUNTIFS(Finance!F:F, "12th FYP", Finance!G:G, "s/l-UNC") + COUNTIFS(Finance!F:F, "12th FYP", Finance!G:G, "s/l-POS") + COUNTIFS(Finance!F:F, "12th FYP", Finance!G:G, "s/l-NEG") | Q13: Renewable energy | R13: =COUNTIFS('GHG Emissions'!H:H, "Renewable energy", 'GHG Emissions'!G:G, "n") + COUNTIFS('GHG Emissions'!H:H, "Renewable energy", 'GHG Emissions'!G:G, "s/l-UNC") + COUNTIFS('GHG Emissions'!H:H, "Renewable energy", 'GHG Emissions'!G:G, "s/l-POS") + COUNTIFS('GHG Emissions'!H:H, "Renewable energy", 'GHG Emissions'!G:G, "s/l-NEG") + COUNTIFS(Pollution!H:H, "Renewable energy", Pollution!G:G, "n") + COUNTIFS(Pollution!H:H, "Renewable energy", Pollution!G:G, "s/l-UNC") + COUNTIFS(Pollution!H:H, "Renewable energy", Pollution!G:G, "s/l-POS") + COUNTIFS(Pollution!H:H, "Renewable energy", Pollution!G:G, "s/l-NEG") + COUNTIFS('Energy|Power'!H:H, "Renewable energy", 'Energy|Power'!G:G, "n") + COUNTIFS('Energy|Power'!H:H, "Renewable energy", 'Energy|Power'!G:G, "s/l-UNC") + COUNTIFS('Energy|Power'!H:H, "Renewable energy", 'Energy|Power'!G:G, "s/l-POS") + COUNTIFS('Energy|Power'!H:H, "Renewable energy", 'Energy|Power'!G:G, "s/l-NEG") + COUNTIFS(Industry!H:H, "Renewable energy", Industry!G:G, "n") + COUNTIFS(Industry!H:H, "Renewable energy", Industry!G:G, "s/l-UNC") + COUNTIFS(Industry!H:H, "Renewable energy", Industry!G:G, "s/l-POS") + COUNTIFS(Industry!H:H, "Renewable energy", Industry!G:G, "s/l-NEG") + COUNTIFS(Buildings!H:H, "Renewable energy", Buildings!G:G, "n") + COUNTIFS(Buildings!H:H, "Renewable energy", Buildings!G:G, "s/l-UNC") + COUNTIFS(Buildings!H:H, "Renewable energy", Buildings!G:G, "s/l-POS") + COUNTIFS(Buildings!H:H, "Renewable energy", Buildings!G:G, "s/l-NEG") + COUNTIFS(Transport!H:H, "Renewable energy", Transport!G:G, "n") + COUNTIFS(Transport!H:H, "Renewable energy", Transport!G:G, "s/l-UNC") + COUNTIFS(Transport!H:H, "Renewable energy", Transport!G:G, "s/l-POS") + COUNTIFS(Transport!H:H, "Renewable energy", Transport!G:G, "s/l-NEG") + COUNTIFS(LULUCF!H:H, "Renewable energy", LULUCF!G:G, "n") + COUNTIFS(LULUCF!H:H, "Renewable energy", LULUCF!G:G, "s/l-UNC") + COUNTIFS(LULUCF!H:H, "Renewable energy", LULUCF!G:G, "s/l-POS") + COUNTIFS(LULUCF!H:H, "Renewable energy", LULUCF!G:G, "s/l-NEG") + COUNTIFS('Circular Economy'!H:H, "Renewable energy", 'Circular Economy'!G:G, "n") + COUNTIFS('Circular Economy'!H:H, "Renewable energy", 'Circular Economy'!G:G, "s/l-UNC") + COUNTIFS('Circular Economy'!H:H, "Renewable energy", 'Circular Economy'!G:G, "s/l-POS") + COUNTIFS('Circular Economy'!H:H, "Renewable energy", 'Circular Economy'!G:G, "s/l-NEG") + COUNTIFS(Finance!H:H, "Renewable energy", Finance!G:G, "n") + COUNTIFS(Finance!H:H, "Renewable energy", Finance!G:G, "s/l-UNC") + COUNTIFS(Finance!H:H, "Renewable energy", Finance!G:G, "s/l-POS") + COUNTIFS(Finance!H:H, "Renewable energy", Finance!G:G, "s/l-NEG")
B14: Finance | C14: =COUNTIFS(Finance!G:G, "n") + COUNTIFS(Finance!G:G, "s/l-UNC") + COUNTIFS(Finance!G:G, "s/l-POS") + COUNTIFS(Finance!G:G, "s/l-NEG") | K14: 2012 | L14: =COUNTIFS('GHG Emissions'!A:A, 2012, 'GHG Emissions'!G:G, "n") + COUNTIFS('GHG Emissions'!A:A, 2012, 'GHG Emissions'!G:G, "s/l-UNC") + COUNTIFS('GHG Emissions'!A:A, 2012, 'GHG Emissions'!G:G, "s/l-POS") + COUNTIFS('GHG Emissions'!A:A, 2012, 'GHG Emissions'!G:G, "s/l-NEG") + COUNTIFS(Pollution!A:A, 2012, Pollution!G:G, "n") + COUNTIFS(Pollution!A:A, 2012, Pollution!G:G, "s/l-UNC") + COUNTIFS(Pollution!A:A, 2012, Pollution!G:G, "s/l-POS") + COUNTIFS(Pollution!A:A, 2012, Pollution!G:G, "s/l-NEG") + COUNTIFS('Energy|Power'!A:A, 2012, 'Energy|Power'!G:G, "n") + COUNTIFS('Energy|Power'!A:A, 2012, 'Energy|Power'!G:G, "s/l-UNC") + COUNTIFS('Energy|Power'!A:A, 2012, 'Energy|Power'!G:G, "s/l-POS") + COUNTIFS('Energy|Power'!A:A, 2012, 'Energy|Power'!G:G, "s/l-NEG") + COUNTIFS(Industry!A:A, 2012, Industry!G:G, "n") + COUNTIFS(Industry!A:A, 2012, Industry!G:G, "s/l-UNC") + COUNTIFS(Industry!A:A, 2012, Industry!G:G, "s/l-POS") + COUNTIFS(Industry!A:A, 2012, Industry!G:G, "s/l-NEG") + COUNTIFS(Buildings!A:A, 2012, Buildings!G:G, "n") + COUNTIFS(Buildings!A:A, 2012, Buildings!G:G, "s/l-UNC") + COUNTIFS(Buildings!A:A, 2012, Buildings!G:G, "s/l-POS") + COUNTIFS(Buildings!A:A, 2012, Buildings!G:G, "s/l-NEG") + COUNTIFS(Transport!A:A, 2012, Transport!G:G, "n") + COUNTIFS(Transport!A:A, 2012, Transport!G:G, "s/l-UNC") + COUNTIFS(Transport!A:A, 2012, Transport!G:G, "s/l-POS") + COUNTIFS(Transport!A:A, 2012, Transport!G:G, "s/l-NEG") + COUNTIFS(LULUCF!A:A, 2012, LULUCF!G:G, "n") + COUNTIFS(LULUCF!A:A, 2012, LULUCF!G:G, "s/l-UNC") + COUNTIFS(LULUCF!A:A, 2012, LULUCF!G:G, "s/l-POS") + COUNTIFS(LULUCF!A:A, 2012, LULUCF!G:G, "s/l-NEG") + COUNTIFS('Circular Economy'!A:A, 2012, 'Circular Economy'!G:G, "n") + COUNTIFS('Circular Economy'!A:A, 2012, 'Circular Economy'!G:G, "s/l-UNC") + COUNTIFS('Circular Economy'!A:A, 2012, 'Circular Economy'!G:G, "s/l-POS") + COUNTIFS('Circular Economy'!A:A, 2012, 'Circular Economy'!G:G, "s/l-NEG") + COUNTIFS(Finance!A:A, 2012, Finance!G:G, "n") + COUNTIFS(Finance!A:A, 2012, Finance!G:G, "s/l-UNC") + COUNTIFS(Finance!A:A, 2012, Finance!G:G, "s/l-POS") + COUNTIFS(Finance!A:A, 2012, Finance!G:G, "s/l-NEG") | N14: 2016 | O14: =COUNTIFS('GHG Emissions'!F:F, 2016, 'GHG Emissions'!G:G, "n") + COUNTIFS('GHG Emissions'!F:F, 2016, 'GHG Emissions'!G:G, "s/l-UNC") + COUNTIFS('GHG Emissions'!F:F, 2016, 'GHG Emissions'!G:G, "s/l-POS") + COUNTIFS('GHG Emissions'!F:F, 2016, 'GHG Emissions'!G:G, "s/l-NEG") + COUNTIFS(Pollution!F:F, 2016, Pollution!G:G, "n") + COUNTIFS(Pollution!F:F, 2016, Pollution!G:G, "s/l-UNC") + COUNTIFS(Pollution!F:F, 2016, Pollution!G:G, "s/l-POS") + COUNTIFS(Pollution!F:F, 2016, Pollution!G:G, "s/l-NEG") + COUNTIFS('Energy|Power'!F:F, 2016, 'Energy|Power'!G:G, "n") + COUNTIFS('Energy|Power'!F:F, 2016, 'Energy|Power'!G:G, "s/l-UNC") + COUNTIFS('Energy|Power'!F:F, 2016, 'Energy|Power'!G:G, "s/l-POS") + COUNTIFS('Energy|Power'!F:F, 2016, 'Energy|Power'!G:G, "s/l-NEG") + COUNTIFS(Industry!F:F, 2016, Industry!G:G, "n") + COUNTIFS(Industry!F:F, 2016, Industry!G:G, "s/l-UNC") + COUNTIFS(Industry!F:F, 2016, Industry!G:G, "s/l-POS") + COUNTIFS(Industry!F:F, 2016, Industry!G:G, "s/l-NEG") + COUNTIFS(Buildings!F:F, 2016, Buildings!G:G, "n") + COUNTIFS(Buildings!F:F, 2016, Buildings!G:G, "s/l-UNC") + COUNTIFS(Buildings!F:F, 2016, Buildings!G:G, "s/l-POS") + COUNTIFS(Buildings!F:F, 2016, Buildings!G:G, "s/l-NEG") + COUNTIFS(Transport!F:F, 2016, Transport!G:G, "n") + COUNTIFS(Transport!F:F, 2016, Transport!G:G, "s/l-UNC") + COUNTIFS(Transport!F:F, 2016, Transport!G:G, "s/l-POS") + COUNTIFS(Transport!F:F, 2016, Transport!G:G, "s/l-NEG") + COUNTIFS(LULUCF!F:F, 2016, LULUCF!G:G, "n") + COUNTIFS(LULUCF!F:F, 2016, LULUCF!G:G, "s/l-UNC") + COUNTIFS(LULUCF!F:F, 2016, LULUCF!G:G, "s/l-POS") + COUNTIFS(LULUCF!F:F, 2016, LULUCF!G:G, "s/l-NEG") + COUNTIFS('Circular Economy'!F:F, 2016, 'Circular Economy'!G:G, "n") + COUNTIFS('Circular Economy'!F:F, 2016, 'Circular Economy'!G:G, "s/l-UNC") + COUNTIFS('Circular Economy'!F:F, 2016, 'Circular Economy'!G:G, "s/l-POS") + COUNTIFS('Circular Economy'!F:F, 2016, 'Circular Economy'!G:G, "s/l-NEG") + COUNTIFS(Finance!F:F, 2016, Finance!G:G, "n") + COUNTIFS(Finance!F:F, 2016, Finance!G:G, "s/l-UNC") + COUNTIFS(Finance!F:F, 2016, Finance!G:G, "s/l-POS") + COUNTIFS(Finance!F:F, 2016, Finance!G:G, "s/l-NEG") | Q14: Transitional energy | R14: =COUNTIFS('GHG Emissions'!H:H, "Transitional energy", 'GHG Emissions'!G:G, "n") + COUNTIFS('GHG Emissions'!H:H, "Transitional energy", 'GHG Emissions'!G:G, "s/l-UNC") + COUNTIFS('GHG Emissions'!H:H, "Transitional energy", 'GHG Emissions'!G:G, "s/l-POS") + COUNTIFS('GHG Emissions'!H:H, "Transitional energy", 'GHG Emissions'!G:G, "s/l-NEG") + COUNTIFS(Pollution!H:H, "Transitional energy", Pollution!G:G, "n") + COUNTIFS(Pollution!H:H, "Transitional energy", Pollution!G:G, "s/l-UNC") + COUNTIFS(Pollution!H:H, "Transitional energy", Pollution!G:G, "s/l-POS") + COUNTIFS(Pollution!H:H, "Transitional energy", Pollution!G:G, "s/l-NEG") + COUNTIFS('Energy|Power'!H:H, "Transitional energy", 'Energy|Power'!G:G, "n") + COUNTIFS('Energy|Power'!H:H, "Transitional energy", 'Energy|Power'!G:G, "s/l-UNC") + COUNTIFS('Energy|Power'!H:H, "Transitional energy", 'Energy|Power'!G:G, "s/l-POS") + COUNTIFS('Energy|Power'!H:H, "Transitional energy", 'Energy|Power'!G:G, "s/l-NEG") + COUNTIFS(Industry!H:H, "Transitional energy", Industry!G:G, "n") + COUNTIFS(Industry!H:H, "Transitional energy", Industry!G:G, "s/l-UNC") + COUNTIFS(Industry!H:H, "Transitional energy", Industry!G:G, "s/l-POS") + COUNTIFS(Industry!H:H, "Transitional energy", Industry!G:G, "s/l-NEG") + COUNTIFS(Buildings!H:H, "Transitional energy", Buildings!G:G, "n") + COUNTIFS(Buildings!H:H, "Transitional energy", Buildings!G:G, "s/l-UNC") + COUNTIFS(Buildings!H:H, "Transitional energy", Buildings!G:G, "s/l-POS") + COUNTIFS(Buildings!H:H, "Transitional energy", Buildings!G:G, "s/l-NEG") + COUNTIFS(Transport!H:H, "Transitional energy", Transport!G:G, "n") + COUNTIFS(Transport!H:H, "Transitional energy", Transport!G:G, "s/l-UNC") + COUNTIFS(Transport!H:H, "Transitional energy", Transport!G:G, "s/l-POS") + COUNTIFS(Transport!H:H, "Transitional energy", Transport!G:G, "s/l-NEG") + COUNTIFS(LULUCF!H:H, "Transitional energy", LULUCF!G:G, "n") + COUNTIFS(LULUCF!H:H, "Transitional energy", LULUCF!G:G, "s/l-UNC") + COUNTIFS(LULUCF!H:H, "Transitional energy", LULUCF!G:G, "s/l-POS") + COUNTIFS(LULUCF!H:H, "Transitional energy", LULUCF!G:G, "s/l-NEG") + COUNTIFS('Circular Economy'!H:H, "Transitional energy", 'Circular Economy'!G:G, "n") + COUNTIFS('Circular Economy'!H:H, "Transitional energy", 'Circular Economy'!G:G, "s/l-UNC") + COUNTIFS('Circular Economy'!H:H, "Transitional energy", 'Circular Economy'!G:G, "s/l-POS") + COUNTIFS('Circular Economy'!H:H, "Transitional energy", 'Circular Economy'!G:G, "s/l-NEG") + COUNTIFS(Finance!H:H, "Transitional energy", Finance!G:G, "n") + COUNTIFS(Finance!H:H, "Transitional energy", Finance!G:G, "s/l-UNC") + COUNTIFS(Finance!H:H, "Transitional energy", Finance!G:G, "s/l-POS") + COUNTIFS(Finance!H:H, "Transitional energy", Finance!G:G, "s/l-NEG")
B15: Total | C15: =SUM(C6:C14) | K15: 2013 | L15: =COUNTIFS('GHG Emissions'!A:A, 2013, 'GHG Emissions'!G:G, "n") + COUNTIFS('GHG Emissions'!A:A, 2013, 'GHG Emissions'!G:G, "s/l-UNC") + COUNTIFS('GHG Emissions'!A:A, 2013, 'GHG Emissions'!G:G, "s/l-POS") + COUNTIFS('GHG Emissions'!A:A, 2013, 'GHG Emissions'!G:G, "s/l-NEG") + COUNTIFS(Pollution!A:A, 2013, Pollution!G:G, "n") + COUNTIFS(Pollution!A:A, 2013, Pollution!G:G, "s/l-UNC") + COUNTIFS(Pollution!A:A, 2013, Pollution!G:G, "s/l-POS") + COUNTIFS(Pollution!A:A, 2013, Pollution!G:G, "s/l-NEG") + COUNTIFS('Energy|Power'!A:A, 2013, 'Energy|Power'!G:G, "n") + COUNTIFS('Energy|Power'!A:A, 2013, 'Energy|Power'!G:G, "s/l-UNC") + COUNTIFS('Energy|Power'!A:A, 2013, 'Energy|Power'!G:G, "s/l-POS") + COUNTIFS('Energy|Power'!A:A, 2013, 'Energy|Power'!G:G, "s/l-NEG") + COUNTIFS(Industry!A:A, 2013, Industry!G:G, "n") + COUNTIFS(Industry!A:A, 2013, Industry!G:G, "s/l-UNC") + COUNTIFS(Industry!A:A, 2013, Industry!G:G, "s/l-POS") + COUNTIFS(Industry!A:A, 2013, Industry!G:G, "s/l-NEG") + COUNTIFS(Buildings!A:A, 2013, Buildings!G:G, "n") + COUNTIFS(Buildings!A:A, 2013, Buildings!G:G, "s/l-UNC") + COUNTIFS(Buildings!A:A, 2013, Buildings!G:G, "s/l-POS") + COUNTIFS(Buildings!A:A, 2013, Buildings!G:G, "s/l-NEG") + COUNTIFS(Transport!A:A, 2013, Transport!G:G, "n") + COUNTIFS(Transport!A:A, 2013, Transport!G:G, "s/l-UNC") + COUNTIFS(Transport!A:A, 2013, Transport!G:G, "s/l-POS") + COUNTIFS(Transport!A:A, 2013, Transport!G:G, "s/l-NEG") + COUNTIFS(LULUCF!A:A, 2013, LULUCF!G:G, "n") + COUNTIFS(LULUCF!A:A, 2013, LULUCF!G:G, "s/l-UNC") + COUNTIFS(LULUCF!A:A, 2013, LULUCF!G:G, "s/l-POS") + COUNTIFS(LULUCF!A:A, 2013, LULUCF!G:G, "s/l-NEG") + COUNTIFS('Circular Economy'!A:A, 2013, 'Circular Economy'!G:G, "n") + COUNTIFS('Circular Economy'!A:A, 2013, 'Circular Economy'!G:G, "s/l-UNC") + COUNTIFS('Circular Economy'!A:A, 2013, 'Circular Economy'!G:G, "s/l-POS") + COUNTIFS('Circular Economy'!A:A, 2013, 'Circular Economy'!G:G, "s/l-NEG") + COUNTIFS(Finance!A:A, 2013, Finance!G:G, "n") + COUNTIFS(Finance!A:A, 2013, Finance!G:G, "s/l-UNC") + COUNTIFS(Finance!A:A, 2013, Finance!G:G, "s/l-POS") + COUNTIFS(Finance!A:A, 2013, Finance!G:G, "s/l-NEG") | N15: 2017 | O15: =COUNTIFS('GHG Emissions'!F:F, 2017, 'GHG Emissions'!G:G, "n") + COUNTIFS('GHG Emissions'!F:F, 2017, 'GHG Emissions'!G:G, "s/l-UNC") + COUNTIFS('GHG Emissions'!F:F, 2017, 'GHG Emissions'!G:G, "s/l-POS") + COUNTIFS('GHG Emissions'!F:F, 2017, 'GHG Emissions'!G:G, "s/l-NEG") + COUNTIFS(Pollution!F:F, 2017, Pollution!G:G, "n") + COUNTIFS(Pollution!F:F, 2017, Pollution!G:G, "s/l-UNC") + COUNTIFS(Pollution!F:F, 2017, Pollution!G:G, "s/l-POS") + COUNTIFS(Pollution!F:F, 2017, Pollution!G:G, "s/l-NEG") + COUNTIFS('Energy|Power'!F:F, 2017, 'Energy|Power'!G:G, "n") + COUNTIFS('Energy|Power'!F:F, 2017, 'Energy|Power'!G:G, "s/l-UNC") + COUNTIFS('Energy|Power'!F:F, 2017, 'Energy|Power'!G:G, "s/l-POS") + COUNTIFS('Energy|Power'!F:F, 2017, 'Energy|Power'!G:G, "s/l-NEG") + COUNTIFS(Industry!F:F, 2017, Industry!G:G, "n") + COUNTIFS(Industry!F:F, 2017, Industry!G:G, "s/l-UNC") + COUNTIFS(Industry!F:F, 2017, Industry!G:G, "s/l-POS") + COUNTIFS(Industry!F:F, 2017, Industry!G:G, "s/l-NEG") + COUNTIFS(Buildings!F:F, 2017, Buildings!G:G, "n") + COUNTIFS(Buildings!F:F, 2017, Buildings!G:G, "s/l-UNC") + COUNTIFS(Buildings!F:F, 2017, Buildings!G:G, "s/l-POS") + COUNTIFS(Buildings!F:F, 2017, Buildings!G:G, "s/l-NEG") + COUNTIFS(Transport!F:F, 2017, Transport!G:G, "n") + COUNTIFS(Transport!F:F, 2017, Transport!G:G, "s/l-UNC") + COUNTIFS(Transport!F:F, 2017, Transport!G:G, "s/l-POS") + COUNTIFS(Transport!F:F, 2017, Transport!G:G, "s/l-NEG") + COUNTIFS(LULUCF!F:F, 2017, LULUCF!G:G, "n") + COUNTIFS(LULUCF!F:F, 2017, LULUCF!G:G, "s/l-UNC") + COUNTIFS(LULUCF!F:F, 2017, LULUCF!G:G, "s/l-POS") + COUNTIFS(LULUCF!F:F, 2017, LULUCF!G:G, "s/l-NEG") + COUNTIFS('Circular Economy'!F:F, 2017, 'Circular Economy'!G:G, "n") + COUNTIFS('Circular Economy'!F:F, 2017, 'Circular Economy'!G:G, "s/l-UNC") + COUNTIFS('Circular Economy'!F:F, 2017, 'Circular Economy'!G:G, "s/l-POS") + COUNTIFS('Circular Economy'!F:F, 2017, 'Circular Economy'!G:G, "s/l-NEG") + COUNTIFS(Finance!F:F, 2017, Finance!G:G, "n") + COUNTIFS(Finance!F:F, 2017, Finance!G:G, "s/l-UNC") + COUNTIFS(Finance!F:F, 2017, Finance!G:G, "s/l-POS") + COUNTIFS(Finance!F:F, 2017, Finance!G:G, "s/l-NEG") | Q15: Electrification | R15: =COUNTIFS('GHG Emissions'!H:H, "Electrification", 'GHG Emissions'!G:G, "n") + COUNTIFS('GHG Emissions'!H:H, "Electrification", 'GHG Emissions'!G:G, "s/l-UNC") + COUNTIFS('GHG Emissions'!H:H, "Electrification", 'GHG Emissions'!G:G, "s/l-POS") + COUNTIFS('GHG Emissions'!H:H, "Electrification", 'GHG Emissions'!G:G, "s/l-NEG") + COUNTIFS(Pollution!H:H, "Electrification", Pollution!G:G, "n") + COUNTIFS(Pollution!H:H, "Electrification", Pollution!G:G, "s/l-UNC") + COUNTIFS(Pollution!H:H, "Electrification", Pollution!G:G, "s/l-POS") + COUNTIFS(Pollution!H:H, "Electrification", Pollution!G:G, "s/l-NEG") + COUNTIFS('Energy|Power'!H:H, "Electrification", 'Energy|Power'!G:G, "n") + COUNTIFS('Energy|Power'!H:H, "Electrification", 'Energy|Power'!G:G, "s/l-UNC") + COUNTIFS('Energy|Power'!H:H, "Electrification", 'Energy|Power'!G:G, "s/l-POS") + COUNTIFS('Energy|Power'!H:H, "Electrification", 'Energy|Power'!G:G, "s/l-NEG") + COUNTIFS(Industry!H:H, "Electrification", Industry!G:G, "n") + COUNTIFS(Industry!H:H, "Electrification", Industry!G:G, "s/l-UNC") + COUNTIFS(Industry!H:H, "Electrification", Industry!G:G, "s/l-POS") + COUNTIFS(Industry!H:H, "Electrification", Industry!G:G, "s/l-NEG") + COUNTIFS(Buildings!H:H, "Electrification", Buildings!G:G, "n") + COUNTIFS(Buildings!H:H, "Electrification", Buildings!G:G, "s/l-UNC") + COUNTIFS(Buildings!H:H, "Electrification", Buildings!G:G, "s/l-POS") + COUNTIFS(Buildings!H:H, "Electrification", Buildings!G:G, "s/l-NEG") + COUNTIFS(Transport!H:H, "Electrification", Transport!G:G, "n") + COUNTIFS(Transport!H:H, "Electrification", Transport!G:G, "s/l-UNC") + COUNTIFS(Transport!H:H, "Electrification", Transport!G:G, "s/l-POS") + COUNTIFS(Transport!H:H, "Electrification", Transport!G:G, "s/l-NEG") + COUNTIFS(LULUCF!H:H, "Electrification", LULUCF!G:G, "n") + COUNTIFS(LULUCF!H:H, "Electrification", LULUCF!G:G, "s/l-UNC") + COUNTIFS(LULUCF!H:H, "Electrification", LULUCF!G:G, "s/l-POS") + COUNTIFS(LULUCF!H:H, "Electrification", LULUCF!G:G, "s/l-NEG") + COUNTIFS('Circular Economy'!H:H, "Electrification", 'Circular Economy'!G:G, "n") + COUNTIFS('Circular Economy'!H:H, "Electrification", 'Circular Economy'!G:G, "s/l-UNC") + COUNTIFS('Circular Economy'!H:H, "Electrification", 'Circular Economy'!G:G, "s/l-POS") + COUNTIFS('Circular Economy'!H:H, "Electrification", 'Circular Economy'!G:G, "s/l-NEG") + COUNTIFS(Finance!H:H, "Electrification", Finance!G:G, "n") + COUNTIFS(Finance!H:H, "Electrification", Finance!G:G, "s/l-UNC") + COUNTIFS(Finance!H:H, "Electrification", Finance!G:G, "s/l-POS") + COUNTIFS(Finance!H:H, "Electrification", Finance!G:G, "s/l-NEG")
K16: 2014 | L16: =COUNTIFS('GHG Emissions'!A:A, 2014, 'GHG Emissions'!G:G, "n") + COUNTIFS('GHG Emissions'!A:A, 2014, 'GHG Emissions'!G:G, "s/l-UNC") + COUNTIFS('GHG Emissions'!A:A, 2014, 'GHG Emissions'!G:G, "s/l-POS") + COUNTIFS('GHG Emissions'!A:A, 2014, 'GHG Emissions'!G:G, "s/l-NEG") + COUNTIFS(Pollution!A:A, 2014, Pollution!G:G, "n") + COUNTIFS(Pollution!A:A, 2014, Pollution!G:G, "s/l-UNC") + COUNTIFS(Pollution!A:A, 2014, Pollution!G:G, "s/l-POS") + COUNTIFS(Pollution!A:A, 2014, Pollution!G:G, "s/l-NEG") + COUNTIFS('Energy|Power'!A:A, 2014, 'Energy|Power'!G:G, "n") + COUNTIFS('Energy|Power'!A:A, 2014, 'Energy|Power'!G:G, "s/l-UNC") + COUNTIFS('Energy|Power'!A:A, 2014, 'Energy|Power'!G:G, "s/l-POS") + COUNTIFS('Energy|Power'!A:A, 2014, 'Energy|Power'!G:G, "s/l-NEG") + COUNTIFS(Industry!A:A, 2014, Industry!G:G, "n") + COUNTIFS(Industry!A:A, 2014, Industry!G:G, "s/l-UNC") + COUNTIFS(Industry!A:A, 2014, Industry!G:G, "s/l-POS") + COUNTIFS(Industry!A:A, 2014, Industry!G:G, "s/l-NEG") + COUNTIFS(Buildings!A:A, 2014, Buildings!G:G, "n") + COUNTIFS(Buildings!A:A, 2014, Buildings!G:G, "s/l-UNC") + COUNTIFS(Buildings!A:A, 2014, Buildings!G:G, "s/l-POS") + COUNTIFS(Buildings!A:A, 2014, Buildings!G:G, "s/l-NEG") + COUNTIFS(Transport!A:A, 2014, Transport!G:G, "n") + COUNTIFS(Transport!A:A, 2014, Transport!G:G, "s/l-UNC") + COUNTIFS(Transport!A:A, 2014, Transport!G:G, "s/l-POS") + COUNTIFS(Transport!A:A, 2014, Transport!G:G, "s/l-NEG") + COUNTIFS(LULUCF!A:A, 2014, LULUCF!G:G, "n") + COUNTIFS(LULUCF!A:A, 2014, LULUCF!G:G, "s/l-UNC") + COUNTIFS(LULUCF!A:A, 2014, LULUCF!G:G, "s/l-POS") + COUNTIFS(LULUCF!A:A, 2014, LULUCF!G:G, "s/l-NEG") + COUNTIFS('Circular Economy'!A:A, 2014, 'Circular Economy'!G:G, "n") + COUNTIFS('Circular Economy'!A:A, 2014, 'Circular Economy'!G:G, "s/l-UNC") + COUNTIFS('Circular Economy'!A:A, 2014, 'Circular Economy'!G:G, "s/l-POS") + COUNTIFS('Circular Economy'!A:A, 2014, 'Circular Economy'!G:G, "s/l-NEG") + COUNTIFS(Finance!A:A, 2014, Finance!G:G, "n") + COUNTIFS(Finance!A:A, 2014, Finance!G:G, "s/l-UNC") + COUNTIFS(Finance!A:A, 2014, Finance!G:G, "s/l-POS") + COUNTIFS(Finance!A:A, 2014, Finance!G:G, "s/l-NEG") | N16: 2018 | O16: =COUNTIFS('GHG Emissions'!F:F, 2018, 'GHG Emissions'!G:G, "n") + COUNTIFS('GHG Emissions'!F:F, 2018, 'GHG Emissions'!G:G, "s/l-UNC") + COUNTIFS('GHG Emissions'!F:F, 2018, 'GHG Emissions'!G:G, "s/l-POS") + COUNTIFS('GHG Emissions'!F:F, 2018, 'GHG Emissions'!G:G, "s/l-NEG") + COUNTIFS(Pollution!F:F, 2018, Pollution!G:G, "n") + COUNTIFS(Pollution!F:F, 2018, Pollution!G:G, "s/l-UNC") + COUNTIFS(Pollution!F:F, 2018, Pollution!G:G, "s/l-POS") + COUNTIFS(Pollution!F:F, 2018, Pollution!G:G, "s/l-NEG") + COUNTIFS('Energy|Power'!F:F, 2018, 'Energy|Power'!G:G, "n") + COUNTIFS('Energy|Power'!F:F, 2018, 'Energy|Power'!G:G, "s/l-UNC") + COUNTIFS('Energy|Power'!F:F, 2018, 'Energy|Power'!G:G, "s/l-POS") + COUNTIFS('Energy|Power'!F:F, 2018, 'Energy|Power'!G:G, "s/l-NEG") + COUNTIFS(Industry!F:F, 2018, Industry!G:G, "n") + COUNTIFS(Industry!F:F, 2018, Industry!G:G, "s/l-UNC") + COUNTIFS(Industry!F:F, 2018, Industry!G:G, "s/l-POS") + COUNTIFS(Industry!F:F, 2018, Industry!G:G, "s/l-NEG") + COUNTIFS(Buildings!F:F, 2018, Buildings!G:G, "n") + COUNTIFS(Buildings!F:F, 2018, Buildings!G:G, "s/l-UNC") + COUNTIFS(Buildings!F:F, 2018, Buildings!G:G, "s/l-POS") + COUNTIFS(Buildings!F:F, 2018, Buildings!G:G, "s/l-NEG") + COUNTIFS(Transport!F:F, 2018, Transport!G:G, "n") + COUNTIFS(Transport!F:F, 2018, Transport!G:G, "s/l-UNC") + COUNTIFS(Transport!F:F, 2018, Transport!G:G, "s/l-POS") + COUNTIFS(Transport!F:F, 2018, Transport!G:G, "s/l-NEG") + COUNTIFS(LULUCF!F:F, 2018, LULUCF!G:G, "n") + COUNTIFS(LULUCF!F:F, 2018, LULUCF!G:G, "s/l-UNC") + COUNTIFS(LULUCF!F:F, 2018, LULUCF!G:G, "s/l-POS") + COUNTIFS(LULUCF!F:F, 2018, LULUCF!G:G, "s/l-NEG") + COUNTIFS('Circular Economy'!F:F, 2018, 'Circular Economy'!G:G, "n") + COUNTIFS('Circular Economy'!F:F, 2018, 'Circular Economy'!G:G, "s/l-UNC") + COUNTIFS('Circular Economy'!F:F, 2018, 'Circular Economy'!G:G, "s/l-POS") + COUNTIFS('Circular Economy'!F:F, 2018, 'Circular Economy'!G:G, "s/l-NEG") + COUNTIFS(Finance!F:F, 2018, Finance!G:G, "n") + COUNTIFS(Finance!F:F, 2018, Finance!G:G, "s/l-UNC") + COUNTIFS(Finance!F:F, 2018, Finance!G:G, "s/l-POS") + COUNTIFS(Finance!F:F, 2018, Finance!G:G, "s/l-NEG") | Q16: Coal-related | R16: =COUNTIFS('GHG Emissions'!H:H, "Coal-related", 'GHG Emissions'!G:G, "n") + COUNTIFS('GHG Emissions'!H:H, "Coal-related", 'GHG Emissions'!G:G, "s/l-UNC") + COUNTIFS('GHG Emissions'!H:H, "Coal-related", 'GHG Emissions'!G:G, "s/l-POS") + COUNTIFS('GHG Emissions'!H:H, "Coal-related", 'GHG Emissions'!G:G, "s/l-NEG") + COUNTIFS(Pollution!H:H, "Coal-related", Pollution!G:G, "n") + COUNTIFS(Pollution!H:H, "Coal-related", Pollution!G:G, "s/l-UNC") + COUNTIFS(Pollution!H:H, "Coal-related", Pollution!G:G, "s/l-POS") + COUNTIFS(Pollution!H:H, "Coal-related", Pollution!G:G, "s/l-NEG") + COUNTIFS('Energy|Power'!H:H, "Coal-related", 'Energy|Power'!G:G, "n") + COUNTIFS('Energy|Power'!H:H, "Coal-related", 'Energy|Power'!G:G, "s/l-UNC") + COUNTIFS('Energy|Power'!H:H, "Coal-related", 'Energy|Power'!G:G, "s/l-POS") + COUNTIFS('Energy|Power'!H:H, "Coal-related", 'Energy|Power'!G:G, "s/l-NEG") + COUNTIFS(Industry!H:H, "Coal-related", Industry!G:G, "n") + COUNTIFS(Industry!H:H, "Coal-related", Industry!G:G, "s/l-UNC") + COUNTIFS(Industry!H:H, "Coal-related", Industry!G:G, "s/l-POS") + COUNTIFS(Industry!H:H, "Coal-related", Industry!G:G, "s/l-NEG") + COUNTIFS(Buildings!H:H, "Coal-related", Buildings!G:G, "n") + COUNTIFS(Buildings!H:H, "Coal-related", Buildings!G:G, "s/l-UNC") + COUNTIFS(Buildings!H:H, "Coal-related", Buildings!G:G, "s/l-POS") + COUNTIFS(Buildings!H:H, "Coal-related", Buildings!G:G, "s/l-NEG") + COUNTIFS(Transport!H:H, "Coal-related", Transport!G:G, "n") + COUNTIFS(Transport!H:H, "Coal-related", Transport!G:G, "s/l-UNC") + COUNTIFS(Transport!H:H, "Coal-related", Transport!G:G, "s/l-POS") + COUNTIFS(Transport!H:H, "Coal-related", Transport!G:G, "s/l-NEG") + COUNTIFS(LULUCF!H:H, "Coal-related", LULUCF!G:G, "n") + COUNTIFS(LULUCF!H:H, "Coal-related", LULUCF!G:G, "s/l-UNC") + COUNTIFS(LULUCF!H:H, "Coal-related", LULUCF!G:G, "s/l-POS") + COUNTIFS(LULUCF!H:H, "Coal-related", LULUCF!G:G, "s/l-NEG") + COUNTIFS('Circular Economy'!H:H, "Coal-related", 'Circular Economy'!G:G, "n") + COUNTIFS('Circular Economy'!H:H, "Coal-related", 'Circular Economy'!G:G, "s/l-UNC") + COUNTIFS('Circular Economy'!H:H, "Coal-related", 'Circular Economy'!G:G, "s/l-POS") + COUNTIFS('Circular Economy'!H:H, "Coal-related", 'Circular Economy'!G:G, "s/l-NEG") + COUNTIFS(Finance!H:H, "Coal-related", Finance!G:G, "n") + COUNTIFS(Finance!H:H, "Coal-related", Finance!G:G, "s/l-UNC") + COUNTIFS(Finance!H:H, "Coal-related", Finance!G:G, "s/l-POS") + COUNTIFS(Finance!H:H, "Coal-related", Finance!G:G, "s/l-NEG")
K17: 2015 | L17: =COUNTIFS('GHG Emissions'!A:A, 2015, 'GHG Emissions'!G:G, "n") + COUNTIFS('GHG Emissions'!A:A, 2015, 'GHG Emissions'!G:G, "s/l-UNC") + COUNTIFS('GHG Emissions'!A:A, 2015, 'GHG Emissions'!G:G, "s/l-POS") + COUNTIFS('GHG Emissions'!A:A, 2015, 'GHG Emissions'!G:G, "s/l-NEG") + COUNTIFS(Pollution!A:A, 2015, Pollution!G:G, "n") + COUNTIFS(Pollution!A:A, 2015, Pollution!G:G, "s/l-UNC") + COUNTIFS(Pollution!A:A, 2015, Pollution!G:G, "s/l-POS") + COUNTIFS(Pollution!A:A, 2015, Pollution!G:G, "s/l-NEG") + COUNTIFS('Energy|Power'!A:A, 2015, 'Energy|Power'!G:G, "n") + COUNTIFS('Energy|Power'!A:A, 2015, 'Energy|Power'!G:G, "s/l-UNC") + COUNTIFS('Energy|Power'!A:A, 2015, 'Energy|Power'!G:G, "s/l-POS") + COUNTIFS('Energy|Power'!A:A, 2015, 'Energy|Power'!G:G, "s/l-NEG") + COUNTIFS(Industry!A:A, 2015, Industry!G:G, "n") + COUNTIFS(Industry!A:A, 2015, Industry!G:G, "s/l-UNC") + COUNTIFS(Industry!A:A, 2015, Industry!G:G, "s/l-POS") + COUNTIFS(Industry!A:A, 2015, Industry!G:G, "s/l-NEG") + COUNTIFS(Buildings!A:A, 2015, Buildings!G:G, "n") + COUNTIFS(Buildings!A:A, 2015, Buildings!G:G, "s/l-UNC") + COUNTIFS(Buildings!A:A, 2015, Buildings!G:G, "s/l-POS") + COUNTIFS(Buildings!A:A, 2015, Buildings!G:G, "s/l-NEG") + COUNTIFS(Transport!A:A, 2015, Transport!G:G, "n") + COUNTIFS(Transport!A:A, 2015, Transport!G:G, "s/l-UNC") + COUNTIFS(Transport!A:A, 2015, Transport!G:G, "s/l-POS") + COUNTIFS(Transport!A:A, 2015, Transport!G:G, "s/l-NEG") + COUNTIFS(LULUCF!A:A, 2015, LULUCF!G:G, "n") + COUNTIFS(LULUCF!A:A, 2015, LULUCF!G:G, "s/l-UNC") + COUNTIFS(LULUCF!A:A, 2015, LULUCF!G:G, "s/l-POS") + COUNTIFS(LULUCF!A:A, 2015, LULUCF!G:G, "s/l-NEG") + COUNTIFS('Circular Economy'!A:A, 2015, 'Circular Economy'!G:G, "n") + COUNTIFS('Circular Economy'!A:A, 2015, 'Circular Economy'!G:G, "s/l-UNC") + COUNTIFS('Circular Economy'!A:A, 2015, 'Circular Economy'!G:G, "s/l-POS") + COUNTIFS('Circular Economy'!A:A, 2015, 'Circular Economy'!G:G, "s/l-NEG") + COUNTIFS(Finance!A:A, 2015, Finance!G:G, "n") + COUNTIFS(Finance!A:A, 2015, Finance!G:G, "s/l-UNC") + COUNTIFS(Finance!A:A, 2015, Finance!G:G, "s/l-POS") + COUNTIFS(Finance!A:A, 2015, Finance!G:G, "s/l-NEG") | N17: 2019 | O17: =COUNTIFS('GHG Emissions'!F:F, 2019, 'GHG Emissions'!G:G, "n") + COUNTIFS('GHG Emissions'!F:F, 2019, 'GHG Emissions'!G:G, "s/l-UNC") + COUNTIFS('GHG Emissions'!F:F, 2019, 'GHG Emissions'!G:G, "s/l-POS") + COUNTIFS('GHG Emissions'!F:F, 2019, 'GHG Emissions'!G:G, "s/l-NEG") + COUNTIFS(Pollution!F:F, 2019, Pollution!G:G, "n") + COUNTIFS(Pollution!F:F, 2019, Pollution!G:G, "s/l-UNC") + COUNTIFS(Pollution!F:F, 2019, Pollution!G:G, "s/l-POS") + COUNTIFS(Pollution!F:F, 2019, Pollution!G:G, "s/l-NEG") + COUNTIFS('Energy|Power'!F:F, 2019, 'Energy|Power'!G:G, "n") + COUNTIFS('Energy|Power'!F:F, 2019, 'Energy|Power'!G:G, "s/l-UNC") + COUNTIFS('Energy|Power'!F:F, 2019, 'Energy|Power'!G:G, "s/l-POS") + COUNTIFS('Energy|Power'!F:F, 2019, 'Energy|Power'!G:G, "s/l-NEG") + COUNTIFS(Industry!F:F, 2019, Industry!G:G, "n") + COUNTIFS(Industry!F:F, 2019, Industry!G:G, "s/l-UNC") + COUNTIFS(Industry!F:F, 2019, Industry!G:G, "s/l-POS") + COUNTIFS(Industry!F:F, 2019, Industry!G:G, "s/l-NEG") + COUNTIFS(Buildings!F:F, 2019, Buildings!G:G, "n") + COUNTIFS(Buildings!F:F, 2019, Buildings!G:G, "s/l-UNC") + COUNTIFS(Buildings!F:F, 2019, Buildings!G:G, "s/l-POS") + COUNTIFS(Buildings!F:F, 2019, Buildings!G:G, "s/l-NEG") + COUNTIFS(Transport!F:F, 2019, Transport!G:G, "n") + COUNTIFS(Transport!F:F, 2019, Transport!G:G, "s/l-UNC") + COUNTIFS(Transport!F:F, 2019, Transport!G:G, "s/l-POS") + COUNTIFS(Transport!F:F, 2019, Transport!G:G, "s/l-NEG") + COUNTIFS(LULUCF!F:F, 2019, LULUCF!G:G, "n") + COUNTIFS(LULUCF!F:F, 2019, LULUCF!G:G, "s/l-UNC") + COUNTIFS(LULUCF!F:F, 2019, LULUCF!G:G, "s/l-POS") + COUNTIFS(LULUCF!F:F, 2019, LULUCF!G:G, "s/l-NEG") + COUNTIFS('Circular Economy'!F:F, 2019, 'Circular Economy'!G:G, "n") + COUNTIFS('Circular Economy'!F:F, 2019, 'Circular Economy'!G:G, "s/l-UNC") + COUNTIFS('Circular Economy'!F:F, 2019, 'Circular Economy'!G:G, "s/l-POS") + COUNTIFS('Circular Economy'!F:F, 2019, 'Circular Economy'!G:G, "s/l-NEG") + COUNTIFS(Finance!F:F, 2019, Finance!G:G, "n") + COUNTIFS(Finance!F:F, 2019, Finance!G:G, "s/l-UNC") + COUNTIFS(Finance!F:F, 2019, Finance!G:G, "s/l-POS") + COUNTIFS(Finance!F:F, 2019, Finance!G:G, "s/l-NEG") | Q17: Production-oriented | R17: =COUNTIFS('GHG Emissions'!H:H, "Production-oriented", 'GHG Emissions'!G:G, "n") + COUNTIFS('GHG Emissions'!H:H, "Production-oriented", 'GHG Emissions'!G:G, "s/l-UNC") + COUNTIFS('GHG Emissions'!H:H, "Production-oriented", 'GHG Emissions'!G:G, "s/l-POS") + COUNTIFS('GHG Emissions'!H:H, "Production-oriented", 'GHG Emissions'!G:G, "s/l-NEG") + COUNTIFS(Pollution!H:H, "Production-oriented", Pollution!G:G, "n") + COUNTIFS(Pollution!H:H, "Production-oriented", Pollution!G:G, "s/l-UNC") + COUNTIFS(Pollution!H:H, "Production-oriented", Pollution!G:G, "s/l-POS") + COUNTIFS(Pollution!H:H, "Production-oriented", Pollution!G:G, "s/l-NEG") + COUNTIFS('Energy|Power'!H:H, "Production-oriented", 'Energy|Power'!G:G, "n") + COUNTIFS('Energy|Power'!H:H, "Production-oriented", 'Energy|Power'!G:G, "s/l-UNC") + COUNTIFS('Energy|Power'!H:H, "Production-oriented", 'Energy|Power'!G:G, "s/l-POS") + COUNTIFS('Energy|Power'!H:H, "Production-oriented", 'Energy|Power'!G:G, "s/l-NEG") + COUNTIFS(Industry!H:H, "Production-oriented", Industry!G:G, "n") + COUNTIFS(Industry!H:H, "Production-oriented", Industry!G:G, "s/l-UNC") + COUNTIFS(Industry!H:H, "Production-oriented", Industry!G:G, "s/l-POS") + COUNTIFS(Industry!H:H, "Production-oriented", Industry!G:G, "s/l-NEG") + COUNTIFS(Buildings!H:H, "Production-oriented", Buildings!G:G, "n") + COUNTIFS(Buildings!H:H, "Production-oriented", Buildings!G:G, "s/l-UNC") + COUNTIFS(Buildings!H:H, "Production-oriented", Buildings!G:G, "s/l-POS") + COUNTIFS(Buildings!H:H, "Production-oriented", Buildings!G:G, "s/l-NEG") + COUNTIFS(Transport!H:H, "Production-oriented", Transport!G:G, "n") + COUNTIFS(Transport!H:H, "Production-oriented", Transport!G:G, "s/l-UNC") + COUNTIFS(Transport!H:H, "Production-oriented", Transport!G:G, "s/l-POS") + COUNTIFS(Transport!H:H, "Production-oriented", Transport!G:G, "s/l-NEG") + COUNTIFS(LULUCF!H:H, "Production-oriented", LULUCF!G:G, "n") + COUNTIFS(LULUCF!H:H, "Production-oriented", LULUCF!G:G, "s/l-UNC") + COUNTIFS(LULUCF!H:H, "Production-oriented", LULUCF!G:G, "s/l-POS") + COUNTIFS(LULUCF!H:H, "Production-oriented", LULUCF!G:G, "s/l-NEG") + COUNTIFS('Circular Economy'!H:H, "Production-oriented", 'Circular Economy'!G:G, "n") + COUNTIFS('Circular Economy'!H:H, "Production-oriented", 'Circular Economy'!G:G, "s/l-UNC") + COUNTIFS('Circular Economy'!H:H, "Production-oriented", 'Circular Economy'!G:G, "s/l-POS") + COUNTIFS('Circular Economy'!H:H, "Production-oriented", 'Circular Economy'!G:G, "s/l-NEG") + COUNTIFS(Finance!H:H, "Production-oriented", Finance!G:G, "n") + COUNTIFS(Finance!H:H, "Production-oriented", Finance!G:G, "s/l-UNC") + COUNTIFS(Finance!H:H, "Production-oriented", Finance!G:G, "s/l-POS") + COUNTIFS(Finance!H:H, "Production-oriented", Finance!G:G, "s/l-NEG")
K18: 2016 | L18: =COUNTIFS('GHG Emissions'!A:A, 2016, 'GHG Emissions'!G:G, "n") + COUNTIFS('GHG Emissions'!A:A, 2016, 'GHG Emissions'!G:G, "s/l-UNC") + COUNTIFS('GHG Emissions'!A:A, 2016, 'GHG Emissions'!G:G, "s/l-POS") + COUNTIFS('GHG Emissions'!A:A, 2016, 'GHG Emissions'!G:G, "s/l-NEG") + COUNTIFS(Pollution!A:A, 2016, Pollution!G:G, "n") + COUNTIFS(Pollution!A:A, 2016, Pollution!G:G, "s/l-UNC") + COUNTIFS(Pollution!A:A, 2016, Pollution!G:G, "s/l-POS") + COUNTIFS(Pollution!A:A, 2016, Pollution!G:G, "s/l-NEG") + COUNTIFS('Energy|Power'!A:A, 2016, 'Energy|Power'!G:G, "n") + COUNTIFS('Energy|Power'!A:A, 2016, 'Energy|Power'!G:G, "s/l-UNC") + COUNTIFS('Energy|Power'!A:A, 2016, 'Energy|Power'!G:G, "s/l-POS") + COUNTIFS('Energy|Power'!A:A, 2016, 'Energy|Power'!G:G, "s/l-NEG") + COUNTIFS(Industry!A:A, 2016, Industry!G:G, "n") + COUNTIFS(Industry!A:A, 2016, Industry!G:G, "s/l-UNC") + COUNTIFS(Industry!A:A, 2016, Industry!G:G, "s/l-POS") + COUNTIFS(Industry!A:A, 2016, Industry!G:G, "s/l-NEG") + COUNTIFS(Buildings!A:A, 2016, Buildings!G:G, "n") + COUNTIFS(Buildings!A:A, 2016, Buildings!G:G, "s/l-UNC") + COUNTIFS(Buildings!A:A, 2016, Buildings!G:G, "s/l-POS") + COUNTIFS(Buildings!A:A, 2016, Buildings!G:G, "s/l-NEG") + COUNTIFS(Transport!A:A, 2016, Transport!G:G, "n") + COUNTIFS(Transport!A:A, 2016, Transport!G:G, "s/l-UNC") + COUNTIFS(Transport!A:A, 2016, Transport!G:G, "s/l-POS") + COUNTIFS(Transport!A:A, 2016, Transport!G:G, "s/l-NEG") + COUNTIFS(LULUCF!A:A, 2016, LULUCF!G:G, "n") + COUNTIFS(LULUCF!A:A, 2016, LULUCF!G:G, "s/l-UNC") + COUNTIFS(LULUCF!A:A, 2016, LULUCF!G:G, "s/l-POS") + COUNTIFS(LULUCF!A:A, 2016, LULUCF!G:G, "s/l-NEG") + COUNTIFS('Circular Economy'!A:A, 2016, 'Circular Economy'!G:G, "n") + COUNTIFS('Circular Economy'!A:A, 2016, 'Circular Economy'!G:G, "s/l-UNC") + COUNTIFS('Circular Economy'!A:A, 2016, 'Circular Economy'!G:G, "s/l-POS") + COUNTIFS('Circular Economy'!A:A, 2016, 'Circular Economy'!G:G, "s/l-NEG") + COUNTIFS(Finance!A:A, 2016, Finance!G:G, "n") + COUNTIFS(Finance!A:A, 2016, Finance!G:G, "s/l-UNC") + COUNTIFS(Finance!A:A, 2016, Finance!G:G, "s/l-POS") + COUNTIFS(Finance!A:A, 2016, Finance!G:G, "s/l-NEG") | N18: 2020 | O18: =COUNTIFS('GHG Emissions'!F:F, 2020, 'GHG Emissions'!G:G, "n") + COUNTIFS('GHG Emissions'!F:F, 2020, 'GHG Emissions'!G:G, "s/l-UNC") + COUNTIFS('GHG Emissions'!F:F, 2020, 'GHG Emissions'!G:G, "s/l-POS") + COUNTIFS('GHG Emissions'!F:F, 2020, 'GHG Emissions'!G:G, "s/l-NEG") + COUNTIFS(Pollution!F:F, 2020, Pollution!G:G, "n") + COUNTIFS(Pollution!F:F, 2020, Pollution!G:G, "s/l-UNC") + COUNTIFS(Pollution!F:F, 2020, Pollution!G:G, "s/l-POS") + COUNTIFS(Pollution!F:F, 2020, Pollution!G:G, "s/l-NEG") + COUNTIFS('Energy|Power'!F:F, 2020, 'Energy|Power'!G:G, "n") + COUNTIFS('Energy|Power'!F:F, 2020, 'Energy|Power'!G:G, "s/l-UNC") + COUNTIFS('Energy|Power'!F:F, 2020, 'Energy|Power'!G:G, "s/l-POS") + COUNTIFS('Energy|Power'!F:F, 2020, 'Energy|Power'!G:G, "s/l-NEG") + COUNTIFS(Industry!F:F, 2020, Industry!G:G, "n") + COUNTIFS(Industry!F:F, 2020, Industry!G:G, "s/l-UNC") + COUNTIFS(Industry!F:F, 2020, Industry!G:G, "s/l-POS") + COUNTIFS(Industry!F:F, 2020, Industry!G:G, "s/l-NEG") + COUNTIFS(Buildings!F:F, 2020, Buildings!G:G, "n") + COUNTIFS(Buildings!F:F, 2020, Buildings!G:G, "s/l-UNC") + COUNTIFS(Buildings!F:F, 2020, Buildings!G:G, "s/l-POS") + COUNTIFS(Buildings!F:F, 2020, Buildings!G:G, "s/l-NEG") + COUNTIFS(Transport!F:F, 2020, Transport!G:G, "n") + COUNTIFS(Transport!F:F, 2020, Transport!G:G, "s/l-UNC") + COUNTIFS(Transport!F:F, 2020, Transport!G:G, "s/l-POS") + COUNTIFS(Transport!F:F, 2020, Transport!G:G, "s/l-NEG") + COUNTIFS(LULUCF!F:F, 2020, LULUCF!G:G, "n") + COUNTIFS(LULUCF!F:F, 2020, LULUCF!G:G, "s/l-UNC") + COUNTIFS(LULUCF!F:F, 2020, LULUCF!G:G, "s/l-POS") + COUNTIFS(LULUCF!F:F, 2020, LULUCF!G:G, "s/l-NEG") + COUNTIFS('Circular Economy'!F:F, 2020, 'Circular Economy'!G:G, "n") + COUNTIFS('Circular Economy'!F:F, 2020, 'Circular Economy'!G:G, "s/l-UNC") + COUNTIFS('Circular Economy'!F:F, 2020, 'Circular Economy'!G:G, "s/l-POS") + COUNTIFS('Circular Economy'!F:F, 2020, 'Circular Economy'!G:G, "s/l-NEG") + COUNTIFS(Finance!F:F, 2020, Finance!G:G, "n") + COUNTIFS(Finance!F:F, 2020, Finance!G:G, "s/l-UNC") + COUNTIFS(Finance!F:F, 2020, Finance!G:G, "s/l-POS") + COUNTIFS(Finance!F:F, 2020, Finance!G:G, "s/l-NEG") | Q18: Industrial transformation | R18: =COUNTIFS('GHG Emissions'!H:H, "Industrial transformation", 'GHG Emissions'!G:G, "n") + COUNTIFS('GHG Emissions'!H:H, "Industrial transformation", 'GHG Emissions'!G:G, "s/l-UNC") + COUNTIFS('GHG Emissions'!H:H, "Industrial transformation", 'GHG Emissions'!G:G, "s/l-POS") + COUNTIFS('GHG Emissions'!H:H, "Industrial transformation", 'GHG Emissions'!G:G, "s/l-NEG") + COUNTIFS(Pollution!H:H, "Industrial transformation", Pollution!G:G, "n") + COUNTIFS(Pollution!H:H, "Industrial transformation", Pollution!G:G, "s/l-UNC") + COUNTIFS(Pollution!H:H, "Industrial transformation", Pollution!G:G, "s/l-POS") + COUNTIFS(Pollution!H:H, "Industrial transformation", Pollution!G:G, "s/l-NEG") + COUNTIFS('Energy|Power'!H:H, "Industrial transformation", 'Energy|Power'!G:G, "n") + COUNTIFS('Energy|Power'!H:H, "Industrial transformation", 'Energy|Power'!G:G, "s/l-UNC") + COUNTIFS('Energy|Power'!H:H, "Industrial transformation", 'Energy|Power'!G:G, "s/l-POS") + COUNTIFS('Energy|Power'!H:H, "Industrial transformation", 'Energy|Power'!G:G, "s/l-NEG") + COUNTIFS(Industry!H:H, "Industrial transformation", Industry!G:G, "n") + COUNTIFS(Industry!H:H, "Industrial transformation", Industry!G:G, "s/l-UNC") + COUNTIFS(Industry!H:H, "Industrial transformation", Industry!G:G, "s/l-POS") + COUNTIFS(Industry!H:H, "Industrial transformation", Industry!G:G, "s/l-NEG") + COUNTIFS(Buildings!H:H, "Industrial transformation", Buildings!G:G, "n") + COUNTIFS(Buildings!H:H, "Industrial transformation", Buildings!G:G, "s/l-UNC") + COUNTIFS(Buildings!H:H, "Industrial transformation", Buildings!G:G, "s/l-POS") + COUNTIFS(Buildings!H:H, "Industrial transformation", Buildings!G:G, "s/l-NEG") + COUNTIFS(Transport!H:H, "Industrial transformation", Transport!G:G, "n") + COUNTIFS(Transport!H:H, "Industrial transformation", Transport!G:G, "s/l-UNC") + COUNTIFS(Transport!H:H, "Industrial transformation", Transport!G:G, "s/l-POS") + COUNTIFS(Transport!H:H, "Industrial transformation", Transport!G:G, "s/l-NEG") + COUNTIFS(LULUCF!H:H, "Industrial transformation", LULUCF!G:G, "n") + COUNTIFS(LULUCF!H:H, "Industrial transformation", LULUCF!G:G, "s/l-UNC") + COUNTIFS(LULUCF!H:H, "Industrial transformation", LULUCF!G:G, "s/l-POS") + COUNTIFS(LULUCF!H:H, "Industrial transformation", LULUCF!G:G, "s/l-NEG") + COUNTIFS('Circular Economy'!H:H, "Industrial transformation", 'Circular Economy'!G:G, "n") + COUNTIFS('Circular Economy'!H:H, "Industrial transformation", 'Circular Economy'!G:G, "s/l-UNC") + COUNTIFS('Circular Economy'!H:H, "Industrial transformation", 'Circular Economy'!G:G, "s/l-POS") + COUNTIFS('Circular Economy'!H:H, "Industrial transformation", 'Circular Economy'!G:G, "s/l-NEG") + COUNTIFS(Finance!H:H, "Industrial transformation", Finance!G:G, "n") + COUNTIFS(Finance!H:H, "Industrial transformation", Finance!G:G, "s/l-UNC") + COUNTIFS(Finance!H:H, "Industrial transformation", Finance!G:G, "s/l-POS") + COUNTIFS(Finance!H:H, "Industrial transformation", Finance!G:G, "s/l-NEG")
K19: 2017 | L19: =COUNTIFS('GHG Emissions'!A:A, 2017, 'GHG Emissions'!G:G, "n") + COUNTIFS('GHG Emissions'!A:A, 2017, 'GHG Emissions'!G:G, "s/l-UNC") + COUNTIFS('GHG Emissions'!A:A, 2017, 'GHG Emissions'!G:G, "s/l-POS") + COUNTIFS('GHG Emissions'!A:A, 2017, 'GHG Emissions'!G:G, "s/l-NEG") + COUNTIFS(Pollution!A:A, 2017, Pollution!G:G, "n") + COUNTIFS(Pollution!A:A, 2017, Pollution!G:G, "s/l-UNC") + COUNTIFS(Pollution!A:A, 2017, Pollution!G:G, "s/l-POS") + COUNTIFS(Pollution!A:A, 2017, Pollution!G:G, "s/l-NEG") + COUNTIFS('Energy|Power'!A:A, 2017, 'Energy|Power'!G:G, "n") + COUNTIFS('Energy|Power'!A:A, 2017, 'Energy|Power'!G:G, "s/l-UNC") + COUNTIFS('Energy|Power'!A:A, 2017, 'Energy|Power'!G:G, "s/l-POS") + COUNTIFS('Energy|Power'!A:A, 2017, 'Energy|Power'!G:G, "s/l-NEG") + COUNTIFS(Industry!A:A, 2017, Industry!G:G, "n") + COUNTIFS(Industry!A:A, 2017, Industry!G:G, "s/l-UNC") + COUNTIFS(Industry!A:A, 2017, Industry!G:G, "s/l-POS") + COUNTIFS(Industry!A:A, 2017, Industry!G:G, "s/l-NEG") + COUNTIFS(Buildings!A:A, 2017, Buildings!G:G, "n") + COUNTIFS(Buildings!A:A, 2017, Buildings!G:G, "s/l-UNC") + COUNTIFS(Buildings!A:A, 2017, Buildings!G:G, "s/l-POS") + COUNTIFS(Buildings!A:A, 2017, Buildings!G:G, "s/l-NEG") + COUNTIFS(Transport!A:A, 2017, Transport!G:G, "n") + COUNTIFS(Transport!A:A, 2017, Transport!G:G, "s/l-UNC") + COUNTIFS(Transport!A:A, 2017, Transport!G:G, "s/l-POS") + COUNTIFS(Transport!A:A, 2017, Transport!G:G, "s/l-NEG") + COUNTIFS(LULUCF!A:A, 2017, LULUCF!G:G, "n") + COUNTIFS(LULUCF!A:A, 2017, LULUCF!G:G, "s/l-UNC") + COUNTIFS(LULUCF!A:A, 2017, LULUCF!G:G, "s/l-POS") + COUNTIFS(LULUCF!A:A, 2017, LULUCF!G:G, "s/l-NEG") + COUNTIFS('Circular Economy'!A:A, 2017, 'Circular Economy'!G:G, "n") + COUNTIFS('Circular Economy'!A:A, 2017, 'Circular Economy'!G:G, "s/l-UNC") + COUNTIFS('Circular Economy'!A:A, 2017, 'Circular Economy'!G:G, "s/l-POS") + COUNTIFS('Circular Economy'!A:A, 2017, 'Circular Economy'!G:G, "s/l-NEG") + COUNTIFS(Finance!A:A, 2017, Finance!G:G, "n") + COUNTIFS(Finance!A:A, 2017, Finance!G:G, "s/l-UNC") + COUNTIFS(Finance!A:A, 2017, Finance!G:G, "s/l-POS") + COUNTIFS(Finance!A:A, 2017, Finance!G:G, "s/l-NEG") | N19: 13th FYP | O19: =COUNTIFS('GHG Emissions'!F:F, "13th FYP", 'GHG Emissions'!G:G, "n") + COUNTIFS('GHG Emissions'!F:F, "13th FYP", 'GHG Emissions'!G:G, "s/l-UNC") + COUNTIFS('GHG Emissions'!F:F, "13th FYP", 'GHG Emissions'!G:G, "s/l-POS") + COUNTIFS('GHG Emissions'!F:F, "13th FYP", 'GHG Emissions'!G:G, "s/l-NEG") + COUNTIFS(Pollution!F:F, "13th FYP", Pollution!G:G, "n") + COUNTIFS(Pollution!F:F, "13th FYP", Pollution!G:G, "s/l-UNC") + COUNTIFS(Pollution!F:F, "13th FYP", Pollution!G:G, "s/l-POS") + COUNTIFS(Pollution!F:F, "13th FYP", Pollution!G:G, "s/l-NEG") + COUNTIFS('Energy|Power'!F:F, "13th FYP", 'Energy|Power'!G:G, "n") + COUNTIFS('Energy|Power'!F:F, "13th FYP", 'Energy|Power'!G:G, "s/l-UNC") + COUNTIFS('Energy|Power'!F:F, "13th FYP", 'Energy|Power'!G:G, "s/l-POS") + COUNTIFS('Energy|Power'!F:F, "13th FYP", 'Energy|Power'!G:G, "s/l-NEG") + COUNTIFS(Industry!F:F, "13th FYP", Industry!G:G, "n") + COUNTIFS(Industry!F:F, "13th FYP", Industry!G:G, "s/l-UNC") + COUNTIFS(Industry!F:F, "13th FYP", Industry!G:G, "s/l-POS") + COUNTIFS(Industry!F:F, "13th FYP", Industry!G:G, "s/l-NEG") + COUNTIFS(Buildings!F:F, "13th FYP", Buildings!G:G, "n") + COUNTIFS(Buildings!F:F, "13th FYP", Buildings!G:G, "s/l-UNC") + COUNTIFS(Buildings!F:F, "13th FYP", Buildings!G:G, "s/l-POS") + COUNTIFS(Buildings!F:F, "13th FYP", Buildings!G:G, "s/l-NEG") + COUNTIFS(Transport!F:F, "13th FYP", Transport!G:G, "n") + COUNTIFS(Transport!F:F, "13th FYP", Transport!G:G, "s/l-UNC") + COUNTIFS(Transport!F:F, "13th FYP", Transport!G:G, "s/l-POS") + COUNTIFS(Transport!F:F, "13th FYP", Transport!G:G, "s/l-NEG") + COUNTIFS(LULUCF!F:F, "13th FYP", LULUCF!G:G, "n") + COUNTIFS(LULUCF!F:F, "13th FYP", LULUCF!G:G, "s/l-UNC") + COUNTIFS(LULUCF!F:F, "13th FYP", LULUCF!G:G, "s/l-POS") + COUNTIFS(LULUCF!F:F, "13th FYP", LULUCF!G:G, "s/l-NEG") + COUNTIFS('Circular Economy'!F:F, "13th FYP", 'Circular Economy'!G:G, "n") + COUNTIFS('Circular Economy'!F:F, "13th FYP", 'Circular Economy'!G:G, "s/l-UNC") + COUNTIFS('Circular Economy'!F:F, "13th FYP", 'Circular Economy'!G:G, "s/l-POS") + COUNTIFS('Circular Economy'!F:F, "13th FYP", 'Circular Economy'!G:G, "s/l-NEG") + COUNTIFS(Finance!F:F, "13th FYP", Finance!G:G, "n") + COUNTIFS(Finance!F:F, "13th FYP", Finance!G:G, "s/l-UNC") + COUNTIFS(Finance!F:F, "13th FYP", Finance!G:G, "s/l-POS") + COUNTIFS(Finance!F:F, "13th FYP", Finance!G:G, "s/l-NEG") | Q19: Technology innovation | R19: =COUNTIFS('GHG Emissions'!H:H, "Technology innovation", 'GHG Emissions'!G:G, "n") + COUNTIFS('GHG Emissions'!H:H, "Technology innovation", 'GHG Emissions'!G:G, "s/l-UNC") + COUNTIFS('GHG Emissions'!H:H, "Technology innovation", 'GHG Emissions'!G:G, "s/l-POS") + COUNTIFS('GHG Emissions'!H:H, "Technology innovation", 'GHG Emissions'!G:G, "s/l-NEG") + COUNTIFS(Pollution!H:H, "Technology innovation", Pollution!G:G, "n") + COUNTIFS(Pollution!H:H, "Technology innovation", Pollution!G:G, "s/l-UNC") + COUNTIFS(Pollution!H:H, "Technology innovation", Pollution!G:G, "s/l-POS") + COUNTIFS(Pollution!H:H, "Technology innovation", Pollution!G:G, "s/l-NEG") + COUNTIFS('Energy|Power'!H:H, "Technology innovation", 'Energy|Power'!G:G, "n") + COUNTIFS('Energy|Power'!H:H, "Technology innovation", 'Energy|Power'!G:G, "s/l-UNC") + COUNTIFS('Energy|Power'!H:H, "Technology innovation", 'Energy|Power'!G:G, "s/l-POS") + COUNTIFS('Energy|Power'!H:H, "Technology innovation", 'Energy|Power'!G:G, "s/l-NEG") + COUNTIFS(Industry!H:H, "Technology innovation", Industry!G:G, "n") + COUNTIFS(Industry!H:H, "Technology innovation", Industry!G:G, "s/l-UNC") + COUNTIFS(Industry!H:H, "Technology innovation", Industry!G:G, "s/l-POS") + COUNTIFS(Industry!H:H, "Technology innovation", Industry!G:G, "s/l-NEG") + COUNTIFS(Buildings!H:H, "Technology innovation", Buildings!G:G, "n") + COUNTIFS(Buildings!H:H, "Technology innovation", Buildings!G:G, "s/l-UNC") + COUNTIFS(Buildings!H:H, "Technology innovation", Buildings!G:G, "s/l-POS") + COUNTIFS(Buildings!H:H, "Technology innovation", Buildings!G:G, "s/l-NEG") + COUNTIFS(Transport!H:H, "Technology innovation", Transport!G:G, "n") + COUNTIFS(Transport!H:H, "Technology innovation", Transport!G:G, "s/l-UNC") + COUNTIFS(Transport!H:H, "Technology innovation", Transport!G:G, "s/l-POS") + COUNTIFS(Transport!H:H, "Technology innovation", Transport!G:G, "s/l-NEG") + COUNTIFS(LULUCF!H:H, "Technology innovation", LULUCF!G:G, "n") + COUNTIFS(LULUCF!H:H, "Technology innovation", LULUCF!G:G, "s/l-UNC") + COUNTIFS(LULUCF!H:H, "Technology innovation", LULUCF!G:G, "s/l-POS") + COUNTIFS(LULUCF!H:H, "Technology innovation", LULUCF!G:G, "s/l-NEG") + COUNTIFS('Circular Economy'!H:H, "Technology innovation", 'Circular Economy'!G:G, "n") + COUNTIFS('Circular Economy'!H:H, "Technology innovation", 'Circular Economy'!G:G, "s/l-UNC") + COUNTIFS('Circular Economy'!H:H, "Technology innovation", 'Circular Economy'!G:G, "s/l-POS") + COUNTIFS('Circular Economy'!H:H, "Technology innovation", 'Circular Economy'!G:G, "s/l-NEG") + COUNTIFS(Finance!H:H, "Technology innovation", Finance!G:G, "n") + COUNTIFS(Finance!H:H, "Technology innovation", Finance!G:G, "s/l-UNC") + COUNTIFS(Finance!H:H, "Technology innovation", Finance!G:G, "s/l-POS") + COUNTIFS(Finance!H:H, "Technology innovation", Finance!G:G, "s/l-NEG")
K20: 2018 | L20: =COUNTIFS('GHG Emissions'!A:A, 2018, 'GHG Emissions'!G:G, "n") + COUNTIFS('GHG Emissions'!A:A, 2018, 'GHG Emissions'!G:G, "s/l-UNC") + COUNTIFS('GHG Emissions'!A:A, 2018, 'GHG Emissions'!G:G, "s/l-POS") + COUNTIFS('GHG Emissions'!A:A, 2018, 'GHG Emissions'!G:G, "s/l-NEG") + COUNTIFS(Pollution!A:A, 2018, Pollution!G:G, "n") + COUNTIFS(Pollution!A:A, 2018, Pollution!G:G, "s/l-UNC") + COUNTIFS(Pollution!A:A, 2018, Pollution!G:G, "s/l-POS") + COUNTIFS(Pollution!A:A, 2018, Pollution!G:G, "s/l-NEG") + COUNTIFS('Energy|Power'!A:A, 2018, 'Energy|Power'!G:G, "n") + COUNTIFS('Energy|Power'!A:A, 2018, 'Energy|Power'!G:G, "s/l-UNC") + COUNTIFS('Energy|Power'!A:A, 2018, 'Energy|Power'!G:G, "s/l-POS") + COUNTIFS('Energy|Power'!A:A, 2018, 'Energy|Power'!G:G, "s/l-NEG") + COUNTIFS(Industry!A:A, 2018, Industry!G:G, "n") + COUNTIFS(Industry!A:A, 2018, Industry!G:G, "s/l-UNC") + COUNTIFS(Industry!A:A, 2018, Industry!G:G, "s/l-POS") + COUNTIFS(Industry!A:A, 2018, Industry!G:G, "s/l-NEG") + COUNTIFS(Buildings!A:A, 2018, Buildings!G:G, "n") + COUNTIFS(Buildings!A:A, 2018, Buildings!G:G, "s/l-UNC") + COUNTIFS(Buildings!A:A, 2018, Buildings!G:G, "s/l-POS") + COUNTIFS(Buildings!A:A, 2018, Buildings!G:G, "s/l-NEG") + COUNTIFS(Transport!A:A, 2018, Transport!G:G, "n") + COUNTIFS(Transport!A:A, 2018, Transport!G:G, "s/l-UNC") + COUNTIFS(Transport!A:A, 2018, Transport!G:G, "s/l-POS") + COUNTIFS(Transport!A:A, 2018, Transport!G:G, "s/l-NEG") + COUNTIFS(LULUCF!A:A, 2018, LULUCF!G:G, "n") + COUNTIFS(LULUCF!A:A, 2018, LULUCF!G:G, "s/l-UNC") + COUNTIFS(LULUCF!A:A, 2018, LULUCF!G:G, "s/l-POS") + COUNTIFS(LULUCF!A:A, 2018, LULUCF!G:G, "s/l-NEG") + COUNTIFS('Circular Economy'!A:A, 2018, 'Circular Economy'!G:G, "n") + COUNTIFS('Circular Economy'!A:A, 2018, 'Circular Economy'!G:G, "s/l-UNC") + COUNTIFS('Circular Economy'!A:A, 2018, 'Circular Economy'!G:G, "s/l-POS") + COUNTIFS('Circular Economy'!A:A, 2018, 'Circular Economy'!G:G, "s/l-NEG") + COUNTIFS(Finance!A:A, 2018, Finance!G:G, "n") + COUNTIFS(Finance!A:A, 2018, Finance!G:G, "s/l-UNC") + COUNTIFS(Finance!A:A, 2018, Finance!G:G, "s/l-POS") + COUNTIFS(Finance!A:A, 2018, Finance!G:G, "s/l-NEG") | N20: 2021 | O20: =COUNTIFS('GHG Emissions'!F:F, 2021, 'GHG Emissions'!G:G, "n") + COUNTIFS('GHG Emissions'!F:F, 2021, 'GHG Emissions'!G:G, "s/l-UNC") + COUNTIFS('GHG Emissions'!F:F, 2021, 'GHG Emissions'!G:G, "s/l-POS") + COUNTIFS('GHG Emissions'!F:F, 2021, 'GHG Emissions'!G:G, "s/l-NEG") + COUNTIFS(Pollution!F:F, 2021, Pollution!G:G, "n") + COUNTIFS(Pollution!F:F, 2021, Pollution!G:G, "s/l-UNC") + COUNTIFS(Pollution!F:F, 2021, Pollution!G:G, "s/l-POS") + COUNTIFS(Pollution!F:F, 2021, Pollution!G:G, "s/l-NEG") + COUNTIFS('Energy|Power'!F:F, 2021, 'Energy|Power'!G:G, "n") + COUNTIFS('Energy|Power'!F:F, 2021, 'Energy|Power'!G:G, "s/l-UNC") + COUNTIFS('Energy|Power'!F:F, 2021, 'Energy|Power'!G:G, "s/l-POS") + COUNTIFS('Energy|Power'!F:F, 2021, 'Energy|Power'!G:G, "s/l-NEG") + COUNTIFS(Industry!F:F, 2021, Industry!G:G, "n") + COUNTIFS(Industry!F:F, 2021, Industry!G:G, "s/l-UNC") + COUNTIFS(Industry!F:F, 2021, Industry!G:G, "s/l-POS") + COUNTIFS(Industry!F:F, 2021, Industry!G:G, "s/l-NEG") + COUNTIFS(Buildings!F:F, 2021, Buildings!G:G, "n") + COUNTIFS(Buildings!F:F, 2021, Buildings!G:G, "s/l-UNC") + COUNTIFS(Buildings!F:F, 2021, Buildings!G:G, "s/l-POS") + COUNTIFS(Buildings!F:F, 2021, Buildings!G:G, "s/l-NEG") + COUNTIFS(Transport!F:F, 2021, Transport!G:G, "n") + COUNTIFS(Transport!F:F, 2021, Transport!G:G, "s/l-UNC") + COUNTIFS(Transport!F:F, 2021, Transport!G:G, "s/l-POS") + COUNTIFS(Transport!F:F, 2021, Transport!G:G, "s/l-NEG") + COUNTIFS(LULUCF!F:F, 2021, LULUCF!G:G, "n") + COUNTIFS(LULUCF!F:F, 2021, LULUCF!G:G, "s/l-UNC") + COUNTIFS(LULUCF!F:F, 2021, LULUCF!G:G, "s/l-POS") + COUNTIFS(LULUCF!F:F, 2021, LULUCF!G:G, "s/l-NEG") + COUNTIFS('Circular Economy'!F:F, 2021, 'Circular Economy'!G:G, "n") + COUNTIFS('Circular Economy'!F:F, 2021, 'Circular Economy'!G:G, "s/l-UNC") + COUNTIFS('Circular Economy'!F:F, 2021, 'Circular Economy'!G:G, "s/l-POS") + COUNTIFS('Circular Economy'!F:F, 2021, 'Circular Economy'!G:G, "s/l-NEG") + COUNTIFS(Finance!F:F, 2021, Finance!G:G, "n") + COUNTIFS(Finance!F:F, 2021, Finance!G:G, "s/l-UNC") + COUNTIFS(Finance!F:F, 2021, Finance!G:G, "s/l-POS") + COUNTIFS(Finance!F:F, 2021, Finance!G:G, "s/l-NEG") | Q20: Green transportation | R20: =COUNTIFS('GHG Emissions'!H:H, "Green transportation", 'GHG Emissions'!G:G, "n") + COUNTIFS('GHG Emissions'!H:H, "Green transportation", 'GHG Emissions'!G:G, "s/l-UNC") + COUNTIFS('GHG Emissions'!H:H, "Green transportation", 'GHG Emissions'!G:G, "s/l-POS") + COUNTIFS('GHG Emissions'!H:H, "Green transportation", 'GHG Emissions'!G:G, "s/l-NEG") + COUNTIFS(Pollution!H:H, "Green transportation", Pollution!G:G, "n") + COUNTIFS(Pollution!H:H, "Green transportation", Pollution!G:G, "s/l-UNC") + COUNTIFS(Pollution!H:H, "Green transportation", Pollution!G:G, "s/l-POS") + COUNTIFS(Pollution!H:H, "Green transportation", Pollution!G:G, "s/l-NEG") + COUNTIFS('Energy|Power'!H:H, "Green transportation", 'Energy|Power'!G:G, "n") + COUNTIFS('Energy|Power'!H:H, "Green transportation", 'Energy|Power'!G:G, "s/l-UNC") + COUNTIFS('Energy|Power'!H:H, "Green transportation", 'Energy|Power'!G:G, "s/l-POS") + COUNTIFS('Energy|Power'!H:H, "Green transportation", 'Energy|Power'!G:G, "s/l-NEG") + COUNTIFS(Industry!H:H, "Green transportation", Industry!G:G, "n") + COUNTIFS(Industry!H:H, "Green transportation", Industry!G:G, "s/l-UNC") + COUNTIFS(Industry!H:H, "Green transportation", Industry!G:G, "s/l-POS") + COUNTIFS(Industry!H:H, "Green transportation", Industry!G:G, "s/l-NEG") + COUNTIFS(Buildings!H:H, "Green transportation", Buildings!G:G, "n") + COUNTIFS(Buildings!H:H, "Green transportation", Buildings!G:G, "s/l-UNC") + COUNTIFS(Buildings!H:H, "Green transportation", Buildings!G:G, "s/l-POS") + COUNTIFS(Buildings!H:H, "Green transportation", Buildings!G:G, "s/l-NEG") + COUNTIFS(Transport!H:H, "Green transportation", Transport!G:G, "n") + COUNTIFS(Transport!H:H, "Green transportation", Transport!G:G, "s/l-UNC") + COUNTIFS(Transport!H:H, "Green transportation", Transport!G:G, "s/l-POS") + COUNTIFS(Transport!H:H, "Green transportation", Transport!G:G, "s/l-NEG") + COUNTIFS(LULUCF!H:H, "Green transportation", LULUCF!G:G, "n") + COUNTIFS(LULUCF!H:H, "Green transportation", LULUCF!G:G, "s/l-UNC") + COUNTIFS(LULUCF!H:H, "Green transportation", LULUCF!G:G, "s/l-POS") + COUNTIFS(LULUCF!H:H, "Green transportation", LULUCF!G:G, "s/l-NEG") + COUNTIFS('Circular Economy'!H:H, "Green transportation", 'Circular Economy'!G:G, "n") + COUNTIFS('Circular Economy'!H:H, "Green transportation", 'Circular Economy'!G:G, "s/l-UNC") + COUNTIFS('Circular Economy'!H:H, "Green transportation", 'Circular Economy'!G:G, "s/l-POS") + COUNTIFS('Circular Economy'!H:H, "Green transportation", 'Circular Economy'!G:G, "s/l-NEG") + COUNTIFS(Finance!H:H, "Green transportation", Finance!G:G, "n") + COUNTIFS(Finance!H:H, "Green transportation", Finance!G:G, "s/l-UNC") + COUNTIFS(Finance!H:H, "Green transportation", Finance!G:G, "s/l-POS") + COUNTIFS(Finance!H:H, "Green transportation", Finance!G:G, "s/l-NEG")
K21: 2019 | L21: =COUNTIFS('GHG Emissions'!A:A, 2019, 'GHG Emissions'!G:G, "n") + COUNTIFS('GHG Emissions'!A:A, 2019, 'GHG Emissions'!G:G, "s/l-UNC") + COUNTIFS('GHG Emissions'!A:A, 2019, 'GHG Emissions'!G:G, "s/l-POS") + COUNTIFS('GHG Emissions'!A:A, 2019, 'GHG Emissions'!G:G, "s/l-NEG") + COUNTIFS(Pollution!A:A, 2019, Pollution!G:G, "n") + COUNTIFS(Pollution!A:A, 2019, Pollution!G:G, "s/l-UNC") + COUNTIFS(Pollution!A:A, 2019, Pollution!G:G, "s/l-POS") + COUNTIFS(Pollution!A:A, 2019, Pollution!G:G, "s/l-NEG") + COUNTIFS('Energy|Power'!A:A, 2019, 'Energy|Power'!G:G, "n") + COUNTIFS('Energy|Power'!A:A, 2019, 'Energy|Power'!G:G, "s/l-UNC") + COUNTIFS('Energy|Power'!A:A, 2019, 'Energy|Power'!G:G, "s/l-POS") + COUNTIFS('Energy|Power'!A:A, 2019, 'Energy|Power'!G:G, "s/l-NEG") + COUNTIFS(Industry!A:A, 2019, Industry!G:G, "n") + COUNTIFS(Industry!A:A, 2019, Industry!G:G, "s/l-UNC") + COUNTIFS(Industry!A:A, 2019, Industry!G:G, "s/l-POS") + COUNTIFS(Industry!A:A, 2019, Industry!G:G, "s/l-NEG") + COUNTIFS(Buildings!A:A, 2019, Buildings!G:G, "n") + COUNTIFS(Buildings!A:A, 2019, Buildings!G:G, "s/l-UNC") + COUNTIFS(Buildings!A:A, 2019, Buildings!G:G, "s/l-POS") + COUNTIFS(Buildings!A:A, 2019, Buildings!G:G, "s/l-NEG") + COUNTIFS(Transport!A:A, 2019, Transport!G:G, "n") + COUNTIFS(Transport!A:A, 2019, Transport!G:G, "s/l-UNC") + COUNTIFS(Transport!A:A, 2019, Transport!G:G, "s/l-POS") + COUNTIFS(Transport!A:A, 2019, Transport!G:G, "s/l-NEG") + COUNTIFS(LULUCF!A:A, 2019, LULUCF!G:G, "n") + COUNTIFS(LULUCF!A:A, 2019, LULUCF!G:G, "s/l-UNC") + COUNTIFS(LULUCF!A:A, 2019, LULUCF!G:G, "s/l-POS") + COUNTIFS(LULUCF!A:A, 2019, LULUCF!G:G, "s/l-NEG") + COUNTIFS('Circular Economy'!A:A, 2019, 'Circular Economy'!G:G, "n") + COUNTIFS('Circular Economy'!A:A, 2019, 'Circular Economy'!G:G, "s/l-UNC") + COUNTIFS('Circular Economy'!A:A, 2019, 'Circular Economy'!G:G, "s/l-POS") + COUNTIFS('Circular Economy'!A:A, 2019, 'Circular Economy'!G:G, "s/l-NEG") + COUNTIFS(Finance!A:A, 2019, Finance!G:G, "n") + COUNTIFS(Finance!A:A, 2019, Finance!G:G, "s/l-UNC") + COUNTIFS(Finance!A:A, 2019, Finance!G:G, "s/l-POS") + COUNTIFS(Finance!A:A, 2019, Finance!G:G, "s/l-NEG") | N21: 2022 | O21: =COUNTIFS('GHG Emissions'!F:F, 2022, 'GHG Emissions'!G:G, "n") + COUNTIFS('GHG Emissions'!F:F, 2022, 'GHG Emissions'!G:G, "s/l-UNC") + COUNTIFS('GHG Emissions'!F:F, 2022, 'GHG Emissions'!G:G, "s/l-POS") + COUNTIFS('GHG Emissions'!F:F, 2022, 'GHG Emissions'!G:G, "s/l-NEG") + COUNTIFS(Pollution!F:F, 2022, Pollution!G:G, "n") + COUNTIFS(Pollution!F:F, 2022, Pollution!G:G, "s/l-UNC") + COUNTIFS(Pollution!F:F, 2022, Pollution!G:G, "s/l-POS") + COUNTIFS(Pollution!F:F, 2022, Pollution!G:G, "s/l-NEG") + COUNTIFS('Energy|Power'!F:F, 2022, 'Energy|Power'!G:G, "n") + COUNTIFS('Energy|Power'!F:F, 2022, 'Energy|Power'!G:G, "s/l-UNC") + COUNTIFS('Energy|Power'!F:F, 2022, 'Energy|Power'!G:G, "s/l-POS") + COUNTIFS('Energy|Power'!F:F, 2022, 'Energy|Power'!G:G, "s/l-NEG") + COUNTIFS(Industry!F:F, 2022, Industry!G:G, "n") + COUNTIFS(Industry!F:F, 2022, Industry!G:G, "s/l-UNC") + COUNTIFS(Industry!F:F, 2022, Industry!G:G, "s/l-POS") + COUNTIFS(Industry!F:F, 2022, Industry!G:G, "s/l-NEG") + COUNTIFS(Buildings!F:F, 2022, Buildings!G:G, "n") + COUNTIFS(Buildings!F:F, 2022, Buildings!G:G, "s/l-UNC") + COUNTIFS(Buildings!F:F, 2022, Buildings!G:G, "s/l-POS") + COUNTIFS(Buildings!F:F, 2022, Buildings!G:G, "s/l-NEG") + COUNTIFS(Transport!F:F, 2022, Transport!G:G, "n") + COUNTIFS(Transport!F:F, 2022, Transport!G:G, "s/l-UNC") + COUNTIFS(Transport!F:F, 2022, Transport!G:G, "s/l-POS") + COUNTIFS(Transport!F:F, 2022, Transport!G:G, "s/l-NEG") + COUNTIFS(LULUCF!F:F, 2022, LULUCF!G:G, "n") + COUNTIFS(LULUCF!F:F, 2022, LULUCF!G:G, "s/l-UNC") + COUNTIFS(LULUCF!F:F, 2022, LULUCF!G:G, "s/l-POS") + COUNTIFS(LULUCF!F:F, 2022, LULUCF!G:G, "s/l-NEG") + COUNTIFS('Circular Economy'!F:F, 2022, 'Circular Economy'!G:G, "n") + COUNTIFS('Circular Economy'!F:F, 2022, 'Circular Economy'!G:G, "s/l-UNC") + COUNTIFS('Circular Economy'!F:F, 2022, 'Circular Economy'!G:G, "s/l-POS") + COUNTIFS('Circular Economy'!F:F, 2022, 'Circular Economy'!G:G, "s/l-NEG") + COUNTIFS(Finance!F:F, 2022, Finance!G:G, "n") + COUNTIFS(Finance!F:F, 2022, Finance!G:G, "s/l-UNC") + COUNTIFS(Finance!F:F, 2022, Finance!G:G, "s/l-POS") + COUNTIFS(Finance!F:F, 2022, Finance!G:G, "s/l-NEG") | Q21: Environmental quality | R21: =COUNTIFS('GHG Emissions'!H:H, "Environmental quality", 'GHG Emissions'!G:G, "n") + COUNTIFS('GHG Emissions'!H:H, "Environmental quality", 'GHG Emissions'!G:G, "s/l-UNC") + COUNTIFS('GHG Emissions'!H:H, "Environmental quality", 'GHG Emissions'!G:G, "s/l-POS") + COUNTIFS('GHG Emissions'!H:H, "Environmental quality", 'GHG Emissions'!G:G, "s/l-NEG") + COUNTIFS(Pollution!H:H, "Environmental quality", Pollution!G:G, "n") + COUNTIFS(Pollution!H:H, "Environmental quality", Pollution!G:G, "s/l-UNC") + COUNTIFS(Pollution!H:H, "Environmental quality", Pollution!G:G, "s/l-POS") + COUNTIFS(Pollution!H:H, "Environmental quality", Pollution!G:G, "s/l-NEG") + COUNTIFS('Energy|Power'!H:H, "Environmental quality", 'Energy|Power'!G:G, "n") + COUNTIFS('Energy|Power'!H:H, "Environmental quality", 'Energy|Power'!G:G, "s/l-UNC") + COUNTIFS('Energy|Power'!H:H, "Environmental quality", 'Energy|Power'!G:G, "s/l-POS") + COUNTIFS('Energy|Power'!H:H, "Environmental quality", 'Energy|Power'!G:G, "s/l-NEG") + COUNTIFS(Industry!H:H, "Environmental quality", Industry!G:G, "n") + COUNTIFS(Industry!H:H, "Environmental quality", Industry!G:G, "s/l-UNC") + COUNTIFS(Industry!H:H, "Environmental quality", Industry!G:G, "s/l-POS") + COUNTIFS(Industry!H:H, "Environmental quality", Industry!G:G, "s/l-NEG") + COUNTIFS(Buildings!H:H, "Environmental quality", Buildings!G:G, "n") + COUNTIFS(Buildings!H:H, "Environmental quality", Buildings!G:G, "s/l-UNC") + COUNTIFS(Buildings!H:H, "Environmental quality", Buildings!G:G, "s/l-POS") + COUNTIFS(Buildings!H:H, "Environmental quality", Buildings!G:G, "s/l-NEG") + COUNTIFS(Transport!H:H, "Environmental quality", Transport!G:G, "n") + COUNTIFS(Transport!H:H, "Environmental quality", Transport!G:G, "s/l-UNC") + COUNTIFS(Transport!H:H, "Environmental quality", Transport!G:G, "s/l-POS") + COUNTIFS(Transport!H:H, "Environmental quality", Transport!G:G, "s/l-NEG") + COUNTIFS(LULUCF!H:H, "Environmental quality", LULUCF!G:G, "n") + COUNTIFS(LULUCF!H:H, "Environmental quality", LULUCF!G:G, "s/l-UNC") + COUNTIFS(LULUCF!H:H, "Environmental quality", LULUCF!G:G, "s/l-POS") + COUNTIFS(LULUCF!H:H, "Environmental quality", LULUCF!G:G, "s/l-NEG") + COUNTIFS('Circular Economy'!H:H, "Environmental quality", 'Circular Economy'!G:G, "n") + COUNTIFS('Circular Economy'!H:H, "Environmental quality", 'Circular Economy'!G:G, "s/l-UNC") + COUNTIFS('Circular Economy'!H:H, "Environmental quality", 'Circular Economy'!G:G, "s/l-POS") + COUNTIFS('Circular Economy'!H:H, "Environmental quality", 'Circular Economy'!G:G, "s/l-NEG") + COUNTIFS(Finance!H:H, "Environmental quality", Finance!G:G, "n") + COUNTIFS(Finance!H:H, "Environmental quality", Finance!G:G, "s/l-UNC") + COUNTIFS(Finance!H:H, "Environmental quality", Finance!G:G, "s/l-POS") + COUNTIFS(Finance!H:H, "Environmental quality", Finance!G:G, "s/l-NEG")
K22: 2020 | L22: =COUNTIFS('GHG Emissions'!A:A, 2020, 'GHG Emissions'!G:G, "n") + COUNTIFS('GHG Emissions'!A:A, 2020, 'GHG Emissions'!G:G, "s/l-UNC") + COUNTIFS('GHG Emissions'!A:A, 2020, 'GHG Emissions'!G:G, "s/l-POS") + COUNTIFS('GHG Emissions'!A:A, 2020, 'GHG Emissions'!G:G, "s/l-NEG") + COUNTIFS(Pollution!A:A, 2020, Pollution!G:G, "n") + COUNTIFS(Pollution!A:A, 2020, Pollution!G:G, "s/l-UNC") + COUNTIFS(Pollution!A:A, 2020, Pollution!G:G, "s/l-POS") + COUNTIFS(Pollution!A:A, 2020, Pollution!G:G, "s/l-NEG") + COUNTIFS('Energy|Power'!A:A, 2020, 'Energy|Power'!G:G, "n") + COUNTIFS('Energy|Power'!A:A, 2020, 'Energy|Power'!G:G, "s/l-UNC") + COUNTIFS('Energy|Power'!A:A, 2020, 'Energy|Power'!G:G, "s/l-POS") + COUNTIFS('Energy|Power'!A:A, 2020, 'Energy|Power'!G:G, "s/l-NEG") + COUNTIFS(Industry!A:A, 2020, Industry!G:G, "n") + COUNTIFS(Industry!A:A, 2020, Industry!G:G, "s/l-UNC") + COUNTIFS(Industry!A:A, 2020, Industry!G:G, "s/l-POS") + COUNTIFS(Industry!A:A, 2020, Industry!G:G, "s/l-NEG") + COUNTIFS(Buildings!A:A, 2020, Buildings!G:G, "n") + COUNTIFS(Buildings!A:A, 2020, Buildings!G:G, "s/l-UNC") + COUNTIFS(Buildings!A:A, 2020, Buildings!G:G, "s/l-POS") + COUNTIFS(Buildings!A:A, 2020, Buildings!G:G, "s/l-NEG") + COUNTIFS(Transport!A:A, 2020, Transport!G:G, "n") + COUNTIFS(Transport!A:A, 2020, Transport!G:G, "s/l-UNC") + COUNTIFS(Transport!A:A, 2020, Transport!G:G, "s/l-POS") + COUNTIFS(Transport!A:A, 2020, Transport!G:G, "s/l-NEG") + COUNTIFS(LULUCF!A:A, 2020, LULUCF!G:G, "n") + COUNTIFS(LULUCF!A:A, 2020, LULUCF!G:G, "s/l-UNC") + COUNTIFS(LULUCF!A:A, 2020, LULUCF!G:G, "s/l-POS") + COUNTIFS(LULUCF!A:A, 2020, LULUCF!G:G, "s/l-NEG") + COUNTIFS('Circular Economy'!A:A, 2020, 'Circular Economy'!G:G, "n") + COUNTIFS('Circular Economy'!A:A, 2020, 'Circular Economy'!G:G, "s/l-UNC") + COUNTIFS('Circular Economy'!A:A, 2020, 'Circular Economy'!G:G, "s/l-POS") + COUNTIFS('Circular Economy'!A:A, 2020, 'Circular Economy'!G:G, "s/l-NEG") + COUNTIFS(Finance!A:A, 2020, Finance!G:G, "n") + COUNTIFS(Finance!A:A, 2020, Finance!G:G, "s/l-UNC") + COUNTIFS(Finance!A:A, 2020, Finance!G:G, "s/l-POS") + COUNTIFS(Finance!A:A, 2020, Finance!G:G, "s/l-NEG") | N22: 2023 | O22: =COUNTIFS('GHG Emissions'!F:F, 2023, 'GHG Emissions'!G:G, "n") + COUNTIFS('GHG Emissions'!F:F, 2023, 'GHG Emissions'!G:G, "s/l-UNC") + COUNTIFS('GHG Emissions'!F:F, 2023, 'GHG Emissions'!G:G, "s/l-POS") + COUNTIFS('GHG Emissions'!F:F, 2023, 'GHG Emissions'!G:G, "s/l-NEG") + COUNTIFS(Pollution!F:F, 2023, Pollution!G:G, "n") + COUNTIFS(Pollution!F:F, 2023, Pollution!G:G, "s/l-UNC") + COUNTIFS(Pollution!F:F, 2023, Pollution!G:G, "s/l-POS") + COUNTIFS(Pollution!F:F, 2023, Pollution!G:G, "s/l-NEG") + COUNTIFS('Energy|Power'!F:F, 2023, 'Energy|Power'!G:G, "n") + COUNTIFS('Energy|Power'!F:F, 2023, 'Energy|Power'!G:G, "s/l-UNC") + COUNTIFS('Energy|Power'!F:F, 2023, 'Energy|Power'!G:G, "s/l-POS") + COUNTIFS('Energy|Power'!F:F, 2023, 'Energy|Power'!G:G, "s/l-NEG") + COUNTIFS(Industry!F:F, 2023, Industry!G:G, "n") + COUNTIFS(Industry!F:F, 2023, Industry!G:G, "s/l-UNC") + COUNTIFS(Industry!F:F, 2023, Industry!G:G, "s/l-POS") + COUNTIFS(Industry!F:F, 2023, Industry!G:G, "s/l-NEG") + COUNTIFS(Buildings!F:F, 2023, Buildings!G:G, "n") + COUNTIFS(Buildings!F:F, 2023, Buildings!G:G, "s/l-UNC") + COUNTIFS(Buildings!F:F, 2023, Buildings!G:G, "s/l-POS") + COUNTIFS(Buildings!F:F, 2023, Buildings!G:G, "s/l-NEG") + COUNTIFS(Transport!F:F, 2023, Transport!G:G, "n") + COUNTIFS(Transport!F:F, 2023, Transport!G:G, "s/l-UNC") + COUNTIFS(Transport!F:F, 2023, Transport!G:G, "s/l-POS") + COUNTIFS(Transport!F:F, 2023, Transport!G:G, "s/l-NEG") + COUNTIFS(LULUCF!F:F, 2023, LULUCF!G:G, "n") + COUNTIFS(LULUCF!F:F, 2023, LULUCF!G:G, "s/l-UNC") + COUNTIFS(LULUCF!F:F, 2023, LULUCF!G:G, "s/l-POS") + COUNTIFS(LULUCF!F:F, 2023, LULUCF!G:G, "s/l-NEG") + COUNTIFS('Circular Economy'!F:F, 2023, 'Circular Economy'!G:G, "n") + COUNTIFS('Circular Economy'!F:F, 2023, 'Circular Economy'!G:G, "s/l-UNC") + COUNTIFS('Circular Economy'!F:F, 2023, 'Circular Economy'!G:G, "s/l-POS") + COUNTIFS('Circular Economy'!F:F, 2023, 'Circular Economy'!G:G, "s/l-NEG") + COUNTIFS(Finance!F:F, 2023, Finance!G:G, "n") + COUNTIFS(Finance!F:F, 2023, Finance!G:G, "s/l-UNC") + COUNTIFS(Finance!F:F, 2023, Finance!G:G, "s/l-POS") + COUNTIFS(Finance!F:F, 2023, Finance!G:G, "s/l-NEG") | Q22: Recycling | R22: =COUNTIFS('GHG Emissions'!H:H, "Recycling", 'GHG Emissions'!G:G, "n") + COUNTIFS('GHG Emissions'!H:H, "Recycling", 'GHG Emissions'!G:G, "s/l-UNC") + COUNTIFS('GHG Emissions'!H:H, "Recycling", 'GHG Emissions'!G:G, "s/l-POS") + COUNTIFS('GHG Emissions'!H:H, "Recycling", 'GHG Emissions'!G:G, "s/l-NEG") + COUNTIFS(Pollution!H:H, "Recycling", Pollution!G:G, "n") + COUNTIFS(Pollution!H:H, "Recycling", Pollution!G:G, "s/l-UNC") + COUNTIFS(Pollution!H:H, "Recycling", Pollution!G:G, "s/l-POS") + COUNTIFS(Pollution!H:H, "Recycling", Pollution!G:G, "s/l-NEG") + COUNTIFS('Energy|Power'!H:H, "Recycling", 'Energy|Power'!G:G, "n") + COUNTIFS('Energy|Power'!H:H, "Recycling", 'Energy|Power'!G:G, "s/l-UNC") + COUNTIFS('Energy|Power'!H:H, "Recycling", 'Energy|Power'!G:G, "s/l-POS") + COUNTIFS('Energy|Power'!H:H, "Recycling", 'Energy|Power'!G:G, "s/l-NEG") + COUNTIFS(Industry!H:H, "Recycling", Industry!G:G, "n") + COUNTIFS(Industry!H:H, "Recycling", Industry!G:G, "s/l-UNC") + COUNTIFS(Industry!H:H, "Recycling", Industry!G:G, "s/l-POS") + COUNTIFS(Industry!H:H, "Recycling", Industry!G:G, "s/l-NEG") + COUNTIFS(Buildings!H:H, "Recycling", Buildings!G:G, "n") + COUNTIFS(Buildings!H:H, "Recycling", Buildings!G:G, "s/l-UNC") + COUNTIFS(Buildings!H:H, "Recycling", Buildings!G:G, "s/l-POS") + COUNTIFS(Buildings!H:H, "Recycling", Buildings!G:G, "s/l-NEG") + COUNTIFS(Transport!H:H, "Recycling", Transport!G:G, "n") + COUNTIFS(Transport!H:H, "Recycling", Transport!G:G, "s/l-UNC") + COUNTIFS(Transport!H:H, "Recycling", Transport!G:G, "s/l-POS") + COUNTIFS(Transport!H:H, "Recycling", Transport!G:G, "s/l-NEG") + COUNTIFS(LULUCF!H:H, "Recycling", LULUCF!G:G, "n") + COUNTIFS(LULUCF!H:H, "Recycling", LULUCF!G:G, "s/l-UNC") + COUNTIFS(LULUCF!H:H, "Recycling", LULUCF!G:G, "s/l-POS") + COUNTIFS(LULUCF!H:H, "Recycling", LULUCF!G:G, "s/l-NEG") + COUNTIFS('Circular Economy'!H:H, "Recycling", 'Circular Economy'!G:G, "n") + COUNTIFS('Circular Economy'!H:H, "Recycling", 'Circular Economy'!G:G, "s/l-UNC") + COUNTIFS('Circular Economy'!H:H, "Recycling", 'Circular Economy'!G:G, "s/l-POS") + COUNTIFS('Circular Economy'!H:H, "Recycling", 'Circular Economy'!G:G, "s/l-NEG") + COUNTIFS(Finance!H:H, "Recycling", Finance!G:G, "n") + COUNTIFS(Finance!H:H, "Recycling", Finance!G:G, "s/l-UNC") + COUNTIFS(Finance!H:H, "Recycling", Finance!G:G, "s/l-POS") + COUNTIFS(Finance!H:H, "Recycling", Finance!G:G, "s/l-NEG")
K23: 2021 | L23: =COUNTIFS('GHG Emissions'!A:A, 2021, 'GHG Emissions'!G:G, "n") + COUNTIFS('GHG Emissions'!A:A, 2021, 'GHG Emissions'!G:G, "s/l-UNC") + COUNTIFS('GHG Emissions'!A:A, 2021, 'GHG Emissions'!G:G, "s/l-POS") + COUNTIFS('GHG Emissions'!A:A, 2021, 'GHG Emissions'!G:G, "s/l-NEG") + COUNTIFS(Pollution!A:A, 2021, Pollution!G:G, "n") + COUNTIFS(Pollution!A:A, 2021, Pollution!G:G, "s/l-UNC") + COUNTIFS(Pollution!A:A, 2021, Pollution!G:G, "s/l-POS") + COUNTIFS(Pollution!A:A, 2021, Pollution!G:G, "s/l-NEG") + COUNTIFS('Energy|Power'!A:A, 2021, 'Energy|Power'!G:G, "n") + COUNTIFS('Energy|Power'!A:A, 2021, 'Energy|Power'!G:G, "s/l-UNC") + COUNTIFS('Energy|Power'!A:A, 2021, 'Energy|Power'!G:G, "s/l-POS") + COUNTIFS('Energy|Power'!A:A, 2021, 'Energy|Power'!G:G, "s/l-NEG") + COUNTIFS(Industry!A:A, 2021, Industry!G:G, "n") + COUNTIFS(Industry!A:A, 2021, Industry!G:G, "s/l-UNC") + COUNTIFS(Industry!A:A, 2021, Industry!G:G, "s/l-POS") + COUNTIFS(Industry!A:A, 2021, Industry!G:G, "s/l-NEG") + COUNTIFS(Buildings!A:A, 2021, Buildings!G:G, "n") + COUNTIFS(Buildings!A:A, 2021, Buildings!G:G, "s/l-UNC") + COUNTIFS(Buildings!A:A, 2021, Buildings!G:G, "s/l-POS") + COUNTIFS(Buildings!A:A, 2021, Buildings!G:G, "s/l-NEG") + COUNTIFS(Transport!A:A, 2021, Transport!G:G, "n") + COUNTIFS(Transport!A:A, 2021, Transport!G:G, "s/l-UNC") + COUNTIFS(Transport!A:A, 2021, Transport!G:G, "s/l-POS") + COUNTIFS(Transport!A:A, 2021, Transport!G:G, "s/l-NEG") + COUNTIFS(LULUCF!A:A, 2021, LULUCF!G:G, "n") + COUNTIFS(LULUCF!A:A, 2021, LULUCF!G:G, "s/l-UNC") + COUNTIFS(LULUCF!A:A, 2021, LULUCF!G:G, "s/l-POS") + COUNTIFS(LULUCF!A:A, 2021, LULUCF!G:G, "s/l-NEG") + COUNTIFS('Circular Economy'!A:A, 2021, 'Circular Economy'!G:G, "n") + COUNTIFS('Circular Economy'!A:A, 2021, 'Circular Economy'!G:G, "s/l-UNC") + COUNTIFS('Circular Economy'!A:A, 2021, 'Circular Economy'!G:G, "s/l-POS") + COUNTIFS('Circular Economy'!A:A, 2021, 'Circular Economy'!G:G, "s/l-NEG") + COUNTIFS(Finance!A:A, 2021, Finance!G:G, "n") + COUNTIFS(Finance!A:A, 2021, Finance!G:G, "s/l-UNC") + COUNTIFS(Finance!A:A, 2021, Finance!G:G, "s/l-POS") + COUNTIFS(Finance!A:A, 2021, Finance!G:G, "s/l-NEG") | N23: 2024 | O23: =COUNTIFS('GHG Emissions'!F:F, 2024, 'GHG Emissions'!G:G, "n") + COUNTIFS('GHG Emissions'!F:F, 2024, 'GHG Emissions'!G:G, "s/l-UNC") + COUNTIFS('GHG Emissions'!F:F, 2024, 'GHG Emissions'!G:G, "s/l-POS") + COUNTIFS('GHG Emissions'!F:F, 2024, 'GHG Emissions'!G:G, "s/l-NEG") + COUNTIFS(Pollution!F:F, 2024, Pollution!G:G, "n") + COUNTIFS(Pollution!F:F, 2024, Pollution!G:G, "s/l-UNC") + COUNTIFS(Pollution!F:F, 2024, Pollution!G:G, "s/l-POS") + COUNTIFS(Pollution!F:F, 2024, Pollution!G:G, "s/l-NEG") + COUNTIFS('Energy|Power'!F:F, 2024, 'Energy|Power'!G:G, "n") + COUNTIFS('Energy|Power'!F:F, 2024, 'Energy|Power'!G:G, "s/l-UNC") + COUNTIFS('Energy|Power'!F:F, 2024, 'Energy|Power'!G:G, "s/l-POS") + COUNTIFS('Energy|Power'!F:F, 2024, 'Energy|Power'!G:G, "s/l-NEG") + COUNTIFS(Industry!F:F, 2024, Industry!G:G, "n") + COUNTIFS(Industry!F:F, 2024, Industry!G:G, "s/l-UNC") + COUNTIFS(Industry!F:F, 2024, Industry!G:G, "s/l-POS") + COUNTIFS(Industry!F:F, 2024, Industry!G:G, "s/l-NEG") + COUNTIFS(Buildings!F:F, 2024, Buildings!G:G, "n") + COUNTIFS(Buildings!F:F, 2024, Buildings!G:G, "s/l-UNC") + COUNTIFS(Buildings!F:F, 2024, Buildings!G:G, "s/l-POS") + COUNTIFS(Buildings!F:F, 2024, Buildings!G:G, "s/l-NEG") + COUNTIFS(Transport!F:F, 2024, Transport!G:G, "n") + COUNTIFS(Transport!F:F, 2024, Transport!G:G, "s/l-UNC") + COUNTIFS(Transport!F:F, 2024, Transport!G:G, "s/l-POS") + COUNTIFS(Transport!F:F, 2024, Transport!G:G, "s/l-NEG") + COUNTIFS(LULUCF!F:F, 2024, LULUCF!G:G, "n") + COUNTIFS(LULUCF!F:F, 2024, LULUCF!G:G, "s/l-UNC") + COUNTIFS(LULUCF!F:F, 2024, LULUCF!G:G, "s/l-POS") + COUNTIFS(LULUCF!F:F, 2024, LULUCF!G:G, "s/l-NEG") + COUNTIFS('Circular Economy'!F:F, 2024, 'Circular Economy'!G:G, "n") + COUNTIFS('Circular Economy'!F:F, 2024, 'Circular Economy'!G:G, "s/l-UNC") + COUNTIFS('Circular Economy'!F:F, 2024, 'Circular Economy'!G:G, "s/l-POS") + COUNTIFS('Circular Economy'!F:F, 2024, 'Circular Economy'!G:G, "s/l-NEG") + COUNTIFS(Finance!F:F, 2024, Finance!G:G, "n") + COUNTIFS(Finance!F:F, 2024, Finance!G:G, "s/l-UNC") + COUNTIFS(Finance!F:F, 2024, Finance!G:G, "s/l-POS") + COUNTIFS(Finance!F:F, 2024, Finance!G:G, "s/l-NEG") | Q23: Climate finance | R23: =COUNTIFS('GHG Emissions'!H:H, "Climate finance", 'GHG Emissions'!G:G, "n") + COUNTIFS('GHG Emissions'!H:H, "Climate finance", 'GHG Emissions'!G:G, "s/l-UNC") + COUNTIFS('GHG Emissions'!H:H, "Climate finance", 'GHG Emissions'!G:G, "s/l-POS") + COUNTIFS('GHG Emissions'!H:H, "Climate finance", 'GHG Emissions'!G:G, "s/l-NEG") + COUNTIFS(Pollution!H:H, "Climate finance", Pollution!G:G, "n") + COUNTIFS(Pollution!H:H, "Climate finance", Pollution!G:G, "s/l-UNC") + COUNTIFS(Pollution!H:H, "Climate finance", Pollution!G:G, "s/l-POS") + COUNTIFS(Pollution!H:H, "Climate finance", Pollution!G:G, "s/l-NEG") + COUNTIFS('Energy|Power'!H:H, "Climate finance", 'Energy|Power'!G:G, "n") + COUNTIFS('Energy|Power'!H:H, "Climate finance", 'Energy|Power'!G:G, "s/l-UNC") + COUNTIFS('Energy|Power'!H:H, "Climate finance", 'Energy|Power'!G:G, "s/l-POS") + COUNTIFS('Energy|Power'!H:H, "Climate finance", 'Energy|Power'!G:G, "s/l-NEG") + COUNTIFS(Industry!H:H, "Climate finance", Industry!G:G, "n") + COUNTIFS(Industry!H:H, "Climate finance", Industry!G:G, "s/l-UNC") + COUNTIFS(Industry!H:H, "Climate finance", Industry!G:G, "s/l-POS") + COUNTIFS(Industry!H:H, "Climate finance", Industry!G:G, "s/l-NEG") + COUNTIFS(Buildings!H:H, "Climate finance", Buildings!G:G, "n") + COUNTIFS(Buildings!H:H, "Climate finance", Buildings!G:G, "s/l-UNC") + COUNTIFS(Buildings!H:H, "Climate finance", Buildings!G:G, "s/l-POS") + COUNTIFS(Buildings!H:H, "Climate finance", Buildings!G:G, "s/l-NEG") + COUNTIFS(Transport!H:H, "Climate finance", Transport!G:G, "n") + COUNTIFS(Transport!H:H, "Climate finance", Transport!G:G, "s/l-UNC") + COUNTIFS(Transport!H:H, "Climate finance", Transport!G:G, "s/l-POS") + COUNTIFS(Transport!H:H, "Climate finance", Transport!G:G, "s/l-NEG") + COUNTIFS(LULUCF!H:H, "Climate finance", LULUCF!G:G, "n") + COUNTIFS(LULUCF!H:H, "Climate finance", LULUCF!G:G, "s/l-UNC") + COUNTIFS(LULUCF!H:H, "Climate finance", LULUCF!G:G, "s/l-POS") + COUNTIFS(LULUCF!H:H, "Climate finance", LULUCF!G:G, "s/l-NEG") + COUNTIFS('Circular Economy'!H:H, "Climate finance", 'Circular Economy'!G:G, "n") + COUNTIFS('Circular Economy'!H:H, "Climate finance", 'Circular Economy'!G:G, "s/l-UNC") + COUNTIFS('Circular Economy'!H:H, "Climate finance", 'Circular Economy'!G:G, "s/l-POS") + COUNTIFS('Circular Economy'!H:H, "Climate finance", 'Circular Economy'!G:G, "s/l-NEG") + COUNTIFS(Finance!H:H, "Climate finance", Finance!G:G, "n") + COUNTIFS(Finance!H:H, "Climate finance", Finance!G:G, "s/l-UNC") + COUNTIFS(Finance!H:H, "Climate finance", Finance!G:G, "s/l-POS") + COUNTIFS(Finance!H:H, "Climate finance", Finance!G:G, "s/l-NEG")
K24: 2022 | L24: =COUNTIFS('GHG Emissions'!A:A, 2022, 'GHG Emissions'!G:G, "n") + COUNTIFS('GHG Emissions'!A:A, 2022, 'GHG Emissions'!G:G, "s/l-UNC") + COUNTIFS('GHG Emissions'!A:A, 2022, 'GHG Emissions'!G:G, "s/l-POS") + COUNTIFS('GHG Emissions'!A:A, 2022, 'GHG Emissions'!G:G, "s/l-NEG") + COUNTIFS(Pollution!A:A, 2022, Pollution!G:G, "n") + COUNTIFS(Pollution!A:A, 2022, Pollution!G:G, "s/l-UNC") + COUNTIFS(Pollution!A:A, 2022, Pollution!G:G, "s/l-POS") + COUNTIFS(Pollution!A:A, 2022, Pollution!G:G, "s/l-NEG") + COUNTIFS('Energy|Power'!A:A, 2022, 'Energy|Power'!G:G, "n") + COUNTIFS('Energy|Power'!A:A, 2022, 'Energy|Power'!G:G, "s/l-UNC") + COUNTIFS('Energy|Power'!A:A, 2022, 'Energy|Power'!G:G, "s/l-POS") + COUNTIFS('Energy|Power'!A:A, 2022, 'Energy|Power'!G:G, "s/l-NEG") + COUNTIFS(Industry!A:A, 2022, Industry!G:G, "n") + COUNTIFS(Industry!A:A, 2022, Industry!G:G, "s/l-UNC") + COUNTIFS(Industry!A:A, 2022, Industry!G:G, "s/l-POS") + COUNTIFS(Industry!A:A, 2022, Industry!G:G, "s/l-NEG") + COUNTIFS(Buildings!A:A, 2022, Buildings!G:G, "n") + COUNTIFS(Buildings!A:A, 2022, Buildings!G:G, "s/l-UNC") + COUNTIFS(Buildings!A:A, 2022, Buildings!G:G, "s/l-POS") + COUNTIFS(Buildings!A:A, 2022, Buildings!G:G, "s/l-NEG") + COUNTIFS(Transport!A:A, 2022, Transport!G:G, "n") + COUNTIFS(Transport!A:A, 2022, Transport!G:G, "s/l-UNC") + COUNTIFS(Transport!A:A, 2022, Transport!G:G, "s/l-POS") + COUNTIFS(Transport!A:A, 2022, Transport!G:G, "s/l-NEG") + COUNTIFS(LULUCF!A:A, 2022, LULUCF!G:G, "n") + COUNTIFS(LULUCF!A:A, 2022, LULUCF!G:G, "s/l-UNC") + COUNTIFS(LULUCF!A:A, 2022, LULUCF!G:G, "s/l-POS") + COUNTIFS(LULUCF!A:A, 2022, LULUCF!G:G, "s/l-NEG") + COUNTIFS('Circular Economy'!A:A, 2022, 'Circular Economy'!G:G, "n") + COUNTIFS('Circular Economy'!A:A, 2022, 'Circular Economy'!G:G, "s/l-UNC") + COUNTIFS('Circular Economy'!A:A, 2022, 'Circular Economy'!G:G, "s/l-POS") + COUNTIFS('Circular Economy'!A:A, 2022, 'Circular Economy'!G:G, "s/l-NEG") + COUNTIFS(Finance!A:A, 2022, Finance!G:G, "n") + COUNTIFS(Finance!A:A, 2022, Finance!G:G, "s/l-UNC") + COUNTIFS(Finance!A:A, 2022, Finance!G:G, "s/l-POS") + COUNTIFS(Finance!A:A, 2022, Finance!G:G, "s/l-NEG") | N24: 2025 | O24: =COUNTIFS('GHG Emissions'!F:F, 2025, 'GHG Emissions'!G:G, "n") + COUNTIFS('GHG Emissions'!F:F, 2025, 'GHG Emissions'!G:G, "s/l-UNC") + COUNTIFS('GHG Emissions'!F:F, 2025, 'GHG Emissions'!G:G, "s/l-POS") + COUNTIFS('GHG Emissions'!F:F, 2025, 'GHG Emissions'!G:G, "s/l-NEG") + COUNTIFS(Pollution!F:F, 2025, Pollution!G:G, "n") + COUNTIFS(Pollution!F:F, 2025, Pollution!G:G, "s/l-UNC") + COUNTIFS(Pollution!F:F, 2025, Pollution!G:G, "s/l-POS") + COUNTIFS(Pollution!F:F, 2025, Pollution!G:G, "s/l-NEG") + COUNTIFS('Energy|Power'!F:F, 2025, 'Energy|Power'!G:G, "n") + COUNTIFS('Energy|Power'!F:F, 2025, 'Energy|Power'!G:G, "s/l-UNC") + COUNTIFS('Energy|Power'!F:F, 2025, 'Energy|Power'!G:G, "s/l-POS") + COUNTIFS('Energy|Power'!F:F, 2025, 'Energy|Power'!G:G, "s/l-NEG") + COUNTIFS(Industry!F:F, 2025, Industry!G:G, "n") + COUNTIFS(Industry!F:F, 2025, Industry!G:G, "s/l-UNC") + COUNTIFS(Industry!F:F, 2025, Industry!G:G, "s/l-POS") + COUNTIFS(Industry!F:F, 2025, Industry!G:G, "s/l-NEG") + COUNTIFS(Buildings!F:F, 2025, Buildings!G:G, "n") + COUNTIFS(Buildings!F:F, 2025, Buildings!G:G, "s/l-UNC") + COUNTIFS(Buildings!F:F, 2025, Buildings!G:G, "s/l-POS") + COUNTIFS(Buildings!F:F, 2025, Buildings!G:G, "s/l-NEG") + COUNTIFS(Transport!F:F, 2025, Transport!G:G, "n") + COUNTIFS(Transport!F:F, 2025, Transport!G:G, "s/l-UNC") + COUNTIFS(Transport!F:F, 2025, Transport!G:G, "s/l-POS") + COUNTIFS(Transport!F:F, 2025, Transport!G:G, "s/l-NEG") + COUNTIFS(LULUCF!F:F, 2025, LULUCF!G:G, "n") + COUNTIFS(LULUCF!F:F, 2025, LULUCF!G:G, "s/l-UNC") + COUNTIFS(LULUCF!F:F, 2025, LULUCF!G:G, "s/l-POS") + COUNTIFS(LULUCF!F:F, 2025, LULUCF!G:G, "s/l-NEG") + COUNTIFS('Circular Economy'!F:F, 2025, 'Circular Economy'!G:G, "n") + COUNTIFS('Circular Economy'!F:F, 2025, 'Circular Economy'!G:G, "s/l-UNC") + COUNTIFS('Circular Economy'!F:F, 2025, 'Circular Economy'!G:G, "s/l-POS") + COUNTIFS('Circular Economy'!F:F, 2025, 'Circular Economy'!G:G, "s/l-NEG") + COUNTIFS(Finance!F:F, 2025, Finance!G:G, "n") + COUNTIFS(Finance!F:F, 2025, Finance!G:G, "s/l-UNC") + COUNTIFS(Finance!F:F, 2025, Finance!G:G, "s/l-POS") + COUNTIFS(Finance!F:F, 2025, Finance!G:G, "s/l-NEG")
K25: 2023 | L25: =COUNTIFS('GHG Emissions'!A:A, 2023, 'GHG Emissions'!G:G, "n") + COUNTIFS('GHG Emissions'!A:A, 2023, 'GHG Emissions'!G:G, "s/l-UNC") + COUNTIFS('GHG Emissions'!A:A, 2023, 'GHG Emissions'!G:G, "s/l-POS") + COUNTIFS('GHG Emissions'!A:A, 2023, 'GHG Emissions'!G:G, "s/l-NEG") + COUNTIFS(Pollution!A:A, 2023, Pollution!G:G, "n") + COUNTIFS(Pollution!A:A, 2023, Pollution!G:G, "s/l-UNC") + COUNTIFS(Pollution!A:A, 2023, Pollution!G:G, "s/l-POS") + COUNTIFS(Pollution!A:A, 2023, Pollution!G:G, "s/l-NEG") + COUNTIFS('Energy|Power'!A:A, 2023, 'Energy|Power'!G:G, "n") + COUNTIFS('Energy|Power'!A:A, 2023, 'Energy|Power'!G:G, "s/l-UNC") + COUNTIFS('Energy|Power'!A:A, 2023, 'Energy|Power'!G:G, "s/l-POS") + COUNTIFS('Energy|Power'!A:A, 2023, 'Energy|Power'!G:G, "s/l-NEG") + COUNTIFS(Industry!A:A, 2023, Industry!G:G, "n") + COUNTIFS(Industry!A:A, 2023, Industry!G:G, "s/l-UNC") + COUNTIFS(Industry!A:A, 2023, Industry!G:G, "s/l-POS") + COUNTIFS(Industry!A:A, 2023, Industry!G:G, "s/l-NEG") + COUNTIFS(Buildings!A:A, 2023, Buildings!G:G, "n") + COUNTIFS(Buildings!A:A, 2023, Buildings!G:G, "s/l-UNC") + COUNTIFS(Buildings!A:A, 2023, Buildings!G:G, "s/l-POS") + COUNTIFS(Buildings!A:A, 2023, Buildings!G:G, "s/l-NEG") + COUNTIFS(Transport!A:A, 2023, Transport!G:G, "n") + COUNTIFS(Transport!A:A, 2023, Transport!G:G, "s/l-UNC") + COUNTIFS(Transport!A:A, 2023, Transport!G:G, "s/l-POS") + COUNTIFS(Transport!A:A, 2023, Transport!G:G, "s/l-NEG") + COUNTIFS(LULUCF!A:A, 2023, LULUCF!G:G, "n") + COUNTIFS(LULUCF!A:A, 2023, LULUCF!G:G, "s/l-UNC") + COUNTIFS(LULUCF!A:A, 2023, LULUCF!G:G, "s/l-POS") + COUNTIFS(LULUCF!A:A, 2023, LULUCF!G:G, "s/l-NEG") + COUNTIFS('Circular Economy'!A:A, 2023, 'Circular Economy'!G:G, "n") + COUNTIFS('Circular Economy'!A:A, 2023, 'Circular Economy'!G:G, "s/l-UNC") + COUNTIFS('Circular Economy'!A:A, 2023, 'Circular Economy'!G:G, "s/l-POS") + COUNTIFS('Circular Economy'!A:A, 2023, 'Circular Economy'!G:G, "s/l-NEG") + COUNTIFS(Finance!A:A, 2023, Finance!G:G, "n") + COUNTIFS(Finance!A:A, 2023, Finance!G:G, "s/l-UNC") + COUNTIFS(Finance!A:A, 2023, Finance!G:G, "s/l-POS") + COUNTIFS(Finance!A:A, 2023, Finance!G:G, "s/l-NEG") | N25: 14th FYP | O25: =COUNTIFS('GHG Emissions'!F:F, "14th FYP", 'GHG Emissions'!G:G, "n") + COUNTIFS('GHG Emissions'!F:F, "14th FYP", 'GHG Emissions'!G:G, "s/l-UNC") + COUNTIFS('GHG Emissions'!F:F, "14th FYP", 'GHG Emissions'!G:G, "s/l-POS") + COUNTIFS('GHG Emissions'!F:F, "14th FYP", 'GHG Emissions'!G:G, "s/l-NEG") + COUNTIFS(Pollution!F:F, "14th FYP", Pollution!G:G, "n") + COUNTIFS(Pollution!F:F, "14th FYP", Pollution!G:G, "s/l-UNC") + COUNTIFS(Pollution!F:F, "14th FYP", Pollution!G:G, "s/l-POS") + COUNTIFS(Pollution!F:F, "14th FYP", Pollution!G:G, "s/l-NEG") + COUNTIFS('Energy|Power'!F:F, "14th FYP", 'Energy|Power'!G:G, "n") + COUNTIFS('Energy|Power'!F:F, "14th FYP", 'Energy|Power'!G:G, "s/l-UNC") + COUNTIFS('Energy|Power'!F:F, "14th FYP", 'Energy|Power'!G:G, "s/l-POS") + COUNTIFS('Energy|Power'!F:F, "14th FYP", 'Energy|Power'!G:G, "s/l-NEG") + COUNTIFS(Industry!F:F, "14th FYP", Industry!G:G, "n") + COUNTIFS(Industry!F:F, "14th FYP", Industry!G:G, "s/l-UNC") + COUNTIFS(Industry!F:F, "14th FYP", Industry!G:G, "s/l-POS") + COUNTIFS(Industry!F:F, "14th FYP", Industry!G:G, "s/l-NEG") + COUNTIFS(Buildings!F:F, "14th FYP", Buildings!G:G, "n") + COUNTIFS(Buildings!F:F, "14th FYP", Buildings!G:G, "s/l-UNC") + COUNTIFS(Buildings!F:F, "14th FYP", Buildings!G:G, "s/l-POS") + COUNTIFS(Buildings!F:F, "14th FYP", Buildings!G:G, "s/l-NEG") + COUNTIFS(Transport!F:F, "14th FYP", Transport!G:G, "n") + COUNTIFS(Transport!F:F, "14th FYP", Transport!G:G, "s/l-UNC") + COUNTIFS(Transport!F:F, "14th FYP", Transport!G:G, "s/l-POS") + COUNTIFS(Transport!F:F, "14th FYP", Transport!G:G, "s/l-NEG") + COUNTIFS(LULUCF!F:F, "14th FYP", LULUCF!G:G, "n") + COUNTIFS(LULUCF!F:F, "14th FYP", LULUCF!G:G, "s/l-UNC") + COUNTIFS(LULUCF!F:F, "14th FYP", LULUCF!G:G, "s/l-POS") + COUNTIFS(LULUCF!F:F, "14th FYP", LULUCF!G:G, "s/l-NEG") + COUNTIFS('Circular Economy'!F:F, "14th FYP", 'Circular Economy'!G:G, "n") + COUNTIFS('Circular Economy'!F:F, "14th FYP", 'Circular Economy'!G:G, "s/l-UNC") + COUNTIFS('Circular Economy'!F:F, "14th FYP", 'Circular Economy'!G:G, "s/l-POS") + COUNTIFS('Circular Economy'!F:F, "14th FYP", 'Circular Economy'!G:G, "s/l-NEG") + COUNTIFS(Finance!F:F, "14th FYP", Finance!G:G, "n") + COUNTIFS(Finance!F:F, "14th FYP", Finance!G:G, "s/l-UNC") + COUNTIFS(Finance!F:F, "14th FYP", Finance!G:G, "s/l-POS") + COUNTIFS(Finance!F:F, "14th FYP", Finance!G:G, "s/l-NEG")
K26: 2024 | L26: =COUNTIFS('GHG Emissions'!A:A, 2024, 'GHG Emissions'!G:G, "n") + COUNTIFS('GHG Emissions'!A:A, 2024, 'GHG Emissions'!G:G, "s/l-UNC") + COUNTIFS('GHG Emissions'!A:A, 2024, 'GHG Emissions'!G:G, "s/l-POS") + COUNTIFS('GHG Emissions'!A:A, 2024, 'GHG Emissions'!G:G, "s/l-NEG") + COUNTIFS(Pollution!A:A, 2024, Pollution!G:G, "n") + COUNTIFS(Pollution!A:A, 2024, Pollution!G:G, "s/l-UNC") + COUNTIFS(Pollution!A:A, 2024, Pollution!G:G, "s/l-POS") + COUNTIFS(Pollution!A:A, 2024, Pollution!G:G, "s/l-NEG") + COUNTIFS('Energy|Power'!A:A, 2024, 'Energy|Power'!G:G, "n") + COUNTIFS('Energy|Power'!A:A, 2024, 'Energy|Power'!G:G, "s/l-UNC") + COUNTIFS('Energy|Power'!A:A, 2024, 'Energy|Power'!G:G, "s/l-POS") + COUNTIFS('Energy|Power'!A:A, 2024, 'Energy|Power'!G:G, "s/l-NEG") + COUNTIFS(Industry!A:A, 2024, Industry!G:G, "n") + COUNTIFS(Industry!A:A, 2024, Industry!G:G, "s/l-UNC") + COUNTIFS(Industry!A:A, 2024, Industry!G:G, "s/l-POS") + COUNTIFS(Industry!A:A, 2024, Industry!G:G, "s/l-NEG") + COUNTIFS(Buildings!A:A, 2024, Buildings!G:G, "n") + COUNTIFS(Buildings!A:A, 2024, Buildings!G:G, "s/l-UNC") + COUNTIFS(Buildings!A:A, 2024, Buildings!G:G, "s/l-POS") + COUNTIFS(Buildings!A:A, 2024, Buildings!G:G, "s/l-NEG") + COUNTIFS(Transport!A:A, 2024, Transport!G:G, "n") + COUNTIFS(Transport!A:A, 2024, Transport!G:G, "s/l-UNC") + COUNTIFS(Transport!A:A, 2024, Transport!G:G, "s/l-POS") + COUNTIFS(Transport!A:A, 2024, Transport!G:G, "s/l-NEG") + COUNTIFS(LULUCF!A:A, 2024, LULUCF!G:G, "n") + COUNTIFS(LULUCF!A:A, 2024, LULUCF!G:G, "s/l-UNC") + COUNTIFS(LULUCF!A:A, 2024, LULUCF!G:G, "s/l-POS") + COUNTIFS(LULUCF!A:A, 2024, LULUCF!G:G, "s/l-NEG") + COUNTIFS('Circular Economy'!A:A, 2024, 'Circular Economy'!G:G, "n") + COUNTIFS('Circular Economy'!A:A, 2024, 'Circular Economy'!G:G, "s/l-UNC") + COUNTIFS('Circular Economy'!A:A, 2024, 'Circular Economy'!G:G, "s/l-POS") + COUNTIFS('Circular Economy'!A:A, 2024, 'Circular Economy'!G:G, "s/l-NEG") + COUNTIFS(Finance!A:A, 2024, Finance!G:G, "n") + COUNTIFS(Finance!A:A, 2024, Finance!G:G, "s/l-UNC") + COUNTIFS(Finance!A:A, 2024, Finance!G:G, "s/l-POS") + COUNTIFS(Finance!A:A, 2024, Finance!G:G, "s/l-NEG") | N26: 2027 | O26: =COUNTIFS('GHG Emissions'!F:F, 2027, 'GHG Emissions'!G:G, "n") + COUNTIFS('GHG Emissions'!F:F, 2027, 'GHG Emissions'!G:G, "s/l-UNC") + COUNTIFS('GHG Emissions'!F:F, 2027, 'GHG Emissions'!G:G, "s/l-POS") + COUNTIFS('GHG Emissions'!F:F, 2027, 'GHG Emissions'!G:G, "s/l-NEG") + COUNTIFS(Pollution!F:F, 2027, Pollution!G:G, "n") + COUNTIFS(Pollution!F:F, 2027, Pollution!G:G, "s/l-UNC") + COUNTIFS(Pollution!F:F, 2027, Pollution!G:G, "s/l-POS") + COUNTIFS(Pollution!F:F, 2027, Pollution!G:G, "s/l-NEG") + COUNTIFS('Energy|Power'!F:F, 2027, 'Energy|Power'!G:G, "n") + COUNTIFS('Energy|Power'!F:F, 2027, 'Energy|Power'!G:G, "s/l-UNC") + COUNTIFS('Energy|Power'!F:F, 2027, 'Energy|Power'!G:G, "s/l-POS") + COUNTIFS('Energy|Power'!F:F, 2027, 'Energy|Power'!G:G, "s/l-NEG") + COUNTIFS(Industry!F:F, 2027, Industry!G:G, "n") + COUNTIFS(Industry!F:F, 2027, Industry!G:G, "s/l-UNC") + COUNTIFS(Industry!F:F, 2027, Industry!G:G, "s/l-POS") + COUNTIFS(Industry!F:F, 2027, Industry!G:G, "s/l-NEG") + COUNTIFS(Buildings!F:F, 2027, Buildings!G:G, "n") + COUNTIFS(Buildings!F:F, 2027, Buildings!G:G, "s/l-UNC") + COUNTIFS(Buildings!F:F, 2027, Buildings!G:G, "s/l-POS") + COUNTIFS(Buildings!F:F, 2027, Buildings!G:G, "s/l-NEG") + COUNTIFS(Transport!F:F, 2027, Transport!G:G, "n") + COUNTIFS(Transport!F:F, 2027, Transport!G:G, "s/l-UNC") + COUNTIFS(Transport!F:F, 2027, Transport!G:G, "s/l-POS") + COUNTIFS(Transport!F:F, 2027, Transport!G:G, "s/l-NEG") + COUNTIFS(LULUCF!F:F, 2027, LULUCF!G:G, "n") + COUNTIFS(LULUCF!F:F, 2027, LULUCF!G:G, "s/l-UNC") + COUNTIFS(LULUCF!F:F, 2027, LULUCF!G:G, "s/l-POS") + COUNTIFS(LULUCF!F:F, 2027, LULUCF!G:G, "s/l-NEG") + COUNTIFS('Circular Economy'!F:F, 2027, 'Circular Economy'!G:G, "n") + COUNTIFS('Circular Economy'!F:F, 2027, 'Circular Economy'!G:G, "s/l-UNC") + COUNTIFS('Circular Economy'!F:F, 2027, 'Circular Economy'!G:G, "s/l-POS") + COUNTIFS('Circular Economy'!F:F, 2027, 'Circular Economy'!G:G, "s/l-NEG") + COUNTIFS(Finance!F:F, 2027, Finance!G:G, "n") + COUNTIFS(Finance!F:F, 2027, Finance!G:G, "s/l-UNC") + COUNTIFS(Finance!F:F, 2027, Finance!G:G, "s/l-POS") + COUNTIFS(Finance!F:F, 2027, Finance!G:G, "s/l-NEG")
K27: 2025 | L27: =COUNTIFS('GHG Emissions'!B:B, 2025, 'GHG Emissions'!G:G, "n") + COUNTIFS('GHG Emissions'!B:B, 2025, 'GHG Emissions'!G:G, "s/l-UNC") + COUNTIFS('GHG Emissions'!B:B, 2025, 'GHG Emissions'!G:G, "s/l-POS") + COUNTIFS('GHG Emissions'!B:B, 2025, 'GHG Emissions'!G:G, "s/l-NEG") + COUNTIFS(Pollution!A:A, 2025, Pollution!G:G, "n") + COUNTIFS(Pollution!A:A, 2025, Pollution!G:G, "s/l-UNC") + COUNTIFS(Pollution!A:A, 2025, Pollution!G:G, "s/l-POS") + COUNTIFS(Pollution!A:A, 2025, Pollution!G:G, "s/l-NEG") + COUNTIFS('Energy|Power'!A:A, 2025, 'Energy|Power'!G:G, "n") + COUNTIFS('Energy|Power'!A:A, 2025, 'Energy|Power'!G:G, "s/l-UNC") + COUNTIFS('Energy|Power'!A:A, 2025, 'Energy|Power'!G:G, "s/l-POS") + COUNTIFS('Energy|Power'!A:A, 2025, 'Energy|Power'!G:G, "s/l-NEG") + COUNTIFS(Industry!A:A, 2025, Industry!G:G, "n") + COUNTIFS(Industry!A:A, 2025, Industry!G:G, "s/l-UNC") + COUNTIFS(Industry!A:A, 2025, Industry!G:G, "s/l-POS") + COUNTIFS(Industry!A:A, 2025, Industry!G:G, "s/l-NEG") + COUNTIFS(Buildings!B:B, 2025, Buildings!G:G, "n") + COUNTIFS(Buildings!B:B, 2025, Buildings!G:G, "s/l-UNC") + COUNTIFS(Buildings!B:B, 2025, Buildings!G:G, "s/l-POS") + COUNTIFS(Buildings!B:B, 2025, Buildings!G:G, "s/l-NEG") + COUNTIFS(Transport!A:A, 2025, Transport!G:G, "n") + COUNTIFS(Transport!A:A, 2025, Transport!G:G, "s/l-UNC") + COUNTIFS(Transport!A:A, 2025, Transport!G:G, "s/l-POS") + COUNTIFS(Transport!A:A, 2025, Transport!G:G, "s/l-NEG") + COUNTIFS(LULUCF!A:A, 2025, LULUCF!G:G, "n") + COUNTIFS(LULUCF!A:A, 2025, LULUCF!G:G, "s/l-UNC") + COUNTIFS(LULUCF!A:A, 2025, LULUCF!G:G, "s/l-POS") + COUNTIFS(LULUCF!A:A, 2025, LULUCF!G:G, "s/l-NEG") + COUNTIFS('Circular Economy'!A:A, 2025, 'Circular Economy'!G:G, "n") + COUNTIFS('Circular Economy'!A:A, 2025, 'Circular Economy'!G:G, "s/l-UNC") + COUNTIFS('Circular Economy'!A:A, 2025, 'Circular Economy'!G:G, "s/l-POS") + COUNTIFS('Circular Economy'!A:A, 2025, 'Circular Economy'!G:G, "s/l-NEG") + COUNTIFS(Finance!A:A, 2025, Finance!G:G, "n") + COUNTIFS(Finance!A:A, 2025, Finance!G:G, "s/l-UNC") + COUNTIFS(Finance!A:A, 2025, Finance!G:G, "s/l-POS") + COUNTIFS(Finance!A:A, 2025, Finance!G:G, "s/l-NEG") | N27: 2030 | O27: =COUNTIFS('GHG Emissions'!F:F, 2030, 'GHG Emissions'!G:G, "n") + COUNTIFS('GHG Emissions'!F:F, 2030, 'GHG Emissions'!G:G, "s/l-UNC") + COUNTIFS('GHG Emissions'!F:F, 2030, 'GHG Emissions'!G:G, "s/l-POS") + COUNTIFS('GHG Emissions'!F:F, 2030, 'GHG Emissions'!G:G, "s/l-NEG") + COUNTIFS(Pollution!F:F, 2030, Pollution!G:G, "n") + COUNTIFS(Pollution!F:F, 2030, Pollution!G:G, "s/l-UNC") + COUNTIFS(Pollution!F:F, 2030, Pollution!G:G, "s/l-POS") + COUNTIFS(Pollution!F:F, 2030, Pollution!G:G, "s/l-NEG") + COUNTIFS('Energy|Power'!F:F, 2030, 'Energy|Power'!G:G, "n") + COUNTIFS('Energy|Power'!F:F, 2030, 'Energy|Power'!G:G, "s/l-UNC") + COUNTIFS('Energy|Power'!F:F, 2030, 'Energy|Power'!G:G, "s/l-POS") + COUNTIFS('Energy|Power'!F:F, 2030, 'Energy|Power'!G:G, "s/l-NEG") + COUNTIFS(Industry!F:F, 2030, Industry!G:G, "n") + COUNTIFS(Industry!F:F, 2030, Industry!G:G, "s/l-UNC") + COUNTIFS(Industry!F:F, 2030, Industry!G:G, "s/l-POS") + COUNTIFS(Industry!F:F, 2030, Industry!G:G, "s/l-NEG") + COUNTIFS(Buildings!F:F, 2030, Buildings!G:G, "n") + COUNTIFS(Buildings!F:F, 2030, Buildings!G:G, "s/l-UNC") + COUNTIFS(Buildings!F:F, 2030, Buildings!G:G, "s/l-POS") + COUNTIFS(Buildings!F:F, 2030, Buildings!G:G, "s/l-NEG") + COUNTIFS(Transport!F:F, 2030, Transport!G:G, "n") + COUNTIFS(Transport!F:F, 2030, Transport!G:G, "s/l-UNC") + COUNTIFS(Transport!F:F, 2030, Transport!G:G, "s/l-POS") + COUNTIFS(Transport!F:F, 2030, Transport!G:G, "s/l-NEG") + COUNTIFS(LULUCF!F:F, 2030, LULUCF!G:G, "n") + COUNTIFS(LULUCF!F:F, 2030, LULUCF!G:G, "s/l-UNC") + COUNTIFS(LULUCF!F:F, 2030, LULUCF!G:G, "s/l-POS") + COUNTIFS(LULUCF!F:F, 2030, LULUCF!G:G, "s/l-NEG") + COUNTIFS('Circular Economy'!F:F, 2030, 'Circular Economy'!G:G, "n") + COUNTIFS('Circular Economy'!F:F, 2030, 'Circular Economy'!G:G, "s/l-UNC") + COUNTIFS('Circular Economy'!F:F, 2030, 'Circular Economy'!G:G, "s/l-POS") + COUNTIFS('Circular Economy'!F:F, 2030, 'Circular Economy'!G:G, "s/l-NEG") + COUNTIFS(Finance!F:F, 2030, Finance!G:G, "n") + COUNTIFS(Finance!F:F, 2030, Finance!G:G, "s/l-UNC") + COUNTIFS(Finance!F:F, 2030, Finance!G:G, "s/l-POS") + COUNTIFS(Finance!F:F, 2030, Finance!G:G, "s/l-NEG")
K28: 2026 | L28: =COUNTIFS('GHG Emissions'!B:B, 2026, 'GHG Emissions'!G:G, "n") + COUNTIFS('GHG Emissions'!B:B, 2026, 'GHG Emissions'!G:G, "s/l-UNC") + COUNTIFS('GHG Emissions'!B:B, 2026, 'GHG Emissions'!G:G, "s/l-POS") + COUNTIFS('GHG Emissions'!B:B, 2026, 'GHG Emissions'!G:G, "s/l-NEG") + COUNTIFS(Pollution!A:A, 2026, Pollution!G:G, "n") + COUNTIFS(Pollution!A:A, 2026, Pollution!G:G, "s/l-UNC") + COUNTIFS(Pollution!A:A, 2026, Pollution!G:G, "s/l-POS") + COUNTIFS(Pollution!A:A, 2026, Pollution!G:G, "s/l-NEG") + COUNTIFS('Energy|Power'!A:A, 2026, 'Energy|Power'!G:G, "n") + COUNTIFS('Energy|Power'!A:A, 2026, 'Energy|Power'!G:G, "s/l-UNC") + COUNTIFS('Energy|Power'!A:A, 2026, 'Energy|Power'!G:G, "s/l-POS") + COUNTIFS('Energy|Power'!A:A, 2026, 'Energy|Power'!G:G, "s/l-NEG") + COUNTIFS(Industry!A:A, 2026, Industry!G:G, "n") + COUNTIFS(Industry!A:A, 2026, Industry!G:G, "s/l-UNC") + COUNTIFS(Industry!A:A, 2026, Industry!G:G, "s/l-POS") + COUNTIFS(Industry!A:A, 2026, Industry!G:G, "s/l-NEG") + COUNTIFS(Buildings!B:B, 2026, Buildings!G:G, "n") + COUNTIFS(Buildings!B:B, 2026, Buildings!G:G, "s/l-UNC") + COUNTIFS(Buildings!B:B, 2026, Buildings!G:G, "s/l-POS") + COUNTIFS(Buildings!B:B, 2026, Buildings!G:G, "s/l-NEG") + COUNTIFS(Transport!A:A, 2026, Transport!G:G, "n") + COUNTIFS(Transport!A:A, 2026, Transport!G:G, "s/l-UNC") + COUNTIFS(Transport!A:A, 2026, Transport!G:G, "s/l-POS") + COUNTIFS(Transport!A:A, 2026, Transport!G:G, "s/l-NEG") + COUNTIFS(LULUCF!A:A, 2026, LULUCF!G:G, "n") + COUNTIFS(LULUCF!A:A, 2026, LULUCF!G:G, "s/l-UNC") + COUNTIFS(LULUCF!A:A, 2026, LULUCF!G:G, "s/l-POS") + COUNTIFS(LULUCF!A:A, 2026, LULUCF!G:G, "s/l-NEG") + COUNTIFS('Circular Economy'!A:A, 2026, 'Circular Economy'!G:G, "n") + COUNTIFS('Circular Economy'!A:A, 2026, 'Circular Economy'!G:G, "s/l-UNC") + COUNTIFS('Circular Economy'!A:A, 2026, 'Circular Economy'!G:G, "s/l-POS") + COUNTIFS('Circular Economy'!A:A, 2026, 'Circular Economy'!G:G, "s/l-NEG") + COUNTIFS(Finance!A:A, 2026, Finance!G:G, "n") + COUNTIFS(Finance!A:A, 2026, Finance!G:G, "s/l-UNC") + COUNTIFS(Finance!A:A, 2026, Finance!G:G, "s/l-POS") + COUNTIFS(Finance!A:A, 2026, Finance!G:G, "s/l-NEG") | N28: before 2030 | O28: =COUNTIFS('GHG Emissions'!F:F, "before 2030", 'GHG Emissions'!G:G, "n") + COUNTIFS('GHG Emissions'!F:F, "before 2030", 'GHG Emissions'!G:G, "s/l-UNC") + COUNTIFS('GHG Emissions'!F:F, "before 2030", 'GHG Emissions'!G:G, "s/l-POS") + COUNTIFS('GHG Emissions'!F:F, "before 2030", 'GHG Emissions'!G:G, "s/l-NEG") + COUNTIFS(Pollution!F:F, "before 2030", Pollution!G:G, "n") + COUNTIFS(Pollution!F:F, "before 2030", Pollution!G:G, "s/l-UNC") + COUNTIFS(Pollution!F:F, "before 2030", Pollution!G:G, "s/l-POS") + COUNTIFS(Pollution!F:F, "before 2030", Pollution!G:G, "s/l-NEG") + COUNTIFS('Energy|Power'!F:F, "before 2030", 'Energy|Power'!G:G, "n") + COUNTIFS('Energy|Power'!F:F, "before 2030", 'Energy|Power'!G:G, "s/l-UNC") + COUNTIFS('Energy|Power'!F:F, "before 2030", 'Energy|Power'!G:G, "s/l-POS") + COUNTIFS('Energy|Power'!F:F, "before 2030", 'Energy|Power'!G:G, "s/l-NEG") + COUNTIFS(Industry!F:F, "before 2030", Industry!G:G, "n") + COUNTIFS(Industry!F:F, "before 2030", Industry!G:G, "s/l-UNC") + COUNTIFS(Industry!F:F, "before 2030", Industry!G:G, "s/l-POS") + COUNTIFS(Industry!F:F, "before 2030", Industry!G:G, "s/l-NEG") + COUNTIFS(Buildings!F:F, "before 2030", Buildings!G:G, "n") + COUNTIFS(Buildings!F:F, "before 2030", Buildings!G:G, "s/l-UNC") + COUNTIFS(Buildings!F:F, "before 2030", Buildings!G:G, "s/l-POS") + COUNTIFS(Buildings!F:F, "before 2030", Buildings!G:G, "s/l-NEG") + COUNTIFS(Transport!F:F, "before 2030", Transport!G:G, "n") + COUNTIFS(Transport!F:F, "before 2030", Transport!G:G, "s/l-UNC") + COUNTIFS(Transport!F:F, "before 2030", Transport!G:G, "s/l-POS") + COUNTIFS(Transport!F:F, "before 2030", Transport!G:G, "s/l-NEG") + COUNTIFS(LULUCF!F:F, "before 2030", LULUCF!G:G, "n") + COUNTIFS(LULUCF!F:F, "before 2030", LULUCF!G:G, "s/l-UNC") + COUNTIFS(LULUCF!F:F, "before 2030", LULUCF!G:G, "s/l-POS") + COUNTIFS(LULUCF!F:F, "before 2030", LULUCF!G:G, "s/l-NEG") + COUNTIFS('Circular Economy'!F:F, "before 2030", 'Circular Economy'!G:G, "n") + COUNTIFS('Circular Economy'!F:F, "before 2030", 'Circular Economy'!G:G, "s/l-UNC") + COUNTIFS('Circular Economy'!F:F, "before 2030", 'Circular Economy'!G:G, "s/l-POS") + COUNTIFS('Circular Economy'!F:F, "before 2030", 'Circular Economy'!G:G, "s/l-NEG") + COUNTIFS(Finance!F:F, "before 2030", Finance!G:G, "n") + COUNTIFS(Finance!F:F, "before 2030", Finance!G:G, "s/l-UNC") + COUNTIFS(Finance!F:F, "before 2030", Finance!G:G, "s/l-POS") + COUNTIFS(Finance!F:F, "before 2030", Finance!G:G, "s/l-NEG")
N29: around 2030 | O29: =COUNTIFS('GHG Emissions'!F:F, "around 2030", 'GHG Emissions'!G:G, "n") + COUNTIFS('GHG Emissions'!F:F, "around 2030", 'GHG Emissions'!G:G, "s/l-UNC") + COUNTIFS('GHG Emissions'!F:F, "around 2030", 'GHG Emissions'!G:G, "s/l-POS") + COUNTIFS('GHG Emissions'!F:F, "around 2030", 'GHG Emissions'!G:G, "s/l-NEG") + COUNTIFS(Pollution!F:F, "around 2030", Pollution!G:G, "n") + COUNTIFS(Pollution!F:F, "around 2030", Pollution!G:G, "s/l-UNC") + COUNTIFS(Pollution!F:F, "around 2030", Pollution!G:G, "s/l-POS") + COUNTIFS(Pollution!F:F, "around 2030", Pollution!G:G, "s/l-NEG") + COUNTIFS('Energy|Power'!F:F, "around 2030", 'Energy|Power'!G:G, "n") + COUNTIFS('Energy|Power'!F:F, "around 2030", 'Energy|Power'!G:G, "s/l-UNC") + COUNTIFS('Energy|Power'!F:F, "around 2030", 'Energy|Power'!G:G, "s/l-POS") + COUNTIFS('Energy|Power'!F:F, "around 2030", 'Energy|Power'!G:G, "s/l-NEG") + COUNTIFS(Industry!F:F, "around 2030", Industry!G:G, "n") + COUNTIFS(Industry!F:F, "around 2030", Industry!G:G, "s/l-UNC") + COUNTIFS(Industry!F:F, "around 2030", Industry!G:G, "s/l-POS") + COUNTIFS(Industry!F:F, "around 2030", Industry!G:G, "s/l-NEG") + COUNTIFS(Buildings!F:F, "around 2030", Buildings!G:G, "n") + COUNTIFS(Buildings!F:F, "around 2030", Buildings!G:G, "s/l-UNC") + COUNTIFS(Buildings!F:F, "around 2030", Buildings!G:G, "s/l-POS") + COUNTIFS(Buildings!F:F, "around 2030", Buildings!G:G, "s/l-NEG") + COUNTIFS(Transport!F:F, "around 2030", Transport!G:G, "n") + COUNTIFS(Transport!F:F, "around 2030", Transport!G:G, "s/l-UNC") + COUNTIFS(Transport!F:F, "around 2030", Transport!G:G, "s/l-POS") + COUNTIFS(Transport!F:F, "around 2030", Transport!G:G, "s/l-NEG") + COUNTIFS(LULUCF!F:F, "around 2030", LULUCF!G:G, "n") + COUNTIFS(LULUCF!F:F, "around 2030", LULUCF!G:G, "s/l-UNC") + COUNTIFS(LULUCF!F:F, "around 2030", LULUCF!G:G, "s/l-POS") + COUNTIFS(LULUCF!F:F, "around 2030", LULUCF!G:G, "s/l-NEG") + COUNTIFS('Circular Economy'!F:F, "around 2030", 'Circular Economy'!G:G, "n") + COUNTIFS('Circular Economy'!F:F, "around 2030", 'Circular Economy'!G:G, "s/l-UNC") + COUNTIFS('Circular Economy'!F:F, "around 2030", 'Circular Economy'!G:G, "s/l-POS") + COUNTIFS('Circular Economy'!F:F, "around 2030", 'Circular Economy'!G:G, "s/l-NEG") + COUNTIFS(Finance!F:F, "around 2030", Finance!G:G, "n") + COUNTIFS(Finance!F:F, "around 2030", Finance!G:G, "s/l-UNC") + COUNTIFS(Finance!F:F, "around 2030", Finance!G:G, "s/l-POS") + COUNTIFS(Finance!F:F, "around 2030", Finance!G:G, "s/l-NEG")
N30: (around/before) 2030 | O30: =SUM(O27:O29)
N31: 15th FYP | O31: =COUNTIFS('GHG Emissions'!F:F, "15th FYP", 'GHG Emissions'!G:G, "n") + COUNTIFS('GHG Emissions'!F:F, "15th FYP", 'GHG Emissions'!G:G, "s/l-UNC") + COUNTIFS('GHG Emissions'!F:F, "15th FYP", 'GHG Emissions'!G:G, "s/l-POS") + COUNTIFS('GHG Emissions'!F:F, "15th FYP", 'GHG Emissions'!G:G, "s/l-NEG") + COUNTIFS(Pollution!F:F, "15th FYP", Pollution!G:G, "n") + COUNTIFS(Pollution!F:F, "15th FYP", Pollution!G:G, "s/l-UNC") + COUNTIFS(Pollution!F:F, "15th FYP", Pollution!G:G, "s/l-POS") + COUNTIFS(Pollution!F:F, "15th FYP", Pollution!G:G, "s/l-NEG") + COUNTIFS('Energy|Power'!F:F, "15th FYP", 'Energy|Power'!G:G, "n") + COUNTIFS('Energy|Power'!F:F, "15th FYP", 'Energy|Power'!G:G, "s/l-UNC") + COUNTIFS('Energy|Power'!F:F, "15th FYP", 'Energy|Power'!G:G, "s/l-POS") + COUNTIFS('Energy|Power'!F:F, "15th FYP", 'Energy|Power'!G:G, "s/l-NEG") + COUNTIFS(Industry!F:F, "15th FYP", Industry!G:G, "n") + COUNTIFS(Industry!F:F, "15th FYP", Industry!G:G, "s/l-UNC") + COUNTIFS(Industry!F:F, "15th FYP", Industry!G:G, "s/l-POS") + COUNTIFS(Industry!F:F, "15th FYP", Industry!G:G, "s/l-NEG") + COUNTIFS(Buildings!F:F, "15th FYP", Buildings!G:G, "n") + COUNTIFS(Buildings!F:F, "15th FYP", Buildings!G:G, "s/l-UNC") + COUNTIFS(Buildings!F:F, "15th FYP", Buildings!G:G, "s/l-POS") + COUNTIFS(Buildings!F:F, "15th FYP", Buildings!G:G, "s/l-NEG") + COUNTIFS(Transport!F:F, "15th FYP", Transport!G:G, "n") + COUNTIFS(Transport!F:F, "15th FYP", Transport!G:G, "s/l-UNC") + COUNTIFS(Transport!F:F, "15th FYP", Transport!G:G, "s/l-POS") + COUNTIFS(Transport!F:F, "15th FYP", Transport!G:G, "s/l-NEG") + COUNTIFS(LULUCF!F:F, "15th FYP", LULUCF!G:G, "n") + COUNTIFS(LULUCF!F:F, "15th FYP", LULUCF!G:G, "s/l-UNC") + COUNTIFS(LULUCF!F:F, "15th FYP", LULUCF!G:G, "s/l-POS") + COUNTIFS(LULUCF!F:F, "15th FYP", LULUCF!G:G, "s/l-NEG") + COUNTIFS('Circular Economy'!F:F, "15th FYP", 'Circular Economy'!G:G, "n") + COUNTIFS('Circular Economy'!F:F, "15th FYP", 'Circular Economy'!G:G, "s/l-UNC") + COUNTIFS('Circular Economy'!F:F, "15th FYP", 'Circular Economy'!G:G, "s/l-POS") + COUNTIFS('Circular Economy'!F:F, "15th FYP", 'Circular Economy'!G:G, "s/l-NEG") + COUNTIFS(Finance!F:F, "15th FYP", Finance!G:G, "n") + COUNTIFS(Finance!F:F, "15th FYP", Finance!G:G, "s/l-UNC") + COUNTIFS(Finance!F:F, "15th FYP", Finance!G:G, "s/l-POS") + COUNTIFS(Finance!F:F, "15th FYP", Finance!G:G, "s/l-NEG")
N32: 2035 | O32: =COUNTIFS('GHG Emissions'!F:F, 2035, 'GHG Emissions'!G:G, "n") + COUNTIFS('GHG Emissions'!F:F, 2035, 'GHG Emissions'!G:G, "s/l-UNC") + COUNTIFS('GHG Emissions'!F:F, 2035, 'GHG Emissions'!G:G, "s/l-POS") + COUNTIFS('GHG Emissions'!F:F, 2035, 'GHG Emissions'!G:G, "s/l-NEG") + COUNTIFS(Pollution!F:F, 2035, Pollution!G:G, "n") + COUNTIFS(Pollution!F:F, 2035, Pollution!G:G, "s/l-UNC") + COUNTIFS(Pollution!F:F, 2035, Pollution!G:G, "s/l-POS") + COUNTIFS(Pollution!F:F, 2035, Pollution!G:G, "s/l-NEG") + COUNTIFS('Energy|Power'!F:F, 2035, 'Energy|Power'!G:G, "n") + COUNTIFS('Energy|Power'!F:F, 2035, 'Energy|Power'!G:G, "s/l-UNC") + COUNTIFS('Energy|Power'!F:F, 2035, 'Energy|Power'!G:G, "s/l-POS") + COUNTIFS('Energy|Power'!F:F, 2035, 'Energy|Power'!G:G, "s/l-NEG") + COUNTIFS(Industry!F:F, 2035, Industry!G:G, "n") + COUNTIFS(Industry!F:F, 2035, Industry!G:G, "s/l-UNC") + COUNTIFS(Industry!F:F, 2035, Industry!G:G, "s/l-POS") + COUNTIFS(Industry!F:F, 2035, Industry!G:G, "s/l-NEG") + COUNTIFS(Buildings!F:F, 2035, Buildings!G:G, "n") + COUNTIFS(Buildings!F:F, 2035, Buildings!G:G, "s/l-UNC") + COUNTIFS(Buildings!F:F, 2035, Buildings!G:G, "s/l-POS") + COUNTIFS(Buildings!F:F, 2035, Buildings!G:G, "s/l-NEG") + COUNTIFS(Transport!F:F, 2035, Transport!G:G, "n") + COUNTIFS(Transport!F:F, 2035, Transport!G:G, "s/l-UNC") + COUNTIFS(Transport!F:F, 2035, Transport!G:G, "s/l-POS") + COUNTIFS(Transport!F:F, 2035, Transport!G:G, "s/l-NEG") + COUNTIFS(LULUCF!F:F, 2035, LULUCF!G:G, "n") + COUNTIFS(LULUCF!F:F, 2035, LULUCF!G:G, "s/l-UNC") + COUNTIFS(LULUCF!F:F, 2035, LULUCF!G:G, "s/l-POS") + COUNTIFS(LULUCF!F:F, 2035, LULUCF!G:G, "s/l-NEG") + COUNTIFS('Circular Economy'!F:F, 2035, 'Circular Economy'!G:G, "n") + COUNTIFS('Circular Economy'!F:F, 2035, 'Circular Economy'!G:G, "s/l-UNC") + COUNTIFS('Circular Economy'!F:F, 2035, 'Circular Economy'!G:G, "s/l-POS") + COUNTIFS('Circular Economy'!F:F, 2035, 'Circular Economy'!G:G, "s/l-NEG") + COUNTIFS(Finance!F:F, 2035, Finance!G:G, "n") + COUNTIFS(Finance!F:F, 2035, Finance!G:G, "s/l-UNC") + COUNTIFS(Finance!F:F, 2035, Finance!G:G, "s/l-POS") + COUNTIFS(Finance!F:F, 2035, Finance!G:G, "s/l-NEG")
N33: before 2060 | O33: =COUNTIFS('GHG Emissions'!F:F, "before 2060", 'GHG Emissions'!G:G, "n") + COUNTIFS('GHG Emissions'!F:F, "before 2060", 'GHG Emissions'!G:G, "s/l-UNC") + COUNTIFS('GHG Emissions'!F:F, "before 2060", 'GHG Emissions'!G:G, "s/l-POS") + COUNTIFS('GHG Emissions'!F:F, "before 2060", 'GHG Emissions'!G:G, "s/l-NEG") + COUNTIFS(Pollution!F:F, "before 2060", Pollution!G:G, "n") + COUNTIFS(Pollution!F:F, "before 2060", Pollution!G:G, "s/l-UNC") + COUNTIFS(Pollution!F:F, "before 2060", Pollution!G:G, "s/l-POS") + COUNTIFS(Pollution!F:F, "before 2060", Pollution!G:G, "s/l-NEG") + COUNTIFS('Energy|Power'!F:F, "before 2060", 'Energy|Power'!G:G, "n") + COUNTIFS('Energy|Power'!F:F, "before 2060", 'Energy|Power'!G:G, "s/l-UNC") + COUNTIFS('Energy|Power'!F:F, "before 2060", 'Energy|Power'!G:G, "s/l-POS") + COUNTIFS('Energy|Power'!F:F, "before 2060", 'Energy|Power'!G:G, "s/l-NEG") + COUNTIFS(Industry!F:F, "before 2060", Industry!G:G, "n") + COUNTIFS(Industry!F:F, "before 2060", Industry!G:G, "s/l-UNC") + COUNTIFS(Industry!F:F, "before 2060", Industry!G:G, "s/l-POS") + COUNTIFS(Industry!F:F, "before 2060", Industry!G:G, "s/l-NEG") + COUNTIFS(Buildings!F:F, "before 2060", Buildings!G:G, "n") + COUNTIFS(Buildings!F:F, "before 2060", Buildings!G:G, "s/l-UNC") + COUNTIFS(Buildings!F:F, "before 2060", Buildings!G:G, "s/l-POS") + COUNTIFS(Buildings!F:F, "before 2060", Buildings!G:G, "s/l-NEG") + COUNTIFS(Transport!F:F, "before 2060", Transport!G:G, "n") + COUNTIFS(Transport!F:F, "before 2060", Transport!G:G, "s/l-UNC") + COUNTIFS(Transport!F:F, "before 2060", Transport!G:G, "s/l-POS") + COUNTIFS(Transport!F:F, "before 2060", Transport!G:G, "s/l-NEG") + COUNTIFS(LULUCF!F:F, "before 2060", LULUCF!G:G, "n") + COUNTIFS(LULUCF!F:F, "before 2060", LULUCF!G:G, "s/l-UNC") + COUNTIFS(LULUCF!F:F, "before 2060", LULUCF!G:G, "s/l-POS") + COUNTIFS(LULUCF!F:F, "before 2060", LULUCF!G:G, "s/l-NEG") + COUNTIFS('Circular Economy'!F:F, "before 2060", 'Circular Economy'!G:G, "n") + COUNTIFS('Circular Economy'!F:F, "before 2060", 'Circular Economy'!G:G, "s/l-UNC") + COUNTIFS('Circular Economy'!F:F, "before 2060", 'Circular Economy'!G:G, "s/l-POS") + COUNTIFS('Circular Economy'!F:F, "before 2060", 'Circular Economy'!G:G, "s/l-NEG") + COUNTIFS(Finance!F:F, "before 2060", Finance!G:G, "n") + COUNTIFS(Finance!F:F, "before 2060", Finance!G:G, "s/l-UNC") + COUNTIFS(Finance!F:F, "before 2060", Finance!G:G, "s/l-POS") + COUNTIFS(Finance!F:F, "before 2060", Finance!G:G, "s/l-NEG")
N34: 2003-2020 | O34: =COUNTIFS('GHG Emissions'!F:F, "2003-2020", 'GHG Emissions'!G:G, "n") + COUNTIFS('GHG Emissions'!F:F, "2003-2020", 'GHG Emissions'!G:G, "s/l-UNC") + COUNTIFS('GHG Emissions'!F:F, "2003-2020", 'GHG Emissions'!G:G, "s/l-POS") + COUNTIFS('GHG Emissions'!F:F, "2003-2020", 'GHG Emissions'!G:G, "s/l-NEG") + COUNTIFS(Pollution!F:F, "2003-2020", Pollution!G:G, "n") + COUNTIFS(Pollution!F:F, "2003-2020", Pollution!G:G, "s/l-UNC") + COUNTIFS(Pollution!F:F, "2003-2020", Pollution!G:G, "s/l-POS") + COUNTIFS(Pollution!F:F, "2003-2020", Pollution!G:G, "s/l-NEG") + COUNTIFS('Energy|Power'!F:F, "2003-2020", 'Energy|Power'!G:G, "n") + COUNTIFS('Energy|Power'!F:F, "2003-2020", 'Energy|Power'!G:G, "s/l-UNC") + COUNTIFS('Energy|Power'!F:F, "2003-2020", 'Energy|Power'!G:G, "s/l-POS") + COUNTIFS('Energy|Power'!F:F, "2003-2020", 'Energy|Power'!G:G, "s/l-NEG") + COUNTIFS(Industry!F:F, "2003-2020", Industry!G:G, "n") + COUNTIFS(Industry!F:F, "2003-2020", Industry!G:G, "s/l-UNC") + COUNTIFS(Industry!F:F, "2003-2020", Industry!G:G, "s/l-POS") + COUNTIFS(Industry!F:F, "2003-2020", Industry!G:G, "s/l-NEG") + COUNTIFS(Buildings!F:F, "2003-2020", Buildings!G:G, "n") + COUNTIFS(Buildings!F:F, "2003-2020", Buildings!G:G, "s/l-UNC") + COUNTIFS(Buildings!F:F, "2003-2020", Buildings!G:G, "s/l-POS") + COUNTIFS(Buildings!F:F, "2003-2020", Buildings!G:G, "s/l-NEG") + COUNTIFS(Transport!F:F, "2003-2020", Transport!G:G, "n") + COUNTIFS(Transport!F:F, "2003-2020", Transport!G:G, "s/l-UNC") + COUNTIFS(Transport!F:F, "2003-2020", Transport!G:G, "s/l-POS") + COUNTIFS(Transport!F:F, "2003-2020", Transport!G:G, "s/l-NEG") + COUNTIFS(LULUCF!F:F, "2003-2020", LULUCF!G:G, "n") + COUNTIFS(LULUCF!F:F, "2003-2020", LULUCF!G:G, "s/l-UNC") + COUNTIFS(LULUCF!F:F, "2003-2020", LULUCF!G:G, "s/l-POS") + COUNTIFS(LULUCF!F:F, "2003-2020", LULUCF!G:G, "s/l-NEG") + COUNTIFS('Circular Economy'!F:F, "2003-2020", 'Circular Economy'!G:G, "n") + COUNTIFS('Circular Economy'!F:F, "2003-2020", 'Circular Economy'!G:G, "s/l-UNC") + COUNTIFS('Circular Economy'!F:F, "2003-2020", 'Circular Economy'!G:G, "s/l-POS") + COUNTIFS('Circular Economy'!F:F, "2003-2020", 'Circular Economy'!G:G, "s/l-NEG") + COUNTIFS(Finance!F:F, "2003-2020", Finance!G:G, "n") + COUNTIFS(Finance!F:F, "2003-2020", Finance!G:G, "s/l-UNC") + COUNTIFS(Finance!F:F, "2003-2020", Finance!G:G, "s/l-POS") + COUNTIFS(Finance!F:F, "2003-2020", Finance!G:G, "s/l-NEG")
N35: 2007-2010 | O35: =COUNTIFS('GHG Emissions'!F:F, "2007-2010", 'GHG Emissions'!G:G, "n") + COUNTIFS('GHG Emissions'!F:F, "2007-2010", 'GHG Emissions'!G:G, "s/l-UNC") + COUNTIFS('GHG Emissions'!F:F, "2007-2010", 'GHG Emissions'!G:G, "s/l-POS") + COUNTIFS('GHG Emissions'!F:F, "2007-2010", 'GHG Emissions'!G:G, "s/l-NEG") + COUNTIFS(Pollution!F:F, "2007-2010", Pollution!G:G, "n") + COUNTIFS(Pollution!F:F, "2007-2010", Pollution!G:G, "s/l-UNC") + COUNTIFS(Pollution!F:F, "2007-2010", Pollution!G:G, "s/l-POS") + COUNTIFS(Pollution!F:F, "2007-2010", Pollution!G:G, "s/l-NEG") + COUNTIFS('Energy|Power'!F:F, "2007-2010", 'Energy|Power'!G:G, "n") + COUNTIFS('Energy|Power'!F:F, "2007-2010", 'Energy|Power'!G:G, "s/l-UNC") + COUNTIFS('Energy|Power'!F:F, "2007-2010", 'Energy|Power'!G:G, "s/l-POS") + COUNTIFS('Energy|Power'!F:F, "2007-2010", 'Energy|Power'!G:G, "s/l-NEG") + COUNTIFS(Industry!F:F, "2007-2010", Industry!G:G, "n") + COUNTIFS(Industry!F:F, "2007-2010", Industry!G:G, "s/l-UNC") + COUNTIFS(Industry!F:F, "2007-2010", Industry!G:G, "s/l-POS") + COUNTIFS(Industry!F:F, "2007-2010", Industry!G:G, "s/l-NEG") + COUNTIFS(Buildings!F:F, "2007-2010", Buildings!G:G, "n") + COUNTIFS(Buildings!F:F, "2007-2010", Buildings!G:G, "s/l-UNC") + COUNTIFS(Buildings!F:F, "2007-2010", Buildings!G:G, "s/l-POS") + COUNTIFS(Buildings!F:F, "2007-2010", Buildings!G:G, "s/l-NEG") + COUNTIFS(Transport!F:F, "2007-2010", Transport!G:G, "n") + COUNTIFS(Transport!F:F, "2007-2010", Transport!G:G, "s/l-UNC") + COUNTIFS(Transport!F:F, "2007-2010", Transport!G:G, "s/l-POS") + COUNTIFS(Transport!F:F, "2007-2010", Transport!G:G, "s/l-NEG") + COUNTIFS(LULUCF!F:F, "2007-2010", LULUCF!G:G, "n") + COUNTIFS(LULUCF!F:F, "2007-2010", LULUCF!G:G, "s/l-UNC") + COUNTIFS(LULUCF!F:F, "2007-2010", LULUCF!G:G, "s/l-POS") + COUNTIFS(LULUCF!F:F, "2007-2010", LULUCF!G:G, "s/l-NEG") + COUNTIFS('Circular Economy'!F:F, "2007-2010", 'Circular Economy'!G:G, "n") + COUNTIFS('Circular Economy'!F:F, "2007-2010", 'Circular Economy'!G:G, "s/l-UNC") + COUNTIFS('Circular Economy'!F:F, "2007-2010", 'Circular Economy'!G:G, "s/l-POS") + COUNTIFS('Circular Economy'!F:F, "2007-2010", 'Circular Economy'!G:G, "s/l-NEG") + COUNTIFS(Finance!F:F, "2007-2010", Finance!G:G, "n") + COUNTIFS(Finance!F:F, "2007-2010", Finance!G:G, "s/l-UNC") + COUNTIFS(Finance!F:F, "2007-2010", Finance!G:G, "s/l-POS") + COUNTIFS(Finance!F:F, "2007-2010", Finance!G:G, "s/l-NEG")
N36: 2007-2020 | O36: =COUNTIFS('GHG Emissions'!F:F, "2007-2020", 'GHG Emissions'!G:G, "n") + COUNTIFS('GHG Emissions'!F:F, "2007-2020", 'GHG Emissions'!G:G, "s/l-UNC") + COUNTIFS('GHG Emissions'!F:F, "2007-2020", 'GHG Emissions'!G:G, "s/l-POS") + COUNTIFS('GHG Emissions'!F:F, "2007-2020", 'GHG Emissions'!G:G, "s/l-NEG") + COUNTIFS(Pollution!F:F, "2007-2020", Pollution!G:G, "n") + COUNTIFS(Pollution!F:F, "2007-2020", Pollution!G:G, "s/l-UNC") + COUNTIFS(Pollution!F:F, "2007-2020", Pollution!G:G, "s/l-POS") + COUNTIFS(Pollution!F:F, "2007-2020", Pollution!G:G, "s/l-NEG") + COUNTIFS('Energy|Power'!F:F, "2007-2020", 'Energy|Power'!G:G, "n") + COUNTIFS('Energy|Power'!F:F, "2007-2020", 'Energy|Power'!G:G, "s/l-UNC") + COUNTIFS('Energy|Power'!F:F, "2007-2020", 'Energy|Power'!G:G, "s/l-POS") + COUNTIFS('Energy|Power'!F:F, "2007-2020", 'Energy|Power'!G:G, "s/l-NEG") + COUNTIFS(Industry!F:F, "2007-2020", Industry!G:G, "n") + COUNTIFS(Industry!F:F, "2007-2020", Industry!G:G, "s/l-UNC") + COUNTIFS(Industry!F:F, "2007-2020", Industry!G:G, "s/l-POS") + COUNTIFS(Industry!F:F, "2007-2020", Industry!G:G, "s/l-NEG") + COUNTIFS(Buildings!F:F, "2007-2020", Buildings!G:G, "n") + COUNTIFS(Buildings!F:F, "2007-2020", Buildings!G:G, "s/l-UNC") + COUNTIFS(Buildings!F:F, "2007-2020", Buildings!G:G, "s/l-POS") + COUNTIFS(Buildings!F:F, "2007-2020", Buildings!G:G, "s/l-NEG") + COUNTIFS(Transport!F:F, "2007-2020", Transport!G:G, "n") + COUNTIFS(Transport!F:F, "2007-2020", Transport!G:G, "s/l-UNC") + COUNTIFS(Transport!F:F, "2007-2020", Transport!G:G, "s/l-POS") + COUNTIFS(Transport!F:F, "2007-2020", Transport!G:G, "s/l-NEG") + COUNTIFS(LULUCF!F:F, "2007-2020", LULUCF!G:G, "n") + COUNTIFS(LULUCF!F:F, "2007-2020", LULUCF!G:G, "s/l-UNC") + COUNTIFS(LULUCF!F:F, "2007-2020", LULUCF!G:G, "s/l-POS") + COUNTIFS(LULUCF!F:F, "2007-2020", LULUCF!G:G, "s/l-NEG") + COUNTIFS('Circular Economy'!F:F, "2007-2020", 'Circular Economy'!G:G, "n") + COUNTIFS('Circular Economy'!F:F, "2007-2020", 'Circular Economy'!G:G, "s/l-UNC") + COUNTIFS('Circular Economy'!F:F, "2007-2020", 'Circular Economy'!G:G, "s/l-POS") + COUNTIFS('Circular Economy'!F:F, "2007-2020", 'Circular Economy'!G:G, "s/l-NEG") + COUNTIFS(Finance!F:F, "2007-2020", Finance!G:G, "n") + COUNTIFS(Finance!F:F, "2007-2020", Finance!G:G, "s/l-UNC") + COUNTIFS(Finance!F:F, "2007-2020", Finance!G:G, "s/l-POS") + COUNTIFS(Finance!F:F, "2007-2020", Finance!G:G, "s/l-NEG")
N37: 2014-2015 | O37: =COUNTIFS('GHG Emissions'!F:F, "2014-2015", 'GHG Emissions'!G:G, "n") + COUNTIFS('GHG Emissions'!F:F, "2014-2015", 'GHG Emissions'!G:G, "s/l-UNC") + COUNTIFS('GHG Emissions'!F:F, "2014-2015", 'GHG Emissions'!G:G, "s/l-POS") + COUNTIFS('GHG Emissions'!F:F, "2014-2015", 'GHG Emissions'!G:G, "s/l-NEG") + COUNTIFS(Pollution!F:F, "2014-2015", Pollution!G:G, "n") + COUNTIFS(Pollution!F:F, "2014-2015", Pollution!G:G, "s/l-UNC") + COUNTIFS(Pollution!F:F, "2014-2015", Pollution!G:G, "s/l-POS") + COUNTIFS(Pollution!F:F, "2014-2015", Pollution!G:G, "s/l-NEG") + COUNTIFS('Energy|Power'!F:F, "2014-2015", 'Energy|Power'!G:G, "n") + COUNTIFS('Energy|Power'!F:F, "2014-2015", 'Energy|Power'!G:G, "s/l-UNC") + COUNTIFS('Energy|Power'!F:F, "2014-2015", 'Energy|Power'!G:G, "s/l-POS") + COUNTIFS('Energy|Power'!F:F, "2014-2015", 'Energy|Power'!G:G, "s/l-NEG") + COUNTIFS(Industry!F:F, "2014-2015", Industry!G:G, "n") + COUNTIFS(Industry!F:F, "2014-2015", Industry!G:G, "s/l-UNC") + COUNTIFS(Industry!F:F, "2014-2015", Industry!G:G, "s/l-POS") + COUNTIFS(Industry!F:F, "2014-2015", Industry!G:G, "s/l-NEG") + COUNTIFS(Buildings!F:F, "2014-2015", Buildings!G:G, "n") + COUNTIFS(Buildings!F:F, "2014-2015", Buildings!G:G, "s/l-UNC") + COUNTIFS(Buildings!F:F, "2014-2015", Buildings!G:G, "s/l-POS") + COUNTIFS(Buildings!F:F, "2014-2015", Buildings!G:G, "s/l-NEG") + COUNTIFS(Transport!F:F, "2014-2015", Transport!G:G, "n") + COUNTIFS(Transport!F:F, "2014-2015", Transport!G:G, "s/l-UNC") + COUNTIFS(Transport!F:F, "2014-2015", Transport!G:G, "s/l-POS") + COUNTIFS(Transport!F:F, "2014-2015", Transport!G:G, "s/l-NEG") + COUNTIFS(LULUCF!F:F, "2014-2015", LULUCF!G:G, "n") + COUNTIFS(LULUCF!F:F, "2014-2015", LULUCF!G:G, "s/l-UNC") + COUNTIFS(LULUCF!F:F, "2014-2015", LULUCF!G:G, "s/l-POS") + COUNTIFS(LULUCF!F:F, "2014-2015", LULUCF!G:G, "s/l-NEG") + COUNTIFS('Circular Economy'!F:F, "2014-2015", 'Circular Economy'!G:G, "n") + COUNTIFS('Circular Economy'!F:F, "2014-2015", 'Circular Economy'!G:G, "s/l-UNC") + COUNTIFS('Circular Economy'!F:F, "2014-2015", 'Circular Economy'!G:G, "s/l-POS") + COUNTIFS('Circular Economy'!F:F, "2014-2015", 'Circular Economy'!G:G, "s/l-NEG") + COUNTIFS(Finance!F:F, "2014-2015", Finance!G:G, "n") + COUNTIFS(Finance!F:F, "2014-2015", Finance!G:G, "s/l-UNC") + COUNTIFS(Finance!F:F, "2014-2015", Finance!G:G, "s/l-POS") + COUNTIFS(Finance!F:F, "2014-2015", Finance!G:G, "s/l-NEG")
N38: 2014-2016 | O38: =COUNTIFS('GHG Emissions'!F:F, "2014-2016", 'GHG Emissions'!G:G, "n") + COUNTIFS('GHG Emissions'!F:F, "2014-2016", 'GHG Emissions'!G:G, "s/l-UNC") + COUNTIFS('GHG Emissions'!F:F, "2014-2016", 'GHG Emissions'!G:G, "s/l-POS") + COUNTIFS('GHG Emissions'!F:F, "2014-2016", 'GHG Emissions'!G:G, "s/l-NEG") + COUNTIFS(Pollution!F:F, "2014-2016", Pollution!G:G, "n") + COUNTIFS(Pollution!F:F, "2014-2016", Pollution!G:G, "s/l-UNC") + COUNTIFS(Pollution!F:F, "2014-2016", Pollution!G:G, "s/l-POS") + COUNTIFS(Pollution!F:F, "2014-2016", Pollution!G:G, "s/l-NEG") + COUNTIFS('Energy|Power'!F:F, "2014-2016", 'Energy|Power'!G:G, "n") + COUNTIFS('Energy|Power'!F:F, "2014-2016", 'Energy|Power'!G:G, "s/l-UNC") + COUNTIFS('Energy|Power'!F:F, "2014-2016", 'Energy|Power'!G:G, "s/l-POS") + COUNTIFS('Energy|Power'!F:F, "2014-2016", 'Energy|Power'!G:G, "s/l-NEG") + COUNTIFS(Industry!F:F, "2014-2016", Industry!G:G, "n") + COUNTIFS(Industry!F:F, "2014-2016", Industry!G:G, "s/l-UNC") + COUNTIFS(Industry!F:F, "2014-2016", Industry!G:G, "s/l-POS") + COUNTIFS(Industry!F:F, "2014-2016", Industry!G:G, "s/l-NEG") + COUNTIFS(Buildings!F:F, "2014-2016", Buildings!G:G, "n") + COUNTIFS(Buildings!F:F, "2014-2016", Buildings!G:G, "s/l-UNC") + COUNTIFS(Buildings!F:F, "2014-2016", Buildings!G:G, "s/l-POS") + COUNTIFS(Buildings!F:F, "2014-2016", Buildings!G:G, "s/l-NEG") + COUNTIFS(Transport!F:F, "2014-2016", Transport!G:G, "n") + COUNTIFS(Transport!F:F, "2014-2016", Transport!G:G, "s/l-UNC") + COUNTIFS(Transport!F:F, "2014-2016", Transport!G:G, "s/l-POS") + COUNTIFS(Transport!F:F, "2014-2016", Transport!G:G, "s/l-NEG") + COUNTIFS(LULUCF!F:F, "2014-2016", LULUCF!G:G, "n") + COUNTIFS(LULUCF!F:F, "2014-2016", LULUCF!G:G, "s/l-UNC") + COUNTIFS(LULUCF!F:F, "2014-2016", LULUCF!G:G, "s/l-POS") + COUNTIFS(LULUCF!F:F, "2014-2016", LULUCF!G:G, "s/l-NEG") + COUNTIFS('Circular Economy'!F:F, "2014-2016", 'Circular Economy'!G:G, "n") + COUNTIFS('Circular Economy'!F:F, "2014-2016", 'Circular Economy'!G:G, "s/l-UNC") + COUNTIFS('Circular Economy'!F:F, "2014-2016", 'Circular Economy'!G:G, "s/l-POS") + COUNTIFS('Circular Economy'!F:F, "2014-2016", 'Circular Economy'!G:G, "s/l-NEG") + COUNTIFS(Finance!F:F, "2014-2016", Finance!G:G, "n") + COUNTIFS(Finance!F:F, "2014-2016", Finance!G:G, "s/l-UNC") + COUNTIFS(Finance!F:F, "2014-2016", Finance!G:G, "s/l-POS") + COUNTIFS(Finance!F:F, "2014-2016", Finance!G:G, "s/l-NEG")
N39: 2016-2020 | O39: =COUNTIFS('GHG Emissions'!F:F, "2016-2020", 'GHG Emissions'!G:G, "n") + COUNTIFS('GHG Emissions'!F:F, "2016-2020", 'GHG Emissions'!G:G, "s/l-UNC") + COUNTIFS('GHG Emissions'!F:F, "2016-2020", 'GHG Emissions'!G:G, "s/l-POS") + COUNTIFS('GHG Emissions'!F:F, "2016-2020", 'GHG Emissions'!G:G, "s/l-NEG") + COUNTIFS(Pollution!F:F, "2016-2020", Pollution!G:G, "n") + COUNTIFS(Pollution!F:F, "2016-2020", Pollution!G:G, "s/l-UNC") + COUNTIFS(Pollution!F:F, "2016-2020", Pollution!G:G, "s/l-POS") + COUNTIFS(Pollution!F:F, "2016-2020", Pollution!G:G, "s/l-NEG") + COUNTIFS('Energy|Power'!F:F, "2016-2020", 'Energy|Power'!G:G, "n") + COUNTIFS('Energy|Power'!F:F, "2016-2020", 'Energy|Power'!G:G, "s/l-UNC") + COUNTIFS('Energy|Power'!F:F, "2016-2020", 'Energy|Power'!G:G, "s/l-POS") + COUNTIFS('Energy|Power'!F:F, "2016-2020", 'Energy|Power'!G:G, "s/l-NEG") + COUNTIFS(Industry!F:F, "2016-2020", Industry!G:G, "n") + COUNTIFS(Industry!F:F, "2016-2020", Industry!G:G, "s/l-UNC") + COUNTIFS(Industry!F:F, "2016-2020", Industry!G:G, "s/l-POS") + COUNTIFS(Industry!F:F, "2016-2020", Industry!G:G, "s/l-NEG") + COUNTIFS(Buildings!F:F, "2016-2020", Buildings!G:G, "n") + COUNTIFS(Buildings!F:F, "2016-2020", Buildings!G:G, "s/l-UNC") + COUNTIFS(Buildings!F:F, "2016-2020", Buildings!G:G, "s/l-POS") + COUNTIFS(Buildings!F:F, "2016-2020", Buildings!G:G, "s/l-NEG") + COUNTIFS(Transport!F:F, "2016-2020", Transport!G:G, "n") + COUNTIFS(Transport!F:F, "2016-2020", Transport!G:G, "s/l-UNC") + COUNTIFS(Transport!F:F, "2016-2020", Transport!G:G, "s/l-POS") + COUNTIFS(Transport!F:F, "2016-2020", Transport!G:G, "s/l-NEG") + COUNTIFS(LULUCF!F:F, "2016-2020", LULUCF!G:G, "n") + COUNTIFS(LULUCF!F:F, "2016-2020", LULUCF!G:G, "s/l-UNC") + COUNTIFS(LULUCF!F:F, "2016-2020", LULUCF!G:G, "s/l-POS") + COUNTIFS(LULUCF!F:F, "2016-2020", LULUCF!G:G, "s/l-NEG") + COUNTIFS('Circular Economy'!F:F, "2016-2020", 'Circular Economy'!G:G, "n") + COUNTIFS('Circular Economy'!F:F, "2016-2020", 'Circular Economy'!G:G, "s/l-UNC") + COUNTIFS('Circular Economy'!F:F, "2016-2020", 'Circular Economy'!G:G, "s/l-POS") + COUNTIFS('Circular Economy'!F:F, "2016-2020", 'Circular Economy'!G:G, "s/l-NEG") + COUNTIFS(Finance!F:F, "2016-2020", Finance!G:G, "n") + COUNTIFS(Finance!F:F, "2016-2020", Finance!G:G, "s/l-UNC") + COUNTIFS(Finance!F:F, "2016-2020", Finance!G:G, "s/l-POS") + COUNTIFS(Finance!F:F, "2016-2020", Finance!G:G, "s/l-NEG")
N40: 2016-2030 | O40: =COUNTIFS('GHG Emissions'!F:F, "2016-2030", 'GHG Emissions'!G:G, "n") + COUNTIFS('GHG Emissions'!F:F, "2016-2030", 'GHG Emissions'!G:G, "s/l-UNC") + COUNTIFS('GHG Emissions'!F:F, "2016-2030", 'GHG Emissions'!G:G, "s/l-POS") + COUNTIFS('GHG Emissions'!F:F, "2016-2030", 'GHG Emissions'!G:G, "s/l-NEG") + COUNTIFS(Pollution!F:F, "2016-2030", Pollution!G:G, "n") + COUNTIFS(Pollution!F:F, "2016-2030", Pollution!G:G, "s/l-UNC") + COUNTIFS(Pollution!F:F, "2016-2030", Pollution!G:G, "s/l-POS") + COUNTIFS(Pollution!F:F, "2016-2030", Pollution!G:G, "s/l-NEG") + COUNTIFS('Energy|Power'!F:F, "2016-2030", 'Energy|Power'!G:G, "n") + COUNTIFS('Energy|Power'!F:F, "2016-2030", 'Energy|Power'!G:G, "s/l-UNC") + COUNTIFS('Energy|Power'!F:F, "2016-2030", 'Energy|Power'!G:G, "s/l-POS") + COUNTIFS('Energy|Power'!F:F, "2016-2030", 'Energy|Power'!G:G, "s/l-NEG") + COUNTIFS(Industry!F:F, "2016-2030", Industry!G:G, "n") + COUNTIFS(Industry!F:F, "2016-2030", Industry!G:G, "s/l-UNC") + COUNTIFS(Industry!F:F, "2016-2030", Industry!G:G, "s/l-POS") + COUNTIFS(Industry!F:F, "2016-2030", Industry!G:G, "s/l-NEG") + COUNTIFS(Buildings!F:F, "2016-2030", Buildings!G:G, "n") + COUNTIFS(Buildings!F:F, "2016-2030", Buildings!G:G, "s/l-UNC") + COUNTIFS(Buildings!F:F, "2016-2030", Buildings!G:G, "s/l-POS") + COUNTIFS(Buildings!F:F, "2016-2030", Buildings!G:G, "s/l-NEG") + COUNTIFS(Transport!F:F, "2016-2030", Transport!G:G, "n") + COUNTIFS(Transport!F:F, "2016-2030", Transport!G:G, "s/l-UNC") + COUNTIFS(Transport!F:F, "2016-2030", Transport!G:G, "s/l-POS") + COUNTIFS(Transport!F:F, "2016-2030", Transport!G:G, "s/l-NEG") + COUNTIFS(LULUCF!F:F, "2016-2030", LULUCF!G:G, "n") + COUNTIFS(LULUCF!F:F, "2016-2030", LULUCF!G:G, "s/l-UNC") + COUNTIFS(LULUCF!F:F, "2016-2030", LULUCF!G:G, "s/l-POS") + COUNTIFS(LULUCF!F:F, "2016-2030", LULUCF!G:G, "s/l-NEG") + COUNTIFS('Circular Economy'!F:F, "2016-2030", 'Circular Economy'!G:G, "n") + COUNTIFS('Circular Economy'!F:F, "2016-2030", 'Circular Economy'!G:G, "s/l-UNC") + COUNTIFS('Circular Economy'!F:F, "2016-2030", 'Circular Economy'!G:G, "s/l-POS") + COUNTIFS('Circular Economy'!F:F, "2016-2030", 'Circular Economy'!G:G, "s/l-NEG") + COUNTIFS(Finance!F:F, "2016-2030", Finance!G:G, "n") + COUNTIFS(Finance!F:F, "2016-2030", Finance!G:G, "s/l-UNC") + COUNTIFS(Finance!F:F, "2016-2030", Finance!G:G, "s/l-POS") + COUNTIFS(Finance!F:F, "2016-2030", Finance!G:G, "s/l-NEG")
